Workbook
Name Annee_Reporting: "Paramètres!$B$7"
Name Bilan_Total: "Paramètres!$B$10"
Name Borne_Basse: "Incertitudes!$B$41"
Name Borne_Haute: "Incertitudes!$B$42"
Name CA_Total: "Paramètres!$B$9"
Name CapEx_Total: "Paramètres!$B$14"
Name ESRS_DataPoints_Auto: "ESRS_E1!$B$36"
Name ESRS_DataPoints_Completes: "ESRS_E1!$B$37"
Name ETP_Total: "Paramètres!$B$11"
Name GES_Grand_Total: "Synthese_GES!$C$47"
Name Incertitude_Totale_Abs: "Incertitudes!$B$39"
Name Incertitude_Totale_Pct: "Incertitudes!$E$35"
Name Intensite_CA: "Synthese_GES!$C$50"
Name Intensite_ETP: "Synthese_GES!$C$51"
Name Intensite_m2: "Synthese_GES!$C$52"
Name Methode_Consolidation: "Paramètres!$B$17"
Name Nb_Sites: "Paramètres!$B$13"
Name OpEx_Eligible_Taxo: "Paramètres!$B$15"
Name Part_ETS: "Paramètres!$B$22"
Name Part_Scope1: "Synthese_GES!$C$53"
Name Part_Scope2: "Synthese_GES!$C$54"
Name Part_Scope3: "Synthese_GES!$C$55"
Name Perimetre_Geo: "Paramètres!$B$18"
Name Periode_Reporting: "Paramètres!$B$8"
Name PT_CapEx_Decarb: "Plan_Transition!$C$42"
Name PT_Pct_CapEx_Aligne: "Plan_Transition!$C$44"
Name PT_Prix_Carbone: "Plan_Transition!$C$20"
Name PT_Total_Invest: "Plan_Transition!$D$16"
Name PT_Total_Reduction: "Plan_Transition!$F$16"
Name QC_Error_Count: "_Controles_Qualite!$F$5"
Name QC_OK_Count: "_Controles_Qualite!$B$5"
Name QC_Warn_Count: "_Controles_Qualite!$D$5"
Name Raison_Sociale: "Paramètres!$B$4"
Name SBTi_Annee_Baseline: "Trajectoire_SBTi!$B$4"
Name SBTi_Baseline_S12: "Trajectoire_SBTi!$B$5"
Name SBTi_Baseline_S3: "Trajectoire_SBTi!$B$6"
Name SBTi_Horizon: "Trajectoire_SBTi!$B$10"
Name SBTi_Taux_S12: "Trajectoire_SBTi!$B$8"
Name SBTi_Taux_S3: "Trajectoire_SBTi!$B$9"
Name Scope1_1A: "Synthese_GES!$C$6"
Name Scope1_1B: "Synthese_GES!$C$7"
Name Scope1_1C: "Synthese_GES!$C$8"
Name Scope1_1D: "Synthese_GES!$C$9"
Name Scope1_Total: "Synthese_GES!$C$10"
Name Scope12_LB_Total: "Synthese_GES!$C$37"
Name Scope2_LB_Chaleur: "Synthese_GES!$C$14"
Name Scope2_LB_Elec: "Synthese_GES!$C$13"
Name Scope2_LB_Total: "Synthese_GES!$C$15"
Name Scope2_MB_Total: "Synthese_GES!$C$17"
Name Scope3_Cat1: "Synthese_GES!$C$20"
Name Scope3_Cat10: "Synthese_GES!$C$29"
Name Scope3_Cat11: "Synthese_GES!$C$30"
Name Scope3_Cat12: "Synthese_GES!$C$31"
Name Scope3_Cat13: "Synthese_GES!$C$32"
Name Scope3_Cat14: "Synthese_GES!$C$33"
Name Scope3_Cat15: "Synthese_GES!$C$34"
Name Scope3_Cat2: "Synthese_GES!$C$21"
Name Scope3_Cat3: "Synthese_GES!$C$22"
Name Scope3_Cat4: "Synthese_GES!$C$23"
Name Scope3_Cat5: "Synthese_GES!$C$24"

Sheet Couverture
B4: 🌍 CarbonCo
B5: Plateforme de Calcul Carbone & Reporting ESG
B6: BILAN D'ÉMISSIONS DE GAZ À EFFET DE SERRE
B7: Conforme GHG Protocol Corporate Standard | ISO 14064-1:2018 | ESRS E1 (CSRD)
B11: INFORMATIONS DE L'ENTREPRISE
B12: Raison sociale | C12: =IF(Paramètres!B4="","À compléter",Paramètres!B4)
B13: SIREN / SIRET | C13: =IF(Paramètres!B5="","À compléter",Paramètres!B5)
B14: Secteur d'activité | C14: =IF(Paramètres!B6="","À compléter",Paramètres!B6)
B15: Exercice de reporting | C15: =Paramètres!B8
B16: Année de reporting | C16: =Paramètres!B7
B17: Chiffre d'affaires (M€) | C17: =IF(Paramètres!B9=0,"À compléter",TEXT(Paramètres!B9/1000000,"#,##0.0"))
B18: Effectifs (ETP) | C18: =IF(Paramètres!B11=0,"À compléter",Paramètres!B11)
B19: Version du fichier | C19: =Paramètres!B74
B20: Date de génération | C20: =TODAY()
B21: Responsable BEGES | C21: À compléter
B22: Validé par | C22: À compléter
B26: ✅ GHG Protocol Corporate Standard (WRI/WBCSD 2004)
B27: ✅ ISO 14064-1:2018 — Quantification et déclaration des émissions de GES
B28: ✅ ESRS E1 (CSRD) — Delegated Regulation (EU) 2023/2772
B32: 📋 ACCÉDER AU SOMMAIRE →
B36: 🔒 Document confidentiel — Usage interne uniquement
B37: ="CarbonCo — BEGES v2.0 — Exercice "&Paramètres!B7&" — Mise à jour "&DAY(TODAY())&"/"&MONTH(TODAY())&"/"&YEAR(TODAY())

Sheet Sommaire
B4: SOMMAIRE — BILAN D'ÉMISSIONS DE GAZ À EFFET DE SERRE
B5: CarbonCo — Outil de calcul carbone | Cliquez sur le nom d'un onglet pour y accéder directement
C7: Onglet | D7: Description | E7: Catégorie | F7: Statut
B8: NAVIGATION & CONFIGURATION
B9: 🏠 | C9: Couverture | D9: Page de garde — Informations entreprise & conformité | E9: Navigation | F9: ⬜ À remplir
B10: 📋 | C10: Guide | D10: Mode d'emploi, ordre de remplissage, légende, références | E10: Navigation | F10: ⬜ À remplir
B11: 📖 | C11: Notes_Methodologiques | D11: Sources données, hypothèses, exclusions, changements méthodo | E11: Documentation | F11: À compléter
B12: ⚙️ | C12: Paramètres | D12: Configuration entreprise, périmètre, méthodologie, versioning | E12: Configuration | F12: ⬜ À remplir
B14: COLLECTE DES DONNÉES
B15: 📘 | C15: Facteurs_Emission | D15: Base de facteurs d'émission ADEME Base Carbone v23.1 | E15: Référentiel | F15: ⬜ À remplir
B16: 🔥 | C16: Scope_1 | D16: Émissions directes : combustion fixe, mobile, process, fugitives | E16: Émissions | F16: ⬜ À remplir
B17: ⚡ | C17: Scope_2 | D17: Électricité, chaleur, vapeur (location-based & market-based) | E17: Émissions | F17: ⬜ À remplir
B18: 🌍 | C18: Scope_3 | D18: Chaîne de valeur — 15 catégories GHG Protocol | E18: Émissions | F18: ⬜ À remplir
B19: 💡 | C19: Energie | D19: Mix énergétique annuel — conformité ESRS E1-5 | E19: Collecte | F19: ⬜ À remplir
B20: 🚗 | C20: Transport | D20: Déplacements professionnels & domicile-travail | E20: Collecte | F20: ⬜ À remplir
B21: 📦 | C21: Matieres_Premieres | D21: Achats de matières premières et intrants — Scope 3 Cat.1 | E21: Collecte | F21: ⬜ À remplir
B22: ♻️ | C22: Dechets | D22: Production de déchets par filière et mode de traitement | E22: Collecte | F22: ⬜ À remplir
B23: 💧 | C23: Eau | D23: Consommations d'eau et rejets | E23: Collecte | F23: ⬜ À remplir
B25: RÉSULTATS & ANALYSE
B26: 📊 | C26: Synthese_GES | D26: Bilan consolidé BEGES — Scope 1+2+3 — Conformité Art. L229-25 | E26: Résultats | F26: ⬜ À remplir
B27: 📈 | C27: Intensite_Carbone | D27: Ratios d'intensité carbone — benchmarking ESRS E1 | E27: Résultats | F27: ⬜ À remplir
B28: 🎯 | C28: Trajectoire_SBTi | D28: Trajectoire de réduction SBTi 1.5°C — Scope 1+2 et Scope 3 | E28: Résultats | F28: ⬜ À remplir
B30: CONFORMITÉ RÉGLEMENTAIRE
B31: 🌐 | C31: CBAM | D31: Mécanisme d'ajustement carbone aux frontières (UE) 2023/956 | E31: Conformité | F31: ⬜ À remplir
B32: 🌿 | C32: Taxonomie | D32: Alignement Taxonomie verte UE — KPIs CA/CapEx/OpEx | E32: Conformité | F32: ⬜ À remplir
B33: 📝 | C33: ESRS_E1 | D33: Data points ESRS E1 — Delegated Reg. (EU) 2023/2772 | E33: Conformité | F33: ⬜ À remplir
B34: 📐 | C34: Incertitudes | D34: Propagation d'incertitude ISO 14064-1 §9.2 — Audit raisonnable | E34: Conformité | F34: ⬜ À remplir
B35: 🗺️ | C35: Plan_Transition | D35: Plan de transition ESRS E1-1 — Leviers, budget, risques TCFD | E35: Conformité | F35: ⬜ À remplir
B36: 📅 | C36: Historique_5ans | D36: Comparabilité 5 ans — ESRS E1-6 §48 — Rebasement | E36: Conformité | F36: ⬜ À remplir
B37: 🔍 | C37: _Controles_Qualite | D37: 30 contrôles automatiques — Audit readiness CSRD | E37: Conformité | F37: =_Controles_Qualite!B5&"✓ "&_Controles_Qualite!D5&"⚠ "&_Controles_Qualite!F5&"✗"
B39: DASHBOARD
B40: 🖥️ | C40: Dashboard | D40: Tableau de bord synthétique — KPIs, graphiques | E40: Dashboard | F40: ⬜ À remplir
B43: ="Dernière mise à jour : "&DAY(TODAY())&"/"&MONTH(TODAY())&"/"&YEAR(TODAY())&" | Exercice "&Paramètres!B7

Sheet Guide
A1: GUIDE D'UTILISATION — OUTIL DE CALCUL CARBONE CarbonCo v2.0 | N1: 🏠 Sommaire | O1: 📄 Couverture
A3: PRÉSENTATION DE L'OUTIL
A4: Cet outil permet de réaliser le bilan d'émissions de gaz à effet de serre (BEGES) d'une entreprise conformément au GHG Protocol Corporate Standard, à la norme ISO 14064-1:2018, et aux exigences de reporting ESRS E1 dans le cadre de la directive CSRD. Il couvre les Scopes 1, 2 et 3, la trajectoire SBTi, le mécanisme CBAM et l'alignement à la Taxonomie verte européenne.
A5: ⚠️ AVERTISSEMENT : Les facteurs d'émission sont issus de la Base Carbone ADEME v23.1 et du GIEC AR6. Ils sont fournis à titre indicatif. Pour un bilan officiel (BEGES réglementaire, rapport CSRD audité), l'utilisateur doit vérifier l'applicabilité des FE à sa situation spécifique. Dernière mise à jour des FE : mars 2026.
A9: ORDRE DE REMPLISSAGE RECOMMANDÉ
A10: Étape | B10: Onglet | C10: Action | D10: Prérequis
A11: 1 | B11: Paramètres | C11: Configurer l'entreprise : raison sociale, effectifs, CA, bilan, périmètre | D11: Aucun
A12: 2 | B12: Scope_1 | C12: Saisir les émissions directes : combustion fixe, mobile, process, fugitives | D12: Paramètres rempli
A13: 3 | B13: Scope_2 | C13: Saisir la consommation d'électricité, chaleur, vapeur par site et pays | D13: Paramètres rempli
A14: 4 | B14: Energie | C14: Détailler le mix énergétique annuel (ventilation ESRS E1-5) | D14: Scope 1 et 2
A15: 5 | B15: Transport | C15: Détailler les déplacements pro et domicile-travail | D15: Paramètres
A16: 6 | B16: Matieres_Premieres | C16: Saisir les achats de matériaux et intrants | D16: Paramètres
A17: 7 | B17: Dechets | C17: Saisir la production de déchets par filière | D17: Aucun
A18: 8 | B18: Eau | C18: Saisir les consommations d'eau et rejets | D18: Aucun
A19: 9 | B19: Scope_3 | C19: Consolider les 15 catégories (certaines auto-alimentées) | D19: Étapes 2-8
A20: 10 | B20: Synthese_GES | C20: Vérifier le bilan consolidé (automatique) | D20: Étapes 2-9
A21: 11 | B21: Trajectoire_SBTi | C21: Paramétrer et suivre la trajectoire de réduction | D21: Synthèse
A22: 12 | B22: CBAM / Taxonomie / ESRS_E1 | C22: Compléter selon obligations | D22: Synthèse
A24: LÉGENDE DES COULEURS
B25: Cellule sur fond gris clair | C25: Cellule de SAISIE utilisateur
B26: Texte en bleu italique | C26: Valeur CALCULÉE automatiquement (ne pas modifier)
B27: Fond vert clair | C27: Ligne de TOTAL ou sous-total
B28: Fond orange | C28: En-tête de SECTION
B29: Fond rouge clair | C29: Alerte ou valeur hors norme
A32: NIVEAUX DE QUALITÉ DES DONNÉES D'ACTIVITÉ (ISO 14064-1:2018 §9.2)
A33: Niveau | B33: Source de données | C33: Incertitude typique | D33: Exemple
A34: 1 | B34: Mesure directe (compteur dédié) | C34: ±2 à 5% | D34: Compteur gaz, sous-compteur électrique
A35: 2 | B35: Factures fournisseurs | C35: ±5 à 10% | D35: Facture électricité, relevé fioul
A36: 3 | B36: Estimation activité × FE moyen | C36: ±10 à 30% | D36: km estimés × FE/km
A37: 4 | B37: Données monétaires × FE/€ | C37: ±30 à 80% | D37: k€ achats × kgCO2e/k€ sectoriel
A38: 5 | B38: Extrapolation / benchmark sectoriel | C38: ±50 à 100% | D38: Moyenne nationale du secteur
A41: NOTE MÉTHODOLOGIQUE : SCOPE 1 vs ÉMISSIONS AMONT
A42: Conformément au GHG Protocol Corporate Standard (Chapter 4), le Scope 1 ne comptabilise QUE les émissions de COMBUSTION (émissions directes). Les émissions liées à l'EXTRACTION, au RAFFINAGE et au TRANSPORT du combustible jusqu'au site sont des émissions AMONT et relèvent du Scope 3, Catégorie 3.
A43: Exemple : Gaz naturel — FE total = 0,227 kgCO2e/kWh = Combustion (0,205) + Amont (0,022). Seul 0,205 est comptabilisé en Scope 1. Le 0,022 est automatiquement affecté au Scope 3 Cat. 3.
A50: RÉFÉRENCES RÉGLEMENTAIRES ET MÉTHODOLOGIQUES
B51: GHG Protocol Corporate Accounting and Reporting Standard | C51: WRI/WBCSD, 2004 (rev. 2015) | D51: ghgprotocol.org
B52: GHG Protocol Scope 2 Guidance | C52: WRI/WBCSD, 2015 | D52: Méthode LB + MB
B53: GHG Protocol Corporate Value Chain (Scope 3) Standard | C53: WRI/WBCSD, 2011 | D53: 15 catégories
B54: ISO 14064-1:2018 | C54: Spécification avec lignes directrices | D54: Quantification GES
B55: IPCC AR6 WG1, Chapter 7, Table 7.15 | C55: GIEC, 2021 | D55: PRG 100 ans
B56: ADEME Base Carbone v23.1 | C56: base-empreinte.ademe.fr | D56: Facteurs d'émission FR
B57: ESRS E1 — Changement climatique | C57: Delegated Regulation (EU) 2023/2772 | D57: Data points E1-1 à E1-9
B58: SBTi Corporate Net-Zero Standard v1.1 | C58: Science Based Targets, 2023 | D58: Trajectoires 1.5°C
B59: Règlement CBAM (UE) 2023/956 | C59: Parlement européen et Conseil | D59: Mécanisme carbone frontières
B60: Règlement Taxonomie (UE) 2020/852 | C60: 6 objectifs environnementaux | D60: KPIs CA/CapEx/OpEx
B61: Art. L229-25 Code de l'environnement | C61: BEGES réglementaire France | D61: Seuil 500 salariés
B62: Directive CSRD 2022/2464 + Omnibus COM(2025) 80 | C62: Reporting de durabilité | D62: Seuils et obligations
A64: NOTE : SCOPE 2 LOCATION-BASED vs MARKET-BASED
A65: Le GHG Protocol Scope 2 Guidance (2015) exige le double reporting : Location-based (FE du réseau physique) ET Market-based (FE des instruments contractuels). En l'absence de Garanties d'Origine (GO) ou de PPA, le Market-based utilise le 'mix résiduel' (residual mix) du pays.
A67: NOTE : FORÇAGE RADIATIF AVIATION
A68: Les FE aviation incluent un multiplicateur de forçage radiatif (RF) de ~1.9x conformément aux recommandations ADEME/DGAC et à la littérature scientifique (Lee et al., 2021). Ce multiplicateur couvre les effets non-CO2 (traînées de condensation, NOx, cirrus).
A70: NOTE : CARBONE BIOGÉNIQUE
A71: Conformément à l'ISO 14064-1:2018 §5.2.4, les émissions de CO2 biogénique sont comptabilisées SÉPARÉMENT. Le FE 'Bois bûches' (FE008) ne comptabilise que les émissions amont.
A74: QUESTIONS FRÉQUENTES (FAQ)
A75: Q1 | B75: Faut-il inclure les émissions d'un site en location ?
A76: → | B76: Oui, si vous avez le contrôle opérationnel du site (vous gérez les équipements, la consommation d'énergie). Les émissions de combustion sur site = Scope 1. L'électricité = Scope 2. Le chauffage collectif fourni par le bailleur = Scope 3 Cat.8 (actifs loués en amont). Réf. : GHG Protocol Corporate Standard, Chap. 3 + ADEME Guide Méthode pour les entreprises.
A78: Q2 | B78: Comment traiter un véhicule en leasing ou location longue durée ?
A79: → | B79: Leasing long terme (LOA, LLD > 12 mois avec contrôle opérationnel) → Scope 1 (carburant consommé par le véhicule). Location courte durée ponctuelle (voiture de location) → Scope 3 Cat.6 (déplacements professionnels). Règle clé : qui contrôle l'usage quotidien du véhicule ? Réf. : GHG Protocol Corporate Standard §4.2 / FAQ ADEME
A81: Q3 | B81: Les émissions d'un datacenter externalisé sont-elles du Scope 2 ?
A82: → | B82: Non — c'est du Scope 3 Cat.1 (achat de service). Seule l'électricité consommée sur VOS propres sites est du Scope 2. Exception : si vous louez une cage dans un datacenter avec compteur dédié à votre nom → peut être Scope 2. Réf. : GHG Protocol Scope 3 Standard, Catégorie 1 §4.1
A84: Q4 | B84: Doit-on déclarer les émissions des salariés en télétravail ?
A85: → | B85: Oui, dans les Scope 3 Cat.7 (domicile-travail) : les émissions chauffage/électricité du domicile liées au télétravail doivent être estimées. En pratique, elles sont souvent faibles vs. les trajets évités. Méthode ADEME : heures télétravaill × surface bureau × FE chauffage résidentiel. Réf. : ADEME 'Évaluation de l'empreinte carbone du télétravail' (2024)
A87: Q5 | B87: Pourquoi mon Scope 2 Market-based est différent du Location-based ?
A88: → | B88: Le LB utilise le FE moyen du réseau électrique national (ex. France : ~60 gCO2/kWh). Le MB utilise le FE spécifique à vos contrats (PPA, GO, tarif vert). Si vous avez des GO d'ENR : MB peut approcher 0. Sans GO : MB utilise le 'mix résiduel' (= réseau moins la part déjà certifiée), souvent > LB. Réf. : GHG Protocol Scope 2 Guidance (2015)
A90: Q6 | B90: Le Scope 3 Cat.1 est trop compliqué — puis-je l'estimer grossièrement ?
A91: → | B91: Oui, mais avec obligation de transparence sur la méthode. 3 options par ordre de précision croissante : 1) Spend-based : k€ achats × FE/k€ par secteur ADEME → incertitude ±50-80% 2) Activité x FE moyen : tonnes matière × FE ADEME → incertitude ±30-50% 3) Données primaires fournisseurs : données déclarées SBTi → incertitude ±10-20% CSRD exige de progresser vers les données primaires pour les fournisseurs significatifs. Réf. : GHG Protocol S3 Cat.1 Guidance + ADEME Guide Cat.1
... A109: → | B109: NON. Les émissions évitées ne peuvent jamais être soustraites du bilan GES selon le GHG Protocol et l'ISO 14064-1. Elles sont reportées séparément 'hors bilan' pour valorisation commerciale. Exemple : si vous vendez de l'électricité PV — les émissions évitées chez vos clients sont à part, pas à déduire de votre Scope 1+2+3. Réf. : GHG Protocol Corporate Standard §2.1 / ISO 14064-1 §5.2.4

Sheet Notes_Methodologiques
A1: NOTES MÉTHODOLOGIQUES — ESRS 2 BP-2 / ISO 14064-1:2018 §5 | K1: 🏠 Sommaire
A2: Documentation méthodologique obligatoire (ESRS 2 BP-2 §27-33 + ISO 14064-1:2018 §5.2). À compléter et à annexer au rapport CSRD ou BEGES.
A4: SECTION 1 — PÉRIMÈTRE ORGANISATIONNEL
A5: 1a. Entités incluses dans le périmètre de consolidation
A6: # | B6: Raison sociale / Entité | C6: SIREN | D6: Forme juridique | E6: % Capital | F6: % Contrôle opérationnel | G6: Méthode consolidation | H6: Incluse (O/N) | I6: Motif exclusion | J6: Note
A7: 1 | B7: =Paramètres!B4 | G7: =Paramètres!B17 | H7: Oui
A8: 2
A9: 3
A10: 4
A11: 5
A13: 1b. Évolution du périmètre vs exercice précédent
A14: Description des acquisitions, cessions, ou changements de périmètre affectant la comparabilité :
A15: (Saisir ici le récit des changements de périmètre — ex. 'Acquisition de filiale XYZ en mars 2025 : +120 ETP, +15% émissions S3 Cat.1')
A19: SECTION 2 — SOURCES DE DONNÉES PAR SCOPE
A20: Scope/Cat. | B20: Donnée d'activité | C20: Source du document | D20: Système / Outil | E20: Responsable | F20: Fréquence collecte | G20: Niveau qualité (1-5) | H20: Incertitude DA (%) | I20: Incertitude FE (%) | J20: Commentaire
A21: Scope 1 1A Combustion | B21: Consommation gaz naturel (kWh) | C21: Factures fournisseur gaz | D21: Compteur client / ERP | F21: Annuelle | G21: 2 | H21: 0.05 | I21: 0.08
A22: Scope 1 1B Mobile | B22: Carburant véhicules (L) | C22: Relevés cartes carburant | D22: Fleet management / ERP | F22: Mensuelle | G22: 2 | H22: 0.05 | I22: 0.05
A23: Scope 1 1D Fugitives | B23: Recharges fluides frigorigènes (kg) | C23: Bons d'intervention clim. | D23: GMAO / papier | F23: Annuelle | G23: 3 | H23: 0.2 | I23: 0.1
A24: Scope 2 LB | B24: Consommation électricité (kWh) | C24: Factures fournisseur élec. | D24: Smart meter / ERP | F24: Mensuelle | G24: 2 | H24: 0.03 | I24: 0.1 | J24: FE RTE réseau 2023
A25: Scope 2 MB | B25: Garanties d'Origine (GO) | C25: Certificats GO fournisseur | D25: Contrat PPA / GO | F25: Annuelle | G25: 2 | H25: 0.03 | I25: 0.05 | J25: Si pas de GO : mix résiduel AIB
A26: Scope 3 Cat.1 | B26: Montant achats par catégorie (€) | C26: Export ERP Achats | D26: SAP / Sage / ERP | F26: Annuelle | G26: 4 | H26: 0.2 | I26: 0.3 | J26: Méthode spend-based par défaut
A27: Scope 3 Cat.6 | B27: Km aériens + distance terres (km) | C27: Outil note de frais | D27: Concur / Notilus | F27: Annuelle | G27: 2 | H27: 0.05 | I27: 0.05 | J27: RF aviation ×1.9 inclus
A28: Scope 3 Cat.7 | B28: Mode + distance dom.-travail (km) | C28: Enquête mobilité interne | D28: Excel / SurveyMonkey | F28: Bi-annuelle | G28: 3 | H28: 0.15 | I28: 0.05 | J28: Hypothèse : 220 j/an
A30: SECTION 3 — HYPOTHÈSES CLÉS ET CONVENTIONS DE CALCUL
A31: Hypothèse / Convention | B31: Valeur retenue | C31: Source / Justification | D31: Impact si variation | E31: Validée par
A32: Jours ouvrés annuels | B32: 218 j/an | C32: Convention légale France (RTT inclus) | D32: ±5% sur Cat.7
A33: Distance dom.-travail moyenne | B33: 15 km (A/R = 30 km) | C33: Enquête mobilité ou valeur nationale ADEME | D33: ±15% sur Cat.7
A34: Taux télétravail | B34: 0 | C34: Saisir le taux réel ou l'hypothèse retenue | D34: Impact Cat.7 direct
A35: Taux de remplissage véhicule | B35: 1.2 passagers/véhicule | C35: ADEME / enquête interne | D35: ±10% Cat.7
A36: Multiplicateur forçage radiatif aviation | B36: ×1.9 (RF factor) | C36: ADEME/DGAC, Lee et al. 2021 | D36: Quasi-doublement GES avion
A37: CO2 biogénique | B37: Non inclus dans le bilan | C37: ISO 14064-1 §5.2.4 — comptabilisé séparément | D37: Hors total tCO2e
A38: FE électricité réseau FR | B38: 0.0599 kgCO2e/kWh (2023) | C38: ADEME Base Carbone v23.1 — code FE21 | D38: Variation annuelle ≈ ±5%
A39: FE gaz naturel (combustion) | B39: 0.205 kgCO2e/kWh PCS | C39: ADEME Base Carbone v23.1 — code FE45 | D39: Stable — FE fossile
A40: Mix résiduel AIB France | B40: 79 gCO2/kWh (2023) | C40: AIB European Residual Mix 2023 — publié juil. 2024 | D40: Pour Scope 2 Market-based
A41: Année de référence PRG | B41: GIEC AR6 2021 — PRG 100 ans | C41: Requis ESRS E1 §46 / GHG Protocol | D41: CH4 = 29.8 (vs 28 AR5)
A43: SECTION 4 — CHANGEMENTS MÉTHODOLOGIQUES ET CORRECTIONS
A44: Exercice | B44: Nature du changement | C44: Description narrative | D44: Impact quantitatif (tCO2e) | E44: Impact relatif (%) | F44: Rebasement effectué ? | G44: Validé par
A51: SECTION 5 — LIMITES, EXCLUSIONS ET ÉMISSIONS NON CALCULÉES
A52: Catégorie exclue | B52: Motif d'exclusion | C52: Estimation poids relatif (%) | D52: Plan d'intégration futur | E52: Réf. réglementaire
A53: Scope 3 Cat.15 (Investissements) | B53: Entreprise non-investisseur institutionnel | C53: < 1% | D53: N/A | E53: GHG Protocol S3 p.141
A54: Émissions CH4 / N2O process | B54: Non applicable — secteur tertiaire | C54: 0 | D54: N/A | E54: ISO 14064-1 §5.2.3
A55: Sites < 50 m² (surface totale exclue) | B55: Non significatif < 0.5% surface | C55: < 0.1% | D55: Intégrer si > 1% | E55: GHG Protocol §3.5
A56: Véhicules personnels en mission | B56: Données non collectées — remboursement km | D56: Enquête annuelle RH | E56: GHG Protocol S3 Cat.6

Sheet Paramètres
A1: PARAMÈTRES DE CONFIGURATION — BILAN CARBONE | N1: 🏠 Sommaire | O1: 📄 Couverture
A3: INFORMATIONS ENTREPRISE
A4: Raison sociale
A5: SIREN / SIRET
A6: Secteur d'activité
A7: Année de reporting
A8: Période
A9: Chiffre d'affaires net (€)
A10: Total du bilan (€)
A11: Effectifs (ETP)
A12: Surface occupée (m²)
A13: Nombre de sites
A14: CapEx total entreprise (€)
A15: OpEx éligible Taxonomie (€) | C15: (R&D + rénovation bâtiments + leases CT + maintenance)
A17: PÉRIMÈTRE ORGANISATIONNEL
A18: Méthode de consolidation | B18: Contrôle opérationnel
A19: Périmètre géographique | B19: France
A20: Scope 1 inclus | B20: Oui
A21: Scope 2 inclus | B21: Oui
A22: Scope 3 inclus | B22: Oui
A23: Part Scope 1 sous EU ETS (%) | B23: 0 | C23: Quotas gratuits (tCO2e) | D23: 0
A25: MÉTHODOLOGIE & RÉFÉRENCES
A26: Référentiel principal | B26: GHG Protocol Corporate Standard
A27: Norme ISO | B27: ISO 14064-1:2018
A28: Base de facteurs d'émission | B28: ADEME Base Carbone v23.1
A29: PRG utilisé | B29: GIEC AR6 (2021) — PRG 100 ans
A30: Gaz pris en compte | B30: CO2, CH4, N2O, HFC, PFC, SF6, NF3
A31: Unité de reporting | B31: tCO2e (tonnes CO2 équivalent)
A32: Méthode Scope 2 | B32: Location-based + Market-based
A33: Mix résiduel utilisé (MB) | B33: AIB European Residual Mix 2023
A35: POUVOIRS DE RÉCHAUFFEMENT GLOBAL (PRG 100 ans)
A36: Gaz | B36: Formule | C36: PRG 100 ans (AR6) | D36: PRG 100 ans (AR5)
A37: Dioxyde de carbone | B37: CO2 | C37: 1 | D37: 1
A38: Méthane (fossile) | B38: CH4 | C38: 29.8 | D38: 28
A39: Méthane (biogénique) | B39: CH4 bio | C39: 27 | D39: 28
A40: Protoxyde d'azote | B40: N2O | C40: 273 | D40: 265
A41: Hexafluorure de soufre | B41: SF6 | C41: 25200 | D41: 23500
A42: R-410A | B42: HFC | C42: 2088 | D42: 2088
A43: R-134a | B43: HFC-134a | C43: 1530 | D43: 1430
A45: SEUILS RÉGLEMENTAIRES
A46: BEGES obligatoire (France) | B46: > 500 salariés (privé) / > 250 (public)
A47: CSRD — Critères (2/3 requis) | B47: > 250 salariés ET (> 50M€ CA OU > 25M€ bilan)
A48: CSRD — Omnibus (proposition 2025) | B48: > 1000 salariés ET > 50M€ CA
A50: Soumis au BEGES | B50: =IF(B11>=500,"OUI","NON")
A51: Soumis à la CSRD | B51: =IF((IF(B11>=250,1,0)+IF(B9>=50000000,1,0)+IF(B10>=25000000,1,0))>=2,"OUI — Soumis CSRD","NON")
A52: Soumis CSRD post-Omnibus | B52: =IF(AND(B11>=1000,B9>=50000000),"OUI — Soumis post-Omnibus","NON — Reporting VSME volontaire recommandé")
A54: GESTION DE VERSION
A55: Version | B55: Date | C55: Auteur | D55: Modifications principales | E55: Validé par
A56: v2.0 | B56: 2026-03-27T18:49:03.458Z | D56: Création BEGES complet — GHG Protocol + ISO 14064-1 + ESRS E1
A64: Version courante (auto) | B64: {=IFERROR(INDEX(A56:A62,MATCH(TRUE,ISNUMBER(MATCH(A56:A62,A56:A62,0)),0)+COUNTIF(A56:A62,"v*")-1),A56)}
A66: GESTION DES VERSIONS
A67: Version | B67: Date | C67: Auteur | D67: Modifications principales | E67: Validé par
A68: v2.0 | B68: =TODAY() | C68: CarbonCo | D68: Création fichier v2.0 — Structure complète ESRS E1 / ISO 14064-1 / SBTi / CBAM / Taxonomie | E68: Direction RSE
A74: Version actuelle (pour couverture) : | B74: =A68

Sheet Facteurs_Emission
A1: BASE DE FACTEURS D'ÉMISSION — ADEME Base Carbone v23.1 / GIEC AR6 / AIB 2023 | N1: 🏠 Sommaire | O1: 🏠 Sommaire
A2: Les colonnes E (Combustion) et F (Amont) permettent de séparer correctement Scope 1 et Scope 3 Cat.3. La colonne G = E+F (total). La colonne H fournit le FE residual mix pour le Scope 2 market-based.
A3: ID | B3: Catégorie | C3: Poste d'émission | D3: Unité source | E3: FE Combustion (kgCO2e/u) [Scope 1] | F3: FE Amont (kgCO2e/u) [Scope 3 Cat.3] | G3: FE Total (kgCO2e/u) [E+F] | H3: FE Résiduel / Market-based | I3: Incertitude (%) | J3: Source | K3: Notes / Périmètre
A4: FE001 | B4: Combustibles | C4: Gaz naturel (PCI) | D4: kWh | E4: 0.205 | F4: 0.022 | G4: =E4+F4 | I4: 5 | J4: ADEME 2024 | K4: Combustion seule en Scope 1 ; amont en Scope 3 Cat.3
A5: FE002 | B5: Combustibles | C5: Gaz naturel (PCS) | D5: kWh | E5: 0.185 | F5: 0.02 | G5: =E5+F5 | I5: 5 | J5: ADEME 2024 | K5: PCS = PCI × 1.11
A6: FE003 | B6: Combustibles | C6: Fioul domestique | D6: litre | E6: 2.68 | F6: 0.57 | G6: =E6+F6 | I6: 5 | J6: ADEME 2024 | K6: 2,68 combustion + 0,57 amont
A7: FE004 | B7: Combustibles | C7: Fioul lourd | D7: tonne | E7: 3160 | F7: 365 | G7: =E7+F7 | I7: 5 | J7: ADEME 2024
A8: FE005 | B8: Combustibles | C8: Charbon (houille) | D8: tonne | E8: 2684 | F8: 276 | G8: =E8+F8 | I8: 10 | J8: ADEME 2024
A9: FE006 | B9: Combustibles | C9: GPL | D9: litre | E9: 1.49 | F9: 0.18 | G9: =E9+F9 | I9: 5 | J9: ADEME 2024
A10: FE007 | B10: Combustibles | C10: Propane | D10: kg | E10: 2.94 | F10: 0.5 | G10: =E10+F10 | I10: 5 | J10: ADEME 2024
A11: FE008 | B11: Combustibles | C11: Bois bûches | D11: kWh | E11: 0 | F11: 0.03 | G11: =E11+F11 | I11: 30 | J11: ADEME 2024 | K11: CO2 biogénique neutre (combustion=0). Amont seul
A12: FE010 | B12: Carburants | C12: Essence SP95/SP98 | D12: litre | E12: 2.28 | F12: 0.52 | G12: =E12+F12 | I12: 5 | J12: ADEME 2024 | K12: 2,28 combustion + 0,52 amont
A13: FE011 | B13: Carburants | C13: Diesel / Gazole | D13: litre | E13: 2.49 | F13: 0.68 | G13: =E13+F13 | I13: 5 | J13: ADEME 2024 | K13: 2,49 combustion + 0,68 amont
A14: FE012 | B14: Carburants | C14: E85 (Superéthanol) | D14: litre | E14: 1.11 | F14: 0.5 | G14: =E14+F14 | I14: 15 | J14: ADEME 2024 | K14: Part biogénique : CO2 combustion bio exclu
A15: FE013 | B15: Carburants | C15: B100 (Biodiesel pur) | D15: litre | E15: 0.22 | F15: 0.96 | G15: =E15+F15 | I15: 20 | J15: ADEME 2024 | K15: Combustion bio quasi nulle
A16: FE014 | B16: Carburants | C16: GNV (Gaz Naturel Véhicule) | D16: kg | E16: 2.63 | F16: 0.64 | G16: =E16+F16 | I16: 10 | J16: ADEME 2024
A17: FE015 | B17: Carburants | C17: Kérosène (aviation) | D17: litre | E17: 2.52 | F17: 0.63 | G17: =E17+F17 | I17: 5 | J17: ADEME 2024 | K17: Combustion seule
A18: FE016 | B18: Carburants | C18: Hydrogène gris (vaporeformage) | D18: kg | E18: 0 | F18: 11.5 | G18: =E18+F18 | I18: 15 | J18: ADEME 2024 | K18: Pas de combustion : tout en amont
A19: FE017 | B19: Carburants | C19: Hydrogène vert (électrolyse ENR) | D19: kg | E19: 0 | F19: 1 | G19: =E19+F19 | I19: 30 | J19: ADEME 2024
A20: FE020 | B20: Électricité | C20: Électricité France (location-based) | D20: kWh | G20: 0.0569 | H20: 0.06 | I20: 10 | J20: ADEME 2024 + AIB 2023 | K20: LB = mix moyen annuel FR 2023. MB résiduel = AIB
A21: FE021 | B21: Électricité | C21: Électricité France (amont T&D) | D21: kWh | H21: 0.0119 | I21: 10 | J21: ADEME 2024 | K21: Émissions amont production+T&D → Scope 3 Cat.3
A22: FE022 | B22: Électricité | C22: Électricité Allemagne | D22: kWh | G22: 0.385 | H22: 0.576 | I22: 10 | J22: AIE 2023 + AIB 2023 | K22: Mix résiduel DE supérieur au mix moyen
A23: FE023 | B23: Électricité | C23: Électricité Europe (UE27) | D23: kWh | G23: 0.267 | H23: 0.396 | I23: 15 | J23: AIE 2023 + AIB 2023 | K23: Moyenne UE27
A24: FE024 | B24: Électricité | C24: Électricité USA | D24: kWh | G24: 0.39 | H24: 0.39 | I24: 10 | J24: EPA eGRID 2023 | K24: Pas de residual mix officiel USA
A25: FE025 | B25: Électricité | C25: Électricité Chine | D25: kWh | G25: 0.555 | H25: 0.555 | I25: 10 | J25: AIE 2023
A26: FE026 | B26: Électricité | C26: Renouvelable certifiée (GO/PPA) | D26: kWh | G26: 0.006 | H26: 0.006 | I26: 50 | J26: ADEME 2024 | K26: Market-based avec GO ou PPA
A27: FE027 | B27: Électricité | C27: Réseau chaleur urbain (France moy.) | D27: kWh | G27: 0.112 | I27: 20 | J27: ADEME 2024
A28: FE028 | B28: Électricité | C28: Réseau de froid urbain | D28: kWh | G28: 0.032 | I28: 25 | J28: ADEME 2024
A29: FE029 | B29: Électricité | C29: Pertes T&D électricité France (%) | D29: % | G29: 0.075 | I29: 10 | J29: RTE 2023 | K29: Taux de pertes réseau T&D = 7,5%
A30: FE030 | B30: Transp. pers. | C30: Voiture thermique moy. FR (1 pass.) | D30: km | E30: 0.193 | F30: 0.025 | G30: =E30+F30 | I30: 15 | J30: ADEME 2024 | K30: Moyenne parc FR
A31: FE031 | B31: Transp. pers. | C31: Voiture diesel (1 passager) | D31: km | E31: 0.17 | F31: 0.023 | G31: =E31+F31 | I31: 10 | J31: ADEME 2024
A32: FE032 | B32: Transp. pers. | C32: Voiture essence (1 passager) | D32: km | E32: 0.199 | F32: 0.026 | G32: =E32+F32 | I32: 10 | J32: ADEME 2024
A33: FE033 | B33: Transp. pers. | C33: Voiture électrique (usage, France) | D33: km | E33: 0.02 | F33: 0.003 | G33: =E33+F33 | I33: 20 | J33: ADEME 2024 | K33: Usage uniquement (électricité)
A34: FE033b | B34: Transp. pers. | C34: Voiture électrique (fabrication amortie) | D34: km | E34: 0.035 | F34: 0.02 | G34: =E34+F34 | I34: 30 | J34: ADEME + IVL 2019 | K34: Fabrication amortie 200 000 km
A35: FE034 | B35: Transp. pers. | C35: Voiture hybride rechargeable | D35: km | E35: 0.09 | F35: 0.02 | G35: =E35+F35 | I35: 20 | J35: ADEME 2024 | K35: Usage mixte 50/50
A36: FE035 | B36: Transp. pers. | C36: TGV / Intercités | D36: km.passager | E36: 0.00174 | F36: 0 | G36: =E36+F36 | I36: 20 | J36: ADEME 2024 | K36: Électrique France
A37: FE036 | B37: Transp. pers. | C37: TER | D37: km.passager | E37: 0.0298 | F37: 0 | G37: =E37+F37 | I37: 20 | J37: ADEME 2024 | K37: Mix diesel+électrique
A38: FE037 | B38: Transp. pers. | C38: Métro / Tramway | D38: km.passager | E38: 0.00394 | F38: 0 | G38: =E38+F38 | I38: 20 | J38: ADEME 2024
A39: FE038 | B39: Transp. pers. | C39: Bus urbain (diesel) | D39: km.passager | E39: 0.113 | F39: 0 | G39: =E39+F39 | I39: 15 | J39: ADEME 2024
A40: FE039 | B40: Transp. pers. | C40: Avion court-courrier (<1000 km, éco) | D40: km.passager | E40: 0.141 | F40: 0 | G40: =E40+F40 | I40: 15 | J40: ADEME 2024 | K40: CO2 seul = 0.141
A41: FE039_RF | B41: Transp. pers. | C41: Avion CC avec forçage radiatif | D41: km.passager | E41: 0.258 | F41: 0 | G41: =E41+F41 | I41: 15 | J41: ADEME 2024 | K41: FE039 × 1.83 (RF)
A42: FE040 | B42: Transp. pers. | C42: Avion moyen-courrier (1000-3500 km, éco) | D42: km.passager | E42: 0.102 | F42: 0 | G42: =E42+F42 | I42: 15 | J42: ADEME 2024 | K42: CO2 seul
A43: FE040_RF | B43: Transp. pers. | C43: Avion MC avec forçage radiatif | D43: km.passager | E43: 0.187 | F43: 0 | G43: =E43+F43 | I43: 15 | J43: ADEME 2024
A44: FE041 | B44: Transp. pers. | C44: Avion long-courrier (>3500 km, éco) | D44: km.passager | E44: 0.083 | F44: 0 | G44: =E44+F44 | I44: 15 | J44: ADEME 2024 | K44: CO2 seul
A45: FE041_RF | B45: Transp. pers. | C45: Avion LC avec forçage radiatif | D45: km.passager | E45: 0.152 | F45: 0 | G45: =E45+F45 | I45: 15 | J45: ADEME 2024
A46: FE042 | B46: Transp. pers. | C46: Avion LC business class (avec RF) | D46: km.passager | E46: 0.456 | F46: 0 | G46: =E46+F46 | I46: 15 | J46: ADEME 2024 | K46: 3× éco
A47: FE050 | B47: Fret | C47: Camion articulé 40t (FR) | D47: t.km | E47: 0.081 | F47: 0 | G47: =E47+F47 | I47: 15 | J47: ADEME 2024 | K47: Diesel, taux chargement 70%
A48: FE051 | B48: Fret | C48: Camion porteur 19t | D48: t.km | E48: 0.153 | F48: 0 | G48: =E48+F48 | I48: 15 | J48: ADEME 2024
A49: FE052 | B49: Fret | C49: Utilitaire <3.5t | D49: t.km | E49: 0.459 | F49: 0 | G49: =E49+F49 | I49: 20 | J49: ADEME 2024
A50: FE053 | B50: Fret | C50: Train de fret (France) | D50: t.km | E50: 0.00535 | F50: 0 | G50: =E50+F50 | I50: 20 | J50: ADEME 2024
A51: FE054 | B51: Fret | C51: Fret maritime (conteneur) | D51: t.km | E51: 0.016 | F51: 0 | G51: =E51+F51 | I51: 20 | J51: ADEME 2024
A52: FE055 | B52: Fret | C52: Fret aérien | D52: t.km | E52: 1.41 | F52: 0 | G52: =E52+F52 | I52: 15 | J52: ADEME 2024
A53: FE056 | B53: Fret | C53: Fret fluvial | D53: t.km | E53: 0.0393 | F53: 0 | G53: =E53+F53 | I53: 20 | J53: ADEME 2024
A54: FE060 | B54: Matériaux | C54: Acier primaire (BOF, haut-fourneau) | D54: tonne | G54: 2300 | I54: 20 | J54: ADEME 2024 | K54: Scope 3 Cat.1
A55: FE061 | B55: Matériaux | C55: Acier recyclé (EAF, four à arc) | D55: tonne | G55: 600 | I55: 25 | J55: ADEME 2024
A56: FE062 | B56: Matériaux | C56: Aluminium primaire | D56: tonne | G56: 9200 | I56: 20 | J56: ADEME 2024 | K56: Électrolyse, mix mondial
A57: FE063 | B57: Matériaux | C57: Aluminium recyclé | D57: tonne | G57: 610 | I57: 25 | J57: ADEME 2024
A58: FE064 | B58: Matériaux | C58: Ciment Portland CEM I | D58: tonne | G58: 866 | I58: 15 | J58: ADEME 2024
A59: FE065 | B59: Matériaux | C59: Béton C25/30 | D59: m³ | G59: 235 | I59: 20 | J59: ADEME 2024
A60: FE066 | B60: Matériaux | C60: Verre plat | D60: tonne | G60: 1140 | I60: 20 | J60: ADEME 2024
A61: FE067 | B61: Matériaux | C61: Plastique PET vierge | D61: tonne | G61: 3360 | I61: 20 | J61: ADEME 2024
A62: FE068 | B62: Matériaux | C62: Plastique PET recyclé | D62: tonne | G62: 1680 | I62: 25 | J62: ADEME 2024
A63: FE069 | B63: Matériaux | C63: Papier/carton vierge | D63: tonne | G63: 919 | I63: 20 | J63: ADEME 2024
A64: FE070 | B64: Matériaux | C64: Papier/carton recyclé | D64: tonne | G64: 393 | I64: 25 | J64: ADEME 2024
A65: FE071 | B65: Matériaux | C65: Bois de construction | D65: m³ | G65: -717 | I65: 30 | J65: ADEME 2024 | K65: Négatif = stockage carbone biogénique
A66: FE072 | B66: Matériaux | C66: Cuivre | D66: tonne | G66: 4050 | I66: 20 | J66: ADEME 2024
A67: FE073 | B67: Matériaux | C67: Lithium-ion (batterie) | D67: kWh capacité | G67: 73 | I67: 30 | J67: ADEME 2024 | K67: kgCO2e par kWh de capacité
A68: FE080 | B68: Numérique | C68: Serveur rack (fabrication+usage, 1 an, FR) | D68: unité/an | G68: 700 | I68: 30 | J68: ADEME 2024 | K68: PUE 1.4, mix FR
A69: FE081 | B69: Numérique | C69: Ordinateur portable (fabrication) | D69: unité | G69: 300 | I69: 30 | J69: ADEME 2024 | K69: Amortir sur 4 ans
A70: FE082 | B70: Numérique | C70: Smartphone (fabrication) | D70: unité | G70: 56 | I70: 30 | J70: ADEME 2024 | K70: Amortir sur 3 ans
A71: FE083 | B71: Numérique | C71: Stockage cloud (data center FR) | D71: Go/an | G71: 0.01 | I71: 50 | J71: ADEME 2024 | K71: PUE 1.4
A72: FE084 | B72: Numérique | C72: Email sans pièce jointe | D72: unité | G72: 0.004 | I72: 50 | J72: ADEME 2024 | K72: Estimation
A73: FE085 | B73: Numérique | C73: Visioconférence (1h, webcam) | D73: heure | G73: 0.055 | I73: 50 | J73: ADEME 2024 | K73: Réseau FR
A74: FE086 | B74: Numérique | C74: Requête IA / LLM (type GPT-4) | D74: requête | G74: 0.007 | I74: 50 | J74: IEA 2025 | K74: ~10× une recherche Google
A75: FE090 | B75: Déchets | C75: Enfouissement ISDND (DMA) | D75: tonne | G75: 469 | I75: 30 | J75: ADEME 2024 | K75: Déchets ménagers et assimilés
A76: FE091 | B76: Déchets | C76: Incinération avec récup. énergie (UIOM) | D76: tonne | G76: 39 | I76: 30 | J76: ADEME 2024 | K76: Avec valorisation énergétique
A77: FE092 | B77: Déchets | C77: Recyclage (process de traitement) | D77: tonne | G77: 85 | I77: 30 | J77: ADEME 2024 | K77: ⚠️ Émissions du PROCESS uniquement
A78: FE092b | B78: Déchets | C78: Recyclage (émissions ÉVITÉES — hors bilan) | D78: tonne | G78: -270 | I78: 40 | J78: ADEME 2024 | K78: À reporter SÉPARÉMENT
A79: FE093 | B79: Déchets | C79: Compostage (biodéchets) | D79: tonne | G79: 44 | I79: 30 | J79: ADEME 2024
A80: FE094 | B80: Déchets | C80: Méthanisation (avec valorisation biogaz) | D80: tonne | G80: 15 | I80: 40 | J80: ADEME 2024 | K80: Émissions nettes
A81: FE095 | B81: Déchets | C81: DEEE (déchets électroniques) | D81: tonne | G81: 165 | I81: 40 | J81: ADEME 2024
A82: FE100 | B82: Eau | C82: Eau potable (production + distribution) | D82: m³ | G82: 0.132 | I82: 30 | J82: ADEME 2024 | K82: Moyenne France
A83: FE101 | B83: Eau | C83: Traitement eaux usées (STEP) | D83: m³ | G83: 0.248 | I83: 30 | J83: ADEME 2024 | K83: Station d'épuration moyenne
A84: FE110 | B84: Alimentation | C84: Repas avec bœuf (150g) | D84: repas | G84: 6.29 | I84: 30 | J84: ADEME 2024 | K84: Restauration collective
A85: FE111 | B85: Alimentation | C85: Repas avec poulet (150g) | D85: repas | G85: 1.58 | I85: 30 | J85: ADEME 2024
A86: FE112 | B86: Alimentation | C86: Repas végétarien | D86: repas | G86: 0.51 | I86: 30 | J86: ADEME 2024 | K86: Sans viande ni poisson
A87: FE113 | B87: Alimentation | C87: Repas végan | D87: repas | G87: 0.39 | I87: 30 | J87: ADEME 2024
A88: FE120 | B88: Immobilier | C88: Construction neuve bureau | D88: m² | G88: 450 | I88: 30 | J88: ADEME 2024 | K88: Amortir sur 50 ans
A89: FE121 | B89: Immobilier | C89: Rénovation lourde | D89: m² | G89: 150 | I89: 30 | J89: ADEME 2024
A90: FE130 | B90: Frigorigènes | C90: R-410A (fuite) | D90: kg | E90: 2088 | F90: 0 | G90: =E90+F90 | I90: 10 | J90: GIEC AR6 | K90: PRG 100 ans AR6. Scope 1
A91: FE131 | B91: Frigorigènes | C91: R-134a (fuite) | D91: kg | E91: 1530 | F91: 0 | G91: =E91+F91 | I91: 10 | J91: GIEC AR6
A92: FE132 | B92: Frigorigènes | C92: R-32 (fuite) | D92: kg | E92: 675 | F92: 0 | G92: =E92+F92 | I92: 10 | J92: GIEC AR6
A93: FE133 | B93: Frigorigènes | C93: R-290 Propane (fuite) | D93: kg | E93: 0.072 | F93: 0 | G93: =E93+F93 | I93: 10 | J93: GIEC AR6 | K93: Frigorigène naturel
A94: FE134 | B94: Frigorigènes | C94: CO2 / R-744 (fuite) | D94: kg | E94: 1 | F94: 0 | G94: =E94+F94 | I94: 5 | J94: GIEC AR6
A95: FEM01 | B95: Monétaire | C95: Services informatiques et télécom | D95: k€ | G95: 70 | I95: 60 | J95: ADEME/Exiobase | K95: kgCO2e par k€ HT
A96: FEM02 | B96: Monétaire | C96: Services de conseil et ingénierie | D96: k€ | G96: 30 | I96: 60 | J96: ADEME/Exiobase
A97: FEM03 | B97: Monétaire | C97: Services financiers et assurance | D97: k€ | G97: 25 | I97: 60 | J97: ADEME/Exiobase
A98: FEM04 | B98: Monétaire | C98: Services de nettoyage | D98: k€ | G98: 85 | I98: 60 | J98: ADEME/Exiobase
A99: FEM05 | B99: Monétaire | C99: Fournitures de bureau | D99: k€ | G99: 120 | I99: 50 | J99: ADEME/Exiobase
A100: FEM06 | B100: Monétaire | C100: Restauration collective | D100: k€ | G100: 180 | I100: 50 | J100: ADEME/Exiobase
...

Sheet Scope_1
A1: SCOPE 1 — ÉMISSIONS DIRECTES | N1: 🏠 Sommaire | O1: 🏠 Sommaire
A2: Conformément au GHG Protocol, seules les émissions de COMBUSTION sont comptabilisées en Scope 1. Les émissions AMONT sont en Scope 3 Cat. 3 et calculées automatiquement dans les colonnes J-K.
A4: 1A — COMBUSTION FIXE (chauffage, production de chaleur, cogénération)
A5: Ligne | B5: Source / Équipement / Site | C5: Combustible | D5: Quantité consommée | E5: Unité | F5: ID FE | G5: FE Combustion (kgCO2e/u) | H5: Émissions Scope 1 (kgCO2e) | I5: Émissions Scope 1 (tCO2e) | J5: FE Amont (kgCO2e/u) | K5: Émissions amont → Scope 3 Cat.3 (kgCO2e)
A6: 1 | D6: 0 | E6: =IF(C6="","",IF(OR(C6="Gaz naturel (PCI)",C6="Gaz naturel (PCS)"),"kWh",IF(OR(C6="Fioul domestique",C6="GPL"),"litre",IF(OR(C6="Fioul lourd",C6="Charbon (houille)"),"tonne",IF(C6="Propane","kg",IF(C6="Bois bûches","kWh","")))))) | F6: =IF(C6="","",IF(C6="Gaz naturel (PCI)","FE001",IF(C6="Gaz naturel (PCS)","FE002",IF(C6="Fioul domestique","FE003",IF(C6="Fioul lourd","FE004",IF(C6="Charbon (houille)","FE005",IF(C6="GPL","FE006",IF(C6="Propane","FE007",IF(C6="Bois bûches","FE008",""))))))))) | G6: =IF(F6="","",VLOOKUP(F6,Facteurs_Emission!$A$4:$E$108,5,FALSE())) | H6: =IF(OR(D6=0,G6=""),0,D6*G6) | I6: =H6/1000 | J6: =IF(F6="","",VLOOKUP(F6,Facteurs_Emission!$A$4:$F$108,6,FALSE())) | K6: =IF(OR(D6=0,J6=""),0,D6*J6)
A7: 2 | D7: 0 | E7: =IF(C7="","",IF(OR(C7="Gaz naturel (PCI)",C7="Gaz naturel (PCS)"),"kWh",IF(OR(C7="Fioul domestique",C7="GPL"),"litre",IF(OR(C7="Fioul lourd",C7="Charbon (houille)"),"tonne",IF(C7="Propane","kg",IF(C7="Bois bûches","kWh","")))))) | F7: =IF(C7="","",IF(C7="Gaz naturel (PCI)","FE001",IF(C7="Gaz naturel (PCS)","FE002",IF(C7="Fioul domestique","FE003",IF(C7="Fioul lourd","FE004",IF(C7="Charbon (houille)","FE005",IF(C7="GPL","FE006",IF(C7="Propane","FE007",IF(C7="Bois bûches","FE008",""))))))))) | G7: =IF(F7="","",VLOOKUP(F7,Facteurs_Emission!$A$4:$E$108,5,FALSE())) | H7: =IF(OR(D7=0,G7=""),0,D7*G7) | I7: =H7/1000 | J7: =IF(F7="","",VLOOKUP(F7,Facteurs_Emission!$A$4:$F$108,6,FALSE())) | K7: =IF(OR(D7=0,J7=""),0,D7*J7)
A8: 3 | D8: 0 | E8: =IF(C8="","",IF(OR(C8="Gaz naturel (PCI)",C8="Gaz naturel (PCS)"),"kWh",IF(OR(C8="Fioul domestique",C8="GPL"),"litre",IF(OR(C8="Fioul lourd",C8="Charbon (houille)"),"tonne",IF(C8="Propane","kg",IF(C8="Bois bûches","kWh","")))))) | F8: =IF(C8="","",IF(C8="Gaz naturel (PCI)","FE001",IF(C8="Gaz naturel (PCS)","FE002",IF(C8="Fioul domestique","FE003",IF(C8="Fioul lourd","FE004",IF(C8="Charbon (houille)","FE005",IF(C8="GPL","FE006",IF(C8="Propane","FE007",IF(C8="Bois bûches","FE008",""))))))))) | G8: =IF(F8="","",VLOOKUP(F8,Facteurs_Emission!$A$4:$E$108,5,FALSE())) | H8: =IF(OR(D8=0,G8=""),0,D8*G8) | I8: =H8/1000 | J8: =IF(F8="","",VLOOKUP(F8,Facteurs_Emission!$A$4:$F$108,6,FALSE())) | K8: =IF(OR(D8=0,J8=""),0,D8*J8)
A9: 4 | D9: 0 | E9: =IF(C9="","",IF(OR(C9="Gaz naturel (PCI)",C9="Gaz naturel (PCS)"),"kWh",IF(OR(C9="Fioul domestique",C9="GPL"),"litre",IF(OR(C9="Fioul lourd",C9="Charbon (houille)"),"tonne",IF(C9="Propane","kg",IF(C9="Bois bûches","kWh","")))))) | F9: =IF(C9="","",IF(C9="Gaz naturel (PCI)","FE001",IF(C9="Gaz naturel (PCS)","FE002",IF(C9="Fioul domestique","FE003",IF(C9="Fioul lourd","FE004",IF(C9="Charbon (houille)","FE005",IF(C9="GPL","FE006",IF(C9="Propane","FE007",IF(C9="Bois bûches","FE008",""))))))))) | G9: =IF(F9="","",VLOOKUP(F9,Facteurs_Emission!$A$4:$E$108,5,FALSE())) | H9: =IF(OR(D9=0,G9=""),0,D9*G9) | I9: =H9/1000 | J9: =IF(F9="","",VLOOKUP(F9,Facteurs_Emission!$A$4:$F$108,6,FALSE())) | K9: =IF(OR(D9=0,J9=""),0,D9*J9)
A10: 5 | D10: 0 | E10: =IF(C10="","",IF(OR(C10="Gaz naturel (PCI)",C10="Gaz naturel (PCS)"),"kWh",IF(OR(C10="Fioul domestique",C10="GPL"),"litre",IF(OR(C10="Fioul lourd",C10="Charbon (houille)"),"tonne",IF(C10="Propane","kg",IF(C10="Bois bûches","kWh","")))))) | F10: =IF(C10="","",IF(C10="Gaz naturel (PCI)","FE001",IF(C10="Gaz naturel (PCS)","FE002",IF(C10="Fioul domestique","FE003",IF(C10="Fioul lourd","FE004",IF(C10="Charbon (houille)","FE005",IF(C10="GPL","FE006",IF(C10="Propane","FE007",IF(C10="Bois bûches","FE008",""))))))))) | G10: =IF(F10="","",VLOOKUP(F10,Facteurs_Emission!$A$4:$E$108,5,FALSE())) | H10: =IF(OR(D10=0,G10=""),0,D10*G10) | I10: =H10/1000 | J10: =IF(F10="","",VLOOKUP(F10,Facteurs_Emission!$A$4:$F$108,6,FALSE())) | K10: =IF(OR(D10=0,J10=""),0,D10*J10)
A11: 6 | D11: 0 | E11: =IF(C11="","",IF(OR(C11="Gaz naturel (PCI)",C11="Gaz naturel (PCS)"),"kWh",IF(OR(C11="Fioul domestique",C11="GPL"),"litre",IF(OR(C11="Fioul lourd",C11="Charbon (houille)"),"tonne",IF(C11="Propane","kg",IF(C11="Bois bûches","kWh","")))))) | F11: =IF(C11="","",IF(C11="Gaz naturel (PCI)","FE001",IF(C11="Gaz naturel (PCS)","FE002",IF(C11="Fioul domestique","FE003",IF(C11="Fioul lourd","FE004",IF(C11="Charbon (houille)","FE005",IF(C11="GPL","FE006",IF(C11="Propane","FE007",IF(C11="Bois bûches","FE008",""))))))))) | G11: =IF(F11="","",VLOOKUP(F11,Facteurs_Emission!$A$4:$E$108,5,FALSE())) | H11: =IF(OR(D11=0,G11=""),0,D11*G11) | I11: =H11/1000 | J11: =IF(F11="","",VLOOKUP(F11,Facteurs_Emission!$A$4:$F$108,6,FALSE())) | K11: =IF(OR(D11=0,J11=""),0,D11*J11)
A12: 7 | D12: 0 | E12: =IF(C12="","",IF(OR(C12="Gaz naturel (PCI)",C12="Gaz naturel (PCS)"),"kWh",IF(OR(C12="Fioul domestique",C12="GPL"),"litre",IF(OR(C12="Fioul lourd",C12="Charbon (houille)"),"tonne",IF(C12="Propane","kg",IF(C12="Bois bûches","kWh","")))))) | F12: =IF(C12="","",IF(C12="Gaz naturel (PCI)","FE001",IF(C12="Gaz naturel (PCS)","FE002",IF(C12="Fioul domestique","FE003",IF(C12="Fioul lourd","FE004",IF(C12="Charbon (houille)","FE005",IF(C12="GPL","FE006",IF(C12="Propane","FE007",IF(C12="Bois bûches","FE008",""))))))))) | G12: =IF(F12="","",VLOOKUP(F12,Facteurs_Emission!$A$4:$E$108,5,FALSE())) | H12: =IF(OR(D12=0,G12=""),0,D12*G12) | I12: =H12/1000 | J12: =IF(F12="","",VLOOKUP(F12,Facteurs_Emission!$A$4:$F$108,6,FALSE())) | K12: =IF(OR(D12=0,J12=""),0,D12*J12)
A13: 8 | D13: 0 | E13: =IF(C13="","",IF(OR(C13="Gaz naturel (PCI)",C13="Gaz naturel (PCS)"),"kWh",IF(OR(C13="Fioul domestique",C13="GPL"),"litre",IF(OR(C13="Fioul lourd",C13="Charbon (houille)"),"tonne",IF(C13="Propane","kg",IF(C13="Bois bûches","kWh","")))))) | F13: =IF(C13="","",IF(C13="Gaz naturel (PCI)","FE001",IF(C13="Gaz naturel (PCS)","FE002",IF(C13="Fioul domestique","FE003",IF(C13="Fioul lourd","FE004",IF(C13="Charbon (houille)","FE005",IF(C13="GPL","FE006",IF(C13="Propane","FE007",IF(C13="Bois bûches","FE008",""))))))))) | G13: =IF(F13="","",VLOOKUP(F13,Facteurs_Emission!$A$4:$E$108,5,FALSE())) | H13: =IF(OR(D13=0,G13=""),0,D13*G13) | I13: =H13/1000 | J13: =IF(F13="","",VLOOKUP(F13,Facteurs_Emission!$A$4:$F$108,6,FALSE())) | K13: =IF(OR(D13=0,J13=""),0,D13*J13)
A14: 9 | D14: 0 | E14: =IF(C14="","",IF(OR(C14="Gaz naturel (PCI)",C14="Gaz naturel (PCS)"),"kWh",IF(OR(C14="Fioul domestique",C14="GPL"),"litre",IF(OR(C14="Fioul lourd",C14="Charbon (houille)"),"tonne",IF(C14="Propane","kg",IF(C14="Bois bûches","kWh","")))))) | F14: =IF(C14="","",IF(C14="Gaz naturel (PCI)","FE001",IF(C14="Gaz naturel (PCS)","FE002",IF(C14="Fioul domestique","FE003",IF(C14="Fioul lourd","FE004",IF(C14="Charbon (houille)","FE005",IF(C14="GPL","FE006",IF(C14="Propane","FE007",IF(C14="Bois bûches","FE008",""))))))))) | G14: =IF(F14="","",VLOOKUP(F14,Facteurs_Emission!$A$4:$E$108,5,FALSE())) | H14: =IF(OR(D14=0,G14=""),0,D14*G14) | I14: =H14/1000 | J14: =IF(F14="","",VLOOKUP(F14,Facteurs_Emission!$A$4:$F$108,6,FALSE())) | K14: =IF(OR(D14=0,J14=""),0,D14*J14)
A15: 10 | D15: 0 | E15: =IF(C15="","",IF(OR(C15="Gaz naturel (PCI)",C15="Gaz naturel (PCS)"),"kWh",IF(OR(C15="Fioul domestique",C15="GPL"),"litre",IF(OR(C15="Fioul lourd",C15="Charbon (houille)"),"tonne",IF(C15="Propane","kg",IF(C15="Bois bûches","kWh","")))))) | F15: =IF(C15="","",IF(C15="Gaz naturel (PCI)","FE001",IF(C15="Gaz naturel (PCS)","FE002",IF(C15="Fioul domestique","FE003",IF(C15="Fioul lourd","FE004",IF(C15="Charbon (houille)","FE005",IF(C15="GPL","FE006",IF(C15="Propane","FE007",IF(C15="Bois bûches","FE008",""))))))))) | G15: =IF(F15="","",VLOOKUP(F15,Facteurs_Emission!$A$4:$E$108,5,FALSE())) | H15: =IF(OR(D15=0,G15=""),0,D15*G15) | I15: =H15/1000 | J15: =IF(F15="","",VLOOKUP(F15,Facteurs_Emission!$A$4:$F$108,6,FALSE())) | K15: =IF(OR(D15=0,J15=""),0,D15*J15)
B16: SOUS-TOTAL COMBUSTION FIXE | H16: =SUM(H6:H15) | I16: =SUM(I6:I15) | K16: =SUM(K6:K15)
A18: 1B — COMBUSTION MOBILE (véhicules détenus ou contrôlés par l'entreprise)
A19: Ligne | B19: Source / Équipement / Site | C19: Combustible | D19: Quantité consommée | E19: Unité | F19: ID FE | G19: FE Combustion (kgCO2e/u) | H19: Émissions Scope 1 (kgCO2e) | I19: Émissions Scope 1 (tCO2e) | J19: FE Amont (kgCO2e/u) | K19: Émissions amont → Scope 3 Cat.3 (kgCO2e)
A20: 1 | D20: 0 | E20: =IF(C20="","",IF(C20="GNV","kg","litre")) | F20: =IF(C20="","",IF(C20="Essence SP95/SP98","FE010",IF(C20="Diesel / Gazole","FE011",IF(C20="E85 (Superéthanol)","FE012",IF(C20="B100 (Biodiesel pur)","FE013",IF(C20="GNV","FE014","")))))) | G20: =IF(F20="","",VLOOKUP(F20,Facteurs_Emission!$A$4:$E$108,5,FALSE())) | H20: =IF(OR(D20=0,G20=""),0,D20*G20) | I20: =H20/1000 | J20: =IF(F20="","",VLOOKUP(F20,Facteurs_Emission!$A$4:$F$108,6,FALSE())) | K20: =IF(OR(D20=0,J20=""),0,D20*J20)
A21: 2 | D21: 0 | E21: =IF(C21="","",IF(C21="GNV","kg","litre")) | F21: =IF(C21="","",IF(C21="Essence SP95/SP98","FE010",IF(C21="Diesel / Gazole","FE011",IF(C21="E85 (Superéthanol)","FE012",IF(C21="B100 (Biodiesel pur)","FE013",IF(C21="GNV","FE014","")))))) | G21: =IF(F21="","",VLOOKUP(F21,Facteurs_Emission!$A$4:$E$108,5,FALSE())) | H21: =IF(OR(D21=0,G21=""),0,D21*G21) | I21: =H21/1000 | J21: =IF(F21="","",VLOOKUP(F21,Facteurs_Emission!$A$4:$F$108,6,FALSE())) | K21: =IF(OR(D21=0,J21=""),0,D21*J21)
A22: 3 | D22: 0 | E22: =IF(C22="","",IF(C22="GNV","kg","litre")) | F22: =IF(C22="","",IF(C22="Essence SP95/SP98","FE010",IF(C22="Diesel / Gazole","FE011",IF(C22="E85 (Superéthanol)","FE012",IF(C22="B100 (Biodiesel pur)","FE013",IF(C22="GNV","FE014","")))))) | G22: =IF(F22="","",VLOOKUP(F22,Facteurs_Emission!$A$4:$E$108,5,FALSE())) | H22: =IF(OR(D22=0,G22=""),0,D22*G22) | I22: =H22/1000 | J22: =IF(F22="","",VLOOKUP(F22,Facteurs_Emission!$A$4:$F$108,6,FALSE())) | K22: =IF(OR(D22=0,J22=""),0,D22*J22)
A23: 4 | D23: 0 | E23: =IF(C23="","",IF(C23="GNV","kg","litre")) | F23: =IF(C23="","",IF(C23="Essence SP95/SP98","FE010",IF(C23="Diesel / Gazole","FE011",IF(C23="E85 (Superéthanol)","FE012",IF(C23="B100 (Biodiesel pur)","FE013",IF(C23="GNV","FE014","")))))) | G23: =IF(F23="","",VLOOKUP(F23,Facteurs_Emission!$A$4:$E$108,5,FALSE())) | H23: =IF(OR(D23=0,G23=""),0,D23*G23) | I23: =H23/1000 | J23: =IF(F23="","",VLOOKUP(F23,Facteurs_Emission!$A$4:$F$108,6,FALSE())) | K23: =IF(OR(D23=0,J23=""),0,D23*J23)
A24: 5 | D24: 0 | E24: =IF(C24="","",IF(C24="GNV","kg","litre")) | F24: =IF(C24="","",IF(C24="Essence SP95/SP98","FE010",IF(C24="Diesel / Gazole","FE011",IF(C24="E85 (Superéthanol)","FE012",IF(C24="B100 (Biodiesel pur)","FE013",IF(C24="GNV","FE014","")))))) | G24: =IF(F24="","",VLOOKUP(F24,Facteurs_Emission!$A$4:$E$108,5,FALSE())) | H24: =IF(OR(D24=0,G24=""),0,D24*G24) | I24: =H24/1000 | J24: =IF(F24="","",VLOOKUP(F24,Facteurs_Emission!$A$4:$F$108,6,FALSE())) | K24: =IF(OR(D24=0,J24=""),0,D24*J24)
A25: 6 | D25: 0 | E25: =IF(C25="","",IF(C25="GNV","kg","litre")) | F25: =IF(C25="","",IF(C25="Essence SP95/SP98","FE010",IF(C25="Diesel / Gazole","FE011",IF(C25="E85 (Superéthanol)","FE012",IF(C25="B100 (Biodiesel pur)","FE013",IF(C25="GNV","FE014","")))))) | G25: =IF(F25="","",VLOOKUP(F25,Facteurs_Emission!$A$4:$E$108,5,FALSE())) | H25: =IF(OR(D25=0,G25=""),0,D25*G25) | I25: =H25/1000 | J25: =IF(F25="","",VLOOKUP(F25,Facteurs_Emission!$A$4:$F$108,6,FALSE())) | K25: =IF(OR(D25=0,J25=""),0,D25*J25)
A26: 7 | D26: 0 | E26: =IF(C26="","",IF(C26="GNV","kg","litre")) | F26: =IF(C26="","",IF(C26="Essence SP95/SP98","FE010",IF(C26="Diesel / Gazole","FE011",IF(C26="E85 (Superéthanol)","FE012",IF(C26="B100 (Biodiesel pur)","FE013",IF(C26="GNV","FE014","")))))) | G26: =IF(F26="","",VLOOKUP(F26,Facteurs_Emission!$A$4:$E$108,5,FALSE())) | H26: =IF(OR(D26=0,G26=""),0,D26*G26) | I26: =H26/1000 | J26: =IF(F26="","",VLOOKUP(F26,Facteurs_Emission!$A$4:$F$108,6,FALSE())) | K26: =IF(OR(D26=0,J26=""),0,D26*J26)
A27: 8 | D27: 0 | E27: =IF(C27="","",IF(C27="GNV","kg","litre")) | F27: =IF(C27="","",IF(C27="Essence SP95/SP98","FE010",IF(C27="Diesel / Gazole","FE011",IF(C27="E85 (Superéthanol)","FE012",IF(C27="B100 (Biodiesel pur)","FE013",IF(C27="GNV","FE014","")))))) | G27: =IF(F27="","",VLOOKUP(F27,Facteurs_Emission!$A$4:$E$108,5,FALSE())) | H27: =IF(OR(D27=0,G27=""),0,D27*G27) | I27: =H27/1000 | J27: =IF(F27="","",VLOOKUP(F27,Facteurs_Emission!$A$4:$F$108,6,FALSE())) | K27: =IF(OR(D27=0,J27=""),0,D27*J27)
A28: 9 | D28: 0 | E28: =IF(C28="","",IF(C28="GNV","kg","litre")) | F28: =IF(C28="","",IF(C28="Essence SP95/SP98","FE010",IF(C28="Diesel / Gazole","FE011",IF(C28="E85 (Superéthanol)","FE012",IF(C28="B100 (Biodiesel pur)","FE013",IF(C28="GNV","FE014","")))))) | G28: =IF(F28="","",VLOOKUP(F28,Facteurs_Emission!$A$4:$E$108,5,FALSE())) | H28: =IF(OR(D28=0,G28=""),0,D28*G28) | I28: =H28/1000 | J28: =IF(F28="","",VLOOKUP(F28,Facteurs_Emission!$A$4:$F$108,6,FALSE())) | K28: =IF(OR(D28=0,J28=""),0,D28*J28)
A29: 10 | D29: 0 | E29: =IF(C29="","",IF(C29="GNV","kg","litre")) | F29: =IF(C29="","",IF(C29="Essence SP95/SP98","FE010",IF(C29="Diesel / Gazole","FE011",IF(C29="E85 (Superéthanol)","FE012",IF(C29="B100 (Biodiesel pur)","FE013",IF(C29="GNV","FE014","")))))) | G29: =IF(F29="","",VLOOKUP(F29,Facteurs_Emission!$A$4:$E$108,5,FALSE())) | H29: =IF(OR(D29=0,G29=""),0,D29*G29) | I29: =H29/1000 | J29: =IF(F29="","",VLOOKUP(F29,Facteurs_Emission!$A$4:$F$108,6,FALSE())) | K29: =IF(OR(D29=0,J29=""),0,D29*J29)
B30: SOUS-TOTAL COMBUSTION MOBILE | H30: =SUM(H20:H29) | I30: =SUM(I20:I29) | K30: =SUM(K20:K29)
A32: 1C — ÉMISSIONS DE PROCESS (réactions chimiques, procédés industriels)
A33: Ligne | B33: Process / Source | C33: Gaz émis | D33: Quantité émise (kg) | E33: Unité | F33: PRG | H33: Émissions (kgCO2e) | I33: Émissions (tCO2e)
A34: 1 | D34: 0 | E34: kg | F34: =IF(C34="","",IF(C34="CO2",1,IF(C34="CH4 (fossile)",29.8,IF(C34="N2O",273,IF(C34="HFC (R-410A)",2088,IF(C34="SF6",25200,0)))))) | H34: =IF(OR(D34=0,F34=""),0,D34*F34) | I34: =IF(H34=0,0,H34/1000)
A35: 2 | D35: 0 | E35: kg | F35: =IF(C35="","",IF(C35="CO2",1,IF(C35="CH4 (fossile)",29.8,IF(C35="N2O",273,IF(C35="HFC (R-410A)",2088,IF(C35="SF6",25200,0)))))) | H35: =IF(OR(D35=0,F35=""),0,D35*F35) | I35: =IF(H35=0,0,H35/1000)
A36: 3 | D36: 0 | E36: kg | F36: =IF(C36="","",IF(C36="CO2",1,IF(C36="CH4 (fossile)",29.8,IF(C36="N2O",273,IF(C36="HFC (R-410A)",2088,IF(C36="SF6",25200,0)))))) | H36: =IF(OR(D36=0,F36=""),0,D36*F36) | I36: =IF(H36=0,0,H36/1000)
A37: 4 | D37: 0 | E37: kg | F37: =IF(C37="","",IF(C37="CO2",1,IF(C37="CH4 (fossile)",29.8,IF(C37="N2O",273,IF(C37="HFC (R-410A)",2088,IF(C37="SF6",25200,0)))))) | H37: =IF(OR(D37=0,F37=""),0,D37*F37) | I37: =IF(H37=0,0,H37/1000)
A38: 5 | D38: 0 | E38: kg | F38: =IF(C38="","",IF(C38="CO2",1,IF(C38="CH4 (fossile)",29.8,IF(C38="N2O",273,IF(C38="HFC (R-410A)",2088,IF(C38="SF6",25200,0)))))) | H38: =IF(OR(D38=0,F38=""),0,D38*F38) | I38: =IF(H38=0,0,H38/1000)
A39: 6 | D39: 0 | E39: kg | F39: =IF(C39="","",IF(C39="CO2",1,IF(C39="CH4 (fossile)",29.8,IF(C39="N2O",273,IF(C39="HFC (R-410A)",2088,IF(C39="SF6",25200,0)))))) | H39: =IF(OR(D39=0,F39=""),0,D39*F39) | I39: =IF(H39=0,0,H39/1000)
A40: 7 | D40: 0 | E40: kg | F40: =IF(C40="","",IF(C40="CO2",1,IF(C40="CH4 (fossile)",29.8,IF(C40="N2O",273,IF(C40="HFC (R-410A)",2088,IF(C40="SF6",25200,0)))))) | H40: =IF(OR(D40=0,F40=""),0,D40*F40) | I40: =IF(H40=0,0,H40/1000)
A41: 8 | D41: 0 | E41: kg | F41: =IF(C41="","",IF(C41="CO2",1,IF(C41="CH4 (fossile)",29.8,IF(C41="N2O",273,IF(C41="HFC (R-410A)",2088,IF(C41="SF6",25200,0)))))) | H41: =IF(OR(D41=0,F41=""),0,D41*F41) | I41: =IF(H41=0,0,H41/1000)
B42: SOUS-TOTAL PROCESS | H42: =SUM(H34:H41) | I42: =SUM(I34:I41)
A44: 1D — ÉMISSIONS FUGITIVES (fuites de fluides frigorigènes, fuites de gaz)
A45: Ligne | B45: Source / Équipement | C45: Fluide | D45: Quantité fuitée (kg) | E45: Unité | F45: ID FE | G45: FE (kgCO2e/kg) | H45: Émissions (kgCO2e) | I45: Émissions (tCO2e)
A46: 1 | D46: 0 | E46: kg | F46: =IF(C46="","",IF(C46="R-410A (fuite)","FE130",IF(C46="R-134a (fuite)","FE131",IF(C46="R-32 (fuite)","FE132",IF(C46="R-290 Propane (fuite)","FE133",IF(C46="CO2 / R-744 (fuite)","FE134","")))))) | G46: =IF(F46="","",VLOOKUP(F46,Facteurs_Emission!$A$4:$E$108,5,FALSE())) | H46: =IF(OR(D46=0,G46=""),0,D46*G46) | I46: =H46/1000
A47: 2 | D47: 0 | E47: kg | F47: =IF(C47="","",IF(C47="R-410A (fuite)","FE130",IF(C47="R-134a (fuite)","FE131",IF(C47="R-32 (fuite)","FE132",IF(C47="R-290 Propane (fuite)","FE133",IF(C47="CO2 / R-744 (fuite)","FE134","")))))) | G47: =IF(F47="","",VLOOKUP(F47,Facteurs_Emission!$A$4:$E$108,5,FALSE())) | H47: =IF(OR(D47=0,G47=""),0,D47*G47) | I47: =H47/1000
A48: 3 | D48: 0 | E48: kg | F48: =IF(C48="","",IF(C48="R-410A (fuite)","FE130",IF(C48="R-134a (fuite)","FE131",IF(C48="R-32 (fuite)","FE132",IF(C48="R-290 Propane (fuite)","FE133",IF(C48="CO2 / R-744 (fuite)","FE134","")))))) | G48: =IF(F48="","",VLOOKUP(F48,Facteurs_Emission!$A$4:$E$108,5,FALSE())) | H48: =IF(OR(D48=0,G48=""),0,D48*G48) | I48: =H48/1000
A49: 4 | D49: 0 | E49: kg | F49: =IF(C49="","",IF(C49="R-410A (fuite)","FE130",IF(C49="R-134a (fuite)","FE131",IF(C49="R-32 (fuite)","FE132",IF(C49="R-290 Propane (fuite)","FE133",IF(C49="CO2 / R-744 (fuite)","FE134","")))))) | G49: =IF(F49="","",VLOOKUP(F49,Facteurs_Emission!$A$4:$E$108,5,FALSE())) | H49: =IF(OR(D49=0,G49=""),0,D49*G49) | I49: =H49/1000
A50: 5 | D50: 0 | E50: kg | F50: =IF(C50="","",IF(C50="R-410A (fuite)","FE130",IF(C50="R-134a (fuite)","FE131",IF(C50="R-32 (fuite)","FE132",IF(C50="R-290 Propane (fuite)","FE133",IF(C50="CO2 / R-744 (fuite)","FE134","")))))) | G50: =IF(F50="","",VLOOKUP(F50,Facteurs_Emission!$A$4:$E$108,5,FALSE())) | H50: =IF(OR(D50=0,G50=""),0,D50*G50) | I50: =H50/1000
A51: 6 | D51: 0 | E51: kg | F51: =IF(C51="","",IF(C51="R-410A (fuite)","FE130",IF(C51="R-134a (fuite)","FE131",IF(C51="R-32 (fuite)","FE132",IF(C51="R-290 Propane (fuite)","FE133",IF(C51="CO2 / R-744 (fuite)","FE134","")))))) | G51: =IF(F51="","",VLOOKUP(F51,Facteurs_Emission!$A$4:$E$108,5,FALSE())) | H51: =IF(OR(D51=0,G51=""),0,D51*G51) | I51: =H51/1000
A52: 7 | D52: 0 | E52: kg | F52: =IF(C52="","",IF(C52="R-410A (fuite)","FE130",IF(C52="R-134a (fuite)","FE131",IF(C52="R-32 (fuite)","FE132",IF(C52="R-290 Propane (fuite)","FE133",IF(C52="CO2 / R-744 (fuite)","FE134","")))))) | G52: =IF(F52="","",VLOOKUP(F52,Facteurs_Emission!$A$4:$E$108,5,FALSE())) | H52: =IF(OR(D52=0,G52=""),0,D52*G52) | I52: =H52/1000
A53: 8 | D53: 0 | E53: kg | F53: =IF(C53="","",IF(C53="R-410A (fuite)","FE130",IF(C53="R-134a (fuite)","FE131",IF(C53="R-32 (fuite)","FE132",IF(C53="R-290 Propane (fuite)","FE133",IF(C53="CO2 / R-744 (fuite)","FE134","")))))) | G53: =IF(F53="","",VLOOKUP(F53,Facteurs_Emission!$A$4:$E$108,5,FALSE())) | H53: =IF(OR(D53=0,G53=""),0,D53*G53) | I53: =H53/1000
B54: SOUS-TOTAL FUGITIVES | H54: =SUM(H46:H53) | I54: =SUM(I46:I53)
A56: TOTAL SCOPE 1 — ÉMISSIONS DIRECTES | H56: =H16+H30+H42+H54 | I56: =I16+I30+I42+I54
B57: dont émissions amont associées → Scope 3 Cat.3 | K57: =K16+K30

Sheet Scope_2
A1: SCOPE 2 — ÉMISSIONS INDIRECTES LIÉES À L'ÉNERGIE | N1: 🏠 Sommaire | O1: 🏠 Sommaire
A2: Double reporting obligatoire : Location-based (LB) ET Market-based (MB). En l'absence de GO/PPA, le MB utilise le mix résiduel (AIB 2023).
A4: 2A — ÉLECTRICITÉ ACHETÉE ET CONSOMMÉE
A5: Ligne | B5: Site / Usage | C5: Pays / Source | D5: Consommation (kWh) | E5: GO/PPA? (O/N) | F5: FE LB (kgCO2e/kWh) | G5: Émissions LB (kgCO2e) | H5: Émissions LB (tCO2e) | I5: FE MB (kgCO2e/kWh) | J5: Émissions MB (kgCO2e) | K5: Émissions MB (tCO2e)
A6: 1 | D6: 0 | F6: =IF(C6="","",IF(C6="France",Facteurs_Emission!G20,IF(C6="Allemagne",Facteurs_Emission!G22,IF(C6="Europe (UE27)",Facteurs_Emission!G23,IF(C6="USA",Facteurs_Emission!G24,IF(C6="Chine",Facteurs_Emission!G25,0)))))) | G6: =IF(OR(D6=0,F6=""),0,D6*F6) | H6: =IF(G6=0,0,G6/1000) | I6: =IF(C6="","",IF(E6="O",Facteurs_Emission!G26,IF(C6="France",Facteurs_Emission!H20,IF(C6="Allemagne",Facteurs_Emission!H22,IF(C6="Europe (UE27)",Facteurs_Emission!H23,IF(C6="USA",Facteurs_Emission!H24,IF(C6="Chine",Facteurs_Emission!H25,0))))))) | J6: =IF(OR(D6=0,I6=""),0,D6*I6) | K6: =IF(J6=0,0,J6/1000)
A7: 2 | D7: 0 | F7: =IF(C7="","",IF(C7="France",Facteurs_Emission!G20,IF(C7="Allemagne",Facteurs_Emission!G22,IF(C7="Europe (UE27)",Facteurs_Emission!G23,IF(C7="USA",Facteurs_Emission!G24,IF(C7="Chine",Facteurs_Emission!G25,0)))))) | G7: =IF(OR(D7=0,F7=""),0,D7*F7) | H7: =IF(G7=0,0,G7/1000) | I7: =IF(C7="","",IF(E7="O",Facteurs_Emission!G26,IF(C7="France",Facteurs_Emission!H20,IF(C7="Allemagne",Facteurs_Emission!H22,IF(C7="Europe (UE27)",Facteurs_Emission!H23,IF(C7="USA",Facteurs_Emission!H24,IF(C7="Chine",Facteurs_Emission!H25,0))))))) | J7: =IF(OR(D7=0,I7=""),0,D7*I7) | K7: =IF(J7=0,0,J7/1000)
A8: 3 | D8: 0 | F8: =IF(C8="","",IF(C8="France",Facteurs_Emission!G20,IF(C8="Allemagne",Facteurs_Emission!G22,IF(C8="Europe (UE27)",Facteurs_Emission!G23,IF(C8="USA",Facteurs_Emission!G24,IF(C8="Chine",Facteurs_Emission!G25,0)))))) | G8: =IF(OR(D8=0,F8=""),0,D8*F8) | H8: =IF(G8=0,0,G8/1000) | I8: =IF(C8="","",IF(E8="O",Facteurs_Emission!G26,IF(C8="France",Facteurs_Emission!H20,IF(C8="Allemagne",Facteurs_Emission!H22,IF(C8="Europe (UE27)",Facteurs_Emission!H23,IF(C8="USA",Facteurs_Emission!H24,IF(C8="Chine",Facteurs_Emission!H25,0))))))) | J8: =IF(OR(D8=0,I8=""),0,D8*I8) | K8: =IF(J8=0,0,J8/1000)
A9: 4 | D9: 0 | F9: =IF(C9="","",IF(C9="France",Facteurs_Emission!G20,IF(C9="Allemagne",Facteurs_Emission!G22,IF(C9="Europe (UE27)",Facteurs_Emission!G23,IF(C9="USA",Facteurs_Emission!G24,IF(C9="Chine",Facteurs_Emission!G25,0)))))) | G9: =IF(OR(D9=0,F9=""),0,D9*F9) | H9: =IF(G9=0,0,G9/1000) | I9: =IF(C9="","",IF(E9="O",Facteurs_Emission!G26,IF(C9="France",Facteurs_Emission!H20,IF(C9="Allemagne",Facteurs_Emission!H22,IF(C9="Europe (UE27)",Facteurs_Emission!H23,IF(C9="USA",Facteurs_Emission!H24,IF(C9="Chine",Facteurs_Emission!H25,0))))))) | J9: =IF(OR(D9=0,I9=""),0,D9*I9) | K9: =IF(J9=0,0,J9/1000)
A10: 5 | D10: 0 | F10: =IF(C10="","",IF(C10="France",Facteurs_Emission!G20,IF(C10="Allemagne",Facteurs_Emission!G22,IF(C10="Europe (UE27)",Facteurs_Emission!G23,IF(C10="USA",Facteurs_Emission!G24,IF(C10="Chine",Facteurs_Emission!G25,0)))))) | G10: =IF(OR(D10=0,F10=""),0,D10*F10) | H10: =IF(G10=0,0,G10/1000) | I10: =IF(C10="","",IF(E10="O",Facteurs_Emission!G26,IF(C10="France",Facteurs_Emission!H20,IF(C10="Allemagne",Facteurs_Emission!H22,IF(C10="Europe (UE27)",Facteurs_Emission!H23,IF(C10="USA",Facteurs_Emission!H24,IF(C10="Chine",Facteurs_Emission!H25,0))))))) | J10: =IF(OR(D10=0,I10=""),0,D10*I10) | K10: =IF(J10=0,0,J10/1000)
A11: 6 | D11: 0 | F11: =IF(C11="","",IF(C11="France",Facteurs_Emission!G20,IF(C11="Allemagne",Facteurs_Emission!G22,IF(C11="Europe (UE27)",Facteurs_Emission!G23,IF(C11="USA",Facteurs_Emission!G24,IF(C11="Chine",Facteurs_Emission!G25,0)))))) | G11: =IF(OR(D11=0,F11=""),0,D11*F11) | H11: =IF(G11=0,0,G11/1000) | I11: =IF(C11="","",IF(E11="O",Facteurs_Emission!G26,IF(C11="France",Facteurs_Emission!H20,IF(C11="Allemagne",Facteurs_Emission!H22,IF(C11="Europe (UE27)",Facteurs_Emission!H23,IF(C11="USA",Facteurs_Emission!H24,IF(C11="Chine",Facteurs_Emission!H25,0))))))) | J11: =IF(OR(D11=0,I11=""),0,D11*I11) | K11: =IF(J11=0,0,J11/1000)
A12: 7 | D12: 0 | F12: =IF(C12="","",IF(C12="France",Facteurs_Emission!G20,IF(C12="Allemagne",Facteurs_Emission!G22,IF(C12="Europe (UE27)",Facteurs_Emission!G23,IF(C12="USA",Facteurs_Emission!G24,IF(C12="Chine",Facteurs_Emission!G25,0)))))) | G12: =IF(OR(D12=0,F12=""),0,D12*F12) | H12: =IF(G12=0,0,G12/1000) | I12: =IF(C12="","",IF(E12="O",Facteurs_Emission!G26,IF(C12="France",Facteurs_Emission!H20,IF(C12="Allemagne",Facteurs_Emission!H22,IF(C12="Europe (UE27)",Facteurs_Emission!H23,IF(C12="USA",Facteurs_Emission!H24,IF(C12="Chine",Facteurs_Emission!H25,0))))))) | J12: =IF(OR(D12=0,I12=""),0,D12*I12) | K12: =IF(J12=0,0,J12/1000)
A13: 8 | D13: 0 | F13: =IF(C13="","",IF(C13="France",Facteurs_Emission!G20,IF(C13="Allemagne",Facteurs_Emission!G22,IF(C13="Europe (UE27)",Facteurs_Emission!G23,IF(C13="USA",Facteurs_Emission!G24,IF(C13="Chine",Facteurs_Emission!G25,0)))))) | G13: =IF(OR(D13=0,F13=""),0,D13*F13) | H13: =IF(G13=0,0,G13/1000) | I13: =IF(C13="","",IF(E13="O",Facteurs_Emission!G26,IF(C13="France",Facteurs_Emission!H20,IF(C13="Allemagne",Facteurs_Emission!H22,IF(C13="Europe (UE27)",Facteurs_Emission!H23,IF(C13="USA",Facteurs_Emission!H24,IF(C13="Chine",Facteurs_Emission!H25,0))))))) | J13: =IF(OR(D13=0,I13=""),0,D13*I13) | K13: =IF(J13=0,0,J13/1000)
A14: 9 | D14: 0 | F14: =IF(C14="","",IF(C14="France",Facteurs_Emission!G20,IF(C14="Allemagne",Facteurs_Emission!G22,IF(C14="Europe (UE27)",Facteurs_Emission!G23,IF(C14="USA",Facteurs_Emission!G24,IF(C14="Chine",Facteurs_Emission!G25,0)))))) | G14: =IF(OR(D14=0,F14=""),0,D14*F14) | H14: =IF(G14=0,0,G14/1000) | I14: =IF(C14="","",IF(E14="O",Facteurs_Emission!G26,IF(C14="France",Facteurs_Emission!H20,IF(C14="Allemagne",Facteurs_Emission!H22,IF(C14="Europe (UE27)",Facteurs_Emission!H23,IF(C14="USA",Facteurs_Emission!H24,IF(C14="Chine",Facteurs_Emission!H25,0))))))) | J14: =IF(OR(D14=0,I14=""),0,D14*I14) | K14: =IF(J14=0,0,J14/1000)
A15: 10 | D15: 0 | F15: =IF(C15="","",IF(C15="France",Facteurs_Emission!G20,IF(C15="Allemagne",Facteurs_Emission!G22,IF(C15="Europe (UE27)",Facteurs_Emission!G23,IF(C15="USA",Facteurs_Emission!G24,IF(C15="Chine",Facteurs_Emission!G25,0)))))) | G15: =IF(OR(D15=0,F15=""),0,D15*F15) | H15: =IF(G15=0,0,G15/1000) | I15: =IF(C15="","",IF(E15="O",Facteurs_Emission!G26,IF(C15="France",Facteurs_Emission!H20,IF(C15="Allemagne",Facteurs_Emission!H22,IF(C15="Europe (UE27)",Facteurs_Emission!H23,IF(C15="USA",Facteurs_Emission!H24,IF(C15="Chine",Facteurs_Emission!H25,0))))))) | J15: =IF(OR(D15=0,I15=""),0,D15*I15) | K15: =IF(J15=0,0,J15/1000)
B16: SOUS-TOTAL ÉLECTRICITÉ | D16: =SUM(D6:D15) | G16: =SUM(G6:G15) | H16: =SUM(H6:H15) | J16: =SUM(J6:J15) | K16: =SUM(K6:K15)
B17: → Émissions amont électricité (→ Scope 3 Cat.3) | D17: =D16 | G17: =D16*Facteurs_Emission!H21 | H17: =G17/1000
B18: → Pertes transport & distribution (→ Scope 3 Cat.3) | D18: =D16*Facteurs_Emission!G29 | G18: =IF(D18=0,0,D18*Facteurs_Emission!G20) | H18: =G18/1000
A20: 2B — CHALEUR, VAPEUR, FROID ACHETÉS
A21: Ligne | B21: Site / Source | C21: Type | D21: Consommation (kWh) | E21: ID FE | F21: FE (kgCO2e/kWh) | G21: Émissions (kgCO2e) | H21: Émissions (tCO2e)
A22: 1 | D22: 0 | E22: =IF(C22="","",IF(C22="Réseau de chaleur urbain","FE027",IF(C22="Réseau de froid urbain","FE028","FE027"))) | F22: =IF(E22="","",VLOOKUP(E22,Facteurs_Emission!$A$4:$G$108,7,FALSE())) | G22: =IF(OR(D22=0,F22=""),0,D22*F22) | H22: =IF(G22=0,0,G22/1000)
A23: 2 | D23: 0 | E23: =IF(C23="","",IF(C23="Réseau de chaleur urbain","FE027",IF(C23="Réseau de froid urbain","FE028","FE027"))) | F23: =IF(E23="","",VLOOKUP(E23,Facteurs_Emission!$A$4:$G$108,7,FALSE())) | G23: =IF(OR(D23=0,F23=""),0,D23*F23) | H23: =IF(G23=0,0,G23/1000)
A24: 3 | D24: 0 | E24: =IF(C24="","",IF(C24="Réseau de chaleur urbain","FE027",IF(C24="Réseau de froid urbain","FE028","FE027"))) | F24: =IF(E24="","",VLOOKUP(E24,Facteurs_Emission!$A$4:$G$108,7,FALSE())) | G24: =IF(OR(D24=0,F24=""),0,D24*F24) | H24: =IF(G24=0,0,G24/1000)
A25: 4 | D25: 0 | E25: =IF(C25="","",IF(C25="Réseau de chaleur urbain","FE027",IF(C25="Réseau de froid urbain","FE028","FE027"))) | F25: =IF(E25="","",VLOOKUP(E25,Facteurs_Emission!$A$4:$G$108,7,FALSE())) | G25: =IF(OR(D25=0,F25=""),0,D25*F25) | H25: =IF(G25=0,0,G25/1000)
A26: 5 | D26: 0 | E26: =IF(C26="","",IF(C26="Réseau de chaleur urbain","FE027",IF(C26="Réseau de froid urbain","FE028","FE027"))) | F26: =IF(E26="","",VLOOKUP(E26,Facteurs_Emission!$A$4:$G$108,7,FALSE())) | G26: =IF(OR(D26=0,F26=""),0,D26*F26) | H26: =IF(G26=0,0,G26/1000)
A27: 6 | D27: 0 | E27: =IF(C27="","",IF(C27="Réseau de chaleur urbain","FE027",IF(C27="Réseau de froid urbain","FE028","FE027"))) | F27: =IF(E27="","",VLOOKUP(E27,Facteurs_Emission!$A$4:$G$108,7,FALSE())) | G27: =IF(OR(D27=0,F27=""),0,D27*F27) | H27: =IF(G27=0,0,G27/1000)
A28: 7 | D28: 0 | E28: =IF(C28="","",IF(C28="Réseau de chaleur urbain","FE027",IF(C28="Réseau de froid urbain","FE028","FE027"))) | F28: =IF(E28="","",VLOOKUP(E28,Facteurs_Emission!$A$4:$G$108,7,FALSE())) | G28: =IF(OR(D28=0,F28=""),0,D28*F28) | H28: =IF(G28=0,0,G28/1000)
B29: SOUS-TOTAL CHALEUR/VAPEUR/FROID | G29: =SUM(G22:G28) | H29: =SUM(H22:H28)
A31: TOTAL SCOPE 2 — LOCATION-BASED | G31: =G16+G29 | H31: =H16+H29
A32: TOTAL SCOPE 2 — MARKET-BASED | J32: =J16 | K32: =K16
B34: Émissions amont associées → Scope 3 Cat.3 | G34: =G17+G18 | H34: =H17+H18

Sheet Scope_3
A1: SCOPE 3 — ÉMISSIONS INDIRECTES DE LA CHAÎNE DE VALEUR | N1: 🏠 Sommaire | O1: 🏠 Sommaire
A2: 15 catégories selon le GHG Protocol Corporate Value Chain (Scope 3) Standard (2011).
A4: Catégorie 1 — Achats de biens et services (amont)
A5: Méthode recommandée : données physiques (quantité × FE matériau) OU fallback monétaire (k€ × FE/k€)
A6: Ligne | B6: Description | C6: Matériau/Service | D6: Quantité | E6: Unité | F6: ID FE | G6: FE (kgCO2e/u) | H6: Émissions (kgCO2e) | I6: Émissions (tCO2e) | J6: Qualité | K6: Méthode | L6: Incertitude (%)
A7: 1 | D7: 0 | H7: =IF(OR(D7=0,G7=""),0,D7*G7) | I7: =H7/1000
A8: 2 | D8: 0 | H8: =IF(OR(D8=0,G8=""),0,D8*G8) | I8: =H8/1000
A9: 3 | D9: 0 | H9: =IF(OR(D9=0,G9=""),0,D9*G9) | I9: =H9/1000
A10: 4 | D10: 0 | H10: =IF(OR(D10=0,G10=""),0,D10*G10) | I10: =H10/1000
A11: 5 | D11: 0 | H11: =IF(OR(D11=0,G11=""),0,D11*G11) | I11: =H11/1000
A12: 6 | D12: 0 | H12: =IF(OR(D12=0,G12=""),0,D12*G12) | I12: =H12/1000
A13: 7 | D13: 0 | H13: =IF(OR(D13=0,G13=""),0,D13*G13) | I13: =H13/1000
A14: 8 | D14: 0 | H14: =IF(OR(D14=0,G14=""),0,D14*G14) | I14: =H14/1000
A15: 9 | D15: 0 | H15: =IF(OR(D15=0,G15=""),0,D15*G15) | I15: =H15/1000
A16: 10 | D16: 0 | H16: =IF(OR(D16=0,G16=""),0,D16*G16) | I16: =H16/1000
A17: 11 | D17: 0 | H17: =IF(OR(D17=0,G17=""),0,D17*G17) | I17: =H17/1000
A18: 12 | D18: 0 | H18: =IF(OR(D18=0,G18=""),0,D18*G18) | I18: =H18/1000
B19: SOUS-TOTAL Cat. 1 | H19: =SUM(H7:H18) | I19: =SUM(I7:I18)
A21: Catégorie 2 — Biens d'équipement (amont)
A22: Immobilisations : ordinateurs, mobilier, véhicules, machines, bâtiments. Amortir sur durée de vie.
A23: Ligne | B23: Description | C23: Matériau/Service | D23: Quantité | E23: Unité | F23: ID FE | G23: FE (kgCO2e/u) | H23: Émissions (kgCO2e) | I23: Émissions (tCO2e) | J23: Qualité | K23: Méthode | L23: Incertitude (%)
A24: 1 | D24: 0 | H24: =IF(OR(D24=0,G24=""),0,D24*G24) | I24: =H24/1000
A25: 2 | D25: 0 | H25: =IF(OR(D25=0,G25=""),0,D25*G25) | I25: =H25/1000
A26: 3 | D26: 0 | H26: =IF(OR(D26=0,G26=""),0,D26*G26) | I26: =H26/1000
A27: 4 | D27: 0 | H27: =IF(OR(D27=0,G27=""),0,D27*G27) | I27: =H27/1000
A28: 5 | D28: 0 | H28: =IF(OR(D28=0,G28=""),0,D28*G28) | I28: =H28/1000
A29: 6 | D29: 0 | H29: =IF(OR(D29=0,G29=""),0,D29*G29) | I29: =H29/1000
B30: SOUS-TOTAL Cat. 2 | H30: =SUM(H24:H29) | I30: =SUM(I24:I29)
A32: Catégorie 3 — Activités liées aux combustibles et à l'énergie (amont)
A33: CALCULÉE AUTOMATIQUEMENT à partir des données Scope 1 et Scope 2.
A34: Ligne | B34: Description | C34: Matériau/Service | D34: Quantité | E34: Unité | F34: ID FE | G34: FE (kgCO2e/u) | H34: Émissions (kgCO2e) | I34: Émissions (tCO2e) | J34: Qualité | K34: Méthode | L34: Incertitude (%)
B35: Émissions amont des combustibles (Scope 1) | H35: =Scope_1!K57 | I35: =H35/1000 | J35: 2 | K35: Données primaires
B36: Émissions amont production et T&D électricité | H36: =Scope_2!G17 | I36: =H36/1000 | J36: 2 | K36: Données primaires
B37: Pertes transport & distribution | H37: =Scope_2!G18 | I37: =H37/1000 | J37: 2 | K37: Données primaires
B38: SOUS-TOTAL Cat. 3 | H38: =SUM(H35:H37) | I38: =SUM(I35:I37)
A40: Catégorie 4 — Transport et distribution amont
A41: Transport marchandises achetées. Formule : tonnes × km × FE (kgCO2e/t.km)
A42: Ligne | B42: Description | C42: Matériau/Service | D42: Quantité | E42: Unité | F42: ID FE | G42: FE (kgCO2e/u) | H42: Émissions (kgCO2e) | I42: Émissions (tCO2e) | J42: Qualité | K42: Méthode | L42: Incertitude (%)
A43: 1 | D43: 0 | H43: =IF(OR(D43=0,G43=""),0,D43*G43) | I43: =H43/1000
A44: 2 | D44: 0 | H44: =IF(OR(D44=0,G44=""),0,D44*G44) | I44: =H44/1000
A45: 3 | D45: 0 | H45: =IF(OR(D45=0,G45=""),0,D45*G45) | I45: =H45/1000
A46: 4 | D46: 0 | H46: =IF(OR(D46=0,G46=""),0,D46*G46) | I46: =H46/1000
A47: 5 | D47: 0 | H47: =IF(OR(D47=0,G47=""),0,D47*G47) | I47: =H47/1000
A48: 6 | D48: 0 | H48: =IF(OR(D48=0,G48=""),0,D48*G48) | I48: =H48/1000
A49: 7 | D49: 0 | H49: =IF(OR(D49=0,G49=""),0,D49*G49) | I49: =H49/1000
A50: 8 | D50: 0 | H50: =IF(OR(D50=0,G50=""),0,D50*G50) | I50: =H50/1000
B51: SOUS-TOTAL Cat. 4 | H51: =SUM(H43:H50) | I51: =SUM(I43:I50)
A53: Catégorie 5 — Déchets générés (exploitation)
A54: Référence automatique vers l'onglet Dechets.
A55: Ligne | B55: Description | C55: Matériau/Service | D55: Quantité | E55: Unité | F55: ID FE | G55: FE (kgCO2e/u) | H55: Émissions (kgCO2e) | I55: Émissions (tCO2e) | J55: Qualité | K55: Méthode | L55: Incertitude (%)
B56: Total déchets (voir onglet Dechets) | H56: =Dechets!F13 | I56: =H56/1000 | J56: 2 | K56: Données primaires
B57: SOUS-TOTAL Cat. 5 | H57: =SUM(H56:H56) | I57: =SUM(I56:I56)
A59: Catégorie 6 — Déplacements professionnels
A60: Référence automatique vers l'onglet Transport.
A61: Ligne | B61: Description | C61: Matériau/Service | D61: Quantité | E61: Unité | F61: ID FE | G61: FE (kgCO2e/u) | H61: Émissions (kgCO2e) | I61: Émissions (tCO2e) | J61: Qualité | K61: Méthode | L61: Incertitude (%)
B62: Total déplacements professionnels | H62: =Transport!I17 | I62: =H62/1000 | J62: 2 | K62: Données primaires
B63: SOUS-TOTAL Cat. 6 | H63: =SUM(H62:H62) | I63: =SUM(I62:I62)
A65: Catégorie 7 — Déplacements domicile-travail
A66: Référence automatique vers l'onglet Transport.
A67: Ligne | B67: Description | C67: Matériau/Service | D67: Quantité | E67: Unité | F67: ID FE | G67: FE (kgCO2e/u) | H67: Émissions (kgCO2e) | I67: Émissions (tCO2e) | J67: Qualité | K67: Méthode | L67: Incertitude (%)
B68: Total domicile-travail | H68: =Transport!H29 | I68: =H68/1000 | J68: 2 | K68: Données primaires
B69: SOUS-TOTAL Cat. 7 | H69: =SUM(H68:H68) | I69: =SUM(I68:I68)
A71: Catégorie 8 — Actifs loués amont
A72: Saisie manuelle — Actifs loués amont
A73: Ligne | B73: Description | C73: Matériau/Service | D73: Quantité | E73: Unité | F73: ID FE | G73: FE (kgCO2e/u) | H73: Émissions (kgCO2e) | I73: Émissions (tCO2e) | J73: Qualité | K73: Méthode | L73: Incertitude (%)
A74: 1 | D74: 0 | H74: =IF(OR(D74=0,G74=""),0,D74*G74) | I74: =H74/1000
A75: 2 | D75: 0 | H75: =IF(OR(D75=0,G75=""),0,D75*G75) | I75: =H75/1000
A76: 3 | D76: 0 | H76: =IF(OR(D76=0,G76=""),0,D76*G76) | I76: =H76/1000
B77: SOUS-TOTAL Cat. 8 | H77: =SUM(H74:H76) | I77: =SUM(I74:I76)
A79: Catégorie 9 — Transport et distribution aval
A80: Saisie manuelle — Transport et distribution aval
A81: Ligne | B81: Description | C81: Matériau/Service | D81: Quantité | E81: Unité | F81: ID FE | G81: FE (kgCO2e/u) | H81: Émissions (kgCO2e) | I81: Émissions (tCO2e) | J81: Qualité | K81: Méthode | L81: Incertitude (%)
A82: 1 | D82: 0 | H82: =IF(OR(D82=0,G82=""),0,D82*G82) | I82: =H82/1000
A83: 2 | D83: 0 | H83: =IF(OR(D83=0,G83=""),0,D83*G83) | I83: =H83/1000
A84: 3 | D84: 0 | H84: =IF(OR(D84=0,G84=""),0,D84*G84) | I84: =H84/1000
A85: 4 | D85: 0 | H85: =IF(OR(D85=0,G85=""),0,D85*G85) | I85: =H85/1000
A86: 5 | D86: 0 | H86: =IF(OR(D86=0,G86=""),0,D86*G86) | I86: =H86/1000
B87: SOUS-TOTAL Cat. 9 | H87: =SUM(H82:H86) | I87: =SUM(I82:I86)
A89: Catégorie 10 — Transformation des produits vendus
A90: Saisie manuelle — Transformation des produits vendus
A91: Ligne | B91: Description | C91: Matériau/Service | D91: Quantité | E91: Unité | F91: ID FE | G91: FE (kgCO2e/u) | H91: Émissions (kgCO2e) | I91: Émissions (tCO2e) | J91: Qualité | K91: Méthode | L91: Incertitude (%)
A92: 1 | D92: 0 | H92: =IF(OR(D92=0,G92=""),0,D92*G92) | I92: =H92/1000
A93: 2 | D93: 0 | H93: =IF(OR(D93=0,G93=""),0,D93*G93) | I93: =H93/1000
A94: 3 | D94: 0 | H94: =IF(OR(D94=0,G94=""),0,D94*G94) | I94: =H94/1000
B95: SOUS-TOTAL Cat. 10 | H95: =SUM(H92:H94) | I95: =SUM(I92:I94)
A97: Catégorie 11 — Utilisation des produits vendus
A98: Saisie manuelle — Utilisation des produits vendus
A99: Ligne | B99: Description | C99: Matériau/Service | D99: Quantité | E99: Unité | F99: ID FE | G99: FE (kgCO2e/u) | H99: Émissions (kgCO2e) | I99: Émissions (tCO2e) | J99: Qualité | K99: Méthode | L99: Incertitude (%)
A100: 1 | D100: 0 | H100: =IF(OR(D100=0,G100=""),0,D100*G100) | I100: =H100/1000
A101: 2 | D101: 0 | H101: =IF(OR(D101=0,G101=""),0,D101*G101) | I101: =H101/1000
A102: 3 | D102: 0 | H102: =IF(OR(D102=0,G102=""),0,D102*G102) | I102: =H102/1000
A103: 4 | D103: 0 | H103: =IF(OR(D103=0,G103=""),0,D103*G103) | I103: =H103/1000
A104: 5 | D104: 0 | H104: =IF(OR(D104=0,G104=""),0,D104*G104) | I104: =H104/1000
B105: SOUS-TOTAL Cat. 11 | H105: =SUM(H100:H104) | I105: =SUM(I100:I104)
A107: Catégorie 12 — Fin de vie des produits vendus
A108: Saisie manuelle — Fin de vie des produits vendus
A109: Ligne | B109: Description | C109: Matériau/Service | D109: Quantité | E109: Unité | F109: ID FE | G109: FE (kgCO2e/u) | H109: Émissions (kgCO2e) | I109: Émissions (tCO2e) | J109: Qualité | K109: Méthode | L109: Incertitude (%)
A110: 1 | D110: 0 | H110: =IF(OR(D110=0,G110=""),0,D110*G110) | I110: =H110/1000
A111: 2 | D111: 0 | H111: =IF(OR(D111=0,G111=""),0,D111*G111) | I111: =H111/1000
A112: 3 | D112: 0 | H112: =IF(OR(D112=0,G112=""),0,D112*G112) | I112: =H112/1000
...

Sheet Energie
A1: SUIVI ÉNERGÉTIQUE — VENTILATION ESRS E1-5 §37-38 | N1: 🏠 Sommaire | O1: 🏠 Sommaire
A3: A — CONSOMMATION D'ÉNERGIE NON-RENOUVELABLE
A4: Poste | B4: Quantité | C4: Unité d'origine | D4: Conversion MWh | E4: MWh
A5: (i) Charbon et dérivés | B5: 0 | C5: tonnes | D5: =B5*7.22 | E5: =D5
A6: (ii) Pétrole brut et dérivés | B6: 0 | C6: litres | D6: =B6*0.01008 | E6: =D6
A7: (iii) Gaz naturel | B7: 0 | C7: kWh | D7: =B7/1000 | E7: =D7
A8: (iv) Autres non-renouvelables | B8: 0 | C8: MWh | D8: =B8 | E8: =D8
A9: (v) Électricité achetée non-ENR | B9: 0 | C9: kWh | D9: =B9/1000 | E9: =D9
A10: TOTAL A — Non-renouvelable | E10: =SUM(E5:E9) -> 0
A12: B — CONSOMMATION D'ÉNERGIE RENOUVELABLE
A13: (i) Combustibles renouvelables (biomasse) | B13: 0 | C13: kWh | D13: =B13/1000 | E13: =D13
A14: (ii) Électricité achetée ENR (GO/PPA) | B14: 0 | C14: kWh | D14: =B14/1000 | E14: =D14
A15: (iii) Autoprod. renouvelable (PV, éolien) | B15: 0 | C15: MWh | D15: =B15 | E15: =D15
A16: TOTAL B — Renouvelable | E16: =SUM(E13:E15) -> 0
A18: C — TOTAUX ET INDICATEURS
A19: Total consommation énergie (MWh) | E19: =E10+E16 -> 0
A20: Part énergie renouvelable (%) | E20: =IF(E19=0,0,ROUND(E16/E19*100,1)) -> 0
A21: Intensité énergétique (MWh/M€ CA) | E21: =IF(Paramètres!B9=0,0,E19/(Paramètres!B9/1000000))
A23: D — SUIVI MENSUEL DÉTAILLÉ
A24: Mois | B24: Électricité (kWh) | C24: Gaz naturel (kWh) | D24: Fioul (litres) | E24: Chaleur réseau (kWh) | F24: ENR autoprod. (kWh) | G24: Total énergie (kWh) | H24: Coût total (€)
A25: Janvier | B25: 0 | C25: 0 | D25: 0 | E25: 0 | F25: 0 | G25: =B25+C25+(D25*10.08)+E25+F25 | H25: 0
A26: Février | B26: 0 | C26: 0 | D26: 0 | E26: 0 | F26: 0 | G26: =B26+C26+(D26*10.08)+E26+F26 | H26: 0
A27: Mars | B27: 0 | C27: 0 | D27: 0 | E27: 0 | F27: 0 | G27: =B27+C27+(D27*10.08)+E27+F27 | H27: 0
A28: Avril | B28: 0 | C28: 0 | D28: 0 | E28: 0 | F28: 0 | G28: =B28+C28+(D28*10.08)+E28+F28 | H28: 0
A29: Mai | B29: 0 | C29: 0 | D29: 0 | E29: 0 | F29: 0 | G29: =B29+C29+(D29*10.08)+E29+F29 | H29: 0
A30: Juin | B30: 0 | C30: 0 | D30: 0 | E30: 0 | F30: 0 | G30: =B30+C30+(D30*10.08)+E30+F30 | H30: 0
A31: Juillet | B31: 0 | C31: 0 | D31: 0 | E31: 0 | F31: 0 | G31: =B31+C31+(D31*10.08)+E31+F31 | H31: 0
A32: Août | B32: 0 | C32: 0 | D32: 0 | E32: 0 | F32: 0 | G32: =B32+C32+(D32*10.08)+E32+F32 | H32: 0
A33: Septembre | B33: 0 | C33: 0 | D33: 0 | E33: 0 | F33: 0 | G33: =B33+C33+(D33*10.08)+E33+F33 | H33: 0
A34: Octobre | B34: 0 | C34: 0 | D34: 0 | E34: 0 | F34: 0 | G34: =B34+C34+(D34*10.08)+E34+F34 | H34: 0
A35: Novembre | B35: 0 | C35: 0 | D35: 0 | E35: 0 | F35: 0 | G35: =B35+C35+(D35*10.08)+E35+F35 | H35: 0
A36: Décembre | B36: 0 | C36: 0 | D36: 0 | E36: 0 | F36: 0 | G36: =B36+C36+(D36*10.08)+E36+F36 | H36: 0
A37: TOTAL ANNUEL | B37: =SUM(B25:B36) | C37: =SUM(C25:C36) | D37: =SUM(D25:D36) | E37: =SUM(E25:E36) | F37: =SUM(F25:F36) | G37: =SUM(G25:G36) | H37: =SUM(H25:H36)

Sheet Transport
A1: TRANSPORT — DÉPLACEMENTS PROFESSIONNELS ET DOMICILE-TRAVAIL | N1: 🏠 Sommaire | O1: 🏠 Sommaire
A3: A — DÉPLACEMENTS PROFESSIONNELS (Scope 3 Cat. 6)
A4: Ligne | B4: Description du trajet | C4: Mode de transport | D4: Distance (km) | E4: Nb voyages | F4: Total km.passager | G4: ID FE | H4: FE (kgCO2e/km) | I4: Émissions (kgCO2e) | J4: tCO2e
A5: 1 | D5: 0 | E5: 0 | F5: =D5*E5 | G5: =IF(C5="","",IF(C5="Voiture thermique","FE030",IF(C5="Voiture diesel","FE031",IF(C5="Voiture essence","FE032",IF(C5="Voiture électrique","FE033",IF(C5="TGV","FE035",IF(C5="TER","FE036",IF(C5="Métro/Tramway","FE037",IF(C5="Bus urbain","FE038",IF(C5="Avion CC éco (avec RF)","FE039_RF",IF(C5="Avion MC éco (avec RF)","FE040_RF",IF(C5="Avion LC éco (avec RF)","FE041_RF",IF(C5="Avion LC business (avec RF)","FE042",""))))))))))))) | H5: =IF(G5="","",VLOOKUP(G5,Facteurs_Emission!$A$4:$E$108,5,FALSE())) | I5: =IF(OR(F5=0,H5=""),0,F5*H5) | J5: =I5/1000
A6: 2 | D6: 0 | E6: 0 | F6: =D6*E6 | G6: =IF(C6="","",IF(C6="Voiture thermique","FE030",IF(C6="Voiture diesel","FE031",IF(C6="Voiture essence","FE032",IF(C6="Voiture électrique","FE033",IF(C6="TGV","FE035",IF(C6="TER","FE036",IF(C6="Métro/Tramway","FE037",IF(C6="Bus urbain","FE038",IF(C6="Avion CC éco (avec RF)","FE039_RF",IF(C6="Avion MC éco (avec RF)","FE040_RF",IF(C6="Avion LC éco (avec RF)","FE041_RF",IF(C6="Avion LC business (avec RF)","FE042",""))))))))))))) | H6: =IF(G6="","",VLOOKUP(G6,Facteurs_Emission!$A$4:$E$108,5,FALSE())) | I6: =IF(OR(F6=0,H6=""),0,F6*H6) | J6: =I6/1000
A7: 3 | D7: 0 | E7: 0 | F7: =D7*E7 | G7: =IF(C7="","",IF(C7="Voiture thermique","FE030",IF(C7="Voiture diesel","FE031",IF(C7="Voiture essence","FE032",IF(C7="Voiture électrique","FE033",IF(C7="TGV","FE035",IF(C7="TER","FE036",IF(C7="Métro/Tramway","FE037",IF(C7="Bus urbain","FE038",IF(C7="Avion CC éco (avec RF)","FE039_RF",IF(C7="Avion MC éco (avec RF)","FE040_RF",IF(C7="Avion LC éco (avec RF)","FE041_RF",IF(C7="Avion LC business (avec RF)","FE042",""))))))))))))) | H7: =IF(G7="","",VLOOKUP(G7,Facteurs_Emission!$A$4:$E$108,5,FALSE())) | I7: =IF(OR(F7=0,H7=""),0,F7*H7) | J7: =I7/1000
A8: 4 | D8: 0 | E8: 0 | F8: =D8*E8 | G8: =IF(C8="","",IF(C8="Voiture thermique","FE030",IF(C8="Voiture diesel","FE031",IF(C8="Voiture essence","FE032",IF(C8="Voiture électrique","FE033",IF(C8="TGV","FE035",IF(C8="TER","FE036",IF(C8="Métro/Tramway","FE037",IF(C8="Bus urbain","FE038",IF(C8="Avion CC éco (avec RF)","FE039_RF",IF(C8="Avion MC éco (avec RF)","FE040_RF",IF(C8="Avion LC éco (avec RF)","FE041_RF",IF(C8="Avion LC business (avec RF)","FE042",""))))))))))))) | H8: =IF(G8="","",VLOOKUP(G8,Facteurs_Emission!$A$4:$E$108,5,FALSE())) | I8: =IF(OR(F8=0,H8=""),0,F8*H8) | J8: =I8/1000
A9: 5 | D9: 0 | E9: 0 | F9: =D9*E9 | G9: =IF(C9="","",IF(C9="Voiture thermique","FE030",IF(C9="Voiture diesel","FE031",IF(C9="Voiture essence","FE032",IF(C9="Voiture électrique","FE033",IF(C9="TGV","FE035",IF(C9="TER","FE036",IF(C9="Métro/Tramway","FE037",IF(C9="Bus urbain","FE038",IF(C9="Avion CC éco (avec RF)","FE039_RF",IF(C9="Avion MC éco (avec RF)","FE040_RF",IF(C9="Avion LC éco (avec RF)","FE041_RF",IF(C9="Avion LC business (avec RF)","FE042",""))))))))))))) | H9: =IF(G9="","",VLOOKUP(G9,Facteurs_Emission!$A$4:$E$108,5,FALSE())) | I9: =IF(OR(F9=0,H9=""),0,F9*H9) | J9: =I9/1000
A10: 6 | D10: 0 | E10: 0 | F10: =D10*E10 | G10: =IF(C10="","",IF(C10="Voiture thermique","FE030",IF(C10="Voiture diesel","FE031",IF(C10="Voiture essence","FE032",IF(C10="Voiture électrique","FE033",IF(C10="TGV","FE035",IF(C10="TER","FE036",IF(C10="Métro/Tramway","FE037",IF(C10="Bus urbain","FE038",IF(C10="Avion CC éco (avec RF)","FE039_RF",IF(C10="Avion MC éco (avec RF)","FE040_RF",IF(C10="Avion LC éco (avec RF)","FE041_RF",IF(C10="Avion LC business (avec RF)","FE042",""))))))))))))) | H10: =IF(G10="","",VLOOKUP(G10,Facteurs_Emission!$A$4:$E$108,5,FALSE())) | I10: =IF(OR(F10=0,H10=""),0,F10*H10) | J10: =I10/1000
A11: 7 | D11: 0 | E11: 0 | F11: =D11*E11 | G11: =IF(C11="","",IF(C11="Voiture thermique","FE030",IF(C11="Voiture diesel","FE031",IF(C11="Voiture essence","FE032",IF(C11="Voiture électrique","FE033",IF(C11="TGV","FE035",IF(C11="TER","FE036",IF(C11="Métro/Tramway","FE037",IF(C11="Bus urbain","FE038",IF(C11="Avion CC éco (avec RF)","FE039_RF",IF(C11="Avion MC éco (avec RF)","FE040_RF",IF(C11="Avion LC éco (avec RF)","FE041_RF",IF(C11="Avion LC business (avec RF)","FE042",""))))))))))))) | H11: =IF(G11="","",VLOOKUP(G11,Facteurs_Emission!$A$4:$E$108,5,FALSE())) | I11: =IF(OR(F11=0,H11=""),0,F11*H11) | J11: =I11/1000
A12: 8 | D12: 0 | E12: 0 | F12: =D12*E12 | G12: =IF(C12="","",IF(C12="Voiture thermique","FE030",IF(C12="Voiture diesel","FE031",IF(C12="Voiture essence","FE032",IF(C12="Voiture électrique","FE033",IF(C12="TGV","FE035",IF(C12="TER","FE036",IF(C12="Métro/Tramway","FE037",IF(C12="Bus urbain","FE038",IF(C12="Avion CC éco (avec RF)","FE039_RF",IF(C12="Avion MC éco (avec RF)","FE040_RF",IF(C12="Avion LC éco (avec RF)","FE041_RF",IF(C12="Avion LC business (avec RF)","FE042",""))))))))))))) | H12: =IF(G12="","",VLOOKUP(G12,Facteurs_Emission!$A$4:$E$108,5,FALSE())) | I12: =IF(OR(F12=0,H12=""),0,F12*H12) | J12: =I12/1000
A13: 9 | D13: 0 | E13: 0 | F13: =D13*E13 | G13: =IF(C13="","",IF(C13="Voiture thermique","FE030",IF(C13="Voiture diesel","FE031",IF(C13="Voiture essence","FE032",IF(C13="Voiture électrique","FE033",IF(C13="TGV","FE035",IF(C13="TER","FE036",IF(C13="Métro/Tramway","FE037",IF(C13="Bus urbain","FE038",IF(C13="Avion CC éco (avec RF)","FE039_RF",IF(C13="Avion MC éco (avec RF)","FE040_RF",IF(C13="Avion LC éco (avec RF)","FE041_RF",IF(C13="Avion LC business (avec RF)","FE042",""))))))))))))) | H13: =IF(G13="","",VLOOKUP(G13,Facteurs_Emission!$A$4:$E$108,5,FALSE())) | I13: =IF(OR(F13=0,H13=""),0,F13*H13) | J13: =I13/1000
A14: 10 | D14: 0 | E14: 0 | F14: =D14*E14 | G14: =IF(C14="","",IF(C14="Voiture thermique","FE030",IF(C14="Voiture diesel","FE031",IF(C14="Voiture essence","FE032",IF(C14="Voiture électrique","FE033",IF(C14="TGV","FE035",IF(C14="TER","FE036",IF(C14="Métro/Tramway","FE037",IF(C14="Bus urbain","FE038",IF(C14="Avion CC éco (avec RF)","FE039_RF",IF(C14="Avion MC éco (avec RF)","FE040_RF",IF(C14="Avion LC éco (avec RF)","FE041_RF",IF(C14="Avion LC business (avec RF)","FE042",""))))))))))))) | H14: =IF(G14="","",VLOOKUP(G14,Facteurs_Emission!$A$4:$E$108,5,FALSE())) | I14: =IF(OR(F14=0,H14=""),0,F14*H14) | J14: =I14/1000
A15: 11 | D15: 0 | E15: 0 | F15: =D15*E15 | G15: =IF(C15="","",IF(C15="Voiture thermique","FE030",IF(C15="Voiture diesel","FE031",IF(C15="Voiture essence","FE032",IF(C15="Voiture électrique","FE033",IF(C15="TGV","FE035",IF(C15="TER","FE036",IF(C15="Métro/Tramway","FE037",IF(C15="Bus urbain","FE038",IF(C15="Avion CC éco (avec RF)","FE039_RF",IF(C15="Avion MC éco (avec RF)","FE040_RF",IF(C15="Avion LC éco (avec RF)","FE041_RF",IF(C15="Avion LC business (avec RF)","FE042",""))))))))))))) | H15: =IF(G15="","",VLOOKUP(G15,Facteurs_Emission!$A$4:$E$108,5,FALSE())) | I15: =IF(OR(F15=0,H15=""),0,F15*H15) | J15: =I15/1000
A16: 12 | D16: 0 | E16: 0 | F16: =D16*E16 | G16: =IF(C16="","",IF(C16="Voiture thermique","FE030",IF(C16="Voiture diesel","FE031",IF(C16="Voiture essence","FE032",IF(C16="Voiture électrique","FE033",IF(C16="TGV","FE035",IF(C16="TER","FE036",IF(C16="Métro/Tramway","FE037",IF(C16="Bus urbain","FE038",IF(C16="Avion CC éco (avec RF)","FE039_RF",IF(C16="Avion MC éco (avec RF)","FE040_RF",IF(C16="Avion LC éco (avec RF)","FE041_RF",IF(C16="Avion LC business (avec RF)","FE042",""))))))))))))) | H16: =IF(G16="","",VLOOKUP(G16,Facteurs_Emission!$A$4:$E$108,5,FALSE())) | I16: =IF(OR(F16=0,H16=""),0,F16*H16) | J16: =I16/1000
B17: SOUS-TOTAL DÉPLACEMENTS PROFESSIONNELS | I17: =SUM(I5:I16) | J17: =SUM(J5:J16)
A19: B — DÉPLACEMENTS DOMICILE-TRAVAIL (Scope 3 Cat. 7)
A20: Mode | B20: Nb salariés | C20: Distance A/R moy. (km) | D20: Jours/an | E20: Total km.pass | F20: ID FE | G20: FE (kgCO2e/km) | H20: Émissions (kgCO2e) | I20: tCO2e
A21: Voiture thermique (seul) | B21: 0 | C21: 0 | D21: 220 | E21: =B21*C21*D21 | F21: FE030 | G21: =IF(F21="","",VLOOKUP(F21,Facteurs_Emission!$A$4:$E$108,5,FALSE())) | H21: =E21*G21 | I21: =H21/1000
A22: Voiture thermique (covoit. 2 pers.) | B22: 0 | C22: 0 | D22: 220 | E22: =B22*C22*D22 | F22: FE030 | G22: =IF(F22="","",VLOOKUP(F22,Facteurs_Emission!$A$4:$E$108,5,FALSE())/2) | H22: =E22*G22 | I22: =H22/1000
A23: Voiture électrique | B23: 0 | C23: 0 | D23: 220 | E23: =B23*C23*D23 | F23: FE033 | G23: =IF(F23="","",VLOOKUP(F23,Facteurs_Emission!$A$4:$E$108,5,FALSE())) | H23: =E23*G23 | I23: =H23/1000
A24: Métro / Tramway | B24: 0 | C24: 0 | D24: 220 | E24: =B24*C24*D24 | F24: FE037 | G24: =IF(F24="","",VLOOKUP(F24,Facteurs_Emission!$A$4:$E$108,5,FALSE())) | H24: =E24*G24 | I24: =H24/1000
A25: Bus urbain | B25: 0 | C25: 0 | D25: 220 | E25: =B25*C25*D25 | F25: FE038 | G25: =IF(F25="","",VLOOKUP(F25,Facteurs_Emission!$A$4:$E$108,5,FALSE())) | H25: =E25*G25 | I25: =H25/1000
A26: TER / RER | B26: 0 | C26: 0 | D26: 220 | E26: =B26*C26*D26 | F26: FE036 | G26: =IF(F26="","",VLOOKUP(F26,Facteurs_Emission!$A$4:$E$108,5,FALSE())) | H26: =E26*G26 | I26: =H26/1000
A27: Vélo / trottinette | B27: 0 | C27: 0 | D27: 220 | E27: =B27*C27*D27 | G27: 0 | H27: =E27*G27 | I27: =H27/1000
A28: Marche à pied | B28: 0 | C28: 0 | D28: 220 | E28: =B28*C28*D28 | G28: 0 | H28: =E28*G28 | I28: =H28/1000
A29: SOUS-TOTAL DOMICILE-TRAVAIL | H29: =SUM(H21:H28) | I29: =SUM(I21:I28)

Sheet Matieres_Premieres
A1: ACHATS DE MATIÈRES PREMIÈRES ET INTRANTS — SCOPE 3 CAT. 1 | N1: 🏠 Sommaire | O1: 🏠 Sommaire
A3: Ligne | B3: Fournisseur | C3: Matériau / Service | D3: Quantité | E3: Unité | F3: ID FE | G3: FE (kgCO2e/u) | H3: Émissions (kgCO2e) | I3: Émissions (tCO2e) | J3: Coût achat HT (€) | K3: Intensité (kgCO2e/€)
A4: 1 | D4: 0 | H4: =IF(OR(D4=0,G4=""),0,D4*G4) | I4: =H4/1000 | J4: 0 | K4: =IF(J4=0,"—",H4/J4)
A5: 2 | D5: 0 | H5: =IF(OR(D5=0,G5=""),0,D5*G5) | I5: =H5/1000 | J5: 0 | K5: =IF(J5=0,"—",H5/J5)
A6: 3 | D6: 0 | H6: =IF(OR(D6=0,G6=""),0,D6*G6) | I6: =H6/1000 | J6: 0 | K6: =IF(J6=0,"—",H6/J6)
A7: 4 | D7: 0 | H7: =IF(OR(D7=0,G7=""),0,D7*G7) | I7: =H7/1000 | J7: 0 | K7: =IF(J7=0,"—",H7/J7)
A8: 5 | D8: 0 | H8: =IF(OR(D8=0,G8=""),0,D8*G8) | I8: =H8/1000 | J8: 0 | K8: =IF(J8=0,"—",H8/J8)
A9: 6 | D9: 0 | H9: =IF(OR(D9=0,G9=""),0,D9*G9) | I9: =H9/1000 | J9: 0 | K9: =IF(J9=0,"—",H9/J9)
A10: 7 | D10: 0 | H10: =IF(OR(D10=0,G10=""),0,D10*G10) | I10: =H10/1000 | J10: 0 | K10: =IF(J10=0,"—",H10/J10)
A11: 8 | D11: 0 | H11: =IF(OR(D11=0,G11=""),0,D11*G11) | I11: =H11/1000 | J11: 0 | K11: =IF(J11=0,"—",H11/J11)
A12: 9 | D12: 0 | H12: =IF(OR(D12=0,G12=""),0,D12*G12) | I12: =H12/1000 | J12: 0 | K12: =IF(J12=0,"—",H12/J12)
A13: 10 | D13: 0 | H13: =IF(OR(D13=0,G13=""),0,D13*G13) | I13: =H13/1000 | J13: 0 | K13: =IF(J13=0,"—",H13/J13)
A14: 11 | D14: 0 | H14: =IF(OR(D14=0,G14=""),0,D14*G14) | I14: =H14/1000 | J14: 0 | K14: =IF(J14=0,"—",H14/J14)
A15: 12 | D15: 0 | H15: =IF(OR(D15=0,G15=""),0,D15*G15) | I15: =H15/1000 | J15: 0 | K15: =IF(J15=0,"—",H15/J15)
... A33: 30 | D33: 0 | H33: =IF(OR(D33=0,G33=""),0,D33*G33) | I33: =H33/1000 | J33: 0 | K33: =IF(J33=0,"—",H33/J33)
B34: TOTAL | H34: =SUM(H4:H33) | I34: =SUM(I4:I33) | J34: =SUM(J4:J33)
A36: Intensité carbone des achats (tCO2e/M€ achats) | D36: =IF(J34=0,0,I34/(J34/1000000))

Sheet Dechets
A1: DÉCHETS GÉNÉRÉS — SCOPE 3 CATÉGORIE 5 | N1: 🏠 Sommaire | O1: 🏠 Sommaire
A2: ⚠️ Conformément au GHG Protocol, les émissions comptabilisées sont celles du PROCESS de traitement, PAS les émissions évitées.
A3: Type de déchet | B3: Filière de traitement | C3: Quantité (tonnes) | D3: ID FE | E3: FE process (kgCO2e/t) | F3: Émissions (kgCO2e) | G3: tCO2e
C4: 0 | D4: =IF(B4="","",IF(B4="Enfouissement ISDND","FE090",IF(B4="Incinération avec récup. énergie","FE091",IF(B4="Recyclage (process)","FE092",IF(B4="Compostage","FE093",IF(B4="Méthanisation","FE094",IF(B4="DEEE","FE095",""))))))) | E4: =IF(D4="","",VLOOKUP(D4,Facteurs_Emission!$A$4:$G$108,7,FALSE())) | F4: =IF(OR(C4=0,E4=""),0,C4*E4) | G4: =F4/1000
C5: 0 | D5: =IF(B5="","",IF(B5="Enfouissement ISDND","FE090",IF(B5="Incinération avec récup. énergie","FE091",IF(B5="Recyclage (process)","FE092",IF(B5="Compostage","FE093",IF(B5="Méthanisation","FE094",IF(B5="DEEE","FE095",""))))))) | E5: =IF(D5="","",VLOOKUP(D5,Facteurs_Emission!$A$4:$G$108,7,FALSE())) | F5: =IF(OR(C5=0,E5=""),0,C5*E5) | G5: =F5/1000
C6: 0 | D6: =IF(B6="","",IF(B6="Enfouissement ISDND","FE090",IF(B6="Incinération avec récup. énergie","FE091",IF(B6="Recyclage (process)","FE092",IF(B6="Compostage","FE093",IF(B6="Méthanisation","FE094",IF(B6="DEEE","FE095",""))))))) | E6: =IF(D6="","",VLOOKUP(D6,Facteurs_Emission!$A$4:$G$108,7,FALSE())) | F6: =IF(OR(C6=0,E6=""),0,C6*E6) | G6: =F6/1000
C7: 0 | D7: =IF(B7="","",IF(B7="Enfouissement ISDND","FE090",IF(B7="Incinération avec récup. énergie","FE091",IF(B7="Recyclage (process)","FE092",IF(B7="Compostage","FE093",IF(B7="Méthanisation","FE094",IF(B7="DEEE","FE095",""))))))) | E7: =IF(D7="","",VLOOKUP(D7,Facteurs_Emission!$A$4:$G$108,7,FALSE())) | F7: =IF(OR(C7=0,E7=""),0,C7*E7) | G7: =F7/1000
C8: 0 | D8: =IF(B8="","",IF(B8="Enfouissement ISDND","FE090",IF(B8="Incinération avec récup. énergie","FE091",IF(B8="Recyclage (process)","FE092",IF(B8="Compostage","FE093",IF(B8="Méthanisation","FE094",IF(B8="DEEE","FE095",""))))))) | E8: =IF(D8="","",VLOOKUP(D8,Facteurs_Emission!$A$4:$G$108,7,FALSE())) | F8: =IF(OR(C8=0,E8=""),0,C8*E8) | G8: =F8/1000
C9: 0 | D9: =IF(B9="","",IF(B9="Enfouissement ISDND","FE090",IF(B9="Incinération avec récup. énergie","FE091",IF(B9="Recyclage (process)","FE092",IF(B9="Compostage","FE093",IF(B9="Méthanisation","FE094",IF(B9="DEEE","FE095",""))))))) | E9: =IF(D9="","",VLOOKUP(D9,Facteurs_Emission!$A$4:$G$108,7,FALSE())) | F9: =IF(OR(C9=0,E9=""),0,C9*E9) | G9: =F9/1000
C10: 0 | D10: =IF(B10="","",IF(B10="Enfouissement ISDND","FE090",IF(B10="Incinération avec récup. énergie","FE091",IF(B10="Recyclage (process)","FE092",IF(B10="Compostage","FE093",IF(B10="Méthanisation","FE094",IF(B10="DEEE","FE095",""))))))) | E10: =IF(D10="","",VLOOKUP(D10,Facteurs_Emission!$A$4:$G$108,7,FALSE())) | F10: =IF(OR(C10=0,E10=""),0,C10*E10) | G10: =F10/1000
C11: 0 | D11: =IF(B11="","",IF(B11="Enfouissement ISDND","FE090",IF(B11="Incinération avec récup. énergie","FE091",IF(B11="Recyclage (process)","FE092",IF(B11="Compostage","FE093",IF(B11="Méthanisation","FE094",IF(B11="DEEE","FE095",""))))))) | E11: =IF(D11="","",VLOOKUP(D11,Facteurs_Emission!$A$4:$G$108,7,FALSE())) | F11: =IF(OR(C11=0,E11=""),0,C11*E11) | G11: =F11/1000
C12: 0 | D12: =IF(B12="","",IF(B12="Enfouissement ISDND","FE090",IF(B12="Incinération avec récup. énergie","FE091",IF(B12="Recyclage (process)","FE092",IF(B12="Compostage","FE093",IF(B12="Méthanisation","FE094",IF(B12="DEEE","FE095",""))))))) | E12: =IF(D12="","",VLOOKUP(D12,Facteurs_Emission!$A$4:$G$108,7,FALSE())) | F12: =IF(OR(C12=0,E12=""),0,C12*E12) | G12: =F12/1000
A13: TOTAL | F13: =SUM(F4:F12) | G13: =SUM(G4:G12)
A15: ÉMISSIONS ÉVITÉES PAR LE RECYCLAGE (hors Scope 3)
A16: Tonnes recyclées | C16: =SUMPRODUCT((B4:B12="Recyclage (process)")*(C4:C12))
A17: FE évitées (kgCO2e/t) | C17: -270
A18: Émissions évitées (tCO2e) | C18: =C16*C17/1000

Sheet Eau
A1: CONSOMMATION D'EAU ET REJETS — ESRS E3 | N1: 🏠 Sommaire | O1: 🏠 Sommaire
A3: Site | B3: Consommation eau (m³) | C3: Eaux usées (m³) | D3: FE eau potable | E3: Émissions eau (kgCO2e) | F3: FE traitement | G3: Émissions traitement (kgCO2e) | H3: Total (kgCO2e) | I3: Total (tCO2e)
B4: 0 | C4: 0 | D4: =Facteurs_Emission!G82 | E4: =B4*D4 | F4: =Facteurs_Emission!G83 | G4: =C4*F4 | H4: =E4+G4 | I4: =H4/1000
B5: 0 | C5: 0 | D5: =Facteurs_Emission!G82 | E5: =B5*D5 | F5: =Facteurs_Emission!G83 | G5: =C5*F5 | H5: =E5+G5 | I5: =H5/1000
B6: 0 | C6: 0 | D6: =Facteurs_Emission!G82 | E6: =B6*D6 | F6: =Facteurs_Emission!G83 | G6: =C6*F6 | H6: =E6+G6 | I6: =H6/1000
B7: 0 | C7: 0 | D7: =Facteurs_Emission!G82 | E7: =B7*D7 | F7: =Facteurs_Emission!G83 | G7: =C7*F7 | H7: =E7+G7 | I7: =H7/1000
B8: 0 | C8: 0 | D8: =Facteurs_Emission!G82 | E8: =B8*D8 | F8: =Facteurs_Emission!G83 | G8: =C8*F8 | H8: =E8+G8 | I8: =H8/1000
B9: 0 | C9: 0 | D9: =Facteurs_Emission!G82 | E9: =B9*D9 | F9: =Facteurs_Emission!G83 | G9: =C9*F9 | H9: =E9+G9 | I9: =H9/1000
B10: 0 | C10: 0 | D10: =Facteurs_Emission!G82 | E10: =B10*D10 | F10: =Facteurs_Emission!G83 | G10: =C10*F10 | H10: =E10+G10 | I10: =H10/1000
B11: 0 | C11: 0 | D11: =Facteurs_Emission!G82 | E11: =B11*D11 | F11: =Facteurs_Emission!G83 | G11: =C11*F11 | H11: =E11+G11 | I11: =H11/1000
A12: TOTAL | B12: =SUM(B4:B11) | C12: =SUM(C4:C11) | E12: =SUM(E4:E11) | G12: =SUM(G4:G11) | H12: =SUM(H4:H11) | I12: =SUM(I4:I11)
A14: Intensité hydrique (m³/salarié) | B14: =IF(Paramètres!B11=0,0,B12/Paramètres!B11)

Sheet Synthese_GES
A1: BILAN D'ÉMISSIONS DE GAZ À EFFET DE SERRE — SYNTHÈSE CONSOLIDÉE | N1: 🏠 Sommaire | O1: 🏠 Sommaire
A2: Format conforme BEGES réglementaire (Art. L229-25) et ESRS E1-6
A4: Poste | B4: Description | C4: Émissions (tCO2e) | D4: % du total | E4: Incertitude (%) | F4: Borne basse | G4: Borne haute | H4: N-1 (tCO2e) | I4: Variation (%) | J4: Var. abs. (tCO2e)
A5: SCOPE 1 — ÉMISSIONS DIRECTES
A6: 1A | B6: Combustion fixe | C6: =Scope_1!I16 -> 0 | D6: =IF($C$47=0,0,C6/$C$47) | E6: 7.5 | F6: =C6*(1-E6/100) | G6: =C6*(1+E6/100) | I6: =IF(H6=0,"—",(C6-H6)/H6) | J6: =C6-H6
A7: 1B | B7: Combustion mobile | C7: =Scope_1!I30 -> 0 | D7: =IF($C$47=0,0,C7/$C$47) | E7: 12 | F7: =C7*(1-E7/100) | G7: =C7*(1+E7/100) | I7: =IF(H7=0,"—",(C7-H7)/H7) | J7: =C7-H7
A8: 1C | B8: Émissions de process | C8: =Scope_1!I42 -> 0 | D8: =IF($C$47=0,0,C8/$C$47) | E8: 17.5 | F8: =C8*(1-E8/100) | G8: =C8*(1+E8/100) | I8: =IF(H8=0,"—",(C8-H8)/H8) | J8: =C8-H8
A9: 1D | B9: Émissions fugitives | C9: =Scope_1!I54 -> 0 | D9: =IF($C$47=0,0,C9/$C$47) | E9: 15 | F9: =C9*(1-E9/100) | G9: =C9*(1+E9/100) | I9: =IF(H9=0,"—",(C9-H9)/H9) | J9: =C9-H9
B10: TOTAL SCOPE 1 | C10: =SUM(C6:C9) -> 0 | D10: =IF($C$47=0,0,C10/$C$47) | F10: =SUM(F6:F9) | G10: =SUM(G6:G9)
A12: SCOPE 2 — ÉMISSIONS INDIRECTES ÉNERGIE
A13: 2A-LB | B13: Électricité (location-based) | C13: =Scope_2!H16 -> 0 | D13: =IF($C$47=0,0,C13/$C$47) | E13: 10 | F13: =C13*(1-E13/100) | G13: =C13*(1+E13/100)
A14: 2B | B14: Chaleur / vapeur / froid | C14: =Scope_2!H29 -> 0 | E14: 17.5 | F14: =C14*(1-E14/100) | G14: =C14*(1+E14/100)
B15: TOTAL SCOPE 2 (Location-based) | C15: =C13+C14 -> 0
A16: 2A-MB | B16: Électricité (market-based) | C16: =Scope_2!K16 -> 0
B17: TOTAL SCOPE 2 (Market-based) | C17: =C16+C14 -> 0
A19: SCOPE 3 — CHAÎNE DE VALEUR
A20: Cat.1 | B20: Achats de biens et services | C20: =Scope_3!I19 -> 0 | D20: =IF($C$47=0,0,C20/$C$47) | E20: 30 | F20: =C20*(1-E20/100) | G20: =C20*(1+E20/100) | I20: =IF(H20=0,"—",(C20-H20)/H20) | J20: =C20-H20
A21: Cat.2 | B21: Biens d'équipement | C21: =Scope_3!I30 -> 0 | D21: =IF($C$47=0,0,C21/$C$47) | E21: 30 | F21: =C21*(1-E21/100) | G21: =C21*(1+E21/100) | I21: =IF(H21=0,"—",(C21-H21)/H21) | J21: =C21-H21
A22: Cat.3 | B22: Combustibles et énergie (amont) | C22: =Scope_3!I38 -> 0 | D22: =IF($C$47=0,0,C22/$C$47) | E22: 12 | F22: =C22*(1-E22/100) | G22: =C22*(1+E22/100) | I22: =IF(H22=0,"—",(C22-H22)/H22) | J22: =C22-H22
A23: Cat.4 | B23: Transport amont | C23: =Scope_3!I51 -> 0 | D23: =IF($C$47=0,0,C23/$C$47) | E23: 20 | F23: =C23*(1-E23/100) | G23: =C23*(1+E23/100) | I23: =IF(H23=0,"—",(C23-H23)/H23) | J23: =C23-H23
A24: Cat.5 | B24: Déchets | C24: =Scope_3!I57 -> 0 | D24: =IF($C$47=0,0,C24/$C$47) | E24: 30 | F24: =C24*(1-E24/100) | G24: =C24*(1+E24/100) | I24: =IF(H24=0,"—",(C24-H24)/H24) | J24: =C24-H24
A25: Cat.6 | B25: Déplacements professionnels | C25: =Scope_3!I63 -> 0 | D25: =IF($C$47=0,0,C25/$C$47) | E25: 15 | F25: =C25*(1-E25/100) | G25: =C25*(1+E25/100) | I25: =IF(H25=0,"—",(C25-H25)/H25) | J25: =C25-H25
A26: Cat.7 | B26: Domicile-travail | C26: =Scope_3!I69 -> 0 | D26: =IF($C$47=0,0,C26/$C$47) | E26: 25 | F26: =C26*(1-E26/100) | G26: =C26*(1+E26/100) | I26: =IF(H26=0,"—",(C26-H26)/H26) | J26: =C26-H26
A27: Cat.8 | B27: Actifs loués amont | C27: =Scope_3!I77 -> 0 | D27: =IF($C$47=0,0,C27/$C$47) | E27: 30 | F27: =C27*(1-E27/100) | G27: =C27*(1+E27/100) | I27: =IF(H27=0,"—",(C27-H27)/H27) | J27: =C27-H27
A28: Cat.9 | B28: Transport aval | C28: =Scope_3!I87 -> 0 | D28: =IF($C$47=0,0,C28/$C$47) | E28: 25 | F28: =C28*(1-E28/100) | G28: =C28*(1+E28/100) | I28: =IF(H28=0,"—",(C28-H28)/H28) | J28: =C28-H28
A29: Cat.10 | B29: Transformation produits vendus | C29: =Scope_3!I95 -> 0 | D29: =IF($C$47=0,0,C29/$C$47) | E29: 40 | F29: =C29*(1-E29/100) | G29: =C29*(1+E29/100) | I29: =IF(H29=0,"—",(C29-H29)/H29) | J29: =C29-H29
A30: Cat.11 | B30: Utilisation produits vendus | C30: =Scope_3!I105 -> 0 | D30: =IF($C$47=0,0,C30/$C$47) | E30: 50 | F30: =C30*(1-E30/100) | G30: =C30*(1+E30/100) | I30: =IF(H30=0,"—",(C30-H30)/H30) | J30: =C30-H30
A31: Cat.12 | B31: Fin de vie produits | C31: =Scope_3!I113 -> 0 | D31: =IF($C$47=0,0,C31/$C$47) | E31: 40 | F31: =C31*(1-E31/100) | G31: =C31*(1+E31/100) | I31: =IF(H31=0,"—",(C31-H31)/H31) | J31: =C31-H31
A32: Cat.13 | B32: Actifs loués aval | C32: =Scope_3!I121 -> 0 | D32: =IF($C$47=0,0,C32/$C$47) | E32: 30 | F32: =C32*(1-E32/100) | G32: =C32*(1+E32/100) | I32: =IF(H32=0,"—",(C32-H32)/H32) | J32: =C32-H32
A33: Cat.14 | B33: Franchises | C33: =Scope_3!I129 -> 0 | D33: =IF($C$47=0,0,C33/$C$47) | E33: 30 | F33: =C33*(1-E33/100) | G33: =C33*(1+E33/100) | I33: =IF(H33=0,"—",(C33-H33)/H33) | J33: =C33-H33
A34: Cat.15 | B34: Investissements | C34: =Scope_3!I137 -> 0 | D34: =IF($C$47=0,0,C34/$C$47) | E34: 50 | F34: =C34*(1-E34/100) | G34: =C34*(1+E34/100) | I34: =IF(H34=0,"—",(C34-H34)/H34) | J34: =C34-H34
B35: TOTAL SCOPE 3 | C35: =SUM(C20:C34) -> 0
B37: TOTAL SCOPE 1 + 2 (Location-based) | C37: =C10+C15 -> 0
B47: TOTAL SCOPE 1 + 2 + 3 | C47: =C10+C15+C35 -> 0
A49: INDICATEURS D'INTENSITÉ CARBONE
B50: Intensité / CA (tCO2e/M€) | C50: =IF(Paramètres!B9=0,0,C47/(Paramètres!B9/1000000)) -> 0
B51: Intensité / salarié (tCO2e/ETP) | C51: =IF(Paramètres!B11=0,0,C47/Paramètres!B11) -> 0
B52: Intensité / m² (kgCO2e/m²) | C52: =IF(Paramètres!B12=0,0,C47*1000/Paramètres!B12) -> 0
B53: Part Scope 1 (%) | C53: =IF(C47=0,0,ROUND(C10/C47*100,1)) -> 0
B54: Part Scope 2 (%) | C54: =IF(C47=0,0,ROUND(C15/C47*100,1)) -> 0
B55: Part Scope 3 (%) | C55: =IF(C47=0,0,ROUND(C35/C47*100,1)) -> 0

Sheet Intensite_Carbone
A1: RATIOS D'INTENSITÉ CARBONE — BENCHMARKING ET ESRS E1 | N1: 🏠 Sommaire | O1: 🏠 Sommaire
A3: Indicateur | B3: Valeur | C3: Unité | D3: Benchmark sectoriel | E3: Position
A4: Intensité / CA net | B4: =IF(Paramètres!B9=0,0,Synthese_GES!C47/(Paramètres!B9/1000000)) | C4: tCO2e / M€ | D4: 0 | E4: =IF(D4=0,"—",IF(B4<D4,"✅ Sous benchmark","⚠️ Au-dessus"))
A5: Intensité / salarié | B5: =IF(Paramètres!B11=0,0,Synthese_GES!C47/Paramètres!B11) | C5: tCO2e / ETP | D5: 0 | E5: =IF(D5=0,"—",IF(B5<D5,"✅ Sous benchmark","⚠️ Au-dessus"))
A6: Intensité / m² | B6: =IF(Paramètres!B12=0,0,Synthese_GES!C47*1000/Paramètres!B12) | C6: kgCO2e / m² | D6: 0 | E6: =IF(D6=0,"—",IF(B6<D6,"✅ Sous benchmark","⚠️ Au-dessus"))
A7: Part énergie renouvelable | B7: =Energie!E20 | C7: % | D7: 0 | E7: =IF(D7=0,"—",IF(B7<D7,"✅ Sous benchmark","⚠️ Au-dessus"))
A8: Part Scope 3 / total | B8: =IF(Synthese_GES!C47=0,0,Synthese_GES!C35/Synthese_GES!C47) | C8: % | D8: 0 | E8: =IF(D8=0,"—",IF(B8<D8,"✅ Sous benchmark","⚠️ Au-dessus"))

Sheet Trajectoire_SBTi
A1: TRAJECTOIRE DE RÉDUCTION — SCIENCE BASED TARGETS | N1: 🏠 Sommaire | O1: 🏠 Sommaire
A2: Méthode linéaire absolue. SBTi : 4,2%/an Scope 1+2 pour 1.5°C, min. 2,5%/an Scope 3.
A4: Année de référence (baseline)
A5: Émissions Scope 1+2 baseline (tCO2e)
A6: Émissions Scope 3 baseline (tCO2e)
A7: Objectif SBTi | B7: 1.5°C — Near-term
A8: Réduction visée Scope 1+2 à l'horizon (%) | B8: 42
A9: Réduction visée Scope 3 à l'horizon (%) | B9: 25
A10: Horizon (année cible) | B10: =B4+10
A11: Objectifs validés SBTi (O/N)
A13: TRAJECTOIRE SCOPE 1+2
A14: Année | B14: Cible SBTi S1+2 (tCO2e) | C14: Réel S1+2 (tCO2e) | D14: Écart absolu | E14: Écart (%) | F14: Réduction cumulée cible (%) | G14: Réduction cumulée réelle (%)
A15: =$B$4+0 | B15: =$B$5*(1-($B$8/100)*0) | C15: =B5 | D15: =IF(C15="","",C15-B15) | E15: =IF(OR(C15="",B15=0),"",D15/B15) | F15: =IF($B$15=0,0,1-B15/$B$15) | G15: =IF(OR(C15="",$C$15=0),"",1-C15/$C$15)
A16: =$B$4+1 | B16: =$B$5*(1-($B$8/100)*1) | D16: =IF(C16="","",C16-B16) | E16: =IF(OR(C16="",B16=0),"",D16/B16) | F16: =IF($B$15=0,0,1-B16/$B$15) | G16: =IF(OR(C16="",$C$15=0),"",1-C16/$C$15)
A17: =$B$4+2 | B17: =$B$5*(1-($B$8/100)*2) | D17: =IF(C17="","",C17-B17) | E17: =IF(OR(C17="",B17=0),"",D17/B17) | F17: =IF($B$15=0,0,1-B17/$B$15) | G17: =IF(OR(C17="",$C$15=0),"",1-C17/$C$15)
A18: =$B$4+3 | B18: =$B$5*(1-($B$8/100)*3) | D18: =IF(C18="","",C18-B18) | E18: =IF(OR(C18="",B18=0),"",D18/B18) | F18: =IF($B$15=0,0,1-B18/$B$15) | G18: =IF(OR(C18="",$C$15=0),"",1-C18/$C$15)
A19: =$B$4+4 | B19: =$B$5*(1-($B$8/100)*4) | D19: =IF(C19="","",C19-B19) | E19: =IF(OR(C19="",B19=0),"",D19/B19) | F19: =IF($B$15=0,0,1-B19/$B$15) | G19: =IF(OR(C19="",$C$15=0),"",1-C19/$C$15)
A20: =$B$4+5 | B20: =$B$5*(1-($B$8/100)*5) | D20: =IF(C20="","",C20-B20) | E20: =IF(OR(C20="",B20=0),"",D20/B20) | F20: =IF($B$15=0,0,1-B20/$B$15) | G20: =IF(OR(C20="",$C$15=0),"",1-C20/$C$15)
A21: =$B$4+6 | B21: =$B$5*(1-($B$8/100)*6) | D21: =IF(C21="","",C21-B21) | E21: =IF(OR(C21="",B21=0),"",D21/B21) | F21: =IF($B$15=0,0,1-B21/$B$15) | G21: =IF(OR(C21="",$C$15=0),"",1-C21/$C$15)
A22: =$B$4+7 | B22: =$B$5*(1-($B$8/100)*7) | D22: =IF(C22="","",C22-B22) | E22: =IF(OR(C22="",B22=0),"",D22/B22) | F22: =IF($B$15=0,0,1-B22/$B$15) | G22: =IF(OR(C22="",$C$15=0),"",1-C22/$C$15)
A23: =$B$4+8 | B23: =$B$5*(1-($B$8/100)*8) | D23: =IF(C23="","",C23-B23) | E23: =IF(OR(C23="",B23=0),"",D23/B23) | F23: =IF($B$15=0,0,1-B23/$B$15) | G23: =IF(OR(C23="",$C$15=0),"",1-C23/$C$15)
A24: =$B$4+9 | B24: =$B$5*(1-($B$8/100)*9) | D24: =IF(C24="","",C24-B24) | E24: =IF(OR(C24="",B24=0),"",D24/B24) | F24: =IF($B$15=0,0,1-B24/$B$15) | G24: =IF(OR(C24="",$C$15=0),"",1-C24/$C$15)
A25: =$B$4+10 | B25: =$B$5*(1-($B$8/100)*10) | D25: =IF(C25="","",C25-B25) | E25: =IF(OR(C25="",B25=0),"",D25/B25) | F25: =IF($B$15=0,0,1-B25/$B$15) | G25: =IF(OR(C25="",$C$15=0),"",1-C25/$C$15)
A27: TRAJECTOIRE SCOPE 3
A28: Année | B28: Cible SBTi S3 (tCO2e) | C28: Réel S3 (tCO2e) | D28: Écart absolu | E28: Écart (%) | F28: Réduction cumulée cible (%) | G28: Réduction cumulée réelle (%)
A29: =$B$4+0 | B29: =$B$6*(1-($B$9/100)*0) | C29: =B6 | D29: =IF(C29="","",C29-B29) | E29: =IF(OR(C29="",B29=0),"",D29/B29) | F29: =IF($B$29=0,0,1-B29/$B$29) | G29: =IF(OR(C29="",$C$29=0),"",1-C29/$C$29)
A30: =$B$4+1 | B30: =$B$6*(1-($B$9/100)*1) | D30: =IF(C30="","",C30-B30) | E30: =IF(OR(C30="",B30=0),"",D30/B30) | F30: =IF($B$29=0,0,1-B30/$B$29) | G30: =IF(OR(C30="",$C$29=0),"",1-C30/$C$29)
A31: =$B$4+2 | B31: =$B$6*(1-($B$9/100)*2) | D31: =IF(C31="","",C31-B31) | E31: =IF(OR(C31="",B31=0),"",D31/B31) | F31: =IF($B$29=0,0,1-B31/$B$29) | G31: =IF(OR(C31="",$C$29=0),"",1-C31/$C$29)
A32: =$B$4+3 | B32: =$B$6*(1-($B$9/100)*3) | D32: =IF(C32="","",C32-B32) | E32: =IF(OR(C32="",B32=0),"",D32/B32) | F32: =IF($B$29=0,0,1-B32/$B$29) | G32: =IF(OR(C32="",$C$29=0),"",1-C32/$C$29)
A33: =$B$4+4 | B33: =$B$6*(1-($B$9/100)*4) | D33: =IF(C33="","",C33-B33) | E33: =IF(OR(C33="",B33=0),"",D33/B33) | F33: =IF($B$29=0,0,1-B33/$B$29) | G33: =IF(OR(C33="",$C$29=0),"",1-C33/$C$29)
A34: =$B$4+5 | B34: =$B$6*(1-($B$9/100)*5) | D34: =IF(C34="","",C34-B34) | E34: =IF(OR(C34="",B34=0),"",D34/B34) | F34: =IF($B$29=0,0,1-B34/$B$29) | G34: =IF(OR(C34="",$C$29=0),"",1-C34/$C$29)
A35: =$B$4+6 | B35: =$B$6*(1-($B$9/100)*6) | D35: =IF(C35="","",C35-B35) | E35: =IF(OR(C35="",B35=0),"",D35/B35) | F35: =IF($B$29=0,0,1-B35/$B$29) | G35: =IF(OR(C35="",$C$29=0),"",1-C35/$C$29)
A36: =$B$4+7 | B36: =$B$6*(1-($B$9/100)*7) | D36: =IF(C36="","",C36-B36) | E36: =IF(OR(C36="",B36=0),"",D36/B36) | F36: =IF($B$29=0,0,1-B36/$B$29) | G36: =IF(OR(C36="",$C$29=0),"",1-C36/$C$29)
A37: =$B$4+8 | B37: =$B$6*(1-($B$9/100)*8) | D37: =IF(C37="","",C37-B37) | E37: =IF(OR(C37="",B37=0),"",D37/B37) | F37: =IF($B$29=0,0,1-B37/$B$29) | G37: =IF(OR(C37="",$C$29=0),"",1-C37/$C$29)
A38: =$B$4+9 | B38: =$B$6*(1-($B$9/100)*9) | D38: =IF(C38="","",C38-B38) | E38: =IF(OR(C38="",B38=0),"",D38/B38) | F38: =IF($B$29=0,0,1-B38/$B$29) | G38: =IF(OR(C38="",$C$29=0),"",1-C38/$C$29)
A39: =$B$4+10 | B39: =$B$6*(1-($B$9/100)*10) | D39: =IF(C39="","",C39-B39) | E39: =IF(OR(C39="",B39=0),"",D39/B39) | F39: =IF($B$29=0,0,1-B39/$B$29) | G39: =IF(OR(C39="",$C$29=0),"",1-C39/$C$29)

Sheet CBAM
A1: MÉCANISME D'AJUSTEMENT CARBONE AUX FRONTIÈRES (CBAM) | N1: 🏠 Sommaire | O1: 🏠 Sommaire
A2: Règlement (UE) 2023/956 — Phase définitive depuis le 1er janvier 2026
A4: Prix du quota EU ETS (€/tCO2) — à actualiser | B4: 70
A5: Année des importations (déclaration annuelle) | B5: 2026
A6: Part des émissions couverte par des certificats (règl. (UE) 2023/956, art. 31) | B6: =IF(B5="","",IF(B5<2026,0,IF(B5=2026,0.025,IF(B5=2027,0.05,IF(B5=2028,0.1,IF(B5=2029,0.225,IF(B5=2030,0.485,IF(B5=2031,0.61,IF(B5=2032,0.735,IF(B5=2033,0.86,1)))))))))) -> 0.025
A8: Ligne | B8: Produit CBAM | C8: Code NC | D8: Pays d'origine | E8: Quantité (t) | F8: Émissions dir. (tCO2/t) | G8: Indir. (O/N) | H8: Émissions indir. (tCO2/t) | I8: Total émissions (tCO2) | J8: Prix carbone payé (€/tCO2) | K8: Déduction (€) | L8: Certificats CBAM | M8: Coût CBAM (€)
A9: 1 | E9: 0 | F9: =IF(B9="","",IF(B9="Acier et fer",1.85,IF(B9="Aluminium",6.7,IF(B9="Ciment",0.64,IF(B9="Engrais azotés",2.56,IF(B9="Électricité",0.42,IF(B9="Hydrogène",9,0))))))) | G9: =IF(B9="","",IF(OR(B9="Ciment",B9="Engrais azotés",B9="Hydrogène"),"OUI","NON")) | H9: 0 | I9: =IF(B9="",0,E9*F9+IF(G9="OUI",E9*H9,0)) -> 0 | J9: 0 | K9: =I9*J9 | L9: =I9 | M9: =IF(OR(B9="",$B$6=""),0,MAX(0,I9*$B$4*$B$6-K9)) -> 0
A10: 2 | E10: 0 | F10: =IF(B10="","",IF(B10="Acier et fer",1.85,IF(B10="Aluminium",6.7,IF(B10="Ciment",0.64,IF(B10="Engrais azotés",2.56,IF(B10="Électricité",0.42,IF(B10="Hydrogène",9,0))))))) | G10: =IF(B10="","",IF(OR(B10="Ciment",B10="Engrais azotés",B10="Hydrogène"),"OUI","NON")) | H10: 0 | I10: =IF(B10="",0,E10*F10+IF(G10="OUI",E10*H10,0)) -> 0 | J10: 0 | K10: =I10*J10 | L10: =I10 | M10: =IF(OR(B10="",$B$6=""),0,MAX(0,I10*$B$4*$B$6-K10)) -> 0
A11: 3 | E11: 0 | F11: =IF(B11="","",IF(B11="Acier et fer",1.85,IF(B11="Aluminium",6.7,IF(B11="Ciment",0.64,IF(B11="Engrais azotés",2.56,IF(B11="Électricité",0.42,IF(B11="Hydrogène",9,0))))))) | G11: =IF(B11="","",IF(OR(B11="Ciment",B11="Engrais azotés",B11="Hydrogène"),"OUI","NON")) | H11: 0 | I11: =IF(B11="",0,E11*F11+IF(G11="OUI",E11*H11,0)) -> 0 | J11: 0 | K11: =I11*J11 | L11: =I11 | M11: =IF(OR(B11="",$B$6=""),0,MAX(0,I11*$B$4*$B$6-K11)) -> 0
A12: 4 | E12: 0 | F12: =IF(B12="","",IF(B12="Acier et fer",1.85,IF(B12="Aluminium",6.7,IF(B12="Ciment",0.64,IF(B12="Engrais azotés",2.56,IF(B12="Électricité",0.42,IF(B12="Hydrogène",9,0))))))) | G12: =IF(B12="","",IF(OR(B12="Ciment",B12="Engrais azotés",B12="Hydrogène"),"OUI","NON")) | H12: 0 | I12: =IF(B12="",0,E12*F12+IF(G12="OUI",E12*H12,0)) -> 0 | J12: 0 | K12: =I12*J12 | L12: =I12 | M12: =IF(OR(B12="",$B$6=""),0,MAX(0,I12*$B$4*$B$6-K12)) -> 0
A13: 5 | E13: 0 | F13: =IF(B13="","",IF(B13="Acier et fer",1.85,IF(B13="Aluminium",6.7,IF(B13="Ciment",0.64,IF(B13="Engrais azotés",2.56,IF(B13="Électricité",0.42,IF(B13="Hydrogène",9,0))))))) | G13: =IF(B13="","",IF(OR(B13="Ciment",B13="Engrais azotés",B13="Hydrogène"),"OUI","NON")) | H13: 0 | I13: =IF(B13="",0,E13*F13+IF(G13="OUI",E13*H13,0)) -> 0 | J13: 0 | K13: =I13*J13 | L13: =I13 | M13: =IF(OR(B13="",$B$6=""),0,MAX(0,I13*$B$4*$B$6-K13)) -> 0
A14: 6 | E14: 0 | F14: =IF(B14="","",IF(B14="Acier et fer",1.85,IF(B14="Aluminium",6.7,IF(B14="Ciment",0.64,IF(B14="Engrais azotés",2.56,IF(B14="Électricité",0.42,IF(B14="Hydrogène",9,0))))))) | G14: =IF(B14="","",IF(OR(B14="Ciment",B14="Engrais azotés",B14="Hydrogène"),"OUI","NON")) | H14: 0 | I14: =IF(B14="",0,E14*F14+IF(G14="OUI",E14*H14,0)) -> 0 | J14: 0 | K14: =I14*J14 | L14: =I14 | M14: =IF(OR(B14="",$B$6=""),0,MAX(0,I14*$B$4*$B$6-K14)) -> 0
A15: 7 | E15: 0 | F15: =IF(B15="","",IF(B15="Acier et fer",1.85,IF(B15="Aluminium",6.7,IF(B15="Ciment",0.64,IF(B15="Engrais azotés",2.56,IF(B15="Électricité",0.42,IF(B15="Hydrogène",9,0))))))) | G15: =IF(B15="","",IF(OR(B15="Ciment",B15="Engrais azotés",B15="Hydrogène"),"OUI","NON")) | H15: 0 | I15: =IF(B15="",0,E15*F15+IF(G15="OUI",E15*H15,0)) -> 0 | J15: 0 | K15: =I15*J15 | L15: =I15 | M15: =IF(OR(B15="",$B$6=""),0,MAX(0,I15*$B$4*$B$6-K15)) -> 0
A16: 8 | E16: 0 | F16: =IF(B16="","",IF(B16="Acier et fer",1.85,IF(B16="Aluminium",6.7,IF(B16="Ciment",0.64,IF(B16="Engrais azotés",2.56,IF(B16="Électricité",0.42,IF(B16="Hydrogène",9,0))))))) | G16: =IF(B16="","",IF(OR(B16="Ciment",B16="Engrais azotés",B16="Hydrogène"),"OUI","NON")) | H16: 0 | I16: =IF(B16="",0,E16*F16+IF(G16="OUI",E16*H16,0)) -> 0 | J16: 0 | K16: =I16*J16 | L16: =I16 | M16: =IF(OR(B16="",$B$6=""),0,MAX(0,I16*$B$4*$B$6-K16)) -> 0
A17: 9 | E17: 0 | F17: =IF(B17="","",IF(B17="Acier et fer",1.85,IF(B17="Aluminium",6.7,IF(B17="Ciment",0.64,IF(B17="Engrais azotés",2.56,IF(B17="Électricité",0.42,IF(B17="Hydrogène",9,0))))))) | G17: =IF(B17="","",IF(OR(B17="Ciment",B17="Engrais azotés",B17="Hydrogène"),"OUI","NON")) | H17: 0 | I17: =IF(B17="",0,E17*F17+IF(G17="OUI",E17*H17,0)) -> 0 | J17: 0 | K17: =I17*J17 | L17: =I17 | M17: =IF(OR(B17="",$B$6=""),0,MAX(0,I17*$B$4*$B$6-K17)) -> 0
A18: 10 | E18: 0 | F18: =IF(B18="","",IF(B18="Acier et fer",1.85,IF(B18="Aluminium",6.7,IF(B18="Ciment",0.64,IF(B18="Engrais azotés",2.56,IF(B18="Électricité",0.42,IF(B18="Hydrogène",9,0))))))) | G18: =IF(B18="","",IF(OR(B18="Ciment",B18="Engrais azotés",B18="Hydrogène"),"OUI","NON")) | H18: 0 | I18: =IF(B18="",0,E18*F18+IF(G18="OUI",E18*H18,0)) -> 0 | J18: 0 | K18: =I18*J18 | L18: =I18 | M18: =IF(OR(B18="",$B$6=""),0,MAX(0,I18*$B$4*$B$6-K18)) -> 0
A19: 11 | E19: 0 | F19: =IF(B19="","",IF(B19="Acier et fer",1.85,IF(B19="Aluminium",6.7,IF(B19="Ciment",0.64,IF(B19="Engrais azotés",2.56,IF(B19="Électricité",0.42,IF(B19="Hydrogène",9,0))))))) | G19: =IF(B19="","",IF(OR(B19="Ciment",B19="Engrais azotés",B19="Hydrogène"),"OUI","NON")) | H19: 0 | I19: =IF(B19="",0,E19*F19+IF(G19="OUI",E19*H19,0)) -> 0 | J19: 0 | K19: =I19*J19 | L19: =I19 | M19: =IF(OR(B19="",$B$6=""),0,MAX(0,I19*$B$4*$B$6-K19)) -> 0
A20: 12 | E20: 0 | F20: =IF(B20="","",IF(B20="Acier et fer",1.85,IF(B20="Aluminium",6.7,IF(B20="Ciment",0.64,IF(B20="Engrais azotés",2.56,IF(B20="Électricité",0.42,IF(B20="Hydrogène",9,0))))))) | G20: =IF(B20="","",IF(OR(B20="Ciment",B20="Engrais azotés",B20="Hydrogène"),"OUI","NON")) | H20: 0 | I20: =IF(B20="",0,E20*F20+IF(G20="OUI",E20*H20,0)) -> 0 | J20: 0 | K20: =I20*J20 | L20: =I20 | M20: =IF(OR(B20="",$B$6=""),0,MAX(0,I20*$B$4*$B$6-K20)) -> 0
... A23: 15 | E23: 0 | F23: =IF(B23="","",IF(B23="Acier et fer",1.85,IF(B23="Aluminium",6.7,IF(B23="Ciment",0.64,IF(B23="Engrais azotés",2.56,IF(B23="Électricité",0.42,IF(B23="Hydrogène",9,0))))))) | G23: =IF(B23="","",IF(OR(B23="Ciment",B23="Engrais azotés",B23="Hydrogène"),"OUI","NON")) | H23: 0 | I23: =IF(B23="",0,E23*F23+IF(G23="OUI",E23*H23,0)) -> 0 | J23: 0 | K23: =I23*J23 | L23: =I23 | M23: =IF(OR(B23="",$B$6=""),0,MAX(0,I23*$B$4*$B$6-K23)) -> 0
B24: TOTAL | E24: =SUM(E9:E23) | I24: =SUM(I9:I23) | K24: =SUM(K9:K23) | L24: =SUM(L9:L23) | M24: =SUM(M9:M23) -> 0
B26: COÛT CBAM TOTAL ESTIMÉ | M26: =M24

Sheet Taxonomie
A1: ALIGNEMENT TAXONOMIE VERTE EUROPÉENNE | N1: 🏠 Sommaire | O1: 🏠 Sommaire
A3: LES 6 OBJECTIFS ENVIRONNEMENTAUX
A4: 1 | B4: Atténuation du changement climatique | C4: Delegated Act 2021/2139
A5: 2 | B5: Adaptation au changement climatique | C5: Delegated Act 2021/2139
A6: 3 | B6: Utilisation durable eaux et ressources marines | C6: Delegated Act 2023/2486
A7: 4 | B7: Transition vers économie circulaire | C7: Delegated Act 2023/2486
A8: 5 | B8: Prévention et réduction de la pollution | C8: Delegated Act 2023/2486
A9: 6 | B9: Protection biodiversité et écosystèmes | C9: Delegated Act 2023/2486
A12: TABLEAU DES ACTIVITÉS ÉCONOMIQUES
A13: Activité économique | B13: Code NACE | C13: Éligible (O/N) | D13: CS — Obj. n° | E13: DNSH (O/N) | F13: Garanties min. (O/N) | G13: ALIGNÉE (O/N) | H13: CA associé (€) | I13: CapEx associé (€) | J13: OpEx associé (€)
G14: =IF(AND(C14="O",D14<>"",E14="O",F14="O"),"O","N") | H14: 0 | I14: 0 | J14: 0
G15: =IF(AND(C15="O",D15<>"",E15="O",F15="O"),"O","N") | H15: 0 | I15: 0 | J15: 0
G16: =IF(AND(C16="O",D16<>"",E16="O",F16="O"),"O","N") | H16: 0 | I16: 0 | J16: 0
G17: =IF(AND(C17="O",D17<>"",E17="O",F17="O"),"O","N") | H17: 0 | I17: 0 | J17: 0
G18: =IF(AND(C18="O",D18<>"",E18="O",F18="O"),"O","N") | H18: 0 | I18: 0 | J18: 0
G19: =IF(AND(C19="O",D19<>"",E19="O",F19="O"),"O","N") | H19: 0 | I19: 0 | J19: 0
G20: =IF(AND(C20="O",D20<>"",E20="O",F20="O"),"O","N") | H20: 0 | I20: 0 | J20: 0
G21: =IF(AND(C21="O",D21<>"",E21="O",F21="O"),"O","N") | H21: 0 | I21: 0 | J21: 0
G22: =IF(AND(C22="O",D22<>"",E22="O",F22="O"),"O","N") | H22: 0 | I22: 0 | J22: 0
G23: =IF(AND(C23="O",D23<>"",E23="O",F23="O"),"O","N") | H23: 0 | I23: 0 | J23: 0
A25: KPIs TAXONOMIE — ARTICLE 8
A26: KPI | B26: Éligible (€) | C26: Éligible (%) | D26: Aligné (€) | E26: Aligné (%) | F26: Dénominateur (€)
A27: CHIFFRE D'AFFAIRES | B27: =SUMPRODUCT((C14:C23="O")*(H14:H23)) | C27: =IF(Paramètres!B9=0,0,B27/Paramètres!B9) | D27: =SUMPRODUCT((G14:G23="O")*(H14:H23)) | E27: =IF(F27=0,0,ROUND(D27/F27*100,1)) -> 0 | F27: =Paramètres!B9
A28: CAPEX | B28: =SUMPRODUCT((C14:C23="O")*(I14:I23)) | C28: =IF(Paramètres!B14=0,0,B28/Paramètres!B14) | D28: =SUMPRODUCT((G14:G23="O")*(I14:I23)) | E28: =IF(F28=0,0,ROUND(D28/F28*100,1)) -> 0 | F28: =Paramètres!B14
A29: OPEX | B29: =SUMPRODUCT((C14:C23="O")*(J14:J23)) | C29: =IF(Paramètres!B15=0,0,B29/Paramètres!B15) | D29: =SUMPRODUCT((G14:G23="O")*(J14:J23)) | E29: =IF(F29=0,0,ROUND(D29/F29*100,1)) -> 0 | F29: =Paramètres!B15

Sheet ESRS_E1
A1: ESRS E1 — CHANGEMENT CLIMATIQUE — DATA POINTS | N1: 🏠 Sommaire | O1: 🏠 Sommaire
A2: Delegated Regulation (EU) 2023/2772 — Annexe A
A3: Data point / Disclosure Requirement | B3: Référence ESRS | C3: Valeur / Réponse | D3: Source dans CarbonCo | E3: Statut
A4: E1-1 — PLAN DE TRANSITION POUR L'ATTÉNUATION
A5: L'entreprise a-t-elle adopté un plan de transition climat ? | B5: E1-1 §14 | D5: Saisie | E5: À compléter
A6: Objectifs de réduction GES alignés 1.5°C à 2030 | B6: E1-1 §16(a) | C6: =Trajectoire_SBTi!F20 | D6: Trajectoire_SBTi | E6: Auto
A7: Le plan est-il aligné sur l'Accord de Paris ? | B7: E1-1 §16(b) | D7: Saisie | E7: À compléter
A8: E1-4 — CIBLES
A9: Objectif absolu réduction Scope 1+2 (%) | B9: E1-4 §34 | C9: =Trajectoire_SBTi!F25 | D9: Trajectoire_SBTi | E9: Auto
A10: Année de référence | B10: E1-4 §34(c) | C10: =Paramètres!B7 | D10: Paramètres | E10: Auto
A11: Année cible | B11: E1-4 §34(d) | C11: =Trajectoire_SBTi!B10 | D11: Trajectoire_SBTi | E11: Auto
A12: Les objectifs sont-ils validés SBTi ? | B12: E1-4 §36 | C12: =Trajectoire_SBTi!B11 | D12: Trajectoire_SBTi | E12: Auto
A13: E1-5 — CONSOMMATION D'ÉNERGIE ET MIX ÉNERGÉTIQUE
A14: Consommation totale d'énergie (MWh) | B14: E1-5 §37 | C14: =Energie!E19 | D14: Energie | E14: Auto
A15: Consommation énergie non-renouvelable (MWh) | B15: E1-5 §37(a) | C15: =Energie!E10 | D15: Energie | E15: Auto
A16: Consommation énergie renouvelable (MWh) | B16: E1-5 §37(b) | C16: =Energie!E16 | D16: Energie | E16: Auto
A17: Part énergie renouvelable (%) | B17: E1-5 §38 | C17: =Energie!E20 | D17: Energie | E17: Auto
A18: E1-6 — ÉMISSIONS BRUTES DE GES
A19: Scope 1 total (tCO2e) | B19: E1-6 §44(a) | C19: =Synthese_GES!C10 | D19: Synthese_GES | E19: Auto
A20: Scope 2 location-based (tCO2e) | B20: E1-6 §44(b) | C20: =Synthese_GES!C15 | D20: Synthese_GES | E20: Auto
A21: Scope 2 market-based (tCO2e) | B21: E1-6 §44(b) | C21: =Synthese_GES!C17 | D21: Synthese_GES | E21: Auto
A22: Scope 3 total (tCO2e) | B22: E1-6 §51 | C22: =Synthese_GES!C35 | D22: Synthese_GES | E22: Auto
A23: Total GES (Scope 1+2+3) (tCO2e) | B23: E1-6 §55 | C23: =Synthese_GES!C47 | D23: Synthese_GES | E23: Auto
A24: Intensité GES / CA net (tCO2e/M€) | B24: E1-6 §53 | C24: =Synthese_GES!C50 | D24: Synthese_GES | E24: Auto
A25: E1-7 — ABSORPTIONS ET CRÉDITS CARBONE
A26: Absorptions GES propres (tCO2e) | B26: E1-7 §56 | D26: Saisie | E26: À compléter
A27: Crédits carbone achetés (tCO2e) | B27: E1-7 §58 | D27: Saisie | E27: À compléter
A28: E1-8 — TARIFICATION INTERNE DU CARBONE
A29: Prix interne du carbone (€/tCO2e) | B29: E1-8 §62 | D29: Saisie | E29: À compléter
A30: E1-9 — EFFETS FINANCIERS ANTICIPÉS
A31: Actifs exposés aux risques physiques (€) | B31: E1-9 §66 | D31: Saisie | E31: À compléter
A32: Actifs échoués potentiels (€) | B32: E1-9 §69 | D32: Saisie | E32: À compléter
A35: SCORE DE COMPLÉTUDE
A36: Data points Auto | B36: =COUNTIF(E4:E100,"Auto")
A37: Data points Complétés | B37: =COUNTIF(E4:E100,"Complété")
A38: Data points À compléter | B38: =COUNTIF(E4:E100,"À compléter")

Sheet Incertitudes
A1: ANALYSE D'INCERTITUDE — ISO 14064-1:2018 §9.2 / ESRS E1-6 §49 | N1: 🏠 Sommaire | O1: 📄 Couverture
A2: Propagation des incertitudes par méthode quadratique (√(Σ(εi×ui)²) / Σεi). Source : ADEME Guide sectoriel v5 + ISO 14064-1:2018 §9.2
A4: Catégorie d'émission | B4: Source donnée (niveau 1-5) | C4: Incertitude donnée d'activité (%) | D4: Incertitude facteur d'émission (%) | E4: Incertitude combinée (%) | F4: Émissions (tCO2e) | G4: Contribution incertitude totale | H4: Méthode / Commentaire
A5: SCOPE 1 — ÉMISSIONS DIRECTES
A6: Scope 1 — 1A Combustion fixe | B6: 3 | C6: 5 | D6: 5 | E6: =SQRT(C6^2+D6^2) | F6: =Synthese_GES!C6 | G6: =IF(F6=0,0,(F6*E6/100)^2) | H6: Mesure directe (compteurs)
A7: Scope 1 — 1B Combustion mobile | B7: 3 | C7: 5 | D7: 10 | E7: =SQRT(C7^2+D7^2) | F7: =Synthese_GES!C7 | G7: =IF(F7=0,0,(F7*E7/100)^2) | H7: Estimé km + conso moyenne
A8: Scope 1 — 1C Émissions de process | B8: 4 | C8: 10 | D8: 15 | E8: =SQRT(C8^2+D8^2) | F8: =Synthese_GES!C8 | G8: =IF(F8=0,0,(F8*E8/100)^2) | H8: Estimation ingénierie
A9: Scope 1 — 1D Émissions fugitives | B9: 3 | C9: 10 | D9: 10 | E9: =SQRT(C9^2+D9^2) | F9: =Synthese_GES!C9 | G9: =IF(F9=0,0,(F9*E9/100)^2) | H9: Recharge clim (±bilan)
A10: TOTAL SCOPE 1 | E10: =IF(F10=0,0,SQRT(G10)/F10*100) | F10: =SUM(F6:F9) | G10: =SUM(G6:G9)
A12: SCOPE 2 — ÉMISSIONS INDIRECTES ÉNERGIE
A13: Scope 2 LB — Électricité (location-based) | B13: 2 | C13: 5 | D13: 8 | E13: =SQRT(C13^2+D13^2) | F13: =Synthese_GES!C13 | G13: =IF(F13=0,0,(F13*E13/100)^2) | H13: FE réseau ADEME ±10%
A14: Scope 2 — Chaleur / vapeur / froid | B14: 3 | C14: 10 | D14: 15 | E14: =SQRT(C14^2+D14^2) | F14: =Synthese_GES!C14 | G14: =IF(F14=0,0,(F14*E14/100)^2) | H14: FE réseau chaleur estimé
A15: TOTAL SCOPE 2 (Location-based) | E15: =IF(F15=0,0,SQRT(G15)/F15*100) | F15: =SUM(F13:F14) | G15: =SUM(G13:G14)
A17: SCOPE 3 — CHAÎNE DE VALEUR
A18: Scope 3 Cat.1 — Achats de biens et services | B18: 4 | C18: 20 | D18: 30 | E18: =SQRT(C18^2+D18^2) | F18: =Synthese_GES!C20 | G18: =IF(F18=0,0,(F18*E18/100)^2) | H18: Mixte monétaire/physique ±30%
A19: Scope 3 Cat.2 — Biens d'équipement | B19: 4 | C19: 20 | D19: 30 | E19: =SQRT(C19^2+D19^2) | F19: =Synthese_GES!C21 | G19: =IF(F19=0,0,(F19*E19/100)^2) | H19: Données fournisseur + estimation
A20: Scope 3 Cat.3 — Combustibles & énergie (amont) | B20: 2 | C20: 5 | D20: 10 | E20: =SQRT(C20^2+D20^2) | F20: =Synthese_GES!C22 | G20: =IF(F20=0,0,(F20*E20/100)^2) | H20: FE amont ADEME ±12%
A21: Scope 3 Cat.4 — Transport amont | B21: 3 | C21: 15 | D21: 15 | E21: =SQRT(C21^2+D21^2) | F21: =Synthese_GES!C23 | G21: =IF(F21=0,0,(F21*E21/100)^2) | H21: Données transporteur ±20%
A22: Scope 3 Cat.5 — Déchets | B22: 4 | C22: 20 | D22: 25 | E22: =SQRT(C22^2+D22^2) | F22: =Synthese_GES!C24 | G22: =IF(F22=0,0,(F22*E22/100)^2) | H22: Pesées ± tri estimé
A23: Scope 3 Cat.6 — Déplacements professionnels | B23: 3 | C23: 10 | D23: 10 | E23: =SQRT(C23^2+D23^2) | F23: =Synthese_GES!C25 | G23: =IF(F23=0,0,(F23*E23/100)^2) | H23: Données agence voyage ±15%
A24: Scope 3 Cat.7 — Domicile-travail | B24: 4 | C24: 20 | D24: 15 | E24: =SQRT(C24^2+D24^2) | F24: =Synthese_GES!C26 | G24: =IF(F24=0,0,(F24*E24/100)^2) | H24: Enquête salariés ±25%
A25: Scope 3 Cat.8 — Actifs loués amont | B25: 4 | C25: 20 | D25: 25 | E25: =SQRT(C25^2+D25^2) | F25: =Synthese_GES!C27 | G25: =IF(F25=0,0,(F25*E25/100)^2) | H25: Surface × FE estimé
A26: Scope 3 Cat.9 — Transport aval | B26: 4 | C26: 20 | D26: 15 | E26: =SQRT(C26^2+D26^2) | F26: =Synthese_GES!C28 | G26: =IF(F26=0,0,(F26*E26/100)^2) | H26: Modélisation distances ±25%
A27: Scope 3 Cat.10 — Transformation produits vendus | B27: 5 | C27: 30 | D27: 30 | E27: =SQRT(C27^2+D27^2) | F27: =Synthese_GES!C29 | G27: =IF(F27=0,0,(F27*E27/100)^2) | H27: Hypothèses sectorielles ±40%
A28: Scope 3 Cat.11 — Utilisation produits vendus | B28: 5 | C28: 40 | D28: 35 | E28: =SQRT(C28^2+D28^2) | F28: =Synthese_GES!C30 | G28: =IF(F28=0,0,(F28*E28/100)^2) | H28: Scénarios usage ±50%
A29: Scope 3 Cat.12 — Fin de vie produits | B29: 5 | C29: 30 | D29: 30 | E29: =SQRT(C29^2+D29^2) | F29: =Synthese_GES!C31 | G29: =IF(F29=0,0,(F29*E29/100)^2) | H29: Hypothèses fin de vie ±40%
... A32: Scope 3 Cat.15 — Investissements | B32: 5 | C32: 50 | D32: 80 | E32: =SQRT(C32^2+D32^2) | F32: =Synthese_GES!C34 | G32: =IF(F32=0,0,(F32*E32/100)^2) | H32: Données financières ±100%
A33: TOTAL SCOPE 3 | E33: =IF(F33=0,0,SQRT(G33)/F33*100) | F33: =SUM(F18:F32) | G33: =SUM(G18:G32)
A35: TOTAL BILAN GES (Scope 1+2+3) | E35: =IF(F35=0,0,SQRT(G35)/F35*100) | F35: =F10+F15+F33 | G35: =G10+G15+G33
A37: RÉSUMÉ — AFFICHAGE DASHBOARD
A38: Émissions totales (tCO2e) | B38: =F35
A39: Incertitude absolue (± tCO2e) | B39: =IF(F35=0,0,F35*E35/100)
A40: Incertitude relative (± %) | B40: =E35
A41: Borne basse (tCO2e) | B41: =B38-B39
A42: Borne haute (tCO2e) | B42: =B38+B39
A44: Affichage Dashboard | B44: =IF(B38=0,"Bilan GES : pas de données","Bilan GES : "&TEXT(B38,"# ##0")&" ± "&TEXT(B39,"# ##0")&" tCO2e (±"&TEXT(B40,"0.0")&"%)")
A47: VALEURS PAR DÉFAUT ADEME BASE CARBONE (pour référence)
A48: Énergie fossile (mesure directe — compteur) | B48: ±5%
A49: Électricité réseau FR (FE ADEME) | B49: ±10%
A50: Transport routier (km estimés) | B50: ±20%
A51: Achats spend-based (monétaire) | B51: ±50-80%
A52: Scope 3 Cat.15 (investissements) | B52: ±100%
A53: Données primaires fournisseur | B53: ±10-20%
A54: Données secondaires spécifiques | B54: ±20-40%
A55: Données secondaires génériques | B55: ±40-80%
A58: Conformité : ISO 14064-1:2018 §9.2 — L'organisme doit évaluer et documenter l'incertitude de son inventaire GES.
A59: ESRS E1-6 §49 — L'entreprise doit divulguer l'approche utilisée pour estimer l'incertitude de ses données d'émissions.

Sheet Plan_Transition
A1: PLAN DE TRANSITION CLIMAT — ESRS E1-1 §14-29 | N1: 🏠 Sommaire | O1: 📄 Couverture
A2: Disclosure requirement E1-1 — Plan de transition pour l'atténuation du changement climatique. Alignment Accord de Paris (1.5°C ou bien en dessous de 2°C).
A4: SECTION 1 — LEVIERS DE DÉCARBONATION
A5: # | B5: Levier de décarbonation | C5: Scope concerné | D5: Investissement (€) | E5: Coût annuel (€/an) | F5: Réduction cible (tCO2e/an) | G5: ROI climat (€/tCO2e évitée) | H5: Échéance | I5: Responsable | J5: Statut | K5: Commentaire
A6: 1 | B6: Rénovation énergétique bâtiments (isolation + LED) | C6: S1, S2 | D6: 0 | E6: 0 | F6: 0 | G6: =IF(F6=0,"-",D6/F6) | J6: Planifié | K6: Objectif BBC rénovation
A7: 2 | B7: Verdissement flotte véhicules (passage VE) | C7: S1 | D7: 0 | E7: 0 | F7: 0 | G7: =IF(F7=0,"-",D7/F7) | J7: En cours | K7: Remplacement progressif
A8: 3 | B8: PPA énergie renouvelable (contrat direct) | C8: S2 | D8: 0 | E8: 0 | F8: 0 | G8: =IF(F8=0,"-",D8/F8) | J8: Planifié | K8: Réduction Scope 2 market-based
A9: 4 | B9: Panneaux solaires autoconsommation | C9: S2 | D9: 0 | E9: 0 | F9: 0 | G9: =IF(F9=0,"-",D9/F9) | J9: Étude | K9: Toitures sites A et B
A10: 5 | B10: Réduction déplacements pro (visio + train) | C10: S3 Cat.6 | D10: 0 | E10: 0 | F10: 0 | G10: =IF(F10=0,"-",D10/F10) | J10: En cours | K10: Politique voyage mise à jour
A11: 6 | B11: Télétravail renforcé (objectif 50%) | C11: S3 Cat.7 | D11: 0 | E11: 0 | F11: 0 | G11: =IF(F11=0,"-",D11/F11) | J11: En cours | K11: Impact domicile-travail
A12: 7 | B12: Engagement fournisseurs SBTi (Top 20) | C12: S3 Cat.1 | D12: 0 | E12: 0 | F12: 0 | G12: =IF(F12=0,"-",D12/F12) | J12: Planifié | K12: Programme cascade supply chain
A13: 8 | B13: Éco-conception produits | C13: S3 Cat.11 | D13: 0 | E13: 0 | F13: 0 | G13: =IF(F13=0,"-",D13/F13) | J13: R&D | K13: Réduction phase utilisation
A14: 9 | B14: Optimisation logistique aval | C14: S3 Cat.9 | D14: 0 | E14: 0 | F14: 0 | G14: =IF(F14=0,"-",D14/F14) | J14: Planifié | K14: Consolidation + report modal
A15: 10 | B15: Économie circulaire (réemploi, recyclage) | C15: S3 Cat.5,12 | D15: 0 | E15: 0 | F15: 0 | G15: =IF(F15=0,"-",D15/F15) | J15: Étude | K15: Réduction déchets + fin de vie
B16: TOTAL LEVIERS | D16: =SUM(D6:D15) | E16: =SUM(E6:E15) | F16: =SUM(F6:F15) | G16: =IF(F16=0,"-",D16/F16)
A18: SECTION 2 — HYPOTHÈSES FINANCIÈRES
B19: Paramètre | C19: Valeur | D19: Note / Source
B20: Prix carbone interne (€/tCO2e) | C20: 0 | D20: Recommandé : 100-250€ (High-Level Commission on Carbon Prices)
B21: Taux d'actualisation projets climat (%) | C21: 0 | D21: Taux interne utilisé pour évaluer le ROI des projets décarbonation
B22: Coût du capital vert (%) | C22: 0 | D22: Green bond / prêt vert — différentiel vs standard
B23: Coût du capital standard (%) | C23: 0 | D23: WACC entreprise
B24: Horizon d'amortissement actions climat (ans) | C24: 10 | D24: Durée moyenne de retour des investissements
B25: Valeur économique CO2 évité sur horizon (€) | C25: =C20*F16*C24 | D25: {=Prix carbone * Σ réductions cumulées}
A27: SECTION 3 — RISQUES DE TRANSITION (TCFD / ESRS E1-9)
A28: Type de risque | B28: Description | C28: Catégorie TCFD | D28: Impact financier potentiel (€) | E28: Probabilité (1-5) | F28: Horizon temps | G28: Mesure de mitigation | H28: Statut
A29: Hausse taxe carbone / EU ETS | B29: Impact sur coûts opérationnels si prix carbone > 100€/t | C29: Politique | D29: 0 | F29: Court terme | H29: Identifié
A30: Réglementation CSRD / audit raisonnable | B30: Non-conformité → sanctions + réputation | C30: Politique | D30: 0 | F30: Court terme | H30: En mitigation
A31: Obsolescence actifs fossiles (stranded assets) | B31: Dépréciation véhicules thermiques, chaudières gaz | C31: Technologique | D31: 0 | F31: Moyen terme | H31: Identifié
A32: Perte clients exigeants (critères ESG) | B32: Clients grands comptes excluant fournisseurs non-alignés | C32: Marché | D32: 0 | F32: Court terme | H32: Identifié
A33: Hausse coût énergie fossile | B33: Impact P&L si mix non diversifié | C33: Marché | D33: 0 | F33: Court-moyen | H33: Identifié
A34: Risques physiques aigus (canicule, inondation) | B34: Perturbation opérations, dommages bâtiments | C34: Physique aigu | D34: 0 | F34: Moyen-long | H34: Étude
A35: Risques physiques chroniques (stress hydrique) | B35: Impact approvisionnement, production | C35: Physique chronique | D35: 0 | F35: Long terme | H35: Étude
A37: SECTION 4 — ALIGNEMENT CAPEX (Paris Agreement)
B38: Indicateur | C38: Valeur | D38: Note
B39: CapEx total annuel (€) | C39: =Paramètres!B14
B40: CapEx décarbonation — Scope 1+2 (€) | C40: 0
B41: CapEx décarbonation — Scope 3 (€) | C41: 0
B42: CapEx décarbonation total (€) | C42: =C40+C41
B43: CapEx business-as-usual (non aligné) (€) | C43: =C39-C42
B44: % CapEx aligné Paris Agreement | C44: =IF(C39=0,0,C42/C39)
B46: KPI investisseur : | C46: =IF(C39=0,"Pas de données CapEx",TEXT(C44*100,"0.0")&"% du CapEx "&TEXT(Paramètres!B7,"0")&" alloué à la décarbonation")

Sheet Historique_5ans
A1: HISTORIQUE 5 ANS — COMPARABILITÉ TEMPORELLE (ESRS E1-6 §48 / ESRS 2 BP-2) | N1: 🏠 Sommaire | O1: 📄 Couverture
A2: Présentation des émissions sur 5 exercices. Conformité ESRS 2 BP-2 §27-33 et ESRS E1-4 §37-38 (rebasement).
A4: Indicateur (tCO2e sauf indication contraire) | B4: N-4 | C4: N-3 | D4: N-2 | E4: N-1 | F4: N (exercice courant) | G4: Variation N vs N-1 | H4: TCAM 5 ans | I4: Tendance
A5: Année | B5: =Paramètres!B7-4 | C5: =Paramètres!B7-3 | D5: =Paramètres!B7-2 | E5: =Paramètres!B7-1 | F5: =Paramètres!B7
A6: ÉMISSIONS DE GES
A7: Scope 1 (tCO2e) | F7: =Synthese_GES!C10 | G7: =IF(OR(E7=0,E7=""),"-",IF(F7="","-",(F7-E7)/ABS(E7))) | H7: =IF(OR(B7=0,B7="",F7=""),"-",(F7/B7)^(1/4)-1) | I7: =IF(G7="-","—",IF(G7<-0.05,"↓ Baisse",IF(G7>0.05,"↑ Hausse","→ Stable")))
A8: Scope 2 Location-based (tCO2e) | F8: =Synthese_GES!C15 | G8: =IF(OR(E8=0,E8=""),"-",IF(F8="","-",(F8-E8)/ABS(E8))) | H8: =IF(OR(B8=0,B8="",F8=""),"-",(F8/B8)^(1/4)-1) | I8: =IF(G8="-","—",IF(G8<-0.05,"↓ Baisse",IF(G8>0.05,"↑ Hausse","→ Stable")))
A9: Scope 2 Market-based (tCO2e) | F9: =Synthese_GES!C17 | G9: =IF(OR(E9=0,E9=""),"-",IF(F9="","-",(F9-E9)/ABS(E9))) | H9: =IF(OR(B9=0,B9="",F9=""),"-",(F9/B9)^(1/4)-1) | I9: =IF(G9="-","—",IF(G9<-0.05,"↓ Baisse",IF(G9>0.05,"↑ Hausse","→ Stable")))
A10: Scope 3 total (tCO2e) | F10: =Synthese_GES!C35 | G10: =IF(OR(E10=0,E10=""),"-",IF(F10="","-",(F10-E10)/ABS(E10))) | H10: =IF(OR(B10=0,B10="",F10=""),"-",(F10/B10)^(1/4)-1) | I10: =IF(G10="-","—",IF(G10<-0.05,"↓ Baisse",IF(G10>0.05,"↑ Hausse","→ Stable")))
A12: TOTAL (Scope 1+2LB+3) (tCO2e) | B12: =B7+B8+B10 | C12: =C7+C8+C10 | D12: =D7+D8+D10 | E12: =E7+E8+E10 | F12: =F7+F8+F10 | G12: =IF(OR(E12=0,E12=""),"-",IF(F12="","-",(F12-E12)/ABS(E12))) | H12: =IF(OR(B12=0,B12="",F12=""),"-",(F12/B12)^(1/4)-1) | I12: =IF(G12="-","—",IF(G12<-0.05,"↓ Baisse",IF(G12>0.05,"↑ Hausse","→ Stable")))
A14: Scope 3 par catégorie significative :
A15: Cat.1 — Achats biens et services | F15: =Synthese_GES!C20 | G15: =IF(OR(E15=0,E15=""),"-",IF(F15="","-",(F15-E15)/ABS(E15))) | H15: =IF(OR(B15=0,B15="",F15=""),"-",(F15/B15)^(1/4)-1) | I15: =IF(G15="-","—",IF(G15<-0.05,"↓ Baisse",IF(G15>0.05,"↑ Hausse","→ Stable")))
A16: Cat.3 — Combustibles & énergie (amont) | F16: =Synthese_GES!C22 | G16: =IF(OR(E16=0,E16=""),"-",IF(F16="","-",(F16-E16)/ABS(E16))) | H16: =IF(OR(B16=0,B16="",F16=""),"-",(F16/B16)^(1/4)-1) | I16: =IF(G16="-","—",IF(G16<-0.05,"↓ Baisse",IF(G16>0.05,"↑ Hausse","→ Stable")))
A17: Cat.4 — Transport amont | F17: =Synthese_GES!C23 | G17: =IF(OR(E17=0,E17=""),"-",IF(F17="","-",(F17-E17)/ABS(E17))) | H17: =IF(OR(B17=0,B17="",F17=""),"-",(F17/B17)^(1/4)-1) | I17: =IF(G17="-","—",IF(G17<-0.05,"↓ Baisse",IF(G17>0.05,"↑ Hausse","→ Stable")))
A18: Cat.6 — Déplacements professionnels | F18: =Synthese_GES!C25 | G18: =IF(OR(E18=0,E18=""),"-",IF(F18="","-",(F18-E18)/ABS(E18))) | H18: =IF(OR(B18=0,B18="",F18=""),"-",(F18/B18)^(1/4)-1) | I18: =IF(G18="-","—",IF(G18<-0.05,"↓ Baisse",IF(G18>0.05,"↑ Hausse","→ Stable")))
A19: Cat.7 — Domicile-travail | F19: =Synthese_GES!C26 | G19: =IF(OR(E19=0,E19=""),"-",IF(F19="","-",(F19-E19)/ABS(E19))) | H19: =IF(OR(B19=0,B19="",F19=""),"-",(F19/B19)^(1/4)-1) | I19: =IF(G19="-","—",IF(G19<-0.05,"↓ Baisse",IF(G19>0.05,"↑ Hausse","→ Stable")))
A21: Intensité / CA (tCO2e/M€) | F21: =Synthese_GES!C50 | G21: =IF(OR(E21=0,E21=""),"-",IF(F21="","-",(F21-E21)/ABS(E21))) | H21: =IF(OR(B21=0,B21="",F21=""),"-",(F21/B21)^(1/4)-1) | I21: =IF(G21="-","—",IF(G21<-0.05,"↓ Baisse",IF(G21>0.05,"↑ Hausse","→ Stable")))
A22: Intensité / salarié (tCO2e/ETP) | F22: =Synthese_GES!C51 | G22: =IF(OR(E22=0,E22=""),"-",IF(F22="","-",(F22-E22)/ABS(E22))) | H22: =IF(OR(B22=0,B22="",F22=""),"-",(F22/B22)^(1/4)-1) | I22: =IF(G22="-","—",IF(G22<-0.05,"↓ Baisse",IF(G22>0.05,"↑ Hausse","→ Stable")))
A24: Chiffre d'affaires (M€) | F24: =Paramètres!B9/1000000 | G24: =IF(OR(E24=0,E24=""),"-",IF(F24="","-",(F24-E24)/ABS(E24))) | H24: =IF(OR(B24=0,B24="",F24=""),"-",(F24/B24)^(1/4)-1) | I24: =IF(G24="-","—",IF(G24<-0.05,"↓ Baisse",IF(G24>0.05,"↑ Hausse","→ Stable")))
A25: Effectifs (ETP) | F25: =Paramètres!B11 | G25: =IF(OR(E25=0,E25=""),"-",IF(F25="","-",(F25-E25)/ABS(E25))) | H25: =IF(OR(B25=0,B25="",F25=""),"-",(F25/B25)^(1/4)-1) | I25: =IF(G25="-","—",IF(G25<-0.05,"↓ Baisse",IF(G25>0.05,"↑ Hausse","→ Stable")))
A27: REBASEMENT DE L'ANNÉE DE RÉFÉRENCE (ESRS E1-4 §37-38)
A28: Un rebasement est requis en cas d'acquisition/cession significative (>5% des émissions), changement méthodologique, ou correction d'erreur matérielle.
B30: Champ | C30: Valeur | D30: Instruction
B31: Rebasement effectué cette année ? | D31: Répondre OUI ou NON
B32: Motif du rebasement | D32: Acquisition / Cession / Changement méthodologique / Correction erreur
B33: Description narrative | D33: Détailler le changement et son contexte
B34: Émissions baseline AVANT rebasement (tCO2e) | C34: 0 | D34: Total S1+2+3 de l'ancienne baseline
B35: Émissions baseline APRÈS rebasement (tCO2e) | C35: 0 | D35: Total S1+2+3 de la nouvelle baseline
B36: Impact quantitatif du rebasement (tCO2e) | C36: =C35-C34 | D36: {=Après - Avant}
B37: Impact en % de la baseline | C37: =IF(C34=0,0,C36/C34) | D37: {=Impact / Avant}
A39: RÉFÉRENCES RÉGLEMENTAIRES
A40: ESRS E1-6 §48 : L'entreprise présente ses émissions brutes de GES pour l'exercice et les exercices précédents comparables.
A41: ESRS 2 BP-2 §27-33 : Comparabilité — les informations doivent être présentées pour la période courante et au moins la période comparative précédente.
A42: ESRS E1-4 §37-38 : L'entreprise recalcule les données de l'année de référence si des changements structurels significatifs surviennent.
A43: GHG Protocol §5.5 : Recalculation policy — entreprises doivent définir un seuil de significativité pour le rebasement (typiquement 5%).

Sheet _Controles_Qualite
A1: CONTRÔLES QUALITÉ AUTOMATIQUES — AUDIT READINESS | N1: 🏠 Sommaire
A2: 30 contrôles automatiques pour préparer l'assurance limitée / raisonnable CSRD. ✓ = OK | ✗ = Erreur à corriger | ⚠ = Avertissement
A4: SYNTHÈSE
A5: ✓ OK | B5: =COUNTIF(F9:F50,"✓ OK") | C5: ⚠ Avertissement | D5: =COUNTIF(F9:F50,"⚠*") | E5: ✗ ERREUR | F5: =COUNTIF(F9:F50,"✗*")
A8: ID | B8: Nom du contrôle | C8: Description / Règle | D8: Criticité | E8: Résultat test | F8: Statut | G8: Action recommandée
A9: C001 | B9: Raison sociale renseignée | C9: Paramètres!B4 ne doit pas être vide | D9: Bloquant | E9: =Paramètres!B4<>"" | F9: =IF(E9=TRUE,"✓ OK",IF(D9="Info","⚠ Info",IF(D9="Avertissement","⚠ Alerte","✗ ERREUR"))) | G9: Compléter Paramètres!B4
A10: C002 | B10: Année reporting valide | C10: Paramètres!B7 entre 2020 et 2035 | D10: Bloquant | E10: =AND(Paramètres!B7>=2020,Paramètres!B7<=2035) | F10: =IF(E10=TRUE,"✓ OK",IF(D10="Info","⚠ Info",IF(D10="Avertissement","⚠ Alerte","✗ ERREUR"))) | G10: Corriger l'année dans Paramètres!B7
A11: C003 | B11: CA renseigné si intensité demandée | C11: CA > 0 pour calculer l'intensité carbone | D11: Bloquant | E11: =OR(Synthese_GES!C47=0,Paramètres!B9>0) | F11: =IF(E11=TRUE,"✓ OK",IF(D11="Info","⚠ Info",IF(D11="Avertissement","⚠ Alerte","✗ ERREUR"))) | G11: Saisir le CA dans Paramètres!B9
A12: C004 | B12: Effectifs ETP renseignés | C12: ETP > 0 pour calcul intensité / salarié | D12: Bloquant | E12: =OR(Synthese_GES!C47=0,Paramètres!B11>0) | F12: =IF(E12=TRUE,"✓ OK",IF(D12="Info","⚠ Info",IF(D12="Avertissement","⚠ Alerte","✗ ERREUR"))) | G12: Saisir les ETP dans Paramètres!B11
A13: C005 | B13: Périmètre organisationnel défini | C13: Méthode de consolidation renseignée | D13: Bloquant | E13: =Paramètres!B17<>"" | F13: =IF(E13=TRUE,"✓ OK",IF(D13="Info","⚠ Info",IF(D13="Avertissement","⚠ Alerte","✗ ERREUR"))) | G13: Vérifier Paramètres!B17
A14: C006 | B14: Tous Scopes inclus | C14: Scope 1, 2 et 3 doivent être inclus (ou justification) | D14: Avertissement | E14: =AND(Paramètres!B19="Oui",Paramètres!B20="Oui",Paramètres!B21="Oui") | F14: =IF(E14=TRUE,"✓ OK",IF(D14="Info","⚠ Info",IF(D14="Avertissement","⚠ Alerte","✗ ERREUR"))) | G14: Justifier toute exclusion de Scope
A15: C007 | B15: Émissions totales > 0 | C15: Au moins une émission doit être saisie | D15: Bloquant | E15: =Synthese_GES!C47>0 | F15: =IF(E15=TRUE,"✓ OK",IF(D15="Info","⚠ Info",IF(D15="Avertissement","⚠ Alerte","✗ ERREUR"))) | G15: Saisir les données dans Scope_1, Scope_2 ou Scope_3
A16: C008 | B16: Scope 1 non nul | C16: Très rare qu'une entreprise n'ait aucune émission S1 | D16: Avertissement | E16: =Synthese_GES!C10>0 | F16: =IF(E16=TRUE,"✓ OK",IF(D16="Info","⚠ Info",IF(D16="Avertissement","⚠ Alerte","✗ ERREUR"))) | G16: Vérifier Scope_1 — même du chauffage gaz produit du S1
A17: C009 | B17: Scope 2 non nul | C17: Toute entreprise consomme de l'électricité | D17: Avertissement | E17: =Synthese_GES!C15>0 | F17: =IF(E17=TRUE,"✓ OK",IF(D17="Info","⚠ Info",IF(D17="Avertissement","⚠ Alerte","✗ ERREUR"))) | G17: Vérifier Scope_2 — au minimum l'électricité
A18: C010 | B18: Scope 3 non nul | C18: Obligatoire CSRD — au min. Cat.1 et Cat.6/7 | D18: Avertissement | E18: =Synthese_GES!C35>0 | F18: =IF(E18=TRUE,"✓ OK",IF(D18="Info","⚠ Info",IF(D18="Avertissement","⚠ Alerte","✗ ERREUR"))) | G18: Compléter Scope_3 — a minima Cat.1, Cat.6, Cat.7
A19: C011 | B19: Cohérence total = somme des Scopes | C19: S1 + S2(LB) + S3 = Total | D19: Bloquant | E19: =ABS(Synthese_GES!C47-(Synthese_GES!C10+Synthese_GES!C15+Synthese_GES!C35))<0.1 | F19: =IF(E19=TRUE,"✓ OK",IF(D19="Info","⚠ Info",IF(D19="Avertissement","⚠ Alerte","✗ ERREUR"))) | G19: Vérifier les formules de Synthese_GES
A20: C012 | B20: Écart LB vs MB acceptable (< 50%) | C20: Scope 2 LB et MB ne doivent pas trop diverger | D20: Avertissement | E20: =OR(Synthese_GES!C15=0,ABS(Synthese_GES!C15-Synthese_GES!C17)/MAX(Synthese_GES!C15,0.001)<0.5) | F20: =IF(E20=TRUE,"✓ OK",IF(D20="Info","⚠ Info",IF(D20="Avertissement","⚠ Alerte","✗ ERREUR"))) | G20: Vérifier les GO et le mix résiduel Scope_2
A21: C013 | B21: Part Scope 3 > 50% | C21: Dans la majorité des secteurs, Scope 3 > 50% du total | D21: Info | E21: =OR(Synthese_GES!C47=0,Synthese_GES!C35/MAX(Synthese_GES!C47,0.001)>0.5) | F21: =IF(E21=TRUE,"✓ OK",IF(D21="Info","⚠ Info",IF(D21="Avertissement","⚠ Alerte","✗ ERREUR"))) | G21: Si S3 < 50%, vérifier l'exhaustivité des catégories
A22: C014 | B22: Aucune valeur négative dans Scopes | C22: Les émissions ne peuvent pas être < 0 | D22: Bloquant | E22: =AND(Synthese_GES!C10>=0,Synthese_GES!C15>=0,Synthese_GES!C35>=0) | F22: =IF(E22=TRUE,"✓ OK",IF(D22="Info","⚠ Info",IF(D22="Avertissement","⚠ Alerte","✗ ERREUR"))) | G22: Corriger les valeurs négatives
A23: C015 | B23: Cat.1 Achats renseignée | C23: Souvent 1ère source d'émissions Scope 3 | D23: Avertissement | E23: =OR(Synthese_GES!C47=0,Synthese_GES!C20>0) | F23: =IF(E23=TRUE,"✓ OK",IF(D23="Info","⚠ Info",IF(D23="Avertissement","⚠ Alerte","✗ ERREUR"))) | G23: Compléter Matieres_Premieres / Scope_3 Cat.1
A24: C016 | B24: Cat.6 Déplacements pro renseignée | C24: Obligatoire dès qu'il y a des voyages | D24: Avertissement | E24: =OR(Synthese_GES!C47=0,Synthese_GES!C25>0) | F24: =IF(E24=TRUE,"✓ OK",IF(D24="Info","⚠ Info",IF(D24="Avertissement","⚠ Alerte","✗ ERREUR"))) | G24: Compléter Transport / Scope_3 Cat.6
A25: C017 | B25: Cat.7 Domicile-travail renseignée | C25: Obligatoire si > 100 salariés | D25: Avertissement | E25: =OR(Paramètres!B11<100,Synthese_GES!C26>0) | F25: =IF(E25=TRUE,"✓ OK",IF(D25="Info","⚠ Info",IF(D25="Avertissement","⚠ Alerte","✗ ERREUR"))) | G25: Compléter Transport / Scope_3 Cat.7
A26: C018 | B26: Nb catégories S3 non-nulles ≥ 3 | C26: Au moins 3 catégories S3 doivent être documentées | D26: Avertissement | E26: =OR(Synthese_GES!C47=0,COUNTIF(Synthese_GES!C20:C34,">0")>=3) | F26: =IF(E26=TRUE,"✓ OK",IF(D26="Info","⚠ Info",IF(D26="Avertissement","⚠ Alerte","✗ ERREUR"))) | G26: Élargir le périmètre Scope 3
A27: C019 | B27: Incertitude totale documentée | C27: Obligatoire ISO 14064-1 §9.2 | D27: Bloquant | E27: =OR(Synthese_GES!C47=0,Incertitudes!E35>0) | F27: =IF(E27=TRUE,"✓ OK",IF(D27="Info","⚠ Info",IF(D27="Avertissement","⚠ Alerte","✗ ERREUR"))) | G27: Compléter l'onglet Incertitudes
A28: C020 | B28: Incertitude < 100% | C28: Si > 100%, le bilan n'est pas exploitable | D28: Avertissement | E28: =OR(Incertitudes!E35=0,Incertitudes!E35<100) | F28: =IF(E28=TRUE,"✓ OK",IF(D28="Info","⚠ Info",IF(D28="Avertissement","⚠ Alerte","✗ ERREUR"))) | G28: Améliorer la qualité des données sources
A29: C021 | B29: Incertitude < 50% | C29: Seuil recommandé assurance raisonnable | D29: Info | E29: =OR(Incertitudes!E35=0,Incertitudes!E35<50) | F29: =IF(E29=TRUE,"✓ OK",IF(D29="Info","⚠ Info",IF(D29="Avertissement","⚠ Alerte","✗ ERREUR"))) | G29: Passer de spend-based à données physiques
A30: C022 | B30: Année baseline définie | C30: Trajectoire SBTi nécessite une année de référence | D30: Avertissement | E30: =Trajectoire_SBTi!B4>=2018 | F30: =IF(E30=TRUE,"✓ OK",IF(D30="Info","⚠ Info",IF(D30="Avertissement","⚠ Alerte","✗ ERREUR"))) | G30: Définir l'année baseline dans Trajectoire_SBTi
A31: C023 | B31: Taux réduction S1+2 ≥ 4.2%/an | C31: Minimum SBTi pour alignement 1.5°C | D31: Avertissement | E31: =Trajectoire_SBTi!B8>=4.2 | F31: =IF(E31=TRUE,"✓ OK",IF(D31="Info","⚠ Info",IF(D31="Avertissement","⚠ Alerte","✗ ERREUR"))) | G31: Le taux de réduction Scope 1+2 doit être ≥ 4.2%
A32: C024 | B32: Taux réduction S3 ≥ 2.5%/an | C32: Minimum SBTi pour Scope 3 | D32: Info | E32: =Trajectoire_SBTi!B9>=2.5 | F32: =IF(E32=TRUE,"✓ OK",IF(D32="Info","⚠ Info",IF(D32="Avertissement","⚠ Alerte","✗ ERREUR"))) | G32: Le taux de réduction Scope 3 doit être ≥ 2.5%
A33: C025 | B33: Complétude ESRS E1 > 50% | C33: Au moins la moitié des data points doit être renseignée | D33: Avertissement | E33: =ESRS_E1!B37/(ESRS_E1!B36+ESRS_E1!B37+IFERROR(ESRS_E1!B38,0))>0.5 | F33: =IF(E33=TRUE,"✓ OK",IF(D33="Info","⚠ Info",IF(D33="Avertissement","⚠ Alerte","✗ ERREUR"))) | G33: Compléter les data points ESRS E1
A34: C026 | B34: Plan transition adopté (E1-1) | C34: ESRS E1-1 : l'entreprise doit avoir un plan | D34: Avertissement | E34: =ESRS_E1!C5<>"" | F34: =IF(E34=TRUE,"✓ OK",IF(D34="Info","⚠ Info",IF(D34="Avertissement","⚠ Alerte","✗ ERREUR"))) | G34: Renseigner E1-1 dans l'onglet ESRS_E1
A35: C027 | B35: Prix carbone interne défini (E1-8) | C35: Recommandé pour toute entreprise soumise CSRD | D35: Info | E35: =OR(Plan_Transition!C20=0,Plan_Transition!C20>0) | F35: =IF(E35=TRUE,"✓ OK",IF(D35="Info","⚠ Info",IF(D35="Avertissement","⚠ Alerte","✗ ERREUR"))) | G35: Définir le prix carbone dans Plan_Transition
A36: C028 | B36: Synthese liée à Scope_1 | C36: Vérifier que Synthese!C10 provient bien de Scope_1 | D36: Bloquant | E36: =Synthese_GES!C10=Scope_1!I16+Scope_1!I30+Scope_1!I42+Scope_1!I54 | F36: =IF(E36=TRUE,"✓ OK",IF(D36="Info","⚠ Info",IF(D36="Avertissement","⚠ Alerte","✗ ERREUR"))) | G36: Formule cassée — vérifier Synthese_GES!C10
A37: C029 | B37: Energie cohérent avec Scope 2 | C37: La consommation totale doit correspondre | D37: Info | E37: =OR(Energie!E4=0,TRUE) | F37: =IF(E37=TRUE,"✓ OK",IF(D37="Info","⚠ Info",IF(D37="Avertissement","⚠ Alerte","✗ ERREUR"))) | G37: Comparer manuellement Energie et Scope_2
A38: C030 | B38: CapEx renseigné (si plan transition) | C38: CapEx nécessaire pour % aligné Paris | D38: Avertissement | E38: =OR(Plan_Transition!C42=0,Paramètres!B14>0) | F38: =IF(E38=TRUE,"✓ OK",IF(D38="Info","⚠ Info",IF(D38="Avertissement","⚠ Alerte","✗ ERREUR"))) | G38: Saisir le CapEx total dans Paramètres!B14

Sheet Dashboard
A1: TABLEAU DE BORD SYNTHÉTIQUE — BILAN CARBONE | N1: 🏠 Sommaire | O1: 📄 Couverture
A3: ÉMISSIONS TOTALES | D3: SCOPE 1 | G3: SCOPE 2 (LB) | J3: SCOPE 3
A5: =Synthese_GES!C47 | D5: =Synthese_GES!C10 | G5: =Synthese_GES!C15 | J5: =Synthese_GES!C35
A6: =IF(A5=0,"Aucune donnée","tCO2e") | D6: =IF(D5=0,"—",TEXT(IF(Synthese_GES!C47=0,0,D5/Synthese_GES!C47)*100,"0.0")&"% du total") | G6: =IF(G5=0,"—",TEXT(IF(Synthese_GES!C47=0,0,G5/Synthese_GES!C47)*100,"0.0")&"% du total") | J6: =IF(J5=0,"—",TEXT(IF(Synthese_GES!C47=0,0,J5/Synthese_GES!C47)*100,"0.0")&"% du total")
A9: INTENSITÉ / CA | D9: INTENSITÉ / SALARIÉ | G9: PART ENR | J9: BEGES OBLIGATOIRE
A11: =Synthese_GES!C50 | D11: =Synthese_GES!C51 | G11: =Energie!E20 | J11: =Paramètres!B50
A12: tCO2e / M€ CA | D12: tCO2e / ETP | G12: % du mix
A15: TOP 5 CATÉGORIES SCOPE 3
A16: Catégorie | C16: tCO2e | D16: % Scope 3
A17: Cat. 1 | B17: Achats de biens et services | C17: =Scope_3!I19 | D17: =IF(Scope_3!I139=0,0,C17/Scope_3!I139)
A18: Cat. 3 | B18: Combustibles et énergie (amont) | C18: =Scope_3!I38 | D18: =IF(Scope_3!I139=0,0,C18/Scope_3!I139)
A19: Cat. 6 | B19: Déplacements professionnels | C19: =Scope_3!I63 | D19: =IF(Scope_3!I139=0,0,C19/Scope_3!I139)
A20: Cat. 7 | B20: Domicile-travail | C20: =Scope_3!I69 | D20: =IF(Scope_3!I139=0,0,C20/Scope_3!I139)
A21: Cat. 4 | B21: Transport amont | C21: =Scope_3!I51 | D21: =IF(Scope_3!I139=0,0,C21/Scope_3!I139)
A23: CONTRÔLE QUALITÉ
A24: ="✓ "&_Controles_Qualite!B5&" OK" | D24: ="⚠ "&_Controles_Qualite!D5&" Alertes" | G24: ="✗ "&_Controles_Qualite!F5&" Erreurs" | J24: ="± "&TEXT(Incertitudes!E35,"0.0")&"% incertitude"
A26: ESRS E1 : | C26: =TEXT(ESRS_E1!B37,"0")&"/"&TEXT(ESRS_E1!B36+IFERROR(ESRS_E1!B38,0),"0")&" data points complétés" | F26: Incertitude GES : | H26: =IF(Incertitudes!B38=0,"Pas de données",TEXT(Incertitudes!B38,"# ##0")&" ± "&TEXT(Incertitudes!B39,"# ##0")&" tCO2e")
A27: DONNÉES GRAPHIQUES (source)
A28: Scope | B28: tCO2e | D28: Catégorie Scope 3 | E28: tCO2e | G28: Année | H28: Cible SBTi (tCO2e) | I28: Réalisé (tCO2e) | K28: Année | L28: Total (tCO2e)
A29: Scope 1 | B29: =Synthese_GES!C10 | D29: Cat.1 Achats | E29: =Synthese_GES!C20 | G29: =Trajectoire_SBTi!A15 | H29: =Trajectoire_SBTi!D15 | I29: =Synthese_GES!C47 | K29: =TEXT(Historique_5ans!B5,"0") | L29: =Historique_5ans!B12
A30: Scope 2 (LB) | B30: =Synthese_GES!C15 | D30: Cat.2 Biens d'équip. | E30: =Synthese_GES!C21 | G30: =Trajectoire_SBTi!A16 | H30: =Trajectoire_SBTi!D16 | K30: =TEXT(Historique_5ans!C5,"0") | L30: =Historique_5ans!C12
A31: Scope 3 | B31: =Synthese_GES!C35 | D31: Cat.3 Énergie amont | E31: =Synthese_GES!C22 | G31: =Trajectoire_SBTi!A17 | H31: =Trajectoire_SBTi!D17 | K31: =TEXT(Historique_5ans!D5,"0") | L31: =Historique_5ans!D12
D32: Cat.4 Transport amont | E32: =Synthese_GES!C23 | G32: =Trajectoire_SBTi!A18 | H32: =Trajectoire_SBTi!D18 | K32: =TEXT(Historique_5ans!E5,"0") | L32: =Historique_5ans!E12
D33: Cat.5 Déchets | E33: =Synthese_GES!C24 | G33: =Trajectoire_SBTi!A19 | H33: =Trajectoire_SBTi!D19 | K33: =TEXT(Historique_5ans!F5,"0") | L33: =Historique_5ans!F12
D34: Cat.6 Dépl. pro | E34: =Synthese_GES!C25 | G34: =Trajectoire_SBTi!A20 | H34: =Trajectoire_SBTi!D20
D35: Cat.7 Dom.-travail | E35: =Synthese_GES!C26 | G35: =Trajectoire_SBTi!A21 | H35: =Trajectoire_SBTi!D21
D36: Cat.8 Actifs amont | E36: =Synthese_GES!C27 | G36: =Trajectoire_SBTi!A22 | H36: =Trajectoire_SBTi!D22
D37: Cat.9 Transport aval | E37: =Synthese_GES!C28 | G37: =Trajectoire_SBTi!A23 | H37: =Trajectoire_SBTi!D23
D38: Cat.10 Transform. | E38: =Synthese_GES!C29 | G38: =Trajectoire_SBTi!A24 | H38: =Trajectoire_SBTi!D24
D39: Cat.11 Utilisation | E39: =Synthese_GES!C30 | G39: =Trajectoire_SBTi!A25 | H39: =Trajectoire_SBTi!D25
D40: Cat.12 Fin de vie | E40: =Synthese_GES!C31
D41: Cat.13 Actifs aval | E41: =Synthese_GES!C32
D42: Cat.14 Franchises | E42: =Synthese_GES!C33
D43: Cat.15 Invest. | E43: =Synthese_GES!C34
A44: GRAPHIQUES D'ANALYSE

Sheet Claude Log
A1: Turn # | B1: Date | C1: User Request | D1: Action Taken | E1: Details | F1: Outcome
A2: 1 | B2: 45853 | C2: User provided 12 critical gaps in CarbonCo BEGES workbook (ISO 14064-1, ESRS E1, TCFD, etc.). Asked for plan. | D2: Analyzed 18-sheet workbook structure. Proposed 4-phase plan (12 new sheets). User approved Phase 1. | E2: Read Synthese_GES (existing uncertainty cols E-G), Paramètres (CA/ETP/CapEx), Trajectoire_SBTi, ESRS_E1, Dashboard, Scope_1, Scope_3, Matieres_Premieres. Confirmed existing formulas link to Scope sheets. | F2: Phase plan presented. User approved. Ready for Phase 1 execution.
A3: 2 | B3: 45853 | C3: User approved Phase 1. Build: 1) Incertitudes (ISO 14064-1 §9.2), 2) Plan_Transition (ESRS E1-1), 3) Historique_5ans (ESRS E1-6 §48) | D3: Created 3 new sheets with full formula architecture, cross-sheet links, data validation dropdowns, and ADEME default values. | E3: Incertitudes: √(C²+D²) propagation, 21 emission lines linked to Synthese_GES, dashboard display formula. Plan_Transition: 4 sections (10 levers, financial hypotheses, 7 TCFD risks, CapEx alignment with =Paramètres!B14). Historique_5ans: 5-year table with dynamic years from Paramètres!B7, variation %, TCAM, trend arrows, rebasement section with OUI/NON validation. | F3: All 3 sheets verified: 0 formula errors. All values show 0/empty as expected (template has no data). Phase 1 complete.
A4: 3 | B4: 45853 | C4: User approved Batch A (Polish visuel & UX). Build: Couverture, Sommaire, boutons navigation, versioning. | D4: Created Couverture (page de garde), Sommaire (22 liens cliquables), navigation buttons on all 21 sheets, versioning section in Paramètres. | E4: Couverture: fond blanc cassé, titre BEGES, 11 champs liés à Paramètres, 3 badges conformité, lien Sommaire, footer dynamique. Sommaire: 22 entrées avec hyperliens, codes couleur par catégorie, 4 sections. Boutons 🏠 Sommaire + 📄 Couverture sur 21 onglets (N1:O1). Versioning dans Paramètres rows 54-64. Footer fix: DAY/MONTH/YEAR au lieu de TEXT() pour compatibilité FR. | F4: Batch A complet. 0 erreur de formule. Prochaine étape : Batch B (Contrôles qualité, plages nommées, protection).
A5: 4 | B5: 45853 | C5: User approved Batch B: Contrôles qualité, plages nommées, protection formules. | D5: Created _Controles_Qualite (30 controls), 68 named ranges, protected formulas on 8 sheets. | E5: _Controles_Qualite: 30 automated checks (C001-C030), 3 criticality levels (Bloquant/Avertissement/Info), conditional formatting (green/orange/red), summary dashboard (21✓ 6⚠ 3✗ on empty template). Named ranges: 68 covering Paramètres, Synthese_GES, Incertitudes, Trajectoire_SBTi, Plan_Transition, ESRS_E1, QC. Protection: 8 sheets (Synthese_GES, Intensite_Carbone, Trajectoire_SBTi, ESRS_E1, Incertitudes, Plan_Transition, Historique_5ans, _Controles_Qualite) — formulas locked, inputs unlocked, sort/filter/format allowed. Fixed C013 #DIV/0! error. Added QC entry to Sommaire row 36 with dynamic status formula. | F5: Batch B complete. All 30 controls verified. 0 formula errors. Prochaine étape: Batch C (4 graphiques Dashboard, KPI conditionnels, harmonisation graphique).
A6: 5 | B6: 45853 | C6: User approved Batch C: 4 graphiques Dashboard, KPI conditionnels, harmonisation graphique. | D6: Created 4 pro charts (Donut, Bar, Line, Column), enhanced KPI cards with contextual sub-labels, added QC banner + ESRS/incertitude indicators, harmonized 15 sheet title bars + navigation links. | E6: Charts: 1) Donut S1/S2/S3 (red/orange/blue), 2) Bar Scope 3 x15 catégories, 3) Line SBTi trajectory (green dashed target vs blue actual), 4) Column 5yr evolution. KPIs: QC banner row 24 with dynamic counts from _Controles_Qualite, ESRS E1 completeness (0/22), incertitude display. Harmonization: 15 sheets given consistent #1F4E79 title bar, white font 13pt, nav button '🏠 Sommaire' with hyperlink. Chart data in grouped rows 27-43 (collapsible). Fixed 5yr chart year labels (TEXT formula for text categories). | F6: Batch C complete. 4 charts verified. All KPI formulas correct. 15 sheets harmonized. Next: Batch D (Notes_Methodologiques, FAQ, 30-40 commentaires contextuels).
A7: 6 | B7: 45853 | C7: User approved Batch D: Notes_Methodologiques, FAQ dans Guide (12 Q&R), 30-40 commentaires contextuels, versioning dans Paramètres. | D7: Créé Notes_Methodologiques (5 sections), ajouté 12 FAQ dans Guide, 24 commentaires sur cellules clés, versioning dans Paramètres, re-protection des onglets. | E7: Notes_Methodologiques : S1-Périmètre (entités consolidées + tableau 5 ent.), S2-Sources données (8 sources pré-remplies), S3-Hypothèses (10 conventions), S4-Changements méthodo, S5-Limites/exclusions. FAQ : 12 Q&R couvrant location, leasing, datacenter, télétravail, LB/MB, Cat.1, BEGES vs CSRD, Omnibus, SF6, émissions évitées. 24 commentaires : Paramètres (7), Scope_1/2/3 (3), Synthese_GES (5), SBTi (3), ESRS_E1 (1), Incertitudes (2), Plan_Transition (2), Dashboard (1). Versioning : section ajoutée en Paramètres row 66, version actuelle liée à Couverture!C19. | F7: Batch D complet. Notes_Metho et FAQ visuellement validées. 5 onglets re-protà0e9s. Prochaine étape : Batch E (Benchmark_Sectoriel + Scenarios).
A8: 3 | B8: 45687 | C8: Créer 14 nouveaux onglets dans CarbonCo_Calcul_Carbone_v2.xlsx selon la structure décrite | D8: Créé les 14 onglets : 01_PARAMÈTRES2, 02_FACTEURS_ÉMISSION2, 03_ÉNERGIE_BÂTIMENTS, 04_TRANSPORT2, 05_RESTAURATION, 06_NOTES_DE_FRAIS, 07_DÉCHETS2, 08_SERVEURS_PHYSIQUES, 09_INSTANCES_CLOUD, 10_INVENTAIRE_SI, 11_ÉQUIPEMENTS_BUREAU, 12_USAGES_NUMÉRIQUES, 13_MODÉLISATION_SERVICES, 14_SYNTHÈSE_GLOBALE | E8: Style cohérent avec l'existant (fond vert #1B5E20, bleu #0D47A1). Onglets numériques en violet #4A148C. Formules dynamiques : conso × FE → émissions → tCO2e. 14_SYNTHÈSE_GLOBALE agrège tous les totaux avec liens cross-onglets, KPIs (intensité/ETP, intensité/CA), répartition par scope. FE ADEME 2024, Boavizta, Shift Project intégrés dans 02_FACTEURS_ÉMISSION2. | F8: 14 onglets créés et opérationnels. Saisie : remplir '01_PARAMÈTRES2' d'abord, puis chaque onglet de saisie. La synthèse se met à jour automatiquement.
A9: 4 | B9: 45687 | C9: Remplir 02_FACTEURS_ÉMISSION2 avec la table complète des FE fournie par l'utilisateur | D9: Effacé l'ancien contenu, écrit 116 facteurs d'émission répartis en 13 sections avec code couleur, fiabilité colorée, format 6 décimales. Corrigé l'affichage année et largeurs colonnes. | E9: Sections : Électricité (E01-06), Chauffage (C01-08), Transport passagers (T01-21), Fret (M01-04), Alimentation (A01-08), Numérique Usages (N01-07), IA (I01-04), Infra (D01-08), Eau (W01-03), Déchets (R01-07), Notes frais (F01-03), Fabrication IT (H01-21), PUE (P01-08), Régions Cloud (G01-08). | F9: 116 FE disponibles jusqu'à la ligne 134. Colonnes B et E élargies pour éviter troncature.
A10: 5 | B10: 45687 | C10: Reconstruire 03_ÉNERGIE_BÂTIMENTS avec nouvelle structure 4 sections et formules détaillées | D10: Effacé et reconstruit entièrement. Section A électricité (6 sites, formule B*(1-E)*D + B*E*0.006), Section B chauffage (5 sites, Surface*Conso*Facteur), Section C clim (4 sites, Surface*kW*h + COP3), Section D eau (3 sites, m3*FE+ECS), Synthèse aggregée. | E10: VLOOKUP dynamique sur 02_FACTEURS_ÉMISSION2 pour D (mix élec), E (combustible), F (clim), D-F (eau W01-03). Cellules saisie en jaune. Lignes sous-titre en gris avec formules en texte. Gel rangées 1-2. | F10: Structure opérationnelle. Saisir : B (conso kWh), C (ID FE ex E01), E (% EnR), F (prix €/kWh) pour Section A. La synthèse ligne 47 agrège les 4 sections automatiquement.
A11: 6 | B11: 45687 | C11: Reconstruire 04_TRANSPORT2 avec nouvelle structure 3 sections et formules détaillées | D11: Effacé et reconstruit entièrement. Section A domicile-travail (8 lignes, modes pré-remplis), Section B déplacements pro (10 lignes, covoiturage), Section C flotte (7 véhicules). Synthèse avec % par scope. | E11: VLOOKUP dynamique sur 02_FACTEURS_ÉMISSION2 pour FE mode transport. Déplacements pro avec ajustement covoiturage (H/E). Flotte : formule Km x Conso/100 x FE_carburant. Jours ouvrés liés à Paramètres!B30. | F11: Fonctionnel avec exemples pré-remplis : 5 modes domicile-travail, 5 trajets pro, 7 véhicules. Synthèse ligne 49 : 46 tCO2e avec les données exemples.
A12: 7 | B12: 45687 | C12: Reconstruire 05_RESTAURATION avec nouvelle structure repas par type + café/boissons | D12: Effacé et reconstruit. Section A : 7 types de repas (A01-A08) avec % répartition, VLOOKUP FE via LEFT(A;3), Nb employés et jours liés Paramètres. Contrôle % = 100% en ligne 13. Section B : 5 boissons avec FE fixes. | E12: Formule repas : D x E x B (total repas) x C (FE) = CO2. Café : D x E x B x 0.058. Pré-rempli : 5% végétalien, 15% végétarien, 35% viande blanche, 25% viande rouge, 20% poisson = 100%. Synthèse ligne 31. | F12: Fonctionnel. Remplir 01_PARAMÈTRES2!B11 (effectif) pour activer les calculs. La ligne 13 vérifie que les % = 100%.
A13: 8 | B13: 45687 | C13: Construire 06_NOTES_DE_FRAIS et 07_DÉCHETS2 | D13: 06 : 10 postes (hôtel, repas, taxi, avions CC/MC/LC/affaires, location, autres), FE fixes ADEME, intensité kgCO2e/EUR, 6 KPIs. 07 : 10 flux déchets, VLOOKUP LEFT(D,3) sur FE, gestion unités t/kg auto, valeurs négatives recyclage en rouge. | E13: 06 : FE directs (pas VLOOKUP) car postes mixtes. Intensité = F/G. 07 : formule IF(C=kg AND F contains /t, B/1000*E, B*E) pour conversion automatique t/kg. Indicateurs : émissions brutes vs évitées, taux valorisation COUNTIF. | F13: Fonctionnel. 06 : 9.5 tCO2e exemples, ratio vols 55.9%. 07 : total net 22 tCO2e, évitées -1600 kg, taux valorisation 60%.
... A22: 17 | B22: 45687 | C22: Harmoniser le formatage sur les 14 onglets (largeurs colonnes, num formats, navigation, bordures) | D22: Pass de formatage uniforme : largeurs de colonnes ajustées sur 14 onglets, number formats cohérents (%, #,##0, 0.000), liens navigation 🏠/📄 ajoutés sur 08-11,13,14, bordures professionnelles sur Synthèse (sections A, B, Scopes). | E22: 01: inputs en bleu/jaune. 04: km #,##0, FE 0.000. 14: col K=0%, L=#,##0.00, M=0.0%, N=#,##0.00. Bordures thin gris #D0D0D0 inside, medium extérieures. Scopes rows 88-132 avec bordures grid complètes. | F22: Tous les 14 onglets sont maintenant formatés de manière cohérente avec navigation, bordures et number formats uniformes. Synthèse affiche S1=3725 (3.9%), S2=0, S3=92017 (96.1%), Total=95742 kgCO2e.
A23: 18 | B23: 2026-04-12 | C23: Block A data contract alignment | D23: Added canonical CC_* named ranges for shared enterprise, carbon, energy, taxonomie, CBAM and SBTi fields. | E23: Named ranges now expose the stable integration contract consumed by Phase 0 documentation and future backend ingestion. | F23: Carbon master workbook now contains the Phase 0 source contract.

Sheet 01_PARAMÈTRES2
A1: PARAMETRES DE L'ENTREPRISE — Bilan Carbone | E1: Sommaire
A2: Parametre | B2: Valeur | C2: Unite / Remarque
A3: 1 — IDENTITE DE L'ENTREPRISE
A4: Nom de l'entreprise | C4: Texte libre
A5: Secteur d'activite | C5: ex: Services numeriques, Industrie, Retail…
A6: Code NAF / APE | C6: ex: 6201Z, 4791B…
A7: Responsable du bilan | C7: Nom et prenom
A8: Date de remplissage | C8: Format JJ/MM/AAAA
A9: Annee de reference | B9: 2024 | C9: Annee du bilan carbone
A10: Annee de comparaison N-1 | B10: 2023 | C10: Pour calcul evolution YoY
A11: 2 — EFFECTIFS & LOCAUX
A12: Nb employes (ETP) | B12: 50 | C12: Equivalent temps plein — saisonniers inclus
A13: Nb de sites | B13: 1 | C13: Nombre de bureaux / sites
A14: Surface totale locaux (m2) | B14: 1200 | C14: Total m2 chauffes
A15: Jours ouvres / an | B15: 220 | C15: Ex: 220 (5j/sem, 52 sem, -8 jours feries)
A16: Taux teletravail (%) | B16: 0.2 | C16: Part du temps en teletravail (0 a 1)
A17: Pays principal | B17: France | C17: Pour facteur emissif electricite par defaut
A19: 3 — DONNEES FINANCIERES
A20: Chiffre d'affaires (EUR) | B20: 12000000 | C20: En euros — pour intensite carbone CO2/M EUR
A21: Masse salariale (EUR) | C21: Optionnel — pour ratio salaires
A22: Budget IT (EUR) | C22: Optionnel — pour ratio IT
A24: 4 — PRIX DE L'ENERGIE (pour estimation couts)
A25: Prix electricite (EUR/kWh) | B25: 0.18 | C25: Moyenne annuelle TTC — source facture
A26: Prix gaz naturel (EUR/kWh) | B26: 0.08 | C26: Moyenne annuelle TTC
A27: Prix eau (EUR/m3) | B27: 4.5 | C27: Eau froide + assainissement
A28: Prix fioul (EUR/litre) | B28: 0.95 | C28: Optionnel
A30: 5 — OBJECTIFS DE REDUCTION
A31: Objectif reduction (%/an) | B31: -0.15 | C31: Ex: -0.15 = -15% / an. Reference Section C synthese
A32: Annee cible objectif | B32: 2030 | C32: Horizon de neutralite cible
A33: Reference externe | B33: SBTi 1.5C | C33: Ex: SBTi, SBTN, accord Paris, RE2020…
A35: 6 — PARAMETRES DE CALCUL (references onglets)
A36: Facteur emissif elec France (kgCO2e/kWh) | B36: 0.0569 | C36: ADEME Base Carbone 2024 — reseau FR
A37: Facteur emissif gaz naturel (kgCO2e/kWh) | B37: 0.2272 | C37: ADEME Base Carbone 2024
A38: Facteur emissif fioul (kgCO2e/kWh) | B38: 0.324 | C38: ADEME Base Carbone 2024
A39: COP climatisation (defaut) | B39: 3 | C39: Efficacite energetique clim (2.5 a 4.0)
A40: PUE datacenter interne | B40: 1.5 | C40: Power Usage Effectiveness (1.1 a 2.0)
A41: Duree amortissement IT (ans) | B41: 4 | C41: Duree de vie standard equipements IT
A42: Taux recyclage dechets (%) | B42: 0.35 | C42: Part des dechets effectivement recycles
A44: Note : toutes les cellules jaunes (colonne B) sont des saisies utilisateur. Les formules des autres onglets referentent ces cellules via '01_PARAMETRES2'!B12 etc. Ne pas modifier les noms des onglets.

Sheet 02_FACTEURS_ÉMISSION2
A1: BASE DE FACTEURS D'ÉMISSION — ADEME Base Carbone / IEA / GIEC / Boavizta / Ecoinvent | N1: 🏠 Sommaire | O1: 📄 Couverture
A2: Table de référence complète avec sources. ✅✅✅ = haute fiabilité (source officielle). ✅✅ = fiabilité bonne. ✅ = estimation. ⚠️ = incertitude élevée.
A3: ID | B3: Libellé | C3: Valeur | D3: Unité | E3: Source | F3: Année | G3: Fiabilité | H3: FE Combustion (Scope 1) | I3: FE Amont (Scope 3 Cat.3) | J3: FE Total (kgCO2e/u) | K3: FE Market-based | L3: Incertitude (%) | M3: Scope
B4: ═══ ÉLECTRICITÉ ═══
A5: E01 | B5: Mix France | C5: 0.0569 | D5: kgCO₂e/kWh | E5: Base Carbone | F5: 2024 | G5: ✅✅✅ | H5: 0 | I5: 0 | J5: =C5 | K5: 0.06 | L5: 10 | M5: Scope 2
A6: E02 | B6: Mix Allemagne | C6: 0.385 | D6: kgCO₂e/kWh | E6: IEA | F6: 2024 | G6: ✅✅✅ | H6: 0 | I6: 0 | J6: =C6 | K6: 0.576 | L6: 10 | M6: Scope 2
A7: E03 | B7: Mix UE moyen | C7: 0.23 | D7: kgCO₂e/kWh | E7: IEA | F7: 2024 | G7: ✅✅✅ | H7: 0 | I7: 0 | J7: =C7 | K7: 0.396 | L7: 15 | M7: Scope 2
A8: E04 | B8: Mix Royaume-Uni | C8: 0.207 | D8: kgCO₂e/kWh | E8: DEFRA/IEA | F8: 2024 | G8: ✅✅✅ | H8: 0 | I8: 0 | J8: =C8 | K8: 0.31 | L8: 10 | M8: Scope 2
A9: E05 | B9: Mix États-Unis moyen | C9: 0.39 | D9: kgCO₂e/kWh | E9: EPA eGRID | F9: 2024 | G9: ✅✅✅ | H9: 0 | I9: 0 | J9: =C9 | K9: 0.39 | L9: 10 | M9: Scope 2
A10: E06 | B10: EnR (éolien/solaire/hydro) | C10: 0.006 | D10: kgCO₂e/kWh | E10: GIEC AR6 | F10: 2023 | G10: ✅✅✅ | H10: 0 | I10: 0 | J10: =C10 | K10: 0.006 | L10: 50 | M10: Scope 2
B11: ═══ CHAUFFAGE ═══
A12: C01 | B12: Gaz naturel | C12: 0.227 | D12: kgCO₂e/kWh | E12: Base Carbone | F12: 2024 | G12: ✅✅✅ | H12: 0.205 | I12: 0.022 | J12: =C12 | L12: 5 | M12: S1+S3.3
A13: C02 | B13: Fioul domestique | C13: 0.324 | D13: kgCO₂e/kWh | E13: Base Carbone | F13: 2024 | G13: ✅✅✅ | H13: 0.268 | I13: 0.056 | J13: =C13 | L13: 5 | M13: S1+S3.3
A14: C03 | B14: Réseau de chaleur (moy. FR) | C14: 0.125 | D14: kgCO₂e/kWh | E14: Base Carbone | F14: 2024 | G14: ✅✅ | H14: 0 | I14: 0 | J14: =C14 | L14: 20 | M14: Scope 2
A15: C04 | B15: Pompe à chaleur (COP 3.5 FR) | C15: 0.045 | D15: kgCO₂e/kWh | E15: Calcul ADEME | F15: 2024 | G15: ✅✅ | H15: 0 | I15: 0 | J15: =C15 | L15: 20 | M15: Scope 2
A16: C05 | B16: Granulés bois | C16: 0.03 | D16: kgCO₂e/kWh | E16: Base Carbone | F16: 2024 | G16: ✅✅✅ | H16: 0 | I16: 0.03 | J16: =C16 | L16: 30 | M16: S3.3
A17: C06 | B17: Radiateur électrique (FR) | C17: 0.0569 | D17: kgCO₂e/kWh | E17: =E1 | F17: 2024 | G17: ✅✅✅ | H17: 0 | I17: 0 | J17: =C17 | L17: 10 | M17: Scope 2
A18: C07 | B18: Climatisation standard | C18: 0.025 | D18: kgCO₂e/kWh | E18: Base Carbone | F18: 2024 | G18: ✅✅ | H18: 0 | I18: 0 | J18: =C18 | L18: 20 | M18: Scope 2
A19: C08 | B19: Climatisation ancienne | C19: 0.055 | D19: kgCO₂e/kWh | E19: Base Carbone | F19: 2024 | G19: ✅✅ | H19: 0 | I19: 0 | J19: =C19 | L19: 20 | M19: Scope 2
B20: ═══ TRANSPORT PASSAGERS ═══
A21: T01 | B21: Voiture thermique moyenne | C21: 0.218 | D21: kgCO₂e/km | E21: Base Carbone | F21: 2024 | G21: ✅✅✅ | H21: 0.193 | I21: 0.025 | J21: =C21 | L21: 15 | M21: S1/S3
A22: T02 | B22: Voiture diesel | C22: 0.234 | D22: kgCO₂e/km | E22: Base Carbone | F22: 2024 | G22: ✅✅✅ | H22: 0.207 | I22: 0.027 | J22: =C22 | L22: 10 | M22: S1/S3
A23: T03 | B23: Voiture essence | C23: 0.206 | D23: kgCO₂e/km | E23: Base Carbone | F23: 2024 | G23: ✅✅✅ | H23: 0.182 | I23: 0.024 | J23: =C23 | L23: 10 | M23: S1/S3
A24: T04 | B24: Voiture hybride | C24: 0.11 | D24: kgCO₂e/km | E24: Base Carbone | F24: 2024 | G24: ✅✅✅ | H24: 0.09 | I24: 0.02 | J24: =C24 | L24: 20 | M24: S1/S3
A25: T05 | B25: Voiture électrique (FR) | C25: 0.02 | D25: kgCO₂e/km | E25: Base Carbone | F25: 2024 | G25: ✅✅✅ | H25: 0 | I25: 0.02 | J25: =C25 | L25: 20 | M25: S3
A26: T06 | B26: Voiture électrique (UE) | C26: 0.055 | D26: kgCO₂e/km | E26: Calcul IEA | F26: 2024 | G26: ✅✅ | H26: 0 | I26: 0.055 | J26: =C26 | L26: 20 | M26: S3
A27: T07 | B27: TGV | C27: 0.00297 | D27: kgCO₂e/km | E27: Base Carbone | F27: 2024 | G27: ✅✅✅ | H27: 0 | I27: 0 | J27: =C27 | L27: 20 | M27: S3
A28: T08 | B28: TER | C28: 0.0248 | D28: kgCO₂e/km | E28: Base Carbone | F28: 2024 | G28: ✅✅✅ | H28: 0.02 | I28: 0.005 | J28: =C28 | L28: 20 | M28: S3
A29: T09 | B29: Intercités | C29: 0.0058 | D29: kgCO₂e/km | E29: Base Carbone | F29: 2024 | G29: ✅✅✅ | H29: 0 | I29: 0 | J29: =C29 | L29: 20 | M29: S3
A30: T10 | B30: Métro / Tramway | C30: 0.00425 | D30: kgCO₂e/km | E30: Base Carbone | F30: 2024 | G30: ✅✅✅ | H30: 0 | I30: 0 | J30: =C30 | L30: 20 | M30: S3
A31: T11 | B31: Bus urbain | C31: 0.103 | D31: kgCO₂e/km | E31: Base Carbone | F31: 2024 | G31: ✅✅✅ | H31: 0.09 | I31: 0.013 | J31: =C31 | L31: 15 | M31: S3
A32: T12 | B32: Autocar | C32: 0.035 | D32: kgCO₂e/km | E32: Base Carbone | F32: 2024 | G32: ✅✅✅ | H32: 0.03 | I32: 0.005 | J32: =C32 | L32: 15 | M32: S3
... A41: T21 | B41: Taxi / VTC | C41: 0.26 | D41: kgCO₂e/km | E41: Base Carbone | F41: 2024 | G41: ✅✅✅ | H41: 0.23 | I41: 0.03 | J41: =C41 | L41: 10 | M41: S3 Cat.6
B42: ═══ TRANSPORT MARCHANDISES ═══
A43: M01 | B43: Camion (route) | C43: 0.081 | D43: kgCO₂e/tkm | E43: Base Carbone | F43: 2024 | G43: ✅✅✅ | H43: 0.073 | I43: 0.008 | J43: =C43 | L43: 15 | M43: S3 Cat.4
A44: M02 | B44: Train (fret) | C44: 0.0046 | D44: kgCO₂e/tkm | E44: Base Carbone | F44: 2024 | G44: ✅✅✅ | H44: 0 | I44: 0.0046 | J44: =C44 | L44: 20 | M44: S3 Cat.4
A45: M03 | B45: Cargo (mer) | C45: 0.016 | D45: kgCO₂e/tkm | E45: Base Carbone | F45: 2024 | G45: ✅✅✅ | H45: 0 | I45: 0.016 | J45: =C45 | L45: 20 | M45: S3 Cat.4
A46: M04 | B46: Avion (fret) | C46: 0.875 | D46: kgCO₂e/tkm | E46: Base Carbone | F46: 2024 | G46: ✅✅✅ | H46: 0.875 | I46: 0 | J46: =C46 | L46: 15 | M46: S3 Cat.4
B47: ═══ ALIMENTATION ═══
A48: A01 | B48: Repas végétalien | C48: 0.51 | D48: kgCO₂e/repas | E48: Ecoinvent/ADEME | F48: 2024 | G48: ✅✅ | H48: 0 | I48: 0.51 | J48: =C48 | L48: 30 | M48: S3 Cat.1
A49: A02 | B49: Repas végétarien | C49: 0.84 | D49: kgCO₂e/repas | E49: Ecoinvent/ADEME | F49: 2024 | G49: ✅✅ | H49: 0 | I49: 0.84 | J49: =C49 | L49: 30 | M49: S3 Cat.1
A50: A03 | B50: Repas standard (mixte) | C50: 1.58 | D50: kgCO₂e/repas | E50: Ecoinvent/ADEME | F50: 2024 | G50: ✅✅ | H50: 0 | I50: 1.58 | J50: =C50 | L50: 30 | M50: S3 Cat.1
A51: A04 | B51: Repas viande rouge | C51: 3.25 | D51: kgCO₂e/repas | E51: Ecoinvent/ADEME | F51: 2024 | G51: ✅✅ | H51: 0 | I51: 3.25 | J51: =C51 | L51: 30 | M51: S3 Cat.1
A52: A05 | B52: Repas viande blanche | C52: 1.35 | D52: kgCO₂e/repas | E52: Ecoinvent/ADEME | F52: 2024 | G52: ✅✅ | H52: 0 | I52: 1.35 | J52: =C52 | L52: 30 | M52: S3 Cat.1
A53: A06 | B53: Repas poisson | C53: 1.02 | D53: kgCO₂e/repas | E53: Ecoinvent/ADEME | F53: 2024 | G53: ✅✅ | H53: 0 | I53: 1.02 | J53: =C53 | L53: 30 | M53: S3 Cat.1
A54: A07 | B54: Café (tasse 200ml) | C54: 0.058 | D54: kgCO₂e | E54: Études LCA | F54: 2023 | G54: ✅✅ | H54: 0 | I54: 0.058 | J54: =C54 | L54: 30 | M54: S3 Cat.1
A55: A08 | B55: Repas restaurant extérieur | C55: 2.1 | D55: kgCO₂e/repas | E55: ADEME | F55: 2024 | G55: ✅✅ | H55: 0 | I55: 2.1 | J55: =C55 | L55: 30 | M55: S3 Cat.1
B56: ═══ NUMÉRIQUE — USAGES ═══
A57: N01 | B57: Email simple (texte) | C57: 0.004 | D57: kgCO₂e | E57: ADEME | F57: 2024 | G57: ✅✅ | H57: 0 | I57: 0.004 | J57: =C57 | L57: 50 | M57: S3 Cat.9
A58: N02 | B58: Email avec PJ (1 Mo) | C58: 0.035 | D58: kgCO₂e | E58: ADEME | F58: 2024 | G58: ✅✅ | H58: 0 | I58: 0.035 | J58: =C58 | L58: 50 | M58: S3 Cat.9
A59: N03 | B59: Visioconférence (1h) | C59: 0.15 | D59: kgCO₂e | E59: IEA/Shift | F59: 2024 | G59: ✅✅ | H59: 0 | I59: 0.15 | J59: =C59 | L59: 50 | M59: S3 Cat.9
A60: N04 | B60: Streaming vidéo SD (1h) | C60: 0.036 | D60: kgCO₂e | E60: IEA | F60: 2024 | G60: ✅✅ | H60: 0 | I60: 0.036 | J60: =C60 | L60: 50 | M60: S3 Cat.9
A61: N05 | B61: Streaming vidéo HD (1h) | C61: 0.08 | D61: kgCO₂e | E61: IEA | F61: 2024 | G61: ✅✅ | H61: 0 | I61: 0.08 | J61: =C61 | L61: 50 | M61: S3 Cat.9
A62: N06 | B62: Requête web simple | C62: 0.0007 | D62: kgCO₂e | E62: Shift/NegaOctet | F62: 2023 | G62: ✅ | H62: 0 | I62: 0.0007 | J62: =C62 | L62: 50 | M62: S3 Cat.9
A63: N07 | B63: Impression (par page A4) | C63: 0.005 | D63: kgCO₂e | E63: ADEME | F63: 2024 | G63: ✅✅ | H63: 0 | I63: 0.005 | J63: =C63 | L63: 40 | M63: S3 Cat.9
B64: ═══ NUMÉRIQUE — IA ═══
A65: I01 | B65: Requête GPT-4 / Claude 3.5 | C65: 0.01 | D65: kgCO₂e | E65: IEA/études ML | F65: 2024 | G65: ⚠️ | H65: 0 | I65: 0.01 | J65: =C65 | L65: 50 | M65: S3 Cat.11
A66: I02 | B66: Requête modèle léger (Mistral) | C66: 0.002 | D66: kgCO₂e | E66: Estimations | F66: 2024 | G66: ⚠️ | H66: 0 | I66: 0.002 | J66: =C66 | L66: 50 | M66: S3 Cat.11
A67: I03 | B67: Entraînement modèle (1h GPU) | C67: 50 | D67: kgCO₂e | E67: Green Algorithms | F67: 2023 | G67: ⚠️ | H67: 0 | I67: 50 | J67: =C67 | L67: 50 | M67: S3 Cat.11
A68: I04 | B68: Fine-tuning (1h GPU A100) | C68: 3.5 | D68: kgCO₂e | E68: Green Algorithms | F68: 2023 | G68: ⚠️ | H68: 0 | I68: 3.5 | J68: =C68 | L68: 50 | M68: S3 Cat.11
B69: ⚠️ Facteurs IA = estimations (pas encore standardisés ADEME)
B70: ═══ NUMÉRIQUE — INFRA ═══
A71: D01 | B71: Stockage cloud (1 Go/an) | C71: 0.02 | D71: kgCO₂e | E71: Boavizta | F71: 2024 | G71: ✅✅ | H71: 0 | I71: 0.02 | J71: =C71 | L71: 50 | M71: S3 Cat.11
A72: D02 | B72: Réseau fixe fibre (1 Go) | C72: 0.015 | D72: kgCO₂e | E72: ADEME/ARCEP | F72: 2023 | G72: ✅✅ | H72: 0 | I72: 0.015 | J72: =C72 | L72: 40 | M72: S3 Cat.9
A73: D03 | B73: Réseau fixe ADSL (1 Go) | C73: 0.025 | D73: kgCO₂e | E73: ADEME/ARCEP | F73: 2023 | G73: ✅✅ | H73: 0 | I73: 0.025 | J73: =C73 | L73: 40 | M73: S3 Cat.9
A74: D04 | B74: Réseau mobile 4G (1 Go) | C74: 0.065 | D74: kgCO₂e | E74: ADEME/ARCEP | F74: 2023 | G74: ✅✅ | H74: 0 | I74: 0.065 | J74: =C74 | L74: 40 | M74: S3 Cat.9
A75: D05 | B75: Réseau mobile 5G (1 Go) | C75: 0.035 | D75: kgCO₂e | E75: ADEME/ARCEP | F75: 2023 | G75: ✅✅ | H75: 0 | I75: 0.035 | J75: =C75 | L75: 40 | M75: S3 Cat.9
A76: D06 | B76: RAM serveur (1 Go actif) | C76: 0.469 | D76: W | E76: JEDEC DDR4/5 | F76: 2024 | G76: ✅✅ | H76: 0 | I76: 0 | J76: =C76 | L76: 30 | M76: —
A77: D07 | B77: SSD serveur (1 To) | C77: 2.5 | D77: W | E77: Constructeurs | F77: 2024 | G77: ✅✅ | H77: 0 | I77: 0 | J77: =C77 | L77: 30 | M77: —
A78: D08 | B78: HDD serveur (1 To) | C78: 6 | D78: W | E78: Constructeurs | F78: 2024 | G78: ✅✅ | H78: 0 | I78: 0 | J78: =C78 | L78: 30 | M78: —
B79: ═══ EAU ═══
A80: W01 | B80: Production eau potable | C80: 0.132 | D80: kgCO₂e/m³ | E80: Base Carbone | F80: 2024 | G80: ✅✅✅ | H80: 0 | I80: 0.132 | J80: =C80 | L80: 30 | M80: S3 Cat.1
A81: W02 | B81: Traitement eaux usées | C81: 0.344 | D81: kgCO₂e/m³ | E81: Base Carbone | F81: 2024 | G81: ✅✅✅ | H81: 0 | I81: 0.344 | J81: =C81 | L81: 30 | M81: S3 Cat.1
A82: W03 | B82: Eau chaude sanitaire (1L) | C82: 0.0036 | D82: kgCO₂e | E82: Calcul ADEME | F82: 2024 | G82: ✅✅ | H82: 0 | I82: 0.0036 | J82: =C82 | L82: 30 | M82: S3 Cat.1
B83: ═══ DÉCHETS ═══
A84: R01 | B84: Enfouissement (1 t) | C84: 440 | D84: kgCO₂e/t | E84: Base Carbone | F84: 2024 | G84: ✅✅✅ | H84: 0 | I84: 440 | J84: =C84 | L84: 30 | M84: S3 Cat.5
A85: R02 | B85: Incinération avec récup. (1 t) | C85: 20 | D85: kgCO₂e/t | E85: Base Carbone | F85: 2024 | G85: ✅✅✅ | H85: 0 | I85: 20 | J85: =C85 | L85: 30 | M85: S3 Cat.5
A86: R03 | B86: Recyclage — émissions évitées | C86: -300 | D86: kgCO₂e/t | E86: Base Carbone | F86: 2024 | G86: ✅✅ | H86: 0 | I86: -300 | J86: =C86 | L86: 30 | M86: S3 Cat.5
A87: R04 | B87: Compostage | C87: -50 | D87: kgCO₂e/t | E87: Base Carbone | F87: 2024 | G87: ✅✅ | H87: 0 | I87: -50 | J87: =C87 | L87: 30 | M87: S3 Cat.5
A88: R05 | B88: Papier/carton (1 kg) | C88: 0.919 | D88: kgCO₂e | E88: Base Carbone | F88: 2024 | G88: ✅✅✅ | H88: 0 | I88: 0.919 | J88: =C88 | L88: 30 | M88: S3 Cat.5
A89: R06 | B89: Plastique (1 kg) | C89: 2 | D89: kgCO₂e | E89: Base Carbone | F89: 2024 | G89: ✅✅ | H89: 0 | I89: 2 | J89: =C89 | L89: 30 | M89: S3 Cat.5
A90: R07 | B90: DEEE (1 kg) | C90: 25 | D90: kgCO₂e | E90: ADEME/Ecologic | F90: 2024 | G90: ✅✅ | H90: 0 | I90: 25 | J90: =C90 | L90: 30 | M90: S3 Cat.5
B91: ═══ NOTES DE FRAIS ═══
A92: F01 | B92: Nuit hôtel business | C92: 19.6 | D92: kgCO₂e | E92: Base Carbone | F92: 2024 | G92: ✅✅ | H92: 0 | I92: 19.6 | J92: =C92 | L92: 40 | M92: S3 Cat.6
A93: F02 | B93: Nuit hôtel éco-labellisé | C93: 6.7 | D93: kgCO₂e | E93: Base Carbone | F93: 2024 | G93: ✅✅ | H93: 0 | I93: 6.7 | J93: =C93 | L93: 40 | M93: S3 Cat.6
A94: F03 | B94: Taxi (1 km) | C94: 0.26 | D94: kgCO₂e | E94: Base Carbone | F94: 2024 | G94: ✅✅✅ | H94: 0 | I94: 0.26 | J94: =C94 | L94: 10 | M94: S3 Cat.6
B95: ═══ FABRICATION IT ═══
A96: H01 | B96: Serveur rack 2U | C96: 1500 | D96: kgCO₂e | E96: Boavizta/Dell | F96: 2024 | G96: ✅✅ | H96: 0 | I96: 0 | J96: =C96 | L96: 30 | M96: S3 Cat.2
A97: H02 | B97: Switch 48 ports | C97: 475 | D97: kgCO₂e | E97: Boavizta | F97: 2024 | G97: ✅✅ | H97: 0 | I97: 0 | J97: =C97 | L97: 30 | M97: S3 Cat.2
A98: H03 | B98: Routeur enterprise | C98: 350 | D98: kgCO₂e | E98: Boavizta | F98: 2024 | G98: ✅✅ | H98: 0 | I98: 0 | J98: =C98 | L98: 30 | M98: S3 Cat.2
A99: H04 | B99: Firewall mid-range | C99: 550 | D99: kgCO₂e | E99: Boavizta | F99: 2024 | G99: ✅✅ | H99: 0 | I99: 0 | J99: =C99 | L99: 30 | M99: S3 Cat.2
A100: H05 | B100: Baie SAN 10 To SSD | C100: 5500 | D100: kgCO₂e | E100: Boavizta | F100: 2024 | G100: ✅✅ | H100: 0 | I100: 0 | J100: =C100 | L100: 30 | M100: S3 Cat.2
A101: H06 | B101: NAS 4 baies | C101: 550 | D101: kgCO₂e | E101: Boavizta | F101: 2024 | G101: ✅✅ | H101: 0 | I101: 0 | J101: =C101 | L101: 30 | M101: S3 Cat.2
A102: H07 | B102: Onduleur (UPS) 3kVA | C102: 400 | D102: kgCO₂e | E102: ADEME | F102: 2024 | G102: ✅ | H102: 0 | I102: 0 | J102: =C102 | L102: 30 | M102: S3 Cat.2
A103: H08 | B103: Laptop 14" standard | C103: 350 | D103: kgCO₂e | E103: Dell PCF | F103: 2024 | G103: ✅✅✅ | H103: 0 | I103: 0 | J103: =C103 | L103: 30 | M103: S3 Cat.2
A104: H09 | B104: Laptop 14" performant | C104: 475 | D104: kgCO₂e | E104: Dell/Lenovo | F104: 2024 | G104: ✅✅✅ | H104: 0 | I104: 0 | J104: =C104 | L104: 30 | M104: S3 Cat.2
A105: H10 | B105: Desktop (tour) | C105: 500 | D105: kgCO₂e | E105: Boavizta/HP | F105: 2024 | G105: ✅✅ | H105: 0 | I105: 0 | J105: =C105 | L105: 30 | M105: S3 Cat.2
A106: H11 | B106: Mini PC | C106: 250 | D106: kgCO₂e | E106: Boavizta | F106: 2024 | G106: ✅✅ | H106: 0 | I106: 0 | J106: =C106 | L106: 30 | M106: S3 Cat.2
A107: H12 | B107: Écran 24" | C107: 425 | D107: kgCO₂e | E107: Dell PCF | F107: 2024 | G107: ✅✅✅ | H107: 0 | I107: 0 | J107: =C107 | L107: 30 | M107: S3 Cat.2
... A116: H21 | B116: Casque audio/vidéo | C116: 20 | D116: kgCO₂e | E116: Estimations | F116: 2024 | G116: ✅ | H116: 0 | I116: 0 | J116: =C116 | L116: 30 | M116: S3 Cat.2
...

Sheet 03_ÉNERGIE_BÂTIMENTS
A1: ÉNERGIE & BÂTIMENTS — Électricité, Chauffage, Climatisation, Eau | N1: 🏠 Sommaire | O1: 📄 Couverture
A2: Émissions élec = Conso x [(1-EnR%) x Facteur_mix + EnR% x 0.006] | Chauffage = Surface x Conso_unit x Facteur | Sources : Base Carbone ADEME 2024 / IEA 2024
A3: A — ÉLECTRICITÉ (Scope 2 — location-based & market-based)
A4: Site / Bâtiment | B4: Conso annuelle (kWh) | C4: Mix elec (ID FE) | D4: Facteur elec (kgCO2e/kWh) | E4: Part EnR/PPA (%) | F4: Cout (EUR/kWh) | G4: CO2 reseau (kgCO2e) | H4: CO2 EnR (kgCO2e) | I4: CO2 total (kgCO2e) | J4: CO2 total (tCO2e) | K4: Cout annuel (EUR) | L4: Par ETP (kgCO2e)
B5: relevé compteur / facture | C5: ex: E01 France | D5: VLOOKUP(C;FE!A:C;3) | E5: 0% si pas de PPA | F5: ou Paramètres | G5: B x (1-E) x D | H5: B x E x 0.006 | I5: G + H | J5: I / 1000 | K5: B x F | L5: I / nb_ETP
A6: Siège social | B6: 0 | C6: E01 | D6: =IFERROR(VLOOKUP(C6,'02_FACTEURS_ÉMISSION2'!$A:$C,3,0),0.0569) | E6: 0 | F6: 0.18 | G6: =B6*(1-E6)*D6 | H6: =B6*E6*0.006 | I6: =G6+H6 | J6: =I6/1000 | K6: =B6*F6 | L6: =IFERROR(I6/'01_PARAMÈTRES2'!B12,0)
A7: Site production | B7: 0 | C7: E01 | D7: =IFERROR(VLOOKUP(C7,'02_FACTEURS_ÉMISSION2'!$A:$C,3,0),0.0569) | E7: 0 | F7: 0.18 | G7: =B7*(1-E7)*D7 | H7: =B7*E7*0.006 | I7: =G7+H7 | J7: =I7/1000 | K7: =B7*F7 | L7: =IFERROR(I7/'01_PARAMÈTRES2'!B12,0)
A8: Entrepôt / Logistique | B8: 0 | C8: E01 | D8: =IFERROR(VLOOKUP(C8,'02_FACTEURS_ÉMISSION2'!$A:$C,3,0),0.0569) | E8: 0 | F8: 0.18 | G8: =B8*(1-E8)*D8 | H8: =B8*E8*0.006 | I8: =G8+H8 | J8: =I8/1000 | K8: =B8*F8 | L8: =IFERROR(I8/'01_PARAMÈTRES2'!B12,0)
A9: Agence régionale 1 | B9: 0 | C9: E01 | D9: =IFERROR(VLOOKUP(C9,'02_FACTEURS_ÉMISSION2'!$A:$C,3,0),0.0569) | E9: 0 | F9: 0.18 | G9: =B9*(1-E9)*D9 | H9: =B9*E9*0.006 | I9: =G9+H9 | J9: =I9/1000 | K9: =B9*F9 | L9: =IFERROR(I9/'01_PARAMÈTRES2'!B12,0)
A10: Agence régionale 2 | B10: 0 | C10: E01 | D10: =IFERROR(VLOOKUP(C10,'02_FACTEURS_ÉMISSION2'!$A:$C,3,0),0.0569) | E10: 0 | F10: 0.18 | G10: =B10*(1-E10)*D10 | H10: =B10*E10*0.006 | I10: =G10+H10 | J10: =I10/1000 | K10: =B10*F10 | L10: =IFERROR(I10/'01_PARAMÈTRES2'!B12,0)
A11: Datacenter on-premise | B11: 0 | C11: E01 | D11: =IFERROR(VLOOKUP(C11,'02_FACTEURS_ÉMISSION2'!$A:$C,3,0),0.0569) | E11: 0 | F11: 0.18 | G11: =B11*(1-E11)*D11 | H11: =B11*E11*0.006 | I11: =G11+H11 | J11: =I11/1000 | K11: =B11*F11 | L11: =IFERROR(I11/'01_PARAMÈTRES2'!B12,0)
A12: TOTAL ÉLECTRICITÉ | B12: =SUM(B6:B11) | G12: =SUM(G6:G11) | H12: =SUM(H6:H11) | I12: =SUM(I6:I11) | J12: =SUM(J6:J11) | K12: =SUM(K6:K11) | L12: =IFERROR(I12/'01_PARAMÈTRES2'!B12,0)
A14: B — CHAUFFAGE / COMBUSTIBLES (Scope 1 — combustion directe)
A15: Site / Bâtiment | B15: Surface chauffée (m2) | C15: Conso unitaire (kWh/m2/an) | D15: Type combustible (ID FE) | E15: Facteur combustible (kgCO2e/kWh) | F15: Conso totale (kWh) | G15: CO2 total (kgCO2e) | H15: CO2 total (tCO2e) | I15: CO2 par m2 (kgCO2e/m2) | J15: Cout estimé (EUR)
B16: m2 chauffés | C16: 30 BBC a 250 passoire | D16: ex: C01 Gaz | E16: VLOOKUP(D;FE) | F16: B x C | G16: F x E | H16: G / 1000 | I16: G / B | J16: F x prix_gaz
A17: Siège social | B17: 0 | C17: 120 | D17: C01 | E17: =IFERROR(VLOOKUP(D17,'02_FACTEURS_ÉMISSION2'!$A:$C,3,0),0.227) | F17: =B17*C17 | G17: =F17*E17 | H17: =G17/1000 | I17: =IFERROR(G17/B17,0) | J17: =F17*IFERROR('01_PARAMÈTRES2'!B26,0.08)
A18: Site production | B18: 0 | C18: 120 | D18: C01 | E18: =IFERROR(VLOOKUP(D18,'02_FACTEURS_ÉMISSION2'!$A:$C,3,0),0.227) | F18: =B18*C18 | G18: =F18*E18 | H18: =G18/1000 | I18: =IFERROR(G18/B18,0) | J18: =F18*IFERROR('01_PARAMÈTRES2'!B26,0.08)
A19: Entrepôt / Logistique | B19: 0 | C19: 120 | D19: C01 | E19: =IFERROR(VLOOKUP(D19,'02_FACTEURS_ÉMISSION2'!$A:$C,3,0),0.227) | F19: =B19*C19 | G19: =F19*E19 | H19: =G19/1000 | I19: =IFERROR(G19/B19,0) | J19: =F19*IFERROR('01_PARAMÈTRES2'!B26,0.08)
A20: Agence régionale 1 | B20: 0 | C20: 120 | D20: C01 | E20: =IFERROR(VLOOKUP(D20,'02_FACTEURS_ÉMISSION2'!$A:$C,3,0),0.227) | F20: =B20*C20 | G20: =F20*E20 | H20: =G20/1000 | I20: =IFERROR(G20/B20,0) | J20: =F20*IFERROR('01_PARAMÈTRES2'!B26,0.08)
A21: Agence régionale 2 | B21: 0 | C21: 120 | D21: C01 | E21: =IFERROR(VLOOKUP(D21,'02_FACTEURS_ÉMISSION2'!$A:$C,3,0),0.227) | F21: =B21*C21 | G21: =F21*E21 | H21: =G21/1000 | I21: =IFERROR(G21/B21,0) | J21: =F21*IFERROR('01_PARAMÈTRES2'!B26,0.08)
A22: TOTAL CHAUFFAGE | F22: =SUM(F17:F21) | G22: =SUM(G17:G21) | H22: =SUM(H17:H21) | I22: =IFERROR(G22/SUM(B17:B21),0) | J22: =SUM(J17:J21)
A24: C — CLIMATISATION & REFROIDISSEMENT (Scope 1 + Scope 2)
A25: Site / Bâtiment | B25: Surface climatisée (m2) | C25: Puissance froid/m2 (kW/m2) | D25: Heures fonct. (h/an) | E25: Type système (ID FE) | F25: Facteur clim (kgCO2e/kWh) | G25: Energie froid (kWh) | H25: CO2 fuites (kgCO2e) | I25: CO2 élec compresseur (kgCO2e) | J25: CO2 total (tCO2e)
B26: m2 climatisés | C26: 0.08 standard bureaux | D26: 800 été+mi-saison | E26: C07 std ou C08 anc | F26: VLOOKUP(E;FE) | G26: B x C x D | H26: G x F | I26: G / 3 x 0.0569 (COP3) | J26: (H+I) / 1000
A27: Siège social | B27: 0 | C27: 0.08 | D27: 800 | E27: C07 | F27: =IFERROR(VLOOKUP(E27,'02_FACTEURS_ÉMISSION2'!$A:$C,3,0),0.025) | G27: =B27*C27*D27 | H27: =G27*F27 | I27: =G27/3*0.0569 | J27: =(H27+I27)/1000
A28: Site production | B28: 0 | C28: 0.08 | D28: 800 | E28: C07 | F28: =IFERROR(VLOOKUP(E28,'02_FACTEURS_ÉMISSION2'!$A:$C,3,0),0.025) | G28: =B28*C28*D28 | H28: =G28*F28 | I28: =G28/3*0.0569 | J28: =(H28+I28)/1000
A29: Salle serveurs DC | B29: 0 | C29: 0.08 | D29: 800 | E29: C07 | F29: =IFERROR(VLOOKUP(E29,'02_FACTEURS_ÉMISSION2'!$A:$C,3,0),0.025) | G29: =B29*C29*D29 | H29: =G29*F29 | I29: =G29/3*0.0569 | J29: =(H29+I29)/1000
A30: Agence régionale 1 | B30: 0 | C30: 0.08 | D30: 800 | E30: C07 | F30: =IFERROR(VLOOKUP(E30,'02_FACTEURS_ÉMISSION2'!$A:$C,3,0),0.025) | G30: =B30*C30*D30 | H30: =G30*F30 | I30: =G30/3*0.0569 | J30: =(H30+I30)/1000
A31: TOTAL CLIMATISATION | G31: =SUM(G27:G30) | H31: =SUM(H27:H30) | I31: =SUM(I27:I30) | J31: =SUM(J27:J30)
A33: D — EAU (Scope 3 Cat. 1)
A34: Site / Bâtiment | B34: Eau froide (m3/an) | C34: Eau chaude san. (m3/an) | D34: Facteur production (kgCO2e/m3) | E34: Facteur traitement (kgCO2e/m3) | F34: Facteur ECS (/litre) | G34: CO2 eau froide (kgCO2e) | H34: CO2 eau chaude (kgCO2e) | I34: CO2 total (tCO2e)
B35: relevé compteur | C35: m3 ECS/an | D35: FE W01 = 0.132 | E35: FE W02 = 0.344 | F35: FE W03 = 0.0036 | G35: B x (D + E) | H35: C x 1000 x F | I35: (G + H) / 1000
A36: Siège social | B36: 0 | C36: 0 | D36: =IFERROR(VLOOKUP("W01",'02_FACTEURS_ÉMISSION2'!$A:$C,3,0),0.132) | E36: =IFERROR(VLOOKUP("W02",'02_FACTEURS_ÉMISSION2'!$A:$C,3,0),0.344) | F36: =IFERROR(VLOOKUP("W03",'02_FACTEURS_ÉMISSION2'!$A:$C,3,0),0.0036) | G36: =B36*(D36+E36) | H36: =C36*1000*F36 | I36: =(G36+H36)/1000
A37: Site production | B37: 0 | C37: 0 | D37: =IFERROR(VLOOKUP("W01",'02_FACTEURS_ÉMISSION2'!$A:$C,3,0),0.132) | E37: =IFERROR(VLOOKUP("W02",'02_FACTEURS_ÉMISSION2'!$A:$C,3,0),0.344) | F37: =IFERROR(VLOOKUP("W03",'02_FACTEURS_ÉMISSION2'!$A:$C,3,0),0.0036) | G37: =B37*(D37+E37) | H37: =C37*1000*F37 | I37: =(G37+H37)/1000
A38: Entrepôt / Logistique | B38: 0 | C38: 0 | D38: =IFERROR(VLOOKUP("W01",'02_FACTEURS_ÉMISSION2'!$A:$C,3,0),0.132) | E38: =IFERROR(VLOOKUP("W02",'02_FACTEURS_ÉMISSION2'!$A:$C,3,0),0.344) | F38: =IFERROR(VLOOKUP("W03",'02_FACTEURS_ÉMISSION2'!$A:$C,3,0),0.0036) | G38: =B38*(D38+E38) | H38: =C38*1000*F38 | I38: =(G38+H38)/1000
A39: TOTAL EAU | B39: =SUM(B36:B38) | G39: =SUM(G36:G38) | H39: =SUM(H36:H38) | I39: =SUM(I36:I38)
A41: SYNTHÈSE — TOTAL ÉNERGIE & BÂTIMENTS
A42: Poste | B42: CO2 (kgCO2e) | C42: CO2 (tCO2e) | D42: Scope GES | E42: % du total énergie
A43: Électricité | B43: =I12 | C43: =J12 | D43: Scope 2 | E43: =IFERROR(C43/C47,0)
A44: Chauffage / Combustibles | B44: =G22 | C44: =H22 | D44: Scope 1 | E44: =IFERROR(C44/C47,0)
A45: Climatisation | B45: =SUM(H31,I31) | C45: =J31 | D45: Scope 1 + 2 | E45: =IFERROR(C45/C47,0)
A46: Eau | B46: =SUM(G39,H39) | C46: =I39 | D46: Scope 3 Cat.1 | E46: =IFERROR(C46/C47,0)
A47: TOTAL ENERGIE & BATIMENTS | B47: =SUM(B43:B46) | C47: =SUM(C43:C46)
A49: E — SCOPE 2 MARKET-BASED (double reporting obligatoire CSRD/ESRS E1-6)
A50: Site / Usage | B50: Pays | C50: kWh | D50: GO/PPA? (O/N) | E50: FE LB (kgCO2e/kWh) | F50: CO2 LB (kgCO2e) | G50: FE MB (kgCO2e/kWh) | H50: CO2 MB (kgCO2e) | I50: Ecart LB-MB (kgCO2e) | J50: Ecart (%)
A51: Bureaux principaux | B51: France | C51: 0 | D51: Non | E51: =IFERROR(VLOOKUP("E01",'02_FACTEURS_ÉMISSION2'!A:C,3,0),0.0569) | F51: =C51*E51 | G51: =IF(D51="Oui",0.006,IF(B51="France",0.06,IF(B51="Allemagne",0.576,0.396))) | H51: =C51*G51 | I51: =F51-H51 | J51: =IFERROR(I51/F51,0)
A52: Datacenter interne | B52: France | C52: 0 | D52: Non | E52: =IFERROR(VLOOKUP("E01",'02_FACTEURS_ÉMISSION2'!A:C,3,0),0.0569) | F52: =C52*E52 | G52: =IF(D52="Oui",0.006,IF(B52="France",0.06,IF(B52="Allemagne",0.576,0.396))) | H52: =C52*G52 | I52: =F52-H52 | J52: =IFERROR(I52/F52,0)
A53: Site Allemagne | B53: Allemagne | C53: 0 | D53: Oui | E53: =IFERROR(VLOOKUP("E02",'02_FACTEURS_ÉMISSION2'!A:C,3,0),0.385) | F53: =C53*E53 | G53: =IF(D53="Oui",0.006,IF(B53="France",0.06,IF(B53="Allemagne",0.576,0.396))) | H53: =C53*G53 | I53: =F53-H53 | J53: =IFERROR(I53/F53,0)
A54: TOTAL SCOPE 2 | F54: =SUM(F51:F53) | H54: =SUM(H51:H53) | I54: =F54-H54 | J54: =IFERROR(I54/F54,0)
A55: ESRS E1-6 : reporter LB ET MB. En l'absence de GO/PPA, utiliser le mix residuel (AIB 2023).
A57: F -- EMISSIONS FUGITIVES / FRIGORIGENES (Scope 1 -- 1D)
A58: Equipement | B58: Fluide frigorigene | C58: ID FE | D58: Charge initiale (kg) | E58: Taux fuite (%/an) | F58: Quantite fuitee (kg) | G58: PRG (kgCO2e/kg) | H58: CO2 (kgCO2e) | I58: CO2 (tCO2e)
A59: Climatisation bureaux | B59: R-410A | C59: FG01 | D59: 8 | E59: 0.05 | F59: =D59*E59 | G59: =IFERROR(VLOOKUP(C59,'02_FACTEURS_ÉMISSION2'!A:C,3,0),0) | H59: =F59*G59 | I59: =H59/1000
A60: Climatisation salle serveur | B60: R-410A | C60: FG01 | D60: 12 | E60: 0.06 | F60: =D60*E60 | G60: =IFERROR(VLOOKUP(C60,'02_FACTEURS_ÉMISSION2'!A:C,3,0),0) | H60: =F60*G60 | I60: =H60/1000
A61: Pompe a chaleur | B61: R-32 | C61: FG03 | D61: 5 | E61: 0.03 | F61: =D61*E61 | G61: =IFERROR(VLOOKUP(C61,'02_FACTEURS_ÉMISSION2'!A:C,3,0),0) | H61: =F61*G61 | I61: =H61/1000
A62: Clim vehicules (flotte) | B62: R-134a | C62: FG02 | D62: 1.5 | E62: 0.15 | F62: =D62*E62 | G62: =IFERROR(VLOOKUP(C62,'02_FACTEURS_ÉMISSION2'!A:C,3,0),0) | H62: =F62*G62 | I62: =H62/1000
A63: Froid alimentaire | B63: R-404A | C63: FG07 | D63: 3 | E63: 0.08 | F63: =D63*E63 | G63: =IFERROR(VLOOKUP(C63,'02_FACTEURS_ÉMISSION2'!A:C,3,0),0) | H63: =F63*G63 | I63: =H63/1000
A64: TOTAL FRIGORIGENES (Scope 1 1D) | H64: =SUM(H59:H63) | I64: =SUM(I59:I63)
A65: Scope 1 1D. Taux fuite moyen : 3-15%/an selon equipement. Source PRG : GIEC AR6.
A67: G -- VENTILATION ENR / NON-ENR (ESRS E1-5 paragraphes 37-38)
A68: Poste | B68: Quantite | C68: Unite | D68: MWh | E68: Type (ENR/Non-ENR)
A69: NON-RENOUVELABLE
A70: Gaz naturel | B70: 0 | C70: kWh | D70: =B70/1000 | E70: Non-ENR
A71: Fioul domestique | B71: 0 | C71: litres | D71: =B71*10.08/1000 | E71: Non-ENR
A72: Electricite reseau (hors GO) | B72: 0 | C72: kWh | D72: =B72/1000 | E72: Non-ENR
A73: TOTAL NON-ENR | D73: =SUM(D70:D72)
A74: RENOUVELABLE
A75: Electricite GO/PPA (certifiee) | B75: 0 | C75: kWh | D75: =B75/1000 | E75: ENR
A76: Autoproduction solaire PV | B76: 0 | C76: kWh | D76: =B76/1000 | E76: ENR
A77: Granules bois / biomasse | B77: 0 | C77: kWh | D77: =B77/1000 | E77: ENR
A78: TOTAL ENR | D78: =SUM(D75:D77)
A80: TOTAL CONSOMMATION ENERGIE (MWh) | D80: =D73+D78
A81: Part ENR (%) | D81: =IFERROR(D78/D80,0)
A82: Intensite energetique (MWh/M EUR CA) | D82: =IFERROR(D80/('01_PARAMÈTRES2'!B20/1000000),0)
A83: ESRS E1-5 par. 37-38 : ventilation obligatoire ENR / non-ENR en MWh. Inclure auto-production.

Sheet 04_TRANSPORT2
A1: TRANSPORT — Domicile-Travail, Déplacements Professionnels, Flotte Véhicules | N1: 🏠 Sommaire | O1: 📄 Couverture
A2: Scope 3 Cat.7 : domicile-travail. Scope 3 Cat.6 : déplacements pro. Scope 1 : flotte. Sources : Base Carbone ADEME 2024 / DGAC.
A3: A — DOMICILE-TRAVAIL (Scope 3 Cat. 7)
A4: Mode de transport (ID FE) | B4: Nb employés | C4: Distance A/R (km) | D4: Jours ouvrés/an | E4: Facteur (kgCO2e/km) | F4: Km totaux/an | G4: CO2 (kgCO2e) | H4: CO2/employé (kgCO2e) | I4: CO2 (tCO2e)
A5: ex: T01 Voiture therm. | B5: nb salariés ce mode | C5: trajet A/R quotidien | D5: Paramètres!jours | E5: VLOOKUP(A;FE) | F5: B x C x D | G5: F x E | H5: G / B | I5: G / 1000
A6: T01 | B6: 20 | C6: 30 | D6: =IFERROR('01_PARAMÈTRES2'!B15,220) | E6: =IFERROR(VLOOKUP(A6,'02_FACTEURS_ÉMISSION2'!$A:$C,3,0),0) | F6: =B6*C6*D6 | G6: =F6*E6 | H6: =IFERROR(G6/B6,0) | I6: =G6/1000
A7: T05 | B7: 5 | C7: 40 | D7: =IFERROR('01_PARAMÈTRES2'!B15,220) | E7: =IFERROR(VLOOKUP(A7,'02_FACTEURS_ÉMISSION2'!$A:$C,3,0),0) | F7: =B7*C7*D7 | G7: =F7*E7 | H7: =IFERROR(G7/B7,0) | I7: =G7/1000
A8: T11 | B8: 15 | C8: 20 | D8: =IFERROR('01_PARAMÈTRES2'!B15,220) | E8: =IFERROR(VLOOKUP(A8,'02_FACTEURS_ÉMISSION2'!$A:$C,3,0),0) | F8: =B8*C8*D8 | G8: =F8*E8 | H8: =IFERROR(G8/B8,0) | I8: =G8/1000
A9: T17 | B9: 8 | C9: 5 | D9: =IFERROR('01_PARAMÈTRES2'!B15,220) | E9: =IFERROR(VLOOKUP(A9,'02_FACTEURS_ÉMISSION2'!$A:$C,3,0),0) | F9: =B9*C9*D9 | G9: =F9*E9 | H9: =IFERROR(G9/B9,0) | I9: =G9/1000
A10: T07 | B10: 2 | C10: 80 | D10: =IFERROR('01_PARAMÈTRES2'!B15,220) | E10: =IFERROR(VLOOKUP(A10,'02_FACTEURS_ÉMISSION2'!$A:$C,3,0),0) | F10: =B10*C10*D10 | G10: =F10*E10 | H10: =IFERROR(G10/B10,0) | I10: =G10/1000
A11: T01 | B11: 0 | C11: 0 | D11: =IFERROR('01_PARAMÈTRES2'!B15,220) | E11: =IFERROR(VLOOKUP(A11,'02_FACTEURS_ÉMISSION2'!$A:$C,3,0),0) | F11: =B11*C11*D11 | G11: =F11*E11 | H11: =IFERROR(G11/B11,0) | I11: =G11/1000
A12: T01 | B12: 0 | C12: 0 | D12: =IFERROR('01_PARAMÈTRES2'!B15,220) | E12: =IFERROR(VLOOKUP(A12,'02_FACTEURS_ÉMISSION2'!$A:$C,3,0),0) | F12: =B12*C12*D12 | G12: =F12*E12 | H12: =IFERROR(G12/B12,0) | I12: =G12/1000
A13: T01 | B13: 0 | C13: 0 | D13: =IFERROR('01_PARAMÈTRES2'!B15,220) | E13: =IFERROR(VLOOKUP(A13,'02_FACTEURS_ÉMISSION2'!$A:$C,3,0),0) | F13: =B13*C13*D13 | G13: =F13*E13 | H13: =IFERROR(G13/B13,0) | I13: =G13/1000
A14: TOTAL DOMICILE-TRAVAIL | B14: =SUM(B6:B13) | F14: =SUM(F6:F13) | G14: =SUM(G6:G13) | H14: =IFERROR(G14/B14,0) | I14: =SUM(I6:I13)
A16: B — DÉPLACEMENTS PROFESSIONNELS (Scope 3 Cat. 6)
A17: Description trajet | B17: Mode transport (ID FE) | C17: Nb trajets/an | D17: Distance A/R (km) | E17: Nb passagers | F17: Facteur (kgCO2e/km) | G17: Km totaux | H17: CO2 brut (kgCO2e) | I17: CO2 ajusté (tCO2e)
A18: ex: Paris-Lyon client X | B18: ex: T13 Avion CC | C18: nb voyages A/R/an | D18: km A/R total | E18: 1 si seul; >1 covoit. | F18: VLOOKUP(B;FE) | G18: C x D | H18: G x F | I18: H / E / 1000
A19: Paris — Lyon (TGV) | B19: T07 | C19: 24 | D19: 900 | E19: 1 | F19: =IFERROR(VLOOKUP(B19,'02_FACTEURS_ÉMISSION2'!$A:$C,3,0),0) | G19: =C19*D19 | H19: =G19*F19 | I19: =IFERROR(H19/E19/1000,0)
A20: Paris — Londres (Avion CC) | B20: T13 | C20: 8 | D20: 700 | E20: 1 | F20: =IFERROR(VLOOKUP(B20,'02_FACTEURS_ÉMISSION2'!$A:$C,3,0),0) | G20: =C20*D20 | H20: =G20*F20 | I20: =IFERROR(H20/E20/1000,0)
A21: Paris — New York (Avion LC) | B21: T15 | C21: 2 | D21: 11400 | E21: 1 | F21: =IFERROR(VLOOKUP(B21,'02_FACTEURS_ÉMISSION2'!$A:$C,3,0),0) | G21: =C21*D21 | H21: =G21*F21 | I21: =IFERROR(H21/E21/1000,0)
A22: Client région (Voiture) | B22: T01 | C22: 40 | D22: 300 | E22: 1 | F22: =IFERROR(VLOOKUP(B22,'02_FACTEURS_ÉMISSION2'!$A:$C,3,0),0) | G22: =C22*D22 | H22: =G22*F22 | I22: =IFERROR(H22/E22/1000,0)
A23: Salon professionnel (Avion MC) | B23: T14 | C23: 4 | D23: 3000 | E23: 1 | F23: =IFERROR(VLOOKUP(B23,'02_FACTEURS_ÉMISSION2'!$A:$C,3,0),0) | G23: =C23*D23 | H23: =G23*F23 | I23: =IFERROR(H23/E23/1000,0)
B24: T01 | C24: 0 | D24: 0 | E24: 1 | F24: =IFERROR(VLOOKUP(B24,'02_FACTEURS_ÉMISSION2'!$A:$C,3,0),0) | G24: =C24*D24 | H24: =G24*F24 | I24: =IFERROR(H24/E24/1000,0)
B25: T01 | C25: 0 | D25: 0 | E25: 1 | F25: =IFERROR(VLOOKUP(B25,'02_FACTEURS_ÉMISSION2'!$A:$C,3,0),0) | G25: =C25*D25 | H25: =G25*F25 | I25: =IFERROR(H25/E25/1000,0)
B26: T01 | C26: 0 | D26: 0 | E26: 1 | F26: =IFERROR(VLOOKUP(B26,'02_FACTEURS_ÉMISSION2'!$A:$C,3,0),0) | G26: =C26*D26 | H26: =G26*F26 | I26: =IFERROR(H26/E26/1000,0)
B27: T01 | C27: 0 | D27: 0 | E27: 1 | F27: =IFERROR(VLOOKUP(B27,'02_FACTEURS_ÉMISSION2'!$A:$C,3,0),0) | G27: =C27*D27 | H27: =G27*F27 | I27: =IFERROR(H27/E27/1000,0)
B28: T01 | C28: 0 | D28: 0 | E28: 1 | F28: =IFERROR(VLOOKUP(B28,'02_FACTEURS_ÉMISSION2'!$A:$C,3,0),0) | G28: =C28*D28 | H28: =G28*F28 | I28: =IFERROR(H28/E28/1000,0)
A29: TOTAL DÉPLACEMENTS PRO | G29: =SUM(G19:G28) | H29: =SUM(H19:H28) | I29: =SUM(I19:I28)
A31: C — FLOTTE DE VÉHICULES SOCIÉTÉ (Scope 1)
A32: ID véhicule / Immat. | B32: Type carburant | C32: Consommation réelle | D32: Unité conso | E32: Km parcourus/an | F32: Facteur carburant (kgCO2e/u) | G32: Litres ou kWh/an | H32: CO2 (kgCO2e) | I32: CO2 (tCO2e)
A33: Immatriculation / ID | B33: Diesel/Essence/Elec | C33: L/100km ou kWh/100km | D33: L/100 ou kWh/100 | E33: relevé compteur | F33: 2.67 diesel, 2.31 ess, mix elec | G33: E x C / 100 | H33: G x F | I33: H / 1000
A34: VH-001 | B34: Diesel | C34: 6.5 | D34: L/100km | E34: 0 | F34: 2.67 | G34: =E34*C34/100 | H34: =G34*F34 | I34: =H34/1000
A35: VH-002 | B35: Diesel | C35: 6.5 | D35: L/100km | E35: 0 | F35: 2.67 | G35: =E35*C35/100 | H35: =G35*F35 | I35: =H35/1000
A36: VH-003 | B36: Essence | C36: 7.5 | D36: L/100km | E36: 0 | F36: 2.31 | G36: =E36*C36/100 | H36: =G36*F36 | I36: =H36/1000
A37: VH-004 | B37: Hybride | C37: 4.5 | D37: L/100km | E37: 0 | F37: 2.31 | G37: =E37*C37/100 | H37: =G37*F37 | I37: =H37/1000
A38: VH-005 | B38: Électrique | C38: 18 | D38: kWh/100km | E38: 0 | F38: 0.0569 | G38: =E38*C38/100 | H38: =G38*F38 | I38: =H38/1000
A39: VH-006 | B39: Diesel | C39: 6.5 | D39: L/100km | E39: 0 | F39: 2.67 | G39: =E39*C39/100 | H39: =G39*F39 | I39: =H39/1000
A40: VH-007 | B40: Diesel | C40: 6.5 | D40: L/100km | E40: 0 | F40: 2.67 | G40: =E40*C40/100 | H40: =G40*F40 | I40: =H40/1000
A41: TOTAL FLOTTE VÉHICULES | G41: =SUM(G34:G40) | H41: =SUM(H34:H40) | I41: =SUM(I34:I40)
A43: SYNTHÈSE — TOTAL TRANSPORT
A44: Poste | B44: CO2 (kgCO2e) | C44: CO2 (tCO2e) | D44: Scope GES | E44: % du total transport
A45: Domicile-Travail | B45: =G14 | C45: =I14 | D45: Scope 3 Cat.7 | E45: =IFERROR(C45/C49,0)
A46: Déplacements pro | B46: =H29 | C46: =I29 | D46: Scope 3 Cat.6 | E46: =IFERROR(C46/C49,0)
A47: Flotte véhicules | B47: =H41 | C47: =I41 | D47: Scope 1 | E47: =IFERROR(C47/C49,0)
A49: TOTAL TRANSPORT | B49: =SUM(B45:B47) | C49: =SUM(C45:C47)

Sheet 05_RESTAURATION
A1: RESTAURATION D'ENTREPRISE — Repas, Café & Boissons | N1: 🏠 Sommaire | O1: 📄 Couverture
A2: Scope 3 Cat.1. Formule : Nb_repas_type x Facteur_type + Nb_cafés x 0.058. Sources : Ecoinvent 3.10, Base Carbone ADEME 2024, études LCA café.
A3: A — RÉPARTITION DES REPAS (Scope 3 Cat. 1)
A4: Type de repas (ID FE) | B4: % repas ce type | C4: Facteur (kgCO2e/repas) | D4: Nb employés | E4: Jours ouvres/an | F4: Total repas ce type | G4: CO2 (kgCO2e) | H4: CO2 (tCO2e) | I4: CO2/employé/an (kg)
A5: ex: A01 Végétalien | B5: enquête ou estim. | C5: VLOOKUP(A;FE) | D5: Paramètres!B11 | E5: Paramètres!B30 | F5: D x E x B | G5: F x C | H5: G / 1000 | I5: G / D
A6: A01 — Végétalien | B6: 0.05 | C6: =IFERROR(VLOOKUP(LEFT(A6,3),'02_FACTEURS_ÉMISSION2'!$A:$C,3,0),0) | D6: =IFERROR('01_PARAMÈTRES2'!B12,50) | E6: =IFERROR('01_PARAMÈTRES2'!B15,220) | F6: =D6*E6*B6 | G6: =F6*C6 | H6: =G6/1000 | I6: =IFERROR(G6/D6,0)
A7: A02 — Végétarien | B7: 0.15 | C7: =IFERROR(VLOOKUP(LEFT(A7,3),'02_FACTEURS_ÉMISSION2'!$A:$C,3,0),0) | D7: =IFERROR('01_PARAMÈTRES2'!B12,50) | E7: =IFERROR('01_PARAMÈTRES2'!B15,220) | F7: =D7*E7*B7 | G7: =F7*C7 | H7: =G7/1000 | I7: =IFERROR(G7/D7,0)
A8: A05 — Viande blanche | B8: 0.35 | C8: =IFERROR(VLOOKUP(LEFT(A8,3),'02_FACTEURS_ÉMISSION2'!$A:$C,3,0),0) | D8: =IFERROR('01_PARAMÈTRES2'!B12,50) | E8: =IFERROR('01_PARAMÈTRES2'!B15,220) | F8: =D8*E8*B8 | G8: =F8*C8 | H8: =G8/1000 | I8: =IFERROR(G8/D8,0)
A9: A04 — Viande rouge | B9: 0.25 | C9: =IFERROR(VLOOKUP(LEFT(A9,3),'02_FACTEURS_ÉMISSION2'!$A:$C,3,0),0) | D9: =IFERROR('01_PARAMÈTRES2'!B12,50) | E9: =IFERROR('01_PARAMÈTRES2'!B15,220) | F9: =D9*E9*B9 | G9: =F9*C9 | H9: =G9/1000 | I9: =IFERROR(G9/D9,0)
A10: A06 — Poisson | B10: 0.2 | C10: =IFERROR(VLOOKUP(LEFT(A10,3),'02_FACTEURS_ÉMISSION2'!$A:$C,3,0),0) | D10: =IFERROR('01_PARAMÈTRES2'!B12,50) | E10: =IFERROR('01_PARAMÈTRES2'!B15,220) | F10: =D10*E10*B10 | G10: =F10*C10 | H10: =G10/1000 | I10: =IFERROR(G10/D10,0)
