Workbook

Sheet Dashboard
A1: 🏛️ NEURAL — DASHBOARD EXÉCUTIF INVENTAIRE LUXE
A2: Mise à jour automatique - Date: 25/03/2026
A4: 💰 INDICATEURS FINANCIERS CLÉS
A5: KPI | B5: Valeur | C5: Évolution
A6: 💰 Stock Brut (valeur comptable) | B6: =Inventaire!H12 -> 3581600 | C6: Référence
A7: 📊 Stock Immobilisé (>6 mois) | B7: =SUMIFS(Inventaire!H5:H11,Inventaire!M5:M11,">180") -> 3581600 | C7: =B7/B6 -> 1
A8: 🔄 Rotation Moyenne (jours) | B8: =AVERAGE(Inventaire!M5:M11) -> 763.71429 | C8: Tendance ↗
A9: ⚠️ Articles en Surstock | B9: =COUNTIF(Inventaire!Z5:Z11,"⚠️*") -> 5 | C9: Alerte
A10: 💎 Valeur MP | B10: =SUMIF(Inventaire!D5:D11,"MP",Inventaire!H5:H11) -> 2206500 | C10: =B10/B6 -> 0.61606545
A11: ⚙️ Valeur EC | B11: =SUMIF(Inventaire!D5:D11,"EC",Inventaire!H5:H11) -> 874000 | C11: =B11/B6 -> 0.24402502
A12: ✨ Valeur PF | B12: =SUMIF(Inventaire!D5:D11,"PF",Inventaire!H5:H11) -> 501100 | C12: =B12/B6 -> 0.13990954
A14: 📊 RÉPARTITION PATRIMOINE
A15: Catégorie | B15: Valeur | C15: % Total | D15: Qté | E15: % Qté
A16: 💎 Matières 1ères | B16: =SUMIF(Inventaire!D5:D11,"MP",Inventaire!H5:H11) -> 2206500 | C16: =B16/Inventaire!$H$12 -> 0.61606545 | D16: =SUMIF(Inventaire!D5:D11,"MP",Inventaire!F5:F11) -> 165 | E16: =D16/SUM(D$16:D$18) -> 0.41984733
A17: ⚙️ En-Cours Prod. | B17: =SUMIF(Inventaire!D5:D11,"EC",Inventaire!H5:H11) -> 874000 | C17: =B17/Inventaire!$H$12 -> 0.24402502 | D17: =SUMIF(Inventaire!D5:D11,"EC",Inventaire!F5:F11) -> 212 | E17: =D17/SUM(D$16:D$18) -> 0.5394402
A18: ✨ Produits Finis | B18: =SUMIF(Inventaire!D5:D11,"PF",Inventaire!H5:H11) -> 501100 | C18: =B18/Inventaire!$H$12 -> 0.13990954 | D18: =SUMIF(Inventaire!D5:D11,"PF",Inventaire!F5:F11) -> 16 | E18: =D18/SUM(D$16:D$18) -> 0.040712468
A19: TOTAL | B19: =SUM(B16:B18) -> 3581600 | C19: =SUM(C16:C18) -> 1 | D19: =SUM(D16:D18) -> 393 | E19: =SUM(E16:E18) -> 1
A21: 🏛️ PERFORMANCE PAR MAISON
A22: Maison | B22: Valeur | C22: % Mix | D22: Nb Réf. | E22: Val. Moy.
A23: 🏛️ Hermès | B23: =SUMIF(Inventaire!C5:C11,"Hermès",Inventaire!H5:H11) -> 416100 | C23: =B23/Inventaire!$H$12 -> 0.11617713 | D23: =COUNTIF(Inventaire!C5:C11,"Hermès") -> 2 | E23: =B23/D23 -> 208050
A24: 🏛️ Patek Philippe | B24: =SUMIF(Inventaire!C5:C11,"Patek Philippe",Inventaire!H5:H11) -> 596500 | C24: =B24/Inventaire!$H$12 -> 0.16654568 | D24: =COUNTIF(Inventaire!C5:C11,"Patek Philippe") -> 2 | E24: =B24/D24 -> 298250
A25: 🏛️ Cartier | B25: =SUMIF(Inventaire!C5:C11,"Cartier",Inventaire!H5:H11) -> 2199000 | C25: =B25/Inventaire!$H$12 -> 0.61397141 | D25: =COUNTIF(Inventaire!C5:C11,"Cartier") -> 2 | E25: =B25/D25 -> 1099500
A26: 🏛️ Chanel | B26: =SUMIF(Inventaire!C5:C11,"Chanel",Inventaire!H5:H11) -> 370000 | C26: =B26/Inventaire!$H$12 -> 0.10330579 | D26: =COUNTIF(Inventaire!C5:C11,"Chanel") -> 1 | E26: =B26/D26 -> 370000
A27: TOTAL | B27: =SUM(B23:B26) -> 3581600 | C27: =SUM(C23:C26) -> 1 | D27: =SUM(D23:D26) -> 7 | E27: =B27/D27 -> 511657.14

Sheet Inventaire
A1: 🏛️ NEURAL — Gestion Inventaire Luxe v3.0
A2: Inventaire physique au 25 Mars 2026 — Enrichi avec Rotation & Prévisions
A4: Réf. | B4: Article | C4: Maison | D4: Catégorie | E4: Unité | F4: Qté | G4: Coût Unit. | H4: Coût Total | I4: Méthode | J4: Date Entrée | K4: Localisation | L4: Statut | M4: Ancienneté (j) | N4: Alerte | O4: Prix Vente Est. | P4: Coûts Achèv. | Q4: Coûts Vente | R4: Prix Public | S4: Nb Vendus 12M | T4: Qté Réservée | U4: Qté Disponible | V4: Dernière Sortie | W4: Jours sans Mvt | X4: Tx Rotation | Y4: Alerte Rupture | Z4: Risque Surstock
A5: LUX-001 | B5: Cuir Crocodile Himalaya | C5: Hermès | D5: MP | E5: m² | F5: 45 | G5: 8500 | H5: =F5*G5 -> 382500 | I5: Coût Réel | J5: 45306 | K5: Paris — Faubourg St-Honoré | L5: Actif | M5: =TODAY()-J5 -> 804 | N5: =IF(M5>270,"🟠",IF(M5>180,"🟡","✅")) -> 🟠 | O5: 12800 | P5: 0 | Q5: 640 | T5: 5 | U5: =F5-T5 -> 40 | V5: 46011 | W5: =IF(ISBLANK(V5),"N/A",TODAY()-V5) -> 99 | X5: =IF(W5="N/A",0,365/W5) -> 3.6868687 | Y5: ✅ OK | Z5: =IF(AND(M5>270,L5="Actif",D5<>"EC"),"⚠️ SURSTOCK",IF(AND(M5>180,X5<2),"⚠️ ROTATION LENTE","")) -> ⚠️ SURSTOCK
A6: LUX-002 | B6: Mouvement Tourbillon Cal.3135 | C6: Patek Philippe | D6: EC | E6: Pièce | F6: 12 | G6: 42000 | H6: =F6*G6 -> 504000 | I6: Coût Réel | J6: 45342 | K6: Genève — Plan-les-Ouates | L6: Actif | M6: =TODAY()-J6 -> 768 | N6: =IF(M6>270,"🟠",IF(M6>180,"🟡","✅")) -> 🟠 | O6: 85000 | P6: 15000 | Q6: 4250 | T6: 2 | U6: =F6-T6 -> 10 | V6: 46032 | W6: =IF(ISBLANK(V6),"N/A",TODAY()-V6) -> 78 | X6: =IF(W6="N/A",0,365/W6) -> 4.6794872 | Y6: ✅ OK | Z6: =IF(AND(M6>270,L6="Actif",D6<>"EC"),"⚠️ SURSTOCK",IF(AND(M6>180,X6<2),"⚠️ ROTATION LENTE",""))
A7: LUX-003 | B7: Sac Birkin 30 Togo | C7: Hermès | D7: PF | E7: Unité | F7: 8 | G7: 4200 | H7: =F7*G7 -> 33600 | I7: Coût Complet | J7: 45361 | K7: Paris — Faubourg St-Honoré | L7: Actif | M7: =TODAY()-J7 -> 749 | N7: =IF(M7>270,"🟠",IF(M7>180,"🟡","✅")) -> 🟠 | O7: 9800 | P7: 0 | Q7: 490 | R7: 9800 | S7: 110 | T7: 1 | U7: =F7-T7 -> 7 | V7: 46096 | W7: =IF(ISBLANK(V7),"N/A",TODAY()-V7) -> 14 | X7: =IF(W7="N/A",0,365/W7) -> 26.071429 | Y7: =IF(U7=0,"🔴 RUPTURE",IF(U7<(S7/365*30),"🟠 <1 MOIS",IF(U7<(S7/365*60),"🟡 <2 MOIS","✅ OK"))) -> 🟠 <1 MOIS | Z7: =IF(AND(M7>270,L7="Actif",D7<>"EC"),"⚠️ SURSTOCK",IF(AND(M7>180,X7<2),"⚠️ ROTATION LENTE","")) -> ⚠️ SURSTOCK
A8: LUX-004 | B8: Diamants VVS1 D-Color (1ct) | C8: Cartier | D8: MP | E8: Carat | F8: 120 | G8: 15200 | H8: =F8*G8 -> 1824000 | I8: CUMP | J8: 45319 | K8: Paris — Place Vendôme | L8: Actif | M8: =TODAY()-J8 -> 791 | N8: =IF(M8>270,"🟠",IF(M8>180,"🟡","✅")) -> 🟠 | O8: 28500 | P8: 2500 | Q8: 1425 | T8: 10 | U8: =F8-T8 -> 110 | V8: 46058 | W8: =IF(ISBLANK(V8),"N/A",TODAY()-V8) -> 52 | X8: =IF(W8="N/A",0,365/W8) -> 7.0192308 | Y8: ✅ OK | Z8: =IF(AND(M8>270,L8="Actif",D8<>"EC"),"⚠️ SURSTOCK",IF(AND(M8>180,X8<2),"⚠️ ROTATION LENTE","")) -> ⚠️ SURSTOCK
A9: LUX-005 | B9: Montre Nautilus 5711/1A | C9: Patek Philippe | D9: PF | E9: Unité | F9: 5 | G9: 18500 | H9: =F9*G9 -> 92500 | I9: Coût Complet | J9: 45387 | K9: Genève — Rue du Rhône | L9: Actif | M9: =TODAY()-J9 -> 723 | N9: =IF(M9>270,"🟠",IF(M9>180,"🟡","✅")) -> 🟠 | O9: 35000 | P9: 0 | Q9: 1750 | R9: 35000 | S9: 30 | T9: 0 | U9: =F9-T9 -> 5 | V9: 46082 | W9: =IF(ISBLANK(V9),"N/A",TODAY()-V9) -> 28 | X9: =IF(W9="N/A",0,365/W9) -> 13.035714 | Y9: =IF(U9=0,"🔴 RUPTURE",IF(U9<(S9/365*30),"🟠 <1 MOIS",IF(U9<(S9/365*60),"🟡 <2 MOIS","✅ OK"))) -> ✅ OK | Z9: =IF(AND(M9>270,L9="Actif",D9<>"EC"),"⚠️ SURSTOCK",IF(AND(M9>180,X9<2),"⚠️ ROTATION LENTE","")) -> ⚠️ SURSTOCK
A10: LUX-006 | B10: Tissu Tweed Haute Couture | C10: Chanel | D10: EC | E10: Mètre | F10: 200 | G10: 1850 | H10: =F10*G10 -> 370000 | I10: Coût Réel | J10: 45373 | K10: Paris — Rue Cambon | L10: Actif | M10: =TODAY()-J10 -> 737 | N10: =IF(M10>270,"🟠",IF(M10>180,"🟡","✅")) -> 🟠 | O10: 1600 | P10: 200 | Q10: 80 | T10: 50 | U10: =F10-T10 -> 150 | V10: 46091 | W10: =IF(ISBLANK(V10),"N/A",TODAY()-V10) -> 19 | X10: =IF(W10="N/A",0,365/W10) -> 19.210526 | Y10: ✅ OK | Z10: =IF(AND(M10>270,L10="Actif",D10<>"EC"),"⚠️ SURSTOCK",IF(AND(M10>180,X10<2),"⚠️ ROTATION LENTE",""))
A11: LUX-007 | B11: Collier Haute Joaillerie Panthère | C11: Cartier | D11: PF | E11: Unité | F11: 3 | G11: 125000 | H11: =F11*G11 -> 375000 | I11: Coût Complet | J11: 45336 | K11: Paris — Place Vendôme | L11: Actif | M11: =TODAY()-J11 -> 774 | N11: =IF(M11>270,"🟠",IF(M11>180,"🟡","✅")) -> 🟠 | O11: 280000 | P11: 0 | Q11: 14000 | R11: 280000 | S11: 6 | T11: 1 | U11: =F11-T11 -> 2 | V11: 45976 | W11: =IF(ISBLANK(V11),"N/A",TODAY()-V11) -> 134 | X11: =IF(W11="N/A",0,365/W11) -> 2.7238806 | Y11: =IF(U11=0,"🔴 RUPTURE",IF(U11<(S11/365*30),"🟠 <1 MOIS",IF(U11<(S11/365*60),"🟡 <2 MOIS","✅ OK"))) -> ✅ OK | Z11: =IF(AND(M11>270,L11="Actif",D11<>"EC"),"⚠️ SURSTOCK",IF(AND(M11>180,X11<2),"⚠️ ROTATION LENTE","")) -> ⚠️ SURSTOCK
A12: TOTAL | B12: 7 Articles Patrimoniaux | H12: =SUM(H5:H11) -> 3581600
A14: 📊 INDICATEURS CLÉS DE PERFORMANCE (KPIs)
A15: KPI 1 — Valeur Totale du Stock | C15: =H12 -> 3581600
A16: KPI 2 — Valeur Matières Premières | C16: =SUMIF(D5:D11,"MP",H5:H11) -> 2206500
A17: KPI 3 — Valeur En-Cours Production | C17: =SUMIF(D5:D11,"EC",H5:H11) -> 874000
A18: KPI 4 — Valeur Produits Finis | C18: =SUMIF(D5:D11,"PF",H5:H11) -> 501100
A19: KPI 5 — Stock Immobilisé (>6 mois) | C19: =SUMIFS(H5:H11,M5:M11,">180") -> 3581600
A20: KPI 6 — Ancienneté Moyenne (jours) | C20: =AVERAGE(M5:M11) -> 763.71429
A21: KPI 7 — Valeur Moyenne par Article | C21: =H12/7 -> 511657.14
A22: KPI 8 — Rotation Stock Moyenne | C22: =AVERAGE(X5:X11) -> 10.918162
A23: KPI 9 — Articles en Surstock/Rotation Lente | C23: =COUNTIF(Z5:Z11,"⚠️*") -> 5
A24: KPI 10 — Quantité Totale Disponible | C24: =SUM(U5:U11) -> 324

Sheet Analyse_Risques
A1: ⚠️ NEURAL — CARTOGRAPHIE DES RISQUES INVENTAIRE
A2: Analyse multidimensionnelle - Mise à jour: 25/03/2026
A4: 🚨 TABLEAU DE BORD RISQUES
A5: Type Risque | B5: Niveau | C5: Impact | D5: Valeur | E5: Action
A6: 🔴 CONCENTRATION (Top 3 > 50%) | B6: =SUMPRODUCT(LARGE(Inventaire!H5:H11,{1;2;3}))/Inventaire!H12 -> 0.75678468 | C6: ★★★★☆ Critique | D6: =SUMPRODUCT(LARGE(Inventaire!H5:H11,{1;2;3})) -> 2710500 | E6: Urgent
A7: 🟠 OBSOLESCENCE (Stock >365j) | B7: =COUNTIFS(Inventaire!M5:M11,">365")/COUNTA(Inventaire!A5:A11) -> 1 | C7: ★★★☆☆ Élevé | D7: =SUMIFS(Inventaire!H5:H11,Inventaire!M5:M11,">365") -> 3581600 | E7: Court T.
A8: 🟡 DÉPRÉCIATION (NRV < Coût) | B8: =COUNTIF(Test_NRV_IAS2!I5:I11,">0")/7 -> 0.14285714 | C8: ★★☆☆☆ Modéré | D8: =Test_NRV_IAS2!J12 -> 106000 | E8: Surveill.
A9: 🟢 LIQUIDITÉ (Rotation stock) | B9: =AVERAGE(Inventaire!M5:M11)/365 -> 2.0923679 | C9: ★☆☆☆☆ Faible | D9: N/A | E9: OK
A10: 🔵 RUPTURE (Stock = 0) | B10: =COUNTIF(Inventaire!F5:F11,0)/7 -> 0 | C10: ★☆☆☆☆ Nul | D10: =SUMIF(Inventaire!F5:F11,0,Inventaire!H5:H11) -> 0 | E10: OK
A12: 📊 ANALYSE DE CONCENTRATION - Principe de Pareto 80/20
A13: Rang | B13: Article | C13: Valeur | D13: % Total | E13: % Cumul
A14: 1 | B14: =INDEX(Inventaire!B5:B11,MATCH(LARGE(Inventaire!H5:H11,1),Inventaire!H5:H11,0)) -> Diamants VVS1 D-Color (1ct) | C14: =LARGE(Inventaire!H5:H11,1) -> 1824000 | D14: =C14/Inventaire!$H$12 -> 0.5092696 | E14: =SUM($D$14:D14) -> 0.5092696
A15: 2 | B15: =INDEX(Inventaire!B5:B11,MATCH(LARGE(Inventaire!H5:H11,2),Inventaire!H5:H11,0)) -> Mouvement Tourbillon Cal.3135 | C15: =LARGE(Inventaire!H5:H11,2) -> 504000 | D15: =C15/Inventaire!$H$12 -> 0.14071923 | E15: =SUM($D$14:D15) -> 0.64998883
A16: 3 | B16: =INDEX(Inventaire!B5:B11,MATCH(LARGE(Inventaire!H5:H11,3),Inventaire!H5:H11,0)) -> Cuir Crocodile Himalaya | C16: =LARGE(Inventaire!H5:H11,3) -> 382500 | D16: =C16/Inventaire!$H$12 -> 0.10679585 | E16: =SUM($D$14:D16) -> 0.75678468
A17: 4 | B17: =INDEX(Inventaire!B5:B11,MATCH(LARGE(Inventaire!H5:H11,4),Inventaire!H5:H11,0)) -> Collier Haute Joaillerie Panthère | C17: =LARGE(Inventaire!H5:H11,4) -> 375000 | D17: =C17/Inventaire!$H$12 -> 0.10470181 | E17: =SUM($D$14:D17) -> 0.86148649
A18: 5 | B18: =INDEX(Inventaire!B5:B11,MATCH(LARGE(Inventaire!H5:H11,5),Inventaire!H5:H11,0)) -> Tissu Tweed Haute Couture | C18: =LARGE(Inventaire!H5:H11,5) -> 370000 | D18: =C18/Inventaire!$H$12 -> 0.10330579 | E18: =SUM($D$14:D18) -> 0.96479227
A20: 📦 ANALYSE OBSOLESCENCE - Ancienneté du stock
A21: Tranche | B21: Nb Art. | C21: Valeur | D21: % Total | E21: Provis. | F21: Action
A22: 0-90 j | B22: =COUNTIFS(Inventaire!M5:M11,"<=90") -> 0 | C22: =SUMIFS(Inventaire!H5:H11,Inventaire!M5:M11,"<=90") -> 0 | D22: =C22/Inventaire!$H$12 -> 0 | E22: =C22*0 -> 0 | F22: Aucune
A23: 91-180 j | B23: =COUNTIFS(Inventaire!M5:M11,">90",Inventaire!M5:M11,"<=180") -> 0 | C23: =SUMIFS(Inventaire!H5:H11,Inventaire!M5:M11,">90",Inventaire!M5:M11,"<=180") -> 0 | D23: =C23/Inventaire!$H$12 -> 0 | E23: =C23*0 -> 0 | F23: Aucune
A24: 181-270 j | B24: =COUNTIFS(Inventaire!M5:M11,">180",Inventaire!M5:M11,"<=270") -> 0 | C24: =SUMIFS(Inventaire!H5:H11,Inventaire!M5:M11,">180",Inventaire!M5:M11,"<=270") -> 0 | D24: =C24/Inventaire!$H$12 -> 0 | E24: =C24*0.2 -> 0 | F24: Surveill.
A25: 271-365 j | B25: =COUNTIFS(Inventaire!M5:M11,">270",Inventaire!M5:M11,"<=365") -> 0 | C25: =SUMIFS(Inventaire!H5:H11,Inventaire!M5:M11,">270",Inventaire!M5:M11,"<=365") -> 0 | D25: =C25/Inventaire!$H$12 -> 0 | E25: =C25*0.4 -> 0 | F25: Liquider
A26: >365 j | B26: =COUNTIFS(Inventaire!M5:M11,">365",Inventaire!M5:M11,">365") -> 7 | C26: =SUMIFS(Inventaire!H5:H11,Inventaire!M5:M11,">365",Inventaire!M5:M11,">365") -> 3581600 | D26: =C26/Inventaire!$H$12 -> 1 | E26: =C26*0.6 -> 2148960 | F26: URGENT
A27: TOTAL | B27: =SUM(B22:B26) -> 7 | C27: =SUM(C22:C26) -> 3581600 | D27: =SUM(D22:D26) -> 1 | E27: =SUM(E22:E26) -> 2148960

Sheet Valorisation
A1: 💰 Valorisation Stock par Catégorie
A2: Répartition détaillée du patrimoine inventaire
A4: Catégorie | B4: Valeur (€) | C4: % du Total | D4: Nb Articles
A5: Matières Premières (MP) | B5: =SUMIF(Inventaire!D5:D11,"MP",Inventaire!H5:H11) -> 2206500 | C5: =B5/Inventaire!$H$12 -> 0.61606545 | D5: =COUNTIF(Inventaire!D5:D11,"MP") -> 2
A6: En-Cours de Production (EC) | B6: =SUMIF(Inventaire!D5:D11,"EC",Inventaire!H5:H11) -> 874000 | C6: =B6/Inventaire!$H$12 -> 0.24402502 | D6: =COUNTIF(Inventaire!D5:D11,"EC") -> 2
A7: Produits Finis (PF) | B7: =SUMIF(Inventaire!D5:D11,"PF",Inventaire!H5:H11) -> 501100 | C7: =B7/Inventaire!$H$12 -> 0.13990954 | D7: =COUNTIF(Inventaire!D5:D11,"PF") -> 3
A8: TOTAL GÉNÉRAL | B8: =Inventaire!H12 -> 3581600 | C8: 1 | D8: 7
A10: 🏛️ Répartition par Maison de Luxe
A11: Maison | B11: Valeur (€) | C11: % du Total | D11: Nb Articles
A12: Hermès | B12: =SUMIF(Inventaire!C5:C11,"Hermès",Inventaire!H5:H11) -> 416100 | C12: =B12/Inventaire!$H$12 -> 0.11617713 | D12: =COUNTIF(Inventaire!C5:C11,"Hermès") -> 2
A13: Patek Philippe | B13: =SUMIF(Inventaire!C5:C11,"Patek Philippe",Inventaire!H5:H11) -> 596500 | C13: =B13/Inventaire!$H$12 -> 0.16654568 | D13: =COUNTIF(Inventaire!C5:C11,"Patek Philippe") -> 2
A14: Cartier | B14: =SUMIF(Inventaire!C5:C11,"Cartier",Inventaire!H5:H11) -> 2199000 | C14: =B14/Inventaire!$H$12 -> 0.61397141 | D14: =COUNTIF(Inventaire!C5:C11,"Cartier") -> 2
A15: Chanel | B15: =SUMIF(Inventaire!C5:C11,"Chanel",Inventaire!H5:H11) -> 370000 | C15: =B15/Inventaire!$H$12 -> 0.10330579 | D15: =COUNTIF(Inventaire!C5:C11,"Chanel") -> 1
A16: TOTAL GÉNÉRAL | B16: =Inventaire!H12 -> 3581600 | C16: 1 | D16: 7
A19: Classification ABC (Pareto)
A21: Classe | C21: Critère | D21: Nb Réf. | E21: % Réf. | F21: Valeur (€) | G21: % Valeur Cum
A22: A - Critique | C22: > 100 000 € / article | D22: =COUNTIF([1]Inventaire!$H$5:$H$11,">100000") -> #VALUE! | E22: =D22/7 -> #VALUE! | F22: =SUMIF(Inventaire!$H$5:$H$11,">100000") -> 3455500 | G22: =IF(E$8<>0,F22/E$8,0) -> 0
A23: B - Important | C23: 30 000 — 100 000 € | D23: =COUNTIFS([1]Inventaire!$H$5:$H$11,">=30000",[1]Inventaire!$H$5:$H$11,"<=100000") -> #VALUE! | E23: =D23/7 -> #VALUE! | F23: =SUMIFS(Inventaire!$H$5:$H$11,Inventaire!H5:H11,">=30000",Inventaire!$H$5:$H$11,"<=100000") -> 126100 | G23: =IF(E$8<>0,(F22+F23)/E$8,0) -> 0
A24: C - Courant | C24: < 30 000 € | D24: =COUNTIF([1]Inventaire!$H$5:$H$11,"<30000") -> #VALUE! | E24: =D24/7 -> #VALUE! | F24: =SUMIF(Inventaire!$H$5:$H$11,"<30000") -> 0 | G24: =IF(E$8<>0,(F22+F23+F24)/E$8,0) -> 0
A26: Contrôle | C26: Somme A+B+C = Total ? | F26: =SUM(F22:F24) -> 3581600 | G26: =IF(ABS(SUM(F22:F24)-E8)<1,"✅ OK","❌ Écart") -> ❌ Écart

Sheet Test_NRV_IAS2
A1: ⚖️ Test Net Realizable Value (NRV) — IAS 2
A2: Dépréciation selon IFRS et comparaison Coût vs Valeur Nette de Réalisation
A4: Réf. | B4: Article | C4: Catégorie | D4: Coût Comptable | E4: Prix Vente Est. | F4: Coûts Achèvement | G4: Coûts Vente | H4: NRV | I4: Écart | J4: Provision | K4: Statut
A5: =Inventaire!A5 -> LUX-001 | B5: =Inventaire!B5 -> Cuir Crocodile Himalaya | C5: =Inventaire!D5 -> MP | D5: =Inventaire!G5*Inventaire!F5 -> 382500 | E5: =Inventaire!O5*Inventaire!F5 -> 576000 | F5: =Inventaire!P5*Inventaire!F5 -> 0 | G5: =Inventaire!Q5*Inventaire!F5 -> 28800 | H5: =E5-F5-G5 -> 547200 | I5: =D5-H5 -> -164700 | J5: =MAX(0,I5) -> 0 | K5: =IF(I5>0,"🔴 Dépréciation","✅ Conforme") -> ✅ Conforme
A6: =Inventaire!A6 -> LUX-002 | B6: =Inventaire!B6 -> Mouvement Tourbillon Cal.3135 | C6: =Inventaire!D6 -> EC | D6: =Inventaire!G6*Inventaire!F6 -> 504000 | E6: =Inventaire!O6*Inventaire!F6 -> 1020000 | F6: =Inventaire!P6*Inventaire!F6 -> 180000 | G6: =Inventaire!Q6*Inventaire!F6 -> 51000 | H6: =E6-F6-G6 -> 789000 | I6: =D6-H6 -> -285000 | J6: =MAX(0,I6) -> 0 | K6: =IF(I6>0,"🔴 Dépréciation","✅ Conforme") -> ✅ Conforme
A7: =Inventaire!A7 -> LUX-003 | B7: =Inventaire!B7 -> Sac Birkin 30 Togo | C7: =Inventaire!D7 -> PF | D7: =Inventaire!G7*Inventaire!F7 -> 33600 | E7: =Inventaire!O7*Inventaire!F7 -> 78400 | F7: =Inventaire!P7*Inventaire!F7 -> 0 | G7: =Inventaire!Q7*Inventaire!F7 -> 3920 | H7: =E7-F7-G7 -> 74480 | I7: =D7-H7 -> -40880 | J7: =MAX(0,I7) -> 0 | K7: =IF(I7>0,"🔴 Dépréciation","✅ Conforme") -> ✅ Conforme
A8: =Inventaire!A8 -> LUX-004 | B8: =Inventaire!B8 -> Diamants VVS1 D-Color (1ct) | C8: =Inventaire!D8 -> MP | D8: =Inventaire!G8*Inventaire!F8 -> 1824000 | E8: =Inventaire!O8*Inventaire!F8 -> 3420000 | F8: =Inventaire!P8*Inventaire!F8 -> 300000 | G8: =Inventaire!Q8*Inventaire!F8 -> 171000 | H8: =E8-F8-G8 -> 2949000 | I8: =D8-H8 -> -1125000 | J8: =MAX(0,I8) -> 0 | K8: =IF(I8>0,"🔴 Dépréciation","✅ Conforme") -> ✅ Conforme
A9: =Inventaire!A9 -> LUX-005 | B9: =Inventaire!B9 -> Montre Nautilus 5711/1A | C9: =Inventaire!D9 -> PF | D9: =Inventaire!G9*Inventaire!F9 -> 92500 | E9: =Inventaire!O9*Inventaire!F9 -> 175000 | F9: =Inventaire!P9*Inventaire!F9 -> 0 | G9: =Inventaire!Q9*Inventaire!F9 -> 8750 | H9: =E9-F9-G9 -> 166250 | I9: =D9-H9 -> -73750 | J9: =MAX(0,I9) -> 0 | K9: =IF(I9>0,"🔴 Dépréciation","✅ Conforme") -> ✅ Conforme
A10: =Inventaire!A10 -> LUX-006 | B10: =Inventaire!B10 -> Tissu Tweed Haute Couture | C10: =Inventaire!D10 -> EC | D10: =Inventaire!G10*Inventaire!F10 -> 370000 | E10: =Inventaire!O10*Inventaire!F10 -> 320000 | F10: =Inventaire!P10*Inventaire!F10 -> 40000 | G10: =Inventaire!Q10*Inventaire!F10 -> 16000 | H10: =E10-F10-G10 -> 264000 | I10: =D10-H10 -> 106000 | J10: =MAX(0,I10) -> 106000 | K10: =IF(I10>0,"🔴 Dépréciation","✅ Conforme") -> 🔴 Dépréciation
A11: =Inventaire!A11 -> LUX-007 | B11: =Inventaire!B11 -> Collier Haute Joaillerie Panthère | C11: =Inventaire!D11 -> PF | D11: =Inventaire!G11*Inventaire!F11 -> 375000 | E11: =Inventaire!O11*Inventaire!F11 -> 840000 | F11: =Inventaire!P11*Inventaire!F11 -> 0 | G11: =Inventaire!Q11*Inventaire!F11 -> 42000 | H11: =E11-F11-G11 -> 798000 | I11: =D11-H11 -> -423000 | J11: =MAX(0,I11) -> 0 | K11: =IF(I11>0,"🔴 Dépréciation","✅ Conforme") -> ✅ Conforme
A12: TOTAL GÉNÉRAL | B12: Synthèse Patrimoine | D12: =SUM(D5:D11) -> 3581600 | E12: =SUM(E5:E11) -> 6429400 | F12: =SUM(F5:F11) -> 520000 | G12: =SUM(G5:G11) -> 321470 | H12: =SUM(H5:H11) -> 5587930 | I12: =SUM(I5:I11) -> -2006330 | J12: =SUM(J5:J11) -> 106000
A14: 📉 Indicateurs IAS 2 — Provisions Requises
A15: Provision Totale IAS 2 Requise | C15: =J12 -> 106000
A16: % Provision / Stock Total | C16: =J12/D12 -> 0.029595711
A17: Nombre Articles Dépréciés | C17: =COUNTIF(K5:K11,"🔴*") -> 1
A18: Articles Testés | C18: =COUNTA(A5:A11) -> 7
A19: Articles sans dépréciation | C19: =COUNTIF(J5:J11,0) -> 6
A20: Articles avec dépréciation | C20: =COUNTIF(J5:J11,">0") -> 1
A21: Impact sur la valeur stock | C21: =IF(Inventaire!H12<>0,-SUM(J5:J11)/Inventaire!H12,0) -> -0.029595711
A22: % Articles dépréciés | C22: =IF(C18>0,C20/C18,0) -> 0.14285714
A26: 📝 Écriture Comptable Recommandée
A28: N° | C28: Compte | D28: Libellé | G28: Débit (€) | I28: Crédit (€)
A29: 1 | C29: 6817 | D29: Dotation aux dépréciations des stocks | G29: =C15 -> 106000
A30: 2 | C30: 39xx | D30: Dépréciation des stocks et en-cours | I30: =C15 -> 106000
A31: C | D31: Contrôle d'équilibre : | G31: =IF(G29=I30,"✅ Équilibré","❌ Déséquilibré") -> ✅ Équilibré
A34: 💰 Valeur du Stock Ajustée
A36: Stock brut (avant test) | C36: =Inventaire!H12 -> 3581600
A37: (−) Provision IAS 2 | C37: =-SUM(J5:J11) -> -106000
A38: ★ STOCK NET (après IAS 2) | C38: =C36+C37 -> 3475600
A40: Vérification | C40: =IF(ABS(C38-(Inventaire!H12-SUM(Test_NRV_IAS2!J5:J11)))<1,"Vérifié ✅","Erreur ❌") -> Vérifié ✅

Sheet Marges_PF
A1: 💎 Analyse des Marges — Produits Finis
A2: Calcul des marges brutes et contribution par PF
A4: Réf. | B4: Produit Fini | C4: Maison | D4: Coût Production | E4: Prix de vente | F4: Marge Brute | G4: Taux Marge | H4: Qté Stock | I4: CA Potentiel | J4: Contribution | K4: Nb Vendus
A5: =Inventaire!A7 -> LUX-003 | B5: =Inventaire!B7 -> Sac Birkin 30 Togo | C5: =Inventaire!C7 -> Hermès | D5: =Inventaire!G7 -> 4200 | E5: =Inventaire!R7 -> 9800 | F5: =E5-D5 -> 5600 | G5: =F5/E5 -> 0.57142857 | H5: =Inventaire!F7 -> 8 | I5: =E5*H5 -> 78400 | J5: =F5*H5 -> 44800 | K5: =Inventaire!S7 -> 110
A6: =Inventaire!A9 -> LUX-005 | B6: =Inventaire!B9 -> Montre Nautilus 5711/1A | C6: =Inventaire!C9 -> Patek Philippe | D6: =Inventaire!G9 -> 18500 | E6: =Inventaire!R9 -> 35000 | F6: =E6-D6 -> 16500 | G6: =F6/E6 -> 0.47142857 | H6: =Inventaire!F9 -> 5 | I6: =E6*H6 -> 175000 | J6: =F6*H6 -> 82500 | K6: =Inventaire!S9 -> 30
A7: =Inventaire!A11 -> LUX-007 | B7: =Inventaire!B11 -> Collier Haute Joaillerie Panthère | C7: =Inventaire!C11 -> Cartier | D7: =Inventaire!G11 -> 125000 | E7: =Inventaire!R11 -> 280000 | F7: =E7-D7 -> 155000 | G7: =F7/E7 -> 0.55357143 | H7: =Inventaire!F11 -> 3 | I7: =E7*H7 -> 840000 | J7: =F7*H7 -> 465000 | K7: =Inventaire!S11 -> 6
A8: TOTAL PF | B8: 3 Produits Finis en Stock | D8: =SUM(D5:D7) -> 147700 | E8: =SUM(E5:E7) -> 324800 | F8: =SUM(F5:F7) -> 177100 | G8: =F8/E8 -> 0.54525862 | H8: =SUM(H5:H7) -> 16 | I8: =SUM(I5:I7) -> 1093400 | J8: =SUM(J5:J7) -> 592300 | K8: =SUM(K5:K7) -> 146
A10: 📊 KPIs Rentabilité Produits Finis
A11: Taux de Marge Moyen PF | C11: =G8 -> 0.54525862
A12: CA Potentiel Total PF | C12: =I8 -> 1093400
A13: Contribution Totale PF | C13: =J8 -> 592300
A14: Meilleur Produit (Marge) | C14: =INDEX(B5:B7,MATCH(MAX(G5:G7),G5:G7,0)) -> Sac Birkin 30 Togo
A17: 📊 Contribution au Chiffre d'Affaires & Classement
A19: Produit | D19: % du CA | E19: Marge Tot. (€) | F19: % Marge Glob. | H19: Rang CA | I19: Rang Taux
A20: =B5 -> Sac Birkin 30 Togo | D20: =IF(I$8<>0,I5/I$8,0) -> 0.071702945
A21: =B6 -> Montre Nautilus 5711/1A | D21: =IF(I$8<>0,I6/I$8,0) -> 0.16005122
A22: =B7 -> Collier Haute Joaillerie Panthère | D22: =IF(I$8<>0,I7/I$8,0) -> 0.76824584
A26: 📈 Analyse de Sensibilité (±10% Prix de Vente)
A28: Article | C28: Coût (€) | D28: Prix −10% | E28: Marge −10% | G28: Prix Base | H28: Marge Base | I28: Prix +10% | J28: Marge +10%
B29: =B5 -> Sac Birkin 30 Togo | C29: =D5 -> 4200 | D29: =E5*0.9 -> 8820 | E29: =IF(D29<>0,(D29-C29)/D29,0) -> 0.52380952 | G29: =E5 -> 9800 | H29: =G5 -> 0.57142857 | I29: =E5*1.1 -> 10780 | J29: =IF(I29<>0,(I29-C29)/I29,0) -> 0.61038961
B30: =B6 -> Montre Nautilus 5711/1A | C30: =D6 -> 18500 | D30: =E6*0.9 -> 31500 | E30: =IF(D30<>0,(D30-C30)/D30,0) -> 0.41269841 | G30: =E6 -> 35000 | H30: =G6 -> 0.47142857 | I30: =E6*1.1 -> 38500 | J30: =IF(I30<>0,(I30-C30)/I30,0) -> 0.51948052
B31: =B7 -> Collier Haute Joaillerie Panthère | C31: =D7 -> 125000 | D31: =E7*0.9 -> 252000 | E31: =IF(D31<>0,(D31-C31)/D31,0) -> 0.50396825 | G31: =E7 -> 280000 | H31: =G7 -> 0.55357143 | I31: =E7*1.1 -> 308000 | J31: =IF(I31<>0,(I31-C31)/I31,0) -> 0.59415584
A34: 🎯 Seuil de Rentabilité (Break-Even) — Hyp. : 15% CA en frais fixes
A36: Article | C36: Coût (€) | D36: Marge Unit. (€) | E36: Seuil (unités) | G36: CA au seuil | I36: Marge de sécurité
A37: =B5 -> Sac Birkin 30 Togo | C37: =(K5*E5)*0.15 -> 161700 | D37: =F5 -> 5600 | E37: =IF(C37<>0,ROUNDUP(C37/D37,0),0) -> 29 | G37: =E37*E5 -> 284200 | I37: =IF(K5<>0,(K5-E37)/K5,0) -> 0.73636364
A38: =B6 -> Montre Nautilus 5711/1A | C38: =(K6*E6)*0.15 -> 157500 | D38: =F6 -> 16500 | E38: =IF(C38<>0,ROUNDUP(C38/D38,0),0) -> 10 | G38: =E38*E6 -> 350000 | I38: =IF(K6<>0,(K6-E38)/K6,0) -> 0.66666667
A39: =B7 -> Collier Haute Joaillerie Panthère | C39: =(K7*E7)*0.15 -> 252000 | D39: =F7 -> 155000 | E39: =IF(C39<>0,ROUNDUP(C39/D39,0),0) -> 2 | G39: =E39*E7 -> 560000 | I39: =IF(K7<>0,(K7-E39)/K7,0) -> 0.66666667
