Workbook

Sheet 1_DASHBOARD
A1: AGENT ARTISANALQUALITYAI — TABLEAU DE BORD QUALITE
A2: Neural Enterprise Framework — Qualite Artisanale Luxe — Documentation & Controle — Avril 2026
A3: Donnees temps reel | Maroquinerie • Joaillerie • Horlogerie • Pret-a-Porter | Connexion Agent LuxeTraceability

Sheet 2_CRITERES
A1: CRITERES DE QUALITE PAR METIER — AGENT ARTISANALQUALITYAI
A2: Referentiel qualite artisanale — Tolerances, methodes de mesure, seuils — Par maison et metier — Avril 2026
A3: REFERENTIEL DES CRITERES DE QUALITE ARTISANALE
A4: ID_Critere | B4: Metier | C4: Categorie produit | D4: Critere qualite | E4: Description detaillee | F4: Methode de mesure | G4: Outil / Instrument | H4: Tolerance min | I4: Tolerance max | J4: Unite | K4: Niveau criticite | L4: Reference norme | M4: Specificite Maison | N4: Frequence controle
A5: CQ-MAR-001 | B5: Maroquinerie | C5: Sac a main | D5: Densite de piqure | E5: Nombre de points par cm sur couture sellier — Regularite absolue exigee — Pas de variation >0.5pt/cm | F5: Comptage visuel + loupe 10x | G5: Loupe binoculaire + regle graduee | H5: 5 | I5: 7 | J5: pts/cm | K5: CRITIQUE | L5: Norme interne MQ-001 | M5: Point sellier : 5 pts/cm tradition Hermes — 6 pts/cm standard maison | N5: 100% des pieces
A6: CQ-MAR-002 | B6: Maroquinerie | C6: Sac a main | D6: Symetrie des coutures | E6: Ecart maximal entre coutures symetriques gauche/droite — Mesure sur 5 points de reference | F6: Mesure au pied a coulisse digital | G6: Pied a coulisse Mitutoyo 0.01mm | H6: 0 | I6: 0.5 | J6: mm | K6: CRITIQUE | L6: Norme interne MQ-002 | M6: Tolerance 0.3mm pour collections Haute Maroquinerie | N6: 100% des pieces
A7: CQ-MAR-003 | B7: Maroquinerie | C7: Sac a main | D7: Finition des tranches | E7: Qualite du filetage de tranche — Regularite, brillance, absence de bulles, adherence | F7: Inspection visuelle + test adherence (flexion 90°) | G7: Loupe 10x + flexion manuelle | H7: Regulier | I7: Parfait | J7: Qualitatif | K7: ELEVE | L7: Norme interne MQ-003 | M7: Tranche teintee a la main — Minimum 4 couches — Polissage buis | N7: 100% des pieces
A8: CQ-MAR-004 | B8: Maroquinerie | C8: Sac a main | D8: Pose quincaillerie | E8: Alignement et solidite des fermoirs, boucles, rivets — Test d'arrachement — Positionnement symetrique | F8: Test dynamometrique + controle visuel | G8: Dynamometre + gabarit positionnement | H8: 15 | I8: 999 | J8: kg (arrachement) | K8: CRITIQUE | L8: Norme EN 17396 | M8: Quincaillerie palladiee — Force arrachement min 15kg — Alignement ±0.3mm | N8: 100% des pieces
A9: CQ-MAR-005 | B9: Maroquinerie | C9: Petite maroquinerie | D9: Qualite du cuir | E9: Absence de defauts visuels sur parement — Griffures, veines marquees, taches, irregularites grain | F9: Inspection visuelle lumiere rasante 45° | G9: Table lumineuse + loupe | H9: Grade A | I9: Grade A+ | J9: Grade | K9: CRITIQUE | L9: Norme ISO 3378 | M9: Selection parements — Cuir pleine fleur uniquement — Taux de chute accepte 40% | N9: 100% peaux
A10: CQ-JOA-001 | B10: Joaillerie | C10: Bague | D10: Precision du sertissage | E10: Positionnement pierre dans le serti — Symetrie, hauteur, inclinaison — Pierre ne doit pas bouger sous pression moderee | F10: Inspection loupe 20x + test pression doigt | G10: Loupe gemmologique 20x + pince brucelles | H10: 0 | I10: 0.02 | J10: mm (jeu) | K10: CRITIQUE | L10: Norme RJC Standards | M10: Serti clos : jeu max 0.01mm — Serti griffe : alignement ±0.02mm | N10: 100% des pieces
A11: CQ-JOA-002 | B11: Joaillerie | C11: Bracelet | D11: Finition de surface metal | E11: Qualite du polissage — Absence de rayures, marques d'outils, porosites — Brillance miroir (poli) ou satine uniforme | F11: Inspection visuelle + mesure rugosite | G11: Rugosimetre Mitutoyo SJ-310 + loupe 20x | H11: Ra 0.025 | I11: Ra 0.05 | J11: µm (rugosite) | K11: ELEVE | L11: Norme ISO 4287 | M11: Polissage main minimum 3 passes — Finition avivage rhodie pour or blanc | N11: 100% des pieces
A12: CQ-JOA-003 | B12: Joaillerie | C12: Collier | D12: Tolerance poids metal | E12: Poids de la piece en metal precieux — Tolerance par rapport au poids theorique du dessin technique | F12: Pesee balance de precision 0.01g | G12: Balance Mettler Toledo XSR205 | H12: -2 | I12: 2 | J12: % (ecart) | K12: ELEVE | L12: Norme LBMA | M12: Poincon de garantie verifie — Titre 750‰ confirme par touchau | N12: 100% des pieces
A13: CQ-HOR-001 | B13: Horlogerie | C13: Montre mecanique | D13: Precision du mouvement | E13: Ecart de marche journalier — Mesure en 5 positions + 2 temperatures sur 10 jours — Criteres COSC | F13: Test chronometrique 10 jours | G13: Witschi Chronoscope + stand 5 positions | H13: -4 | I13: 6 | J13: sec/jour | K13: CRITIQUE | L13: COSC ISO 3159 | M13: Critere COSC standard — Maison exige -2/+4 sec/jour pour Haute Horlogerie | N13: 100% mouvements
A14: CQ-HOR-002 | B14: Horlogerie | C14: Montre | D14: Etancheite | E14: Resistance a la pression d'eau — Test de pression selon profondeur annoncee + marge 25% | F14: Test pression eau/air | G14: Appareil Witschi Proofmaster + chambre pression | H14: 0 | I14: 0 | J14: bar (fuite) | K14: CRITIQUE | L14: ISO 22810 | M14: Test a 125% de la pression annoncee — 3 cycles — Fuite = 0 tolere | N14: 100% boitiers
A15: CQ-HOR-003 | B15: Horlogerie | C15: Montre | D15: Finition du mouvement | E15: Qualite des decorations : cotes de Geneve, perlage, anglage, polissage — Evaluation sur 8 criteres | F15: Inspection loupe binoculaire 40x | G15: Loupe Leica M205 + eclairage rasant | H15: Bon | I15: Excellent | J15: Qualitatif (8 criteres) | K15: ELEVE | L15: Poincon de Geneve / Qualite Fleurier | M15: Anglage interne obligatoire — Cotes de Geneve sur ponts — Polissage speculaire vis | N15: 100% mouvements
A16: CQ-PAP-001 | B16: Pret-a-Porter | C16: Veste / Blazer | D16: Solidite des coutures | E16: Resistance a la traction des coutures — Test normalise sur eprouvette — Mesure force de rupture | F16: Test dynamometrique sur eprouvette | G16: Dynamometre Instron 5944 + machoires tissu | H16: 80 | I16: 999 | J16: N (resistance) | K16: ELEVE | L16: ISO 13935-1 | M16: Resistance min 80N couture principale — 60N couture decorative | N16: Par lot (5 pieces)
A17: CQ-PAP-002 | B17: Pret-a-Porter | C17: Robe | D17: Alignement droit-fil | E17: Ecart du droit-fil tissu par rapport a l'axe de symetrie du vetement — Mesure sur patron et piece finie | F17: Mesure au rapporteur + laser | G17: Laser d'alignement + rapporteur gradue | H17: 0 | I17: 1 | J17: ° (degres) | K17: ELEVE | L17: Norme interne PAP-002 | M17: Tolerance 0.5° pour soie — 1° pour laine — Tissus imprimes : raccord motif obligatoire | N17: 100% des pieces
A18: CQ-PAP-003 | B18: Pret-a-Porter | C18: Chemise | D18: Regularite des boutonnieres | E18: Taille, positionnement et finition des boutonnieres — Regularite de l'espacement — Solidite de la bride | F18: Mesure pied a coulisse + test boutonnage 50 cycles | G18: Pied a coulisse + mannequin d'essai | H18: 0 | I18: 0.5 | J18: mm (ecart taille) | K18: MOYEN | L18: Norme interne PAP-003 | M18: Boutonniere a la main pour Haute Couture — Machine pour PAP standard — Points de renfort | N18: 100% pieces HC / lot PAP
A19: CQ-GEN-001 | B19: Tous metiers | C19: Tous produits | D19: Conformite colorimetrique | E19: Coherence couleur entre pieces d'un meme lot et par rapport au standard colorimetrique — ΔE* ≤ 1.5 | F19: Spectrophotometre | G19: X-Rite Ci7800 + cabine lumiere D65 | H19: 0 | I19: 1.5 | J19: ΔE* (ecart) | K19: ELEVE | L19: ISO 105-J03 | M19: ΔE* ≤ 1.0 pour cuir — ΔE* ≤ 1.5 pour textile — Validation sous D65 + TL84 | N19: Par lot + standard
A20: CQ-GEN-002 | B20: Tous metiers | C20: Tous produits | D20: Test de solidite des teintures | E20: Resistance de la teinture au frottement sec et humide — a la lumiere — a la transpiration | F20: Test Crockmeter (frottement) + test lumiere xenon | G20: Crockmeter James Heal + Xenotest | H20: 4 | I20: 5 | J20: Niveau (echelle 1-5) | K20: ELEVE | L20: ISO 105-X12 / ISO 105-B02 | M20: Note min 4 frottement sec — Note min 3-4 frottement humide — 6 lumiere | N20: Par lot (3 eprouvettes)
A21: SYNTHESE CRITERES | B21: Total criteres : | C21: =COUNTA(A5:A20) | E21: CRITIQUES : | F21: =COUNTIF(K5:K20,"CRITIQUE") | G21: ELEVES : | H21: =COUNTIF(K5:K20,"ELEVE")

Sheet 3_CONTROLES
A1: CONTROLES QUALITE — AGENT ARTISANALQUALITYAI
A2: Registre des inspections et resultats — Tracabilite piece par piece — Avril 2026
A3: REGISTRE DES CONTROLES QUALITE
A4: ID_Controle | B4: Date | C4: Heure | D4: Metier | E4: Categorie produit | F4: Ref. produit / Lot | G4: Lot tracabilite (LuxeTrace) | H4: Critere(s) controle(s) | I4: Artisan | J4: Atelier | K4: Resultat | L4: Score (/100) | M4: Defauts constates | N4: Action corrective | O4: Controleur | P4: Observations
A5: CTL-2026-0001 | B5: 2026-04-01 | C5: 09:15 | D5: Maroquinerie | E5: Sac a main | F5: SAC-KE-35-NOIR-001 | G5: LOT-2026-0001 | H5: CQ-MAR-001 + CQ-MAR-002 + CQ-MAR-003 | I5: Jean-Pierre Moreau | J5: Atelier Maroquinerie Paris | K5: Conforme | L5: 97 | M5: Aucun | N5: N/A | O5: Sophie Laurent | P5: Piece d'exception — Point sellier 5.5pts/cm — Symetrie parfaite
A6: CTL-2026-0002 | B6: 2026-04-01 | C6: 10:30 | D6: Maroquinerie | E6: Sac a main | F6: SAC-KE-35-GOLD-002 | G6: LOT-2026-0001 | H6: CQ-MAR-001 + CQ-MAR-002 + CQ-MAR-004 | I6: Marie Dubois | J6: Atelier Maroquinerie Paris | K6: Conforme | L6: 94 | M6: Obs. mineure : legere irregularite tranche coin superieur droit | N6: Reprise finition tranche — Couche supplementaire | O6: Sophie Laurent | P6: Piece validee apres reprise — Score releve de 91 a 94
A7: CTL-2026-0003 | B7: 2026-04-02 | C7: 08:45 | D7: Maroquinerie | E7: Sac a main | F7: SAC-BI-28-CAMEL-003 | G7: LOT-2026-0002 | H7: CQ-MAR-001 + CQ-MAR-005 | I7: Antoine Lefevre | J7: Atelier Maroquinerie Paris | K7: Non conforme | L7: 62 | M7: Defaut cuir : griffure 8mm visible sur parement avant — Densite piqure irreguliere (4.2 a 5.8 pts/cm) | N7: Remplacement parement + reprise couture complete | O7: Sophie Laurent | P7: Rejet initial — Cuir retourne au tri — Nouveau parement selectionne
A8: CTL-2026-0004 | B8: 2026-04-02 | C8: 14:00 | D8: Joaillerie | E8: Bague | F8: BAG-SOL-OR18-DIA-001 | G8: LOT-2026-0004 | H8: CQ-JOA-001 + CQ-JOA-002 + CQ-JOA-003 | I8: Maitre Francois Petit | J8: Atelier Haute Joaillerie Vendome | K8: Conforme | L8: 99 | M8: Aucun | N8: N/A | O8: Alain Mercier | P8: Piece Haute Joaillerie — Sertissage diamant 1.52ct D/IF impeccable — Polissage miroir parfait
A9: CTL-2026-0005 | B9: 2026-04-03 | C9: 09:00 | D9: Joaillerie | E9: Bracelet | F9: BRA-MAN-OR18-007 | G9: LOT-2026-0004 | H9: CQ-JOA-002 + CQ-JOA-003 | I9: Elise Durand | J9: Atelier Haute Joaillerie Vendome | K9: Conditionnel | L9: 82 | M9: Micro-rayure outil visible sur interieur maille — Poids -2.3% vs theorique | N9: Re-polissage interieur maillon — Validation poids dans tolerance | O9: Alain Mercier | P9: Conditionnel : re-polissage suffisant — Poids dans tolerance (-2.3% < -2% frontiere)
A10: CTL-2026-0006 | B10: 2026-04-03 | C10: 11:30 | D10: Horlogerie | E10: Montre mecanique | F10: MON-ETER-AUTO-001 | G10: N/A (mouvement manufacture) | H10: CQ-HOR-001 + CQ-HOR-002 | I10: Maitre Claude Bonnard | J10: Atelier Horlogerie Geneve | K10: Conforme | L10: 98 | M10: Aucun | N10: N/A | O10: Pierre Fontaine | P10: Mouvement manufacture — Marche -1.8s/j (cible -2/+4) — Etancheite 10 bar confirmee
A11: CTL-2026-0007 | B11: 2026-04-04 | C11: 08:30 | D11: Horlogerie | E11: Montre | F11: MON-CLAS-QTZ-015 | G11: N/A | H11: CQ-HOR-002 + CQ-HOR-003 | I11: Isabelle Martin | J11: Atelier Horlogerie Geneve | K11: Conforme | L11: 91 | M11: Obs. mineure : perlage pont legerement irregulier zone 3 — Dans tolerance | N11: N/A — Observation documentee | O11: Pierre Fontaine | P11: Perlage acceptable selon grille — Etancheite 5 bar OK — Mouvement quartz conforme
A12: CTL-2026-0008 | B12: 2026-04-04 | C12: 14:15 | D12: Pret-a-Porter | E12: Veste / Blazer | F12: VES-SM-CASH-NAVY-001 | G12: LOT-2026-0007 | H12: CQ-PAP-001 + CQ-PAP-002 + CQ-GEN-001 | I12: Nathalie Bernard | J12: Atelier PAP Milan | K12: Conforme | L12: 95 | M12: Aucun | N12: N/A | O12: Marco Ricci | P12: Cachemire Gobi — Coutures 120N — Droit-fil 0.3° — ΔE* 0.8 vs standard — Excellent
A13: CTL-2026-0009 | B13: 2026-04-05 | C13: 09:45 | D13: Pret-a-Porter | E13: Robe | F13: ROB-SOI-IMP-FLOR-003 | G13: LOT-2026-0009 | H13: CQ-PAP-002 + CQ-GEN-001 + CQ-GEN-002 | I13: Catherine Moreau | J13: Atelier PAP Milan | K13: Non conforme | L13: 58 | M13: Raccord motif imprime decale 3mm dos — ΔE* 2.1 (> seuil 1.5) — Solidite frottement humide : 2/5 | N13: Recoupe panneaux dos — Reteinture lot tissu — Lot bloque | O13: Marco Ricci | P13: Triple non-conformite — Lot soie bloque — Alerte qualite fournisseur Seteria Bianchi
A14: CTL-2026-0010 | B14: 2026-04-07 | C14: 10:00 | D14: Maroquinerie | E14: Petite maroquinerie | F14: PLM-ZIP-CUI-BURG-012 | G14: LOT-2026-0001 | H14: CQ-MAR-005 + CQ-MAR-003 + CQ-GEN-001 | I14: Jean-Pierre Moreau | J14: Atelier Maroquinerie Paris | K14: Conforme | L14: 93 | M14: Obs. mineure : legere variation teinte cuir entre 2 panneaux (ΔE* 1.1 — dans tolerance) | N14: N/A — Variation naturelle cuir documentee | O14: Sophie Laurent | P14: Variation chromatique naturelle du cuir pleine fleur — Dans tolerance maison (ΔE* ≤ 1.0 cuir strict)
A15: CTL-2026-0011 | B15: 2026-04-08 | C15: 11:00 | D15: Joaillerie | E15: Collier | F15: COL-RIV-OR-SAP-001 | G15: LOT-2026-0005 | H15: CQ-JOA-001 + CQ-JOA-002 | I15: Maitre Francois Petit | J15: Atelier Haute Joaillerie Vendome | K15: En attente | L15: 0 | M15: Controle en cours — Sertissage 47 saphirs en riviere — Etape 32/47 | N15: N/A — Controle non finalise | O15: Alain Mercier | P15: Piece Haute Joaillerie complexe — Controle pierre par pierre — Fin estimee 12/04
A16: CTL-2026-0012 | B16: 2026-04-09 | C16: 09:00 | D16: Maroquinerie | E16: Sac a main | F16: SAC-KE-35-CROC-001 | G16: LOT-2026-0008 | H16: CQ-MAR-001 + CQ-MAR-002 + CQ-MAR-003 + CQ-MAR-004 + CQ-MAR-005 | I16: Marie Dubois | J16: Atelier Maroquinerie Paris | K16: Conforme | L16: 96 | M16: Aucun | N16: N/A | O16: Sophie Laurent | P16: Piece crocodile — Controle exhaustif 5 criteres — Excellence — Ecailles symetriques validees
... A18: CTL-2026-0014 | B18: 2026-04-11 | C18: 08:00 | D18: Horlogerie | E18: Montre mecanique | F18: MON-TOUR-CHRONO-001 | G18: N/A (mouvement complication) | H18: CQ-HOR-001 + CQ-HOR-002 + CQ-HOR-003 | I18: Maitre Claude Bonnard | J18: Atelier Horlogerie Geneve | K18: Conforme | L18: 100 | M18: Aucun — Piece exceptionnelle | N18: N/A | O18: Pierre Fontaine | P18: Score 100/100 — Tourbillon — Marche +0.2s/j — Finition Poincon de Geneve — Chef-d'oeuvre
A19: SYNTHESE CONTROLES | B19: Total : | C19: =COUNTA(A5:A18) | E19: Conformes : | F19: =COUNTIF(K5:K18,"Conforme") | G19: Non conformes : | H19: =COUNTIF(K5:K18,"Non conforme") | I19: Score moyen : | J19: =IFERROR(AVERAGEIF(L5:L18,">0"),0)
B20: First Pass Yield : | C20: =IFERROR(COUNTIF(K5:K18,"Conforme")/COUNTIFS(K5:K18,"<>En attente"),0) | E20: Taux rejet : | F20: =IFERROR(COUNTIF(K5:K18,"Non conforme")/COUNTIFS(K5:K18,"<>En attente"),0)

Sheet 4_DEFAUTS
A1: REGISTRE DES DEFAUTS — AGENT ARTISANALQUALITYAI
A2: Classification, analyse causale, actions correctives — Amelioration continue — Avril 2026
A3: REGISTRE DEFAUTS QUALITE ARTISANALE
A4: ID_Defaut | B4: Date detection | C4: Controle source | D4: Metier | E4: Produit / Lot | F4: Type de defaut | G4: Classification | H4: Severite | I4: Description detaillee | J4: Cause racine identifiee | K4: Action corrective | L4: Action preventive | M4: Cout impact (€) | N4: Responsable | O4: Statut | P4: Date cloture
A5: DEF-2026-001 | B5: 2026-04-02 | C5: CTL-2026-0003 | D5: Maroquinerie | E5: SAC-BI-28-CAMEL-003 | F5: Defaut matiere — Griffure cuir | G5: Esthetique | H5: Majeur | I5: Griffure lineaire 8mm sur parement avant cuir veau — Visible a l'oeil nu — Origine : selection cuir insuffisante | J5: Peau presentant un defaut en zone B non detecte lors du tri initial — Eclairage poste de tri insuffisant | K5: Remplacement parement complet — Selection nouvelle peau Grade A+ | L5: Installation lampe LED lumiere rasante au poste de tri cuir — Formation operateur tri | M5: 450 | N5: Resp. Atelier Maroquinerie | O5: Resolu | P5: 2026-04-04
A6: DEF-2026-002 | B6: 2026-04-02 | C6: CTL-2026-0003 | D6: Maroquinerie | E6: SAC-BI-28-CAMEL-003 | F6: Defaut piqure — Densite irreguliere | G6: Fonctionnel | H6: Majeur | I6: Variation densite piqure de 4.2 a 5.8 pts/cm sur couture principale — Norme 5-7 pts/cm mais variation >0.5pt/cm | J6: Tension fil machine mal reglee — Usure guide-fil detectee — Artisan fatigue (heure tardive) | K6: Decousage + reprise couture integrale — Reglage machine — Verification guide-fil | L6: Procedure de verification tension fil toutes les 2h — Rotation artisans en fin de journee | M6: 380 | N6: Jean-Pierre Moreau (artisan) | O6: Resolu | P6: 2026-04-05
A7: DEF-2026-003 | B7: 2026-04-03 | C7: CTL-2026-0005 | D7: Joaillerie | E7: BRA-MAN-OR18-007 | F7: Defaut finition — Micro-rayure | G7: Esthetique | H7: Mineur | I7: Micro-rayure outil 2mm sur face interieure maillon bracelet or 18K — Non visible porte — Detectable loupe 20x | J7: Contact accidentel outil gravure lors de manipulation piece voisine — Poste de travail encombre | K7: Re-polissage localise — Avivage rhodie zone impactee | L7: Reorganisation poste travail — Separation physique pieces en cours — Protocole manipulation | M7: 120 | N7: Elise Durand (artisan) | O7: Resolu | P7: 2026-04-04
A8: DEF-2026-004 | B8: 2026-04-05 | C8: CTL-2026-0009 | D8: Pret-a-Porter | E8: ROB-SOI-IMP-FLOR-003 | F8: Defaut matiere — Raccord motif | G8: Esthetique | H8: Majeur | I8: Decalage raccord motif imprime floral 3mm sur couture dos — Visible a 1m — Inacceptable pour piece de collection | J8: Erreur placement patron sur tissu imprime — Operateur coupe n'a pas aligne reperes motif | K8: Recoupe panneaux dos avec raccord correct — Piece recoupee dans nouveau metrage | L8: Formation placement patron sur imprimes — Gabarit de raccord obligatoire — Double validation avant coupe | M8: 580 | N8: Resp. Atelier PAP Milan | O8: Resolu | P8: 2026-04-08
A9: DEF-2026-005 | B9: 2026-04-05 | C9: CTL-2026-0009 | D9: Pret-a-Porter | E9: ROB-SOI-IMP-FLOR-003 (lot tissu) | F9: Defaut teinture — ΔE* hors tolerance | G9: Matiere premiere | H9: Critique | I9: ΔE* de 2.1 entre tissu livre et standard colorimetrique — Seuil 1.5 — Lot soie entier potentiellement impacte | J9: Derive bain de teinture chez fournisseur Seteria Bianchi — Lot de teinture #SB-2026-T089 | K9: Lot soie bloque — Retour fournisseur pour reteinture — Alerte qualite emise vers fournisseur | L9: Audit teinture chez Seteria Bianchi — Exigence certificat colorimerique par lot — Controle reception systematique | M9: 2800 | N9: Dir. Qualite + Seteria Bianchi | O9: En cours
A10: DEF-2026-006 | B10: 2026-04-05 | C10: CTL-2026-0009 | D10: Pret-a-Porter | E10: ROB-SOI-IMP-FLOR-003 (lot tissu) | F10: Defaut teinture — Solidite insuffisante | G10: Fonctionnel | H10: Critique | I10: Solidite frottement humide 2/5 (min 3-4 requis) — Risque decoloration au porte — Lot impropre a la commercialisation | J10: Meme cause que DEF-005 — Fixation colorant insuffisante lot teinture #SB-2026-T089 | K10: Lot bloque — Impossibilite de reprise — Remplacement lot complet par Seteria Bianchi | L10: Renforcement cahier des charges teinture — Clause penale fournisseur — Controle solidite reception | M10: 4200 | N10: Dir. Qualite + Dir. Achats | O10: En cours
A11: DEF-2026-007 | B11: 2026-04-10 | C11: CTL-2026-0013 | D11: Pret-a-Porter | E11: CHE-COT-BLA-SLIM #7 et #12 | F11: Defaut confection — Boutonniere irreguliere | G11: Esthetique | H11: Mineur | I11: Boutonniere #3 sur 2 pieces (sur 15) : ecart taille 0.7mm vs 0.5mm tolerance — Legere irregularite visuelle | J11: Reglage machine boutonniere legerement decale — Maintenance preventive retardee de 3 jours | K11: Reprise manuelle boutonnieres pieces #7 et #12 — Reglage machine effectue | L11: Maintenance preventive machine boutonniere strictement toutes les 200 pieces — Check-list pre-production | M11: 60 | N11: Catherine Moreau (operateur) | O11: Resolu | P11: 2026-04-11
A12: DEF-2026-008 | B12: 2026-04-01 | C12: CTL-2026-0002 | D12: Maroquinerie | E12: SAC-KE-35-GOLD-002 | F12: Defaut finition — Tranche irreguliere | G12: Esthetique | H12: Mineur | I12: Legere irregularite finition tranche coin superieur droit — Visible loupe 10x uniquement — Reprise simple | J12: Application de peinture de tranche legerement inegale — 3eme couche trop rapide (sechage incomplet) | K12: Poncage leger + application couche supplementaire — Polissage buis final | L12: Rappel temps de sechage inter-couches minimum 45min — Fiche de suivi sechage au poste | M12: 40 | N12: Marie Dubois (artisan) | O12: Resolu | P12: 2026-04-01
A13: SYNTHESE DEFAUTS | B13: Total defauts : | C13: =COUNTA(A5:A12) | E13: Critiques : | F13: =COUNTIF(H5:H12,"Critique") | G13: Ouverts : | H13: =COUNTIF(O5:O12,"En cours") | L13: Cout total : | M13: =SUM(M5:M12)

Sheet 5_ATELIERS
A1: REGISTRE DES ATELIERS — AGENT ARTISANALQUALITYAI
A2: Ateliers de fabrication — Capacites, certifications, scores qualite — Avril 2026
A3: BASE DES ATELIERS DE FABRICATION
A4: ID_Atelier | B4: Nom de l'atelier | C4: Ville | D4: Pays | E4: Metier principal | F4: Specialite | G4: Nb artisans | H4: Score qualite moyen | I4: Taux First Pass Yield | J4: Certifications atelier | K4: Date dernier audit qualite | L4: Resultat audit | M4: Statut | N4: Notes
A5: ATL-001 | B5: Atelier Maroquinerie Paris | C5: Paris 3e | D5: France | E5: Maroquinerie | F5: Sacs a main — Point sellier — Cuirs exotiques | G5: 12 | H5: =IFERROR(AVERAGEIFS('3_CONTROLES'!L$5:L$5000,'3_CONTROLES'!J$5:J$5000,B5,'3_CONTROLES'!L$5:L$5000,">0"),"-") | I5: =IFERROR(COUNTIFS('3_CONTROLES'!J$5:J$5000,B5,'3_CONTROLES'!K$5:K$5000,"Conforme")/COUNTIFS('3_CONTROLES'!J$5:J$5000,B5,'3_CONTROLES'!K$5:K$5000,"<>En attente"),"-") | J5: ISO 9001 + Label EPV (Entreprise du Patrimoine Vivant) | K5: 2026-03-15 | L5: Conforme | M5: Actif | N5: Atelier historique — Excellence artisanale — Formation compagnonnage — Maitre d'art resident
A6: ATL-002 | B6: Atelier Haute Joaillerie Vendome | C6: Paris 1er | D6: France | E6: Joaillerie | F6: Haute Joaillerie — Sertissage — Polissage — Gravure | G6: 8 | H6: =IFERROR(AVERAGEIFS('3_CONTROLES'!L$5:L$5000,'3_CONTROLES'!J$5:J$5000,B6,'3_CONTROLES'!L$5:L$5000,">0"),"-") | I6: =IFERROR(COUNTIFS('3_CONTROLES'!J$5:J$5000,B6,'3_CONTROLES'!K$5:K$5000,"Conforme")/COUNTIFS('3_CONTROLES'!J$5:J$5000,B6,'3_CONTROLES'!K$5:K$5000,"<>En attente"),"-") | J6: RJC CoP + Label EPV + Poincon de maitre | K6: 2026-02-28 | L6: Conforme | M6: Actif | N6: Place Vendome — Maitres joailliers — Pieces uniques et haute joaillerie — Coffre-fort classe 6
A7: ATL-003 | B7: Atelier Horlogerie Geneve | C7: Geneve | D7: Suisse | E7: Horlogerie | F7: Mouvements manufacture — Complications — Habillage | G7: 6 | H7: =IFERROR(AVERAGEIFS('3_CONTROLES'!L$5:L$5000,'3_CONTROLES'!J$5:J$5000,B7,'3_CONTROLES'!L$5:L$5000,">0"),"-") | I7: =IFERROR(COUNTIFS('3_CONTROLES'!J$5:J$5000,B7,'3_CONTROLES'!K$5:K$5000,"Conforme")/COUNTIFS('3_CONTROLES'!J$5:J$5000,B7,'3_CONTROLES'!K$5:K$5000,"<>En attente"),"-") | J7: Poincon de Geneve + COSC + ISO 9001 | K7: 2026-01-20 | L7: Conforme | M7: Actif | N7: Manufacture horlogere — Poincon de Geneve — Tourbillons et complications
A8: ATL-004 | B8: Atelier PAP Milan | C8: Milan | D8: Italie | E8: Pret-a-Porter | F8: Confection Femme — Tailleur — Couture flou | G8: 18 | H8: =IFERROR(AVERAGEIFS('3_CONTROLES'!L$5:L$5000,'3_CONTROLES'!J$5:J$5000,B8,'3_CONTROLES'!L$5:L$5000,">0"),"-") | I8: =IFERROR(COUNTIFS('3_CONTROLES'!J$5:J$5000,B8,'3_CONTROLES'!K$5:K$5000,"Conforme")/COUNTIFS('3_CONTROLES'!J$5:J$5000,B8,'3_CONTROLES'!K$5:K$5000,"<>En attente"),"-") | J8: ISO 9001 + Camera Nazionale della Moda | K8: 2026-03-01 | L8: Conforme | M8: Actif | N8: Atelier italien — Couture et tailleur — Expertise textiles nobles — 2 modelistes seniors
A9: ATL-005 | B9: Atelier Haute Couture Paris | C9: Paris 8e | D9: France | E9: Haute Couture | F9: Flou — Tailleur — Broderie — Plissage | G9: 22 | H9: =IFERROR(AVERAGEIFS('3_CONTROLES'!L$5:L$5000,'3_CONTROLES'!J$5:J$5000,B9,'3_CONTROLES'!L$5:L$5000,">0"),"-") | I9: =IFERROR(COUNTIFS('3_CONTROLES'!J$5:J$5000,B9,'3_CONTROLES'!K$5:K$5000,"Conforme")/COUNTIFS('3_CONTROLES'!J$5:J$5000,B9,'3_CONTROLES'!K$5:K$5000,"<>En attente"),"-") | J9: Label Haute Couture (Federation) + EPV | K9: 2026-02-15 | L9: Conforme | M9: Actif | N9: Maison membre Chambre Syndicale Haute Couture — Ateliers flou et tailleur separes
A10: ATL-006 | B10: Atelier Ganterie Millau | C10: Millau | D10: France | E10: Maroquinerie | F10: Gants de luxe — Coupe, couture, finition | G10: 5 | H10: =IFERROR(AVERAGEIFS('3_CONTROLES'!L$5:L$5000,'3_CONTROLES'!J$5:J$5000,B10,'3_CONTROLES'!L$5:L$5000,">0"),"-") | I10: =IFERROR(COUNTIFS('3_CONTROLES'!J$5:J$5000,B10,'3_CONTROLES'!K$5:K$5000,"Conforme")/COUNTIFS('3_CONTROLES'!J$5:J$5000,B10,'3_CONTROLES'!K$5:K$5000,"<>En attente"),"-") | J10: Label EPV + IGP Gant de Millau | K10: 2025-11-15 | L10: Conforme | M10: Actif | N10: Savoir-faire centenaire — Coupe a la main — Derniere ganterie de tradition en France
A11: ATL-007 | B11: Atelier Souliers Florence | C11: Florence | D11: Italie | E11: Maroquinerie | F11: Chaussures homme/femme — Cousu Blake — Cousu Goodyear | G11: 10 | H11: =IFERROR(AVERAGEIFS('3_CONTROLES'!L$5:L$5000,'3_CONTROLES'!J$5:J$5000,B11,'3_CONTROLES'!L$5:L$5000,">0"),"-") | I11: =IFERROR(COUNTIFS('3_CONTROLES'!J$5:J$5000,B11,'3_CONTROLES'!K$5:K$5000,"Conforme")/COUNTIFS('3_CONTROLES'!J$5:J$5000,B11,'3_CONTROLES'!K$5:K$5000,"<>En attente"),"-") | J11: ISO 9001 + Consorzio Vera Pelle Italiana | K11: 2026-01-10 | L11: Conforme | M11: Actif | N11: Bottier florentin — Blake et Goodyear — Formes sur mesure disponibles
A12: SYNTHESE ATELIERS | B12: Total ateliers : | C12: =COUNTA(A5:A11) | F12: Total artisans : | G12: =SUM(G5:G11) | H12: Score global : | I12: =IFERROR(AVERAGE(H5:H11),0)

Sheet 6_ARTISANS
A1: REGISTRE DES ARTISANS — AGENT ARTISANALQUALITYAI
A2: Competences, certifications, evaluations qualite, formation — Capital humain artisanal — Avril 2026
A3: BASE DES ARTISANS ET COMPETENCES
A4: ID_Artisan | B4: Nom | C4: Prenom | D4: Atelier | E4: Metier | F4: Specialite principale | G4: Annees experience | H4: Niveau maitrise | I4: Score qualite moyen | J4: Taux defaut (%) | K4: Certifications / Distinctions | L4: Derniere evaluation | M4: Heures formation (12 mois) | N4: Besoins formation identifies | O4: Statut | P4: Notes
A5: ART-001 | B5: Moreau | C5: Jean-Pierre | D5: Atelier Maroquinerie Paris | E5: Maroquinerie | F5: Point sellier — Sacs structures — Cuirs exotiques | G5: 28 | H5: Maitre d'art | I5: =IFERROR(AVERAGEIFS('3_CONTROLES'!L$5:L$5000,'3_CONTROLES'!I$5:I$5000,"*"&C5&"*",'3_CONTROLES'!L$5:L$5000,">0"),"-") | J5: =IFERROR(COUNTIFS('4_DEFAUTS'!N$5:N$5000,"*"&C5&"*")/COUNTIFS('3_CONTROLES'!I$5:I$5000,"*"&C5&"*",'3_CONTROLES'!K$5:K$5000,"<>En attente")*100,0) | K5: Maitre d'Art (2019) + MOF Maroquinier (2015) + EPV | L5: 2026-03-15 | M5: 24 | N5: Formation nouvelles colles ecologiques — Cuirs alternatifs | O5: Actif | P5: Maitre d'art — Formateur compagnons — 28 ans de maison — Referent cuirs exotiques
A6: ART-002 | B6: Dubois | C6: Marie | D6: Atelier Maroquinerie Paris | E6: Maroquinerie | F6: Couture sellier — Petite maroquinerie — Finition tranches | G6: 15 | H6: Expert | I6: =IFERROR(AVERAGEIFS('3_CONTROLES'!L$5:L$5000,'3_CONTROLES'!I$5:I$5000,"*"&C6&"*",'3_CONTROLES'!L$5:L$5000,">0"),"-") | J6: =IFERROR(COUNTIFS('4_DEFAUTS'!N$5:N$5000,"*"&C6&"*")/COUNTIFS('3_CONTROLES'!I$5:I$5000,"*"&C6&"*",'3_CONTROLES'!K$5:K$5000,"<>En attente")*100,0) | K6: MOF Maroquinier candidat 2027 + CQP Maroquinerie Luxe | L6: 2026-03-15 | M6: 32 | N6: Perfectionnement cuirs exotiques — Preparation MOF 2027 | O6: Actif | P6: Candidate MOF 2027 — Excellente — En progression rapide sur exotiques
A7: ART-003 | B7: Lefevre | C7: Antoine | D7: Atelier Maroquinerie Paris | E7: Maroquinerie | F7: Coupe — Patronage — Sacs souples | G7: 8 | H7: Confirme | I7: =IFERROR(AVERAGEIFS('3_CONTROLES'!L$5:L$5000,'3_CONTROLES'!I$5:I$5000,"*"&C7&"*",'3_CONTROLES'!L$5:L$5000,">0"),"-") | J7: =IFERROR(COUNTIFS('4_DEFAUTS'!N$5:N$5000,"*"&C7&"*")/COUNTIFS('3_CONTROLES'!I$5:I$5000,"*"&C7&"*",'3_CONTROLES'!K$5:K$5000,"<>En attente")*100,0) | K7: CQP Maroquinerie Luxe + Formation interne avancee | L7: 2026-03-15 | M7: 48 | N7: Renforcement controle visuel cuir — Regularite piqure | O7: Actif | P7: Defauts DEF-001/002 — Plan amelioration en cours — Formation renforcee tri cuir
A8: ART-004 | B8: Petit | C8: Francois | D8: Atelier Haute Joaillerie Vendome | E8: Joaillerie | F8: Sertissage — Haute Joaillerie — Pierres de centre | G8: 32 | H8: Maitre joaillier | I8: =IFERROR(AVERAGEIFS('3_CONTROLES'!L$5:L$5000,'3_CONTROLES'!I$5:I$5000,"*"&C8&"*",'3_CONTROLES'!L$5:L$5000,">0"),"-") | J8: =IFERROR(COUNTIFS('4_DEFAUTS'!N$5:N$5000,"*"&C8&"*")/COUNTIFS('3_CONTROLES'!I$5:I$5000,"*"&C8&"*",'3_CONTROLES'!K$5:K$5000,"<>En attente")*100,0) | K8: Maitre d'Art (2017) + MOF Joaillier (2011) + Poincon de maitre | L8: 2026-02-28 | M8: 16 | N8: Nouvelles techniques CAO 3D — Impression cire perdue avancee | O8: Actif | P8: Plus haut niveau expertise — Pieces de Haute Joaillerie exclusivement — Mentor 2 apprentis
A9: ART-005 | B9: Durand | C9: Elise | D9: Atelier Haute Joaillerie Vendome | E9: Joaillerie | F9: Polissage — Finition — Rhodiage | G9: 12 | H9: Expert | I9: =IFERROR(AVERAGEIFS('3_CONTROLES'!L$5:L$5000,'3_CONTROLES'!I$5:I$5000,"*"&C9&"*",'3_CONTROLES'!L$5:L$5000,">0"),"-") | J9: =IFERROR(COUNTIFS('4_DEFAUTS'!N$5:N$5000,"*"&C9&"*")/COUNTIFS('3_CONTROLES'!I$5:I$5000,"*"&C9&"*",'3_CONTROLES'!K$5:K$5000,"<>En attente")*100,0) | K9: CQP Joaillerie Luxe + Formation Cartier Academy | L9: 2026-02-28 | M9: 28 | N9: Perfectionnement finitions pierres de couleur — Techniques laser | O9: Actif | P9: Excellente polisseuse — Obs. mineure DEF-003 — Plan attention renforce manipulation
A10: ART-006 | B10: Bonnard | C10: Claude | D10: Atelier Horlogerie Geneve | E10: Horlogerie | F10: Assemblage mouvements — Complications — Tourbillons | G10: 35 | H10: Maitre horloger | I10: =IFERROR(AVERAGEIFS('3_CONTROLES'!L$5:L$5000,'3_CONTROLES'!I$5:I$5000,"*"&C10&"*",'3_CONTROLES'!L$5:L$5000,">0"),"-") | J10: =IFERROR(COUNTIFS('4_DEFAUTS'!N$5:N$5000,"*"&C10&"*")/COUNTIFS('3_CONTROLES'!I$5:I$5000,"*"&C10&"*",'3_CONTROLES'!K$5:K$5000,"<>En attente")*100,0) | K10: Maitre Horloger WOSTEP + Poincon de Geneve + Brevet federal CH | L10: 2026-01-20 | M10: 12 | N10: Nouvelles certifications silicium — Composants haute frequence | O10: Actif | P10: Maitre horloger referent — Score 100/100 sur tourbillon — 35 ans d'excellence
A11: ART-007 | B11: Martin | C11: Isabelle | D11: Atelier Horlogerie Geneve | E11: Horlogerie | F11: Habillage — Decoration — Finition mouvements | G11: 10 | H11: Confirme | I11: =IFERROR(AVERAGEIFS('3_CONTROLES'!L$5:L$5000,'3_CONTROLES'!I$5:I$5000,"*"&C11&"*",'3_CONTROLES'!L$5:L$5000,">0"),"-") | J11: =IFERROR(COUNTIFS('4_DEFAUTS'!N$5:N$5000,"*"&C11&"*")/COUNTIFS('3_CONTROLES'!I$5:I$5000,"*"&C11&"*",'3_CONTROLES'!K$5:K$5000,"<>En attente")*100,0) | K11: CFC Horlogere + Formation Geneve Watchmaking School | L11: 2026-01-20 | M11: 40 | N11: Anglage avance — Perlage haute precision — Preparation Poincon de Geneve | O11: Actif | P11: En progression — Observation perlage (CTL-007) — Formation anglage en cours
A12: ART-008 | B12: Bernard | C12: Nathalie | D12: Atelier PAP Milan | E12: Pret-a-Porter | F12: Tailleur femme — Cachemire — Couture structuree | G12: 20 | H12: Expert | I12: =IFERROR(AVERAGEIFS('3_CONTROLES'!L$5:L$5000,'3_CONTROLES'!I$5:I$5000,"*"&C12&"*",'3_CONTROLES'!L$5:L$5000,">0"),"-") | J12: =IFERROR(COUNTIFS('4_DEFAUTS'!N$5:N$5000,"*"&C12&"*")/COUNTIFS('3_CONTROLES'!I$5:I$5000,"*"&C12&"*",'3_CONTROLES'!K$5:K$5000,"<>En attente")*100,0) | K12: Diploma Accademia del Lusso + Maestro Sartoriale | L12: 2026-03-01 | M12: 20 | N12: Nouveaux textiles techniques — Couture collee — Hybrides | O12: Actif | P12: Experte tailleur italien — Specialiste cachemire — Resultats excellents
A13: ART-009 | B13: Moreau | C13: Catherine | D13: Atelier PAP Milan | E13: Pret-a-Porter | F13: Couture flou — Soie — Imprimes — Boutonnieres | G13: 7 | H13: Confirme | I13: =IFERROR(AVERAGEIFS('3_CONTROLES'!L$5:L$5000,'3_CONTROLES'!I$5:I$5000,"*"&C13&"*",'3_CONTROLES'!L$5:L$5000,">0"),"-") | J13: =IFERROR(COUNTIFS('4_DEFAUTS'!N$5:N$5000,"*"&C13&"*")/COUNTIFS('3_CONTROLES'!I$5:I$5000,"*"&C13&"*",'3_CONTROLES'!K$5:K$5000,"<>En attente")*100,0) | K13: CAP Couture + Formation interne avancee soie | L13: 2026-03-01 | M13: 52 | N13: Perfectionnement placement patron imprimes — Maintenance machine | O13: Actif | P13: Defauts DEF-004 + DEF-007 — Plan formation renforce — Progression attendue
A14: ART-010 | B14: Ricci | C14: Marco | D14: Atelier PAP Milan | E14: Pret-a-Porter | F14: Controle qualite — Chef d'atelier adjoint | G14: 18 | H14: Expert | I14: =IFERROR(AVERAGEIFS('3_CONTROLES'!L$5:L$5000,'3_CONTROLES'!I$5:I$5000,"*"&C14&"*",'3_CONTROLES'!L$5:L$5000,">0"),"-") | J14: =IFERROR(COUNTIFS('4_DEFAUTS'!N$5:N$5000,"*"&C14&"*")/COUNTIFS('3_CONTROLES'!I$5:I$5000,"*"&C14&"*",'3_CONTROLES'!K$5:K$5000,"<>En attente")*100,0) | K14: CQP Industrie Mode Luxe + Formation AFNOR Qualite | L14: 2026-03-01 | M14: 36 | N14: Formation auditeur interne ISO 9001 — Lean Manufacturing luxe | O14: Actif | P14: Controleur qualite principal Milan — Fiable et rigoureux — Candidat chef d'atelier
A15: SYNTHESE ARTISANS | B15: Total artisans : | C15: =COUNTA(A5:A14) | F15: Maitres d'art : | G15: =COUNTIF(H5:H14,"Maitre*") | H15: Exp. moyenne : | I15: =IFERROR(AVERAGE(G5:G14),0) | L15: Formation moy. : | M15: =IFERROR(AVERAGE(M5:M14),0)

Sheet 7_RAPPORTS_QC
A1: RAPPORTS QUALITE AGREGES — AGENT ARTISANALQUALITYAI
A2: Synthese mensuelle par atelier et metier — Tendances et analyse — Avril 2026
A3: RAPPORTS QUALITE MENSUELS — PERIODE : Q1-Q2 2026
A4: ID_Rapport | B4: Periode | C4: Atelier | D4: Metier | E4: Nb controles | F4: Nb conformes | G4: Nb non conformes | H4: First Pass Yield (%) | I4: Score moyen (/100) | J4: Top 3 defauts | K4: Tendance vs M-1 | L4: Actions prioritaires | M4: Responsable | N4: Statut rapport
A5: RPT-2026-Q1-001 | B5: Janvier 2026 | C5: Atelier Maroquinerie Paris | D5: Maroquinerie | E5: =IFERROR(COUNTIFS('3_CONTROLES'!J$5:J$5000,C5),0) | F5: =IFERROR(COUNTIFS('3_CONTROLES'!J$5:J$5000,C5,'3_CONTROLES'!K$5:K$5000,"Conforme"),0) | G5: =IFERROR(COUNTIFS('3_CONTROLES'!J$5:J$5000,C5,'3_CONTROLES'!K$5:K$5000,"Non conforme"),0) | H5: =IFERROR(F5/COUNTIFS('3_CONTROLES'!J$5:J$5000,C5,'3_CONTROLES'!K$5:K$5000,"<>En attente"),0) | I5: =IFERROR(AVERAGEIFS('3_CONTROLES'!L$5:L$5000,'3_CONTROLES'!J$5:J$5000,C5,'3_CONTROLES'!L$5:L$5000,">0"),0) | J5: 1. Finition tranche (3) 2. Symetrie couture (2) 3. Qualite cuir (1) | K5: Amelioration | L5: Renforcement controle tri cuir — Formation finition tranche | M5: Sophie Laurent | N5: Valide
A6: RPT-2026-Q1-002 | B6: Fevrier 2026 | C6: Atelier Maroquinerie Paris | D6: Maroquinerie | E6: =IFERROR(COUNTIFS('3_CONTROLES'!J$5:J$5000,C6),0) | F6: =IFERROR(COUNTIFS('3_CONTROLES'!J$5:J$5000,C6,'3_CONTROLES'!K$5:K$5000,"Conforme"),0) | G6: =IFERROR(COUNTIFS('3_CONTROLES'!J$5:J$5000,C6,'3_CONTROLES'!K$5:K$5000,"Non conforme"),0) | H6: =IFERROR(F6/COUNTIFS('3_CONTROLES'!J$5:J$5000,C6,'3_CONTROLES'!K$5:K$5000,"<>En attente"),0) | I6: =IFERROR(AVERAGEIFS('3_CONTROLES'!L$5:L$5000,'3_CONTROLES'!J$5:J$5000,C6,'3_CONTROLES'!L$5:L$5000,">0"),0) | J6: 1. Qualite cuir (2) 2. Finition tranche (2) 3. Quincaillerie (1) | K6: Stable | L6: Installation eclairage LED poste tri — Suivi plan tranche | M6: Sophie Laurent | N6: Valide
A7: RPT-2026-Q1-003 | B7: Mars 2026 | C7: Atelier Maroquinerie Paris | D7: Maroquinerie | E7: =IFERROR(COUNTIFS('3_CONTROLES'!J$5:J$5000,C7),0) | F7: =IFERROR(COUNTIFS('3_CONTROLES'!J$5:J$5000,C7,'3_CONTROLES'!K$5:K$5000,"Conforme"),0) | G7: =IFERROR(COUNTIFS('3_CONTROLES'!J$5:J$5000,C7,'3_CONTROLES'!K$5:K$5000,"Non conforme"),0) | H7: =IFERROR(F7/COUNTIFS('3_CONTROLES'!J$5:J$5000,C7,'3_CONTROLES'!K$5:K$5000,"<>En attente"),0) | I7: =IFERROR(AVERAGEIFS('3_CONTROLES'!L$5:L$5000,'3_CONTROLES'!J$5:J$5000,C7,'3_CONTROLES'!L$5:L$5000,">0"),0) | J7: 1. Piqure irreguliere (1) 2. Griffure cuir (1) | K7: Amelioration | L7: Plan d'action eclairage deploye — Resultats positifs observes | M7: Sophie Laurent | N7: Valide
A8: RPT-2026-Q1-004 | B8: Janvier 2026 | C8: Atelier Haute Joaillerie Vendome | D8: Joaillerie | E8: =IFERROR(COUNTIFS('3_CONTROLES'!J$5:J$5000,C8),0) | F8: =IFERROR(COUNTIFS('3_CONTROLES'!J$5:J$5000,C8,'3_CONTROLES'!K$5:K$5000,"Conforme"),0) | G8: =IFERROR(COUNTIFS('3_CONTROLES'!J$5:J$5000,C8,'3_CONTROLES'!K$5:K$5000,"Non conforme"),0) | H8: =IFERROR(F8/COUNTIFS('3_CONTROLES'!J$5:J$5000,C8,'3_CONTROLES'!K$5:K$5000,"<>En attente"),0) | I8: =IFERROR(AVERAGEIFS('3_CONTROLES'!L$5:L$5000,'3_CONTROLES'!J$5:J$5000,C8,'3_CONTROLES'!L$5:L$5000,">0"),0) | J8: 1. Micro-rayure polissage (1) | K8: Stable | L8: Reorganisation postes de travail — Separation pieces en cours | M8: Alain Mercier | N8: Valide
A9: RPT-2026-Q1-005 | B9: Fevrier 2026 | C9: Atelier Haute Joaillerie Vendome | D9: Joaillerie | E9: =IFERROR(COUNTIFS('3_CONTROLES'!J$5:J$5000,C9),0) | F9: =IFERROR(COUNTIFS('3_CONTROLES'!J$5:J$5000,C9,'3_CONTROLES'!K$5:K$5000,"Conforme"),0) | G9: =IFERROR(COUNTIFS('3_CONTROLES'!J$5:J$5000,C9,'3_CONTROLES'!K$5:K$5000,"Non conforme"),0) | H9: =IFERROR(F9/COUNTIFS('3_CONTROLES'!J$5:J$5000,C9,'3_CONTROLES'!K$5:K$5000,"<>En attente"),0) | I9: =IFERROR(AVERAGEIFS('3_CONTROLES'!L$5:L$5000,'3_CONTROLES'!J$5:J$5000,C9,'3_CONTROLES'!L$5:L$5000,">0"),0) | J9: Aucun defaut | K9: Amelioration | L9: RAS — Excellence maintenue | M9: Alain Mercier | N9: Valide
A10: RPT-2026-Q1-006 | B10: Mars 2026 | C10: Atelier Haute Joaillerie Vendome | D10: Joaillerie | E10: =IFERROR(COUNTIFS('3_CONTROLES'!J$5:J$5000,C10),0) | F10: =IFERROR(COUNTIFS('3_CONTROLES'!J$5:J$5000,C10,'3_CONTROLES'!K$5:K$5000,"Conforme"),0) | G10: =IFERROR(COUNTIFS('3_CONTROLES'!J$5:J$5000,C10,'3_CONTROLES'!K$5:K$5000,"Non conforme"),0) | H10: =IFERROR(F10/COUNTIFS('3_CONTROLES'!J$5:J$5000,C10,'3_CONTROLES'!K$5:K$5000,"<>En attente"),0) | I10: =IFERROR(AVERAGEIFS('3_CONTROLES'!L$5:L$5000,'3_CONTROLES'!J$5:J$5000,C10,'3_CONTROLES'!L$5:L$5000,">0"),0) | J10: Aucun defaut | K10: Amelioration | L10: RAS — Preparation piece Haute Joaillerie complexe (47 saphirs) | M10: Alain Mercier | N10: Valide
A11: RPT-2026-Q1-007 | B11: Q1 2026 | C11: Atelier Horlogerie Geneve | D11: Horlogerie | E11: =IFERROR(COUNTIFS('3_CONTROLES'!J$5:J$5000,C11),0) | F11: =IFERROR(COUNTIFS('3_CONTROLES'!J$5:J$5000,C11,'3_CONTROLES'!K$5:K$5000,"Conforme"),0) | G11: =IFERROR(COUNTIFS('3_CONTROLES'!J$5:J$5000,C11,'3_CONTROLES'!K$5:K$5000,"Non conforme"),0) | H11: =IFERROR(F11/COUNTIFS('3_CONTROLES'!J$5:J$5000,C11,'3_CONTROLES'!K$5:K$5000,"<>En attente"),0) | I11: =IFERROR(AVERAGEIFS('3_CONTROLES'!L$5:L$5000,'3_CONTROLES'!J$5:J$5000,C11,'3_CONTROLES'!L$5:L$5000,">0"),0) | J11: 1. Perlage irregulier (1 obs.) | K11: Stable | L11: Formation perlage Isabelle Martin — Preparation Poincon de Geneve | M11: Pierre Fontaine | N11: Valide
A12: RPT-2026-Q2-008 | B12: Avril 2026 (partiel) | C12: Atelier PAP Milan | D12: Pret-a-Porter | E12: =IFERROR(COUNTIFS('3_CONTROLES'!J$5:J$5000,C12),0) | F12: =IFERROR(COUNTIFS('3_CONTROLES'!J$5:J$5000,C12,'3_CONTROLES'!K$5:K$5000,"Conforme"),0) | G12: =IFERROR(COUNTIFS('3_CONTROLES'!J$5:J$5000,C12,'3_CONTROLES'!K$5:K$5000,"Non conforme"),0) | H12: =IFERROR(F12/COUNTIFS('3_CONTROLES'!J$5:J$5000,C12,'3_CONTROLES'!K$5:K$5000,"<>En attente"),0) | I12: =IFERROR(AVERAGEIFS('3_CONTROLES'!L$5:L$5000,'3_CONTROLES'!J$5:J$5000,C12,'3_CONTROLES'!L$5:L$5000,">0"),0) | J12: 1. Solidite teinture soie (2 CRIT) 2. Raccord motif (1) 3. Boutonniere (1) | K12: Degradation | L12: ALERTE — Probleme fournisseur Seteria Bianchi — Audit urgent teinture | M12: Marco Ricci | N12: En cours

Sheet 8_KPI_QUALITE
A1: KPI QUALITE & ROI — AGENT ARTISANALQUALITYAI
A2: Indicateurs de performance qualite artisanale — Calcul ROI automatise — Avril 2026
A4: SECTION A — KPIs QUALITE ARTISANALE
A5: ID_KPI | B5: Indicateur | C5: Categorie | D5: Unite | E5: Cible | F5: Valeur actuelle | G5: % Atteinte | H5: Tendance | I5: Source donnees | J5: Frequence | K5: Responsable | L5: Commentaire
A6: KQ-001 | B6: First Pass Yield global | C6: Performance | D6: % | E6: 95 | F6: =IFERROR(COUNTIF('3_CONTROLES'!K$5:K$5000,"Conforme")/COUNTIFS('3_CONTROLES'!K$5:K$5000,"<>En attente")*100,0) | G6: =IFERROR(IF(D6="%",IF(E6>F6,F6/E6,(100-F6)/(100-E6)),F6/E6),"-") | I6: 3_CONTROLES | J6: Mensuel | K6: Dir. Qualite | L6: % pieces conformes des le 1er controle
A7: KQ-002 | B7: Score qualite moyen | C7: Performance | D7: /100 | E7: 92 | F7: =IFERROR(AVERAGEIF('3_CONTROLES'!L$5:L$5000,">0"),0) | G7: =IFERROR(IF(D7="%",IF(E7>F7,F7/E7,(100-F7)/(100-E7)),F7/E7),"-") | I7: 3_CONTROLES | J7: Mensuel | K7: Dir. Qualite | L7: Moyenne ponderee tous ateliers
A8: KQ-003 | B8: Taux de defauts critiques | C8: Defauts | D8: % | E8: 0 | F8: =IFERROR(COUNTIF('4_DEFAUTS'!H$5:H$5000,"Critique")/COUNTA('4_DEFAUTS'!A$5:A$5000)*100,0) | G8: =IFERROR(IF(D8="%",IF(E8>F8,F8/E8,(100-F8)/(100-E8)),F8/E8),"-") | I8: 4_DEFAUTS | J8: Hebdomadaire | K8: Dir. Qualite | L8: Objectif zero defaut critique
A9: KQ-004 | B9: Cout total non-qualite | C9: Financier | D9: EUR/mois | E9: 5000 | F9: =IFERROR(SUM('4_DEFAUTS'!M$5:M$5000),0) | G9: =IFERROR(IF(D9="%",IF(E9>F9,F9/E9,(100-F9)/(100-E9)),F9/E9),"-") | I9: 4_DEFAUTS | J9: Mensuel | K9: Dir. Finance | L9: Couts reprises + rebuts + retours
A10: KQ-005 | B10: Taux de retour client | C10: Client | D10: % | E10: 0.5 | G10: =IFERROR(IF(D10="%",IF(E10>F10,F10/E10,(100-F10)/(100-E10)),F10/E10),"-") | I10: Donnees SAV (ext.) | J10: Mensuel | K10: Dir. Commercial | L10: Retours lies a un defaut qualite
A11: KQ-006 | B11: Nb artisans Maitre d'Art / MOF | C11: Capital humain | D11: Nb | E11: =COUNTA('6_ARTISANS'!A$5:A$5000) | F11: =COUNTIF('6_ARTISANS'!H$5:H$5000,"Maitre*") | G11: =IFERROR(IF(D11="%",IF(E11>F11,F11/E11,(100-F11)/(100-E11)),F11/E11),"-") | I11: 6_ARTISANS | J11: Annuel | K11: Dir. RH | L11: Indicateur excellence savoir-faire
A12: KQ-007 | B12: Heures formation qualite / artisan / an | C12: Formation | D12: h | E12: 40 | F12: =IFERROR(AVERAGE('6_ARTISANS'!M$5:M$5000),0) | G12: =IFERROR(IF(D12="%",IF(E12>F12,F12/E12,(100-F12)/(100-E12)),F12/E12),"-") | I12: 6_ARTISANS | J12: Trimestriel | K12: Dir. RH + Qualite | L12: Minimum 40h/an pour maintien excellence
A13: KQ-008 | B13: Taux de certification ateliers | C13: Certification | D13: % | E13: 100 | F13: =IFERROR(COUNTIF('5_ATELIERS'!M$5:M$5000,"Actif")/COUNTA('5_ATELIERS'!A$5:A$5000)*100,0) | G13: =IFERROR(IF(D13="%",IF(E13>F13,F13/E13,(100-F13)/(100-E13)),F13/E13),"-") | I13: 5_ATELIERS | J13: Annuel | K13: Dir. Qualite | L13: Tous ateliers ISO 9001 ou equivalent
A14: KQ-009 | B14: Delai moyen resolution defaut | C14: Reactivite | D14: jours | E14: 3 | F14: 2.5 | G14: =IFERROR(IF(D14="%",IF(E14>F14,F14/E14,(100-F14)/(100-E14)),F14/E14),"-") | I14: 4_DEFAUTS | J14: Mensuel | K14: Dir. Qualite | L14: De detection a resolution complete
A15: KQ-010 | B15: Taux de reprise vs rejet | C15: Economie | D15: % | E15: 80 | F15: =IFERROR(COUNTIF('4_DEFAUTS'!O$5:O$5000,"Resolu")/COUNTA('4_DEFAUTS'!A$5:A$5000)*100,0) | G15: =IFERROR(IF(D15="%",IF(E15>F15,F15/E15,(100-F15)/(100-E15)),F15/E15),"-") | I15: 4_DEFAUTS | J15: Mensuel | K15: Dir. Production | L15: % defauts resolus par reprise (vs rejet piece)
A19: SECTION B — CALCUL ROI AGENT ARTISANALQUALITYAI
A20: Poste | B20: Description | C20: Avant Agent (EUR/an) | D20: Apres Agent (EUR/an) | E20: Economie (EUR/an) | F20: % Reduction | G20: Temps avant (h/mois) | H20: Temps apres (h/mois) | I20: Heures gagnees | J20: ETP liberes | K20: Source | L20: Notes
A21: Inspection qualite manuelle | B21: Temps inspecteurs sur controles visuels et mesures | C21: 220000 | D21: =IFERROR(C21*0.30,0) | E21: =C21-D21 | F21: =IFERROR(E21/C21,0) | G21: 360 | H21: =IFERROR(G21*0.30,0) | I21: =G21-H21 | J21: =IFERROR(I21/151.67,0) | K21: Benchmark KPMG 2026 | L21: Automatisation partielle par vision IA
A22: Documentation qualite | B22: Redaction rapports, fiches controle, archivage | C22: 85000 | D22: =IFERROR(C22*0.30,0) | E22: =C22-D22 | F22: =IFERROR(E22/C22,0) | G22: 140 | H22: =IFERROR(G22*0.30,0) | I22: =G22-H22 | J22: =IFERROR(I22/151.67,0) | K22: Interne | L22: Generation automatique rapports QC
A23: Gestion des non-conformites | B23: Detection, investigation, traitement, suivi | C23: 130000 | D23: =IFERROR(C23*0.30,0) | E23: =C23-D23 | F23: =IFERROR(E23/C23,0) | G23: 180 | H23: =IFERROR(G23*0.30,0) | I23: =G23-H23 | J23: =IFERROR(I23/151.67,0) | K23: Interne | L23: Workflow automatise + alertes proactives
A24: Formation et evaluation | B24: Suivi competences, plans formation, evaluations | C24: 60000 | D24: =IFERROR(C24*0.30,0) | E24: =C24-D24 | F24: =IFERROR(E24/C24,0) | G24: 80 | H24: =IFERROR(G24*0.30,0) | I24: =G24-H24 | J24: =IFERROR(I24/151.67,0) | K24: DRH | L24: Tableaux de bord competences automatises
A25: Couts de non-qualite evites | B25: Reprises, rebuts, retours clients reduits | C25: 350000 | D25: =IFERROR(C25*0.30,0) | E25: =C25-D25 | F25: =IFERROR(E25/C25,0) | G25: 0 | H25: 0 | I25: =G25-H25 | J25: =IFERROR(I25/151.67,0) | K25: Qualite | L25: Reduction estimee 45% des couts non-qualite
A26: Cout Agent IA | B26: Licence, maintenance, formation utilisateurs | C26: 0 | D26: 75000 | E26: =C26-D26 | F26: =IFERROR(E26/C26,0) | G26: 0 | H26: 30 | I26: =G26-H26 | J26: =IFERROR(I26/151.67,0) | K26: Devis Neural Enterprise | L26: Cout annuel tout compris
A27: TOTAL ROI | C27: =SUM(C21:C26) | D27: =SUM(D21:D26) | E27: =SUM(E21:E26) | F27: =IFERROR(E27/C27,0) | G27: =SUM(G21:G26) | H27: =SUM(H21:H26) | I27: =SUM(I21:I26) | J27: =SUM(J21:J26)
A30: SYNTHESE ROI
A31: ROI annuel net | D31: =E27
A32: ROI en % | D32: =IFERROR(E27/D27,0)
A33: Heures economisees / mois | D33: =I27
A34: ETP liberes | D34: =J27
A35: Payback (mois) | D35: =IFERROR(D27/(E27/12),0)
