Workbook
Name Poste_Botterie: "'_REF_POSTES'!$G$2:$G$11"
Name Poste_Chapellerie: "'_REF_POSTES'!$F$2:$F$11"
Name Poste_Couture: "'_REF_POSTES'!$E$2:$E$11"
Name Poste_Ganterie: "'_REF_POSTES'!$H$2:$H$11"
Name Poste_Horlogerie: "'_REF_POSTES'!$K$2:$K$11"
Name Poste_Joaillerie: "'_REF_POSTES'!$D$2:$D$11"
Name Poste_Maroquinerie: "'_REF_POSTES'!$A$2:$A$11"
Name Poste_Orfevrerie: "'_REF_POSTES'!$C$2:$C$11"
Name Poste_Parfumerie: "'_REF_POSTES'!$J$2:$J$11"
Name Poste_Sellerie: "'_REF_POSTES'!$B$2:$B$11"
Name Poste_Soierie: "'_REF_POSTES'!$I$2:$I$11"

Sheet Claude Log
A1: Tour # | B1: Date | C1: Demande utilisateur | D1: Action effectuée | E1: Détails | F1: Résultat
A2: 1 | B2: 46113 | C2: Analyser et appliquer 4 correctifs de formules détectés (erreurs #11 à #14) sur le fichier NEURAL_LuxeOnboarding.xlsx | D2: Correctifs appliqués sur 06_EVALUATIONS (H14) et 07_PROBATION (B22). Confirmé non-applicabilité de #11 et #12. | E2: #11 PARCOURS : formule avancement B3 déjà correcte (parenthèses OK dans dénominateur COUNTIF). #12 CHECKLIST : délais déjà numériques en colonne D, pas de texte 'J+30'. #13 EVALUATIONS H14 : ajout IF(OR(G14="",F14=""),"—",...) pour éviter faux ↘️ sur données vides. #14 PROBATION B22 : nouvelle logique pondérée — Technique (C16) ET Culture (C18) = critères bloquants ; si l'un ou l'autre est ❌, recommandation NE PAS VALIDER indépendamment du total. | F2: H14 (06_EVALUATIONS) : tendance protégée contre les vides — affiche '—' si G14 ou F14 vide. B22 (07_PROBATION) : logique à 4 niveaux avec pondération critères critiques. 2 formules corrigées, 2 erreurs signalées comme déjà correctes.
A3: 2 | B3: 46113 | C3: Analyser tous les onglets pour détecter les erreurs # et formules cassées | D3: 5 bugs corrigés sur 3 feuilles : 08_DASHBOARD (C17, C18, E6), 07_PROBATION (C7, C8, C9), 05_BUDDY (C22:C25) | E3: #VALEUR! Dashboard C17/C18 : TEXT(0,"DD/MM/YYYY") quand date entrée vide → protégé avec IFERROR+IF vide. Probation C7 : TODAY()-0=46113j → protégé. Probation C9 : avancement inversé (C17-TODAY)/(C19-C17) au lieu de (TODAY-C17)/(C19-C17) → corrigé. Buddy C22:C25 : AVERAGE retournait 0 au lieu de — → remplacé par AVERAGEIF(>0) avec garde COUNTA=0. Dashboard E6 : logique statut non alignée avec pondération critiques → synchro avec 07_PROBATION!B22. | F3: C17/C18 Dashboard : affichent 'Non renseignée' / '—'. C7/C8 Probation : affichent '—'. C9 Probation : vide (normal, date non saisie). C22:C25 Buddy : affichent '—'. E6 Dashboard : logique pondérée active.
A4: 3 | B4: 46113 | C4: Corriger la colonne E (Date cible) de 02_PARCOURS — affichait des entiers bruts (-30, -21, 1...) au lieu de dates | D4: 26 formules colonne E réécrites avec garde IF vide + TEXT en format DD/MM/YY | E4: Problème : '01_PARAMETRES'!C17+(-30) avec C17=0 donnait -30 (entier brut). Solution : IF(C17="","—",TEXT(C17+offset,"DD/MM/YY")) sur les 26 lignes actives (E7:E11, E13:E18, E20:E24, E26:E30, E32:E36). Cellules de section (E6, E12, E19, E25, E31) laissées vides car lignes d'en-tête. | F4: Toutes les 26 cellules affichent — (date entrée non saisie). Dès saisie en 01_PARAMETRES!C17, afficheront les dates formatées ex. 01/03/25.
A5: 4 | B5: 46113 | C5: Ajouter un menu déroulant sur 01_PARAMETRES!C8 (Poste/Fonction) — postes pertinents en Parfumerie / Louis Vuitton | D5: Data validation ajoutée avec 12 postes Parfumerie + message d'aide + alerte souple (Warning) | E5: Postes : Nez/Parfumeur, Évaluateur Parfums, Chef de Projet Parfums, Technicien Formulation, Resp. Développement Olfactif, Artisan Conditionneur, Contrôleur Qualité Parfums, Resp. Réglementaire Cosmétique, Chef de Produit Parfums, Opérateur Production Parfumerie, Gestionnaire Matières Premières, Directeur Artistique Olfactif. Style Warning pour permettre la saisie libre. | F5: Menu déroulant actif sur C8. L'utilisateur peut choisir dans la liste ou saisir manuellement un autre poste.
A6: 5 | B6: 46113 | C6: Créer un menu déroulant dynamique sur C8 (Poste) lié au métier d'art C9 — avec des postes pertinents pour chaque métier | D6: Création onglet _REF_POSTES (caché) avec 11 colonnes × 10 postes + 11 plages nommées + validation INDIRECT dynamique sur C8 | E6: 11 métiers : Maroquinerie, Sellerie, Orfèvrerie, Joaillerie, Couture, Chapellerie, Botterie, Ganterie, Soierie, Parfumerie, Horlogerie. 10 postes spécifiques par métier. Plages nommées Poste_Maroquinerie etc. Formule INDIRECT avec SUBSTITUTE pour gérer accents (è→e, é→e, etc.). Mode Warning pour autoriser saisie libre. | F6: C8 propose désormais une liste dynamique selon le métier C9. Ex : Maroquinerie → Artisan Maroquinier, Coupeur Cuir, Piqueur... Changement de C9 = la liste C8 se met à jour automatiquement.
A7: 6 | B7: 46113 | C7: Le menu déroulant dynamique de C8 ne s'affichait pas au clic — la formule INDIRECT(SUBSTITUTE(...)) dans la validation n'était pas supportée par Excel | D7: Remplacé par cellule helper Z1 cachée + INDIRECT(Z1) simple dans la validation | E7: Cause : Excel Online ne supporte pas les formules SUBSTITUTE imbriquées dans les règles de validation de données. Solution : Z1 contient la formule de conversion (métier→nom de plage), et la validation pointe simplement =INDIRECT(Z1). Colonne Z masquée (largeur 0 + texte blanc). | F7: Menu déroulant C8 désormais fonctionnel. Testé avec C9=Horlogerie → 10 postes Horlogerie affichés.
A8: 7 | B8: 46113 | C8: Le menu déroulant C8 ne s'affichait toujours pas malgré INDIRECT(Z1) — problème de compatibilité Excel Online avec INDIRECT dans les validations | D8: Refonte complète : colonne dynamique M dans _REF_POSTES via INDEX/MATCH + validation pointant vers plage fixe M2:M11. Suppression helper Z1. | E8: Cause racine : Excel Online ne résout pas INDIRECT() dans les data validations (bug connu). Solution : _REF_POSTES!M2:M11 contient 10 formules INDEX($A$2:$K$11,ROW()-1,MATCH('01_PARAMETRES'!$C$9,$A$1:$K$1,0)) qui se recalculent quand C9 change. La validation pointe vers cette plage fixe =_REF_POSTES!$M$2:$M$11 — pas d'INDIRECT. | F8: Vérifié : C9=Joaillerie → M2:M11 = 10 postes joaillerie. Validation type=List, source=plage fixe. Cellule helper Z1 nettoyée.
A9: 8 | B9: 46113 | C9: Erreurs #VALEUR! sur toute la colonne E de 02_PARCOURS et dans 08_DASHBOARD après saisie de la date d'entrée | D9: Correction du format TEXT() : DD/MM/YY → jj/mm/aa (Excel français) sur 26 cellules E7:E36, plus C17, C18, D7, B2 du dashboard | E9: Cause : Excel en configuration française utilise jj/mm/aa au lieu de dd/mm/yy dans la fonction TEXT(). Tous les TEXT() du classeur ont été scannés et corrigés (30 cellules au total). Dernier trouvé : B2 du dashboard avec DD/MM/YYYY → jj/mm/aaaa. | F9: E7:E36 : dates affichées correctement (02/03/26 à 01/04/27). Dashboard C17=01/04/26, C18=30/06/26, D7=Fin:30/06/26, B2=titre dynamique complet. Plus aucun TEXT(DD/MM) dans le classeur.
A10: 9 | B10: 46113 | C10: Appliquer les améliorations AUTO-11 à AUTO-15 proposées | D10: AUTO-12 : alertes 3 niveaux (✅/🟡/🔴) sur 04_CHECKLIST G6:G13. AUTO-13 : tendance glissante robuste H14 (COUNT numeric). AUTO-14 : poids E16:E20 + LET pondéré B22 + score D22. AUTO-15 : à traiter (attente accès LuxeArtisanTalent). AUTO-11 : non modifié (formule existante correcte). | E10: AUTO-12 : 3 niveaux — Fait ✅, 🟡 Échéance dans X j (7j avant), 🔴 EN RETARD de X j. AUTO-13 : COUNT(C14:G14)<2 → —, sinon compare les 2 dernières évals non vides avec IFERROR+INDEX+MATCH. AUTO-14 : colonne E poids (30/15/25/15/15%), LET avec sc=SUMPRODUCT, critiques=AND(Technique+Culture), TRIM(faibles) pour lister points à travailler. Dashboard E6 aligné avec score%. | F10: G6=🟡 Échéance dans 1j (correct, date entrée=aujourd'hui). H14=— (correct, 0 évals). B22=🔴 NE PAS VALIDER — Critères critiques : Culture. D22=Score pondéré 45%. E6 Dashboard=🔴 À RISQUE — 45%.

Sheet 01_PARAMETRES
B2: ⚙️ NEURAL — Paramètres d'Onboarding
B3: Configurez ici le profil — toutes les données se propagent automatiquement
B5: 🏛️ IDENTITÉ DE LA MAISON
B6: Maison | C6: Louis Vuitton | D6: Sélectionner dans la liste ▼
B7: Nouveau collaborateur | C7: Labeaut Ludovic | D7: Prénom NOM
B8: Poste / Fonction | C8: Étireur Peaux Ganterie | D8: Liste adaptée au métier ▼
B9: Métier d'art | C9: Ganterie | D9: Sélectionner dans la liste ▼
B10: Niveau d'entrée | C10: N1 | D10: N1 à N5
B11: Site / Atelier | D11: Ex : Atelier Pantin
B12: Manager | D12: Prénom NOM Manager
B13: Buddy / Mentor | D13: Prénom NOM Artisan Senior
B16: 📅 DATES & CONTRAT
B17: Date d'entrée | C17: 46113
B18: Durée essai (jours) | C18: =IF(C10<="N3",90,120) -> 90
B19: Fin de période d'essai | C19: =IF(C17="","",C17+C18) -> 46203
B20: Renouvellement PE | C20: Oui
B21: Type de contrat | C21: CDD
B24: NEURAL — Intelligence Augmentée pour l'Entreprise | Données confidentielles — Usage interne

Sheet 02_PARCOURS
B2: 📋 PARCOURS ONBOARDING — Timeline J-30 → J+365
B3: =IFERROR("Avancement : "&TEXT(COUNTIF(F6:F60,"☑")/(COUNTIF(F6:F60,"☑")+COUNTIF(F6:F60,"☐")),"0%")&" ("&COUNTIF(F6:F60,"☑")&"/"&(COUNTIF(F6:F60,"☑")+COUNTIF(F6:F60,"☐"))&" actions complétées)","Aucune action saisie") -> Avancement : 0% (0/26 actions complétées)
B5: Jalon | C5: Action / Étape | D5: Responsable | E5: Date cible | F5: Fait | G5: Alerte
B6: ── PRÉ-ONBOARDING (J-30 → J0) ──
B7: J-30 | C7: Welcome pack maison envoyé | D7: RH | E7: =IF('01_PARAMETRES'!$C$17="","—",TEXT('01_PARAMETRES'!$C$17-30,"jj/mm/aa")) -> 02/03/26 | F7: ☐ | G7: =IF(AND(F7="☐",'01_PARAMETRES'!$C$17+-30<TODAY()),"⚠️ En retard","") -> ⚠️ En retard
B8: J-21 | C8: Accès IT préparés | D8: SI / IT | E8: =IF('01_PARAMETRES'!$C$17="","—",TEXT('01_PARAMETRES'!$C$17-21,"jj/mm/aa")) -> 11/03/26 | F8: ☐ | G8: =IF(AND(F8="☐",'01_PARAMETRES'!$C$17+-21<TODAY()),"⚠️ En retard","") -> ⚠️ En retard
B9: J-14 | C9: Poste / atelier préparé + outillage | D9: Logistique | E9: =IF('01_PARAMETRES'!$C$17="","—",TEXT('01_PARAMETRES'!$C$17-14,"jj/mm/aa")) -> 18/03/26 | F9: ☐ | G9: =IF(AND(F9="☐",'01_PARAMETRES'!$C$17+-14<TODAY()),"⚠️ En retard","") -> ⚠️ En retard
B10: J-7 | C10: Buddy informé & briefé | D10: Manager | E10: =IF('01_PARAMETRES'!$C$17="","—",TEXT('01_PARAMETRES'!$C$17-7,"jj/mm/aa")) -> 25/03/26 | F10: ☐ | G10: =IF(AND(F10="☐",'01_PARAMETRES'!$C$17+-7<TODAY()),"⚠️ En retard","") -> ⚠️ En retard
B11: J-3 | C11: Programme J1-J5 envoyé au collaborateur | D11: RH | E11: =IF('01_PARAMETRES'!$C$17="","—",TEXT('01_PARAMETRES'!$C$17-3,"jj/mm/aa")) -> 29/03/26 | F11: ☐ | G11: =IF(AND(F11="☐",'01_PARAMETRES'!$C$17+-3<TODAY()),"⚠️ En retard","") -> ⚠️ En retard
B12: ── SEMAINE 1 — IMMERSION ──
B13: J+1 | C13: Accueil RH (contrat, admin, visite site) | D13: RH | E13: =IF('01_PARAMETRES'!$C$17="","—",TEXT('01_PARAMETRES'!$C$17+1,"jj/mm/aa")) -> 02/04/26 | F13: ☐ | G13: =IF(AND(F13="☐",'01_PARAMETRES'!$C$17+1<TODAY()),"⚠️ En retard","")
B14: J+1 | C14: Rencontre buddy / mentor | D14: Buddy | E14: =IF('01_PARAMETRES'!$C$17="","—",TEXT('01_PARAMETRES'!$C$17+1,"jj/mm/aa")) -> 02/04/26 | F14: ☐ | G14: =IF(AND(F14="☐",'01_PARAMETRES'!$C$17+1<TODAY()),"⚠️ En retard","")
B15: J+2 | C15: Histoire de la Maison (→ 03_CULTURE) | D15: Dir. Patrimoine | E15: =IF('01_PARAMETRES'!$C$17="","—",TEXT('01_PARAMETRES'!$C$17+2,"jj/mm/aa")) -> 03/04/26 | F15: ☐ | G15: =IF(AND(F15="☐",'01_PARAMETRES'!$C$17+2<TODAY()),"⚠️ En retard","")
B16: J+3 | C16: Visite atelier principal | D16: Chef atelier | E16: =IF('01_PARAMETRES'!$C$17="","—",TEXT('01_PARAMETRES'!$C$17+3,"jj/mm/aa")) -> 04/04/26 | F16: ☐ | G16: =IF(AND(F16="☐",'01_PARAMETRES'!$C$17+3<TODAY()),"⚠️ En retard","")
B17: J+4 | C17: Présentation des collections | D17: Studio | E17: =IF('01_PARAMETRES'!$C$17="","—",TEXT('01_PARAMETRES'!$C$17+4,"jj/mm/aa")) -> 05/04/26 | F17: ☐ | G17: =IF(AND(F17="☐",'01_PARAMETRES'!$C$17+4<TODAY()),"⚠️ En retard","")
B18: J+5 | C18: Premier geste en atelier | D18: Mentor | E18: =IF('01_PARAMETRES'!$C$17="","—",TEXT('01_PARAMETRES'!$C$17+5,"jj/mm/aa")) -> 06/04/26 | F18: ☐ | G18: =IF(AND(F18="☐",'01_PARAMETRES'!$C$17+5<TODAY()),"⚠️ En retard","")
B19: ── SEMAINE 2-4 — INTÉGRATION ──
B20: J+8 | C20: Formation sécurité au poste | D20: HSE | E20: =IF('01_PARAMETRES'!$C$17="","—",TEXT('01_PARAMETRES'!$C$17+8,"jj/mm/aa")) -> 09/04/26 | F20: ☐ | G20: =IF(AND(F20="☐",'01_PARAMETRES'!$C$17+8<TODAY()),"⚠️ En retard","")
B21: J+10 | C21: Formation qualité maison | D21: Dir. Qualité | E21: =IF('01_PARAMETRES'!$C$17="","—",TEXT('01_PARAMETRES'!$C$17+10,"jj/mm/aa")) -> 11/04/26 | F21: ☐ | G21: =IF(AND(F21="☐",'01_PARAMETRES'!$C$17+10<TODAY()),"⚠️ En retard","")
B22: J+15 | C22: 1er point buddy | D22: Buddy | E22: =IF('01_PARAMETRES'!$C$17="","—",TEXT('01_PARAMETRES'!$C$17+15,"jj/mm/aa")) -> 16/04/26 | F22: ☐ | G22: =IF(AND(F22="☐",'01_PARAMETRES'!$C$17+15<TODAY()),"⚠️ En retard","")
B23: J+21 | C23: Formation anti-corruption (Sapin II) | D23: Compliance | E23: =IF('01_PARAMETRES'!$C$17="","—",TEXT('01_PARAMETRES'!$C$17+21,"jj/mm/aa")) -> 22/04/26 | F23: ☐ | G23: =IF(AND(F23="☐",'01_PARAMETRES'!$C$17+21<TODAY()),"⚠️ En retard","")
B24: J+25 | C24: Formation export control | D24: Juridique | E24: =IF('01_PARAMETRES'!$C$17="","—",TEXT('01_PARAMETRES'!$C$17+25,"jj/mm/aa")) -> 26/04/26 | F24: ☐ | G24: =IF(AND(F24="☐",'01_PARAMETRES'!$C$17+25<TODAY()),"⚠️ En retard","")
B25: ── MOIS 2-3 — MONTÉE EN COMPÉTENCE ──
B26: J+30 | C26: 🎯 ÉVALUATION 30 JOURS | D26: Manager + RH | E26: =IF('01_PARAMETRES'!$C$17="","—",TEXT('01_PARAMETRES'!$C$17+30,"jj/mm/aa")) -> 01/05/26 | F26: ☐ | G26: =IF(AND(F26="☐",'01_PARAMETRES'!$C$17+30<TODAY()),"🔴 RETARD","")
B27: J+45 | C27: Premier projet autonome | D27: Mentor | E27: =IF('01_PARAMETRES'!$C$17="","—",TEXT('01_PARAMETRES'!$C$17+45,"jj/mm/aa")) -> 16/05/26 | F27: ☐ | G27: =IF(AND(F27="☐",'01_PARAMETRES'!$C$17+45<TODAY()),"⚠️ En retard","")
B28: J+60 | C28: 🎯 ÉVALUATION 60 JOURS | D28: Manager + RH | E28: =IF('01_PARAMETRES'!$C$17="","—",TEXT('01_PARAMETRES'!$C$17+60,"jj/mm/aa")) -> 31/05/26 | F28: ☐ | G28: =IF(AND(F28="☐",'01_PARAMETRES'!$C$17+60<TODAY()),"🔴 RETARD","")
B29: J+75 | C29: Visite fournisseur / tannerie | D29: Achats | E29: =IF('01_PARAMETRES'!$C$17="","—",TEXT('01_PARAMETRES'!$C$17+75,"jj/mm/aa")) -> 15/06/26 | F29: ☐ | G29: =IF(AND(F29="☐",'01_PARAMETRES'!$C$17+75<TODAY()),"⚠️ En retard","")
B30: J+90 | C30: 🎯 ÉVALUATION 90 JOURS + Décision essai | D30: Manager + RH | E30: =IF('01_PARAMETRES'!$C$17="","—",TEXT('01_PARAMETRES'!$C$17+90,"jj/mm/aa")) -> 30/06/26 | F30: ☐ | G30: =IF(AND(F30="☐",'01_PARAMETRES'!$C$17+90<TODAY()),"🔴 RETARD","")
B31: ── MOIS 4-12 — CONSOLIDATION ──
B32: J+120 | C32: Formation CSRD / développement durable | D32: RSE | E32: =IF('01_PARAMETRES'!$C$17="","—",TEXT('01_PARAMETRES'!$C$17+120,"jj/mm/aa")) -> 30/07/26 | F32: ☐ | G32: =IF(AND(F32="☐",'01_PARAMETRES'!$C$17+120<TODAY()),"⚠️ En retard","")
B33: J+150 | C33: Visite boutique flagship | D33: Retail | E33: =IF('01_PARAMETRES'!$C$17="","—",TEXT('01_PARAMETRES'!$C$17+150,"jj/mm/aa")) -> 29/08/26 | F33: ☐ | G33: =IF(AND(F33="☐",'01_PARAMETRES'!$C$17+150<TODAY()),"⚠️ En retard","")
B34: J+180 | C34: 🎯 ÉVALUATION 6 MOIS | D34: Manager + RH | E34: =IF('01_PARAMETRES'!$C$17="","—",TEXT('01_PARAMETRES'!$C$17+180,"jj/mm/aa")) -> 28/09/26 | F34: ☐ | G34: =IF(AND(F34="☐",'01_PARAMETRES'!$C$17+180<TODAY()),"🔴 RETARD","")
B35: J+270 | C35: Participation événement maison (exposition…) | D35: Comms | E35: =IF('01_PARAMETRES'!$C$17="","—",TEXT('01_PARAMETRES'!$C$17+270,"jj/mm/aa")) -> 27/12/26 | F35: ☐ | G35: =IF(AND(F35="☐",'01_PARAMETRES'!$C$17+270<TODAY()),"⚠️ En retard","")
B36: J+365 | C36: 🎯 ÉVALUATION ANNUELLE + Plan de développement | D36: Manager + RH | E36: =IF('01_PARAMETRES'!$C$17="","—",TEXT('01_PARAMETRES'!$C$17+365,"jj/mm/aa")) -> 01/04/27 | F36: ☐ | G36: =IF(AND(F36="☐",'01_PARAMETRES'!$C$17+365<TODAY()),"🔴 RETARD","")
B39: Légende : | C39: Pré-onboarding | D39: Semaine 1 | E39: Semaines 2-4 | F39: Mois 2-3 | G39: Mois 4-12 | H39: 🎯 Évaluation
B40: NEURAL — Intelligence Augmentée pour l'Entreprise | Données confidentielles — Usage interne

Sheet 03_CULTURE
B2: 🏛️ CULTURE DE LA MAISON
B3: Maison sélectionnée : | C3: ='01_PARAMETRES'!C6 -> Louis Vuitton
B5: 🏛️ HISTOIRE & FONDATION
B6: Date de fondation | C6: =IFERROR(VLOOKUP('01_PARAMETRES'!$C$6,'03_CULTURE'!$B$62:$O$74,2,0),"—") -> 1854
B7: Fondateur | C7: =IFERROR(VLOOKUP('01_PARAMETRES'!$C$6,'03_CULTURE'!$B$62:$O$74,3,0),"—") -> Louis Vuitton
B8: Ville d'origine | C8: =IFERROR(VLOOKUP('01_PARAMETRES'!$C$6,'03_CULTURE'!$B$62:$O$74,4,0),"—") -> Paris
B9: Anecdote fondatrice | C9: =IFERROR(VLOOKUP('01_PARAMETRES'!$C$6,'03_CULTURE'!$B$62:$O$74,5,0),"—") -> Venu à pied de Jura à Paris à 14 ans
B11: 💎 ADN & VALEURS
B12: Valeur 1 | C12: =IFERROR(VLOOKUP('01_PARAMETRES'!$C$6,'03_CULTURE'!$B$62:$O$74,6,0),"—") -> Innovation
B13: Valeur 2 | C13: =IFERROR(VLOOKUP('01_PARAMETRES'!$C$6,'03_CULTURE'!$B$62:$O$74,7,0),"—") -> Savoir-faire
B14: Valeur 3 | C14: =IFERROR(VLOOKUP('01_PARAMETRES'!$C$6,'03_CULTURE'!$B$62:$O$74,8,0),"—") -> Voyage
B15: Devise | C15: =IFERROR(VLOOKUP('01_PARAMETRES'!$C$6,'03_CULTURE'!$B$62:$O$74,9,0),"—") -> Créer pour voyager
B17: 🎨 CODES DE LA MAISON
B18: Couleur signature | C18: =IFERROR(VLOOKUP('01_PARAMETRES'!$C$6,'03_CULTURE'!$B$62:$O$74,10,0),"—") -> Beige monogramme
B19: Matière emblématique | C19: =IFERROR(VLOOKUP('01_PARAMETRES'!$C$6,'03_CULTURE'!$B$62:$O$74,11,0),"—") -> Toile Monogram
B20: Geste signature | C20: =IFERROR(VLOOKUP('01_PARAMETRES'!$C$6,'03_CULTURE'!$B$62:$O$74,12,0),"—") -> Couture à cheval
B21: Produit iconique | C21: =IFERROR(VLOOKUP('01_PARAMETRES'!$C$6,'03_CULTURE'!$B$62:$O$74,13,0),"—") -> Speedy
B22: Dress code atelier | C22: =IFERROR(VLOOKUP('01_PARAMETRES'!$C$6,'03_CULTURE'!$B$62:$O$74,14,0),"—") -> Blouse beige monogramme
B24: 📋 COMPLIANCE LUXE — POINTS CLÉS À CONNAÎTRE
B25: ☐ Anti-corruption | C25: Loi Sapin II (France) & UK Bribery Act — aucun avantage indu, cadeaux encadrés
B26: ☐ Export control | C26: Réglementations UE/ITAR si composants américains — valider avant expédition
B27: ☐ RGPD | C27: Protection données clients VIP — accès limité, traçabilité obligatoire
B28: ☐ Propriété intellectuelle | C28: Modèles, dessins, savoir-faire protégés — NDA signé à l'entrée
B29: ☐ Devoir de vigilance | C29: Loi française 2017 — traçabilité fournisseurs, matières premières
B30: ☐ Secret de fabrication | C30: Confidentialité absolue sur les techniques et recettes maison
B32: NEURAL — Intelligence Augmentée pour l'Entreprise | Données confidentielles — Usage interne
B61: BASE DONNÉES MAISONS
B62: Maison | C62: Fondation | D62: Fondateur | E62: Ville | F62: Anecdote | G62: V1 | H62: V2 | I62: V3 | J62: Devise | K62: Couleur | L62: Matière | M62: Geste | N62: Produit | O62: DressCode
B63: Hermès | C63: 1837 | D63: Thierry Hermès | E63: Paris | F63: Né sellier pour la haute équitation | G63: Excellence artisanale | H63: Transmission | I63: Créativité | J63: Qualité sans compromis | K63: Orange vif #F96A15 | L63: Cuir Togo | M63: Point sellier double aiguille | N63: Sac Kelly | O63: Tablier cuir naturel
B64: Louis Vuitton | C64: 1854 | D64: Louis Vuitton | E64: Paris | F64: Venu à pied de Jura à Paris à 14 ans | G64: Innovation | H64: Savoir-faire | I64: Voyage | J64: Créer pour voyager | K64: Beige monogramme | L64: Toile Monogram | M64: Couture à cheval | N64: Speedy | O64: Blouse beige monogramme
B65: Chanel | C65: 1910 | D65: Gabrielle Chanel | E65: Paris | F65: Coco libère la femme du corset avec le tweed | G65: Liberté | H65: Élégance | I65: Intemporalité | J65: L'élégance c'est le refus | K65: Noir & blanc | L65: Tweed | M65: Boutonnière Camélia | N65: Sac 2.55 | O65: Tenue noire sobre
B66: Dior | C66: 1947 | D66: Christian Dior | E66: Paris | F66: Le New Look révolutionne la mode après-guerre | G66: Féminité | H66: Élégance parisienne | I66: Rêve | J66: Je construis des rêves | K66: Gris Dior | L66: Soie | M66: Coupe tailleur Bar | N66: Sac Lady Dior | O66: Blouse grise traditionnelle
B67: Cartier | C67: 1847 | D67: Louis-François Cartier | E67: Paris | F67: La panthère de Windsor : icône royale britannique | G67: Excellence | H67: Amour | I67: Innovation | J67: Joailler des rois, roi des joailliers | K67: Rouge Cartier #E4002B | L67: Platine | M67: Serti mystérieux | N67: Trinity Ring | O67: Tenue sobre noire
B68: Van Cleef & Arpels | C68: 1906 | D68: Alfred Van Cleef | E68: Paris | F68: L'Alhambra né d'une promenade à Grenade | G68: Poésie | H68: Nature | I68: Artisanat | J68: La chance en symbole | K68: Or & vert #D4AF37 | L68: Nacre | M68: Serti secret | N68: Collier Alhambra | O68: Tenue élégante discrète
B69: Bulgari | C69: 1884 | D69: Sotirio Bulgari | E69: Rome | F69: L'audace du colour-blocking inspiré de Rome | G69: Audace créative | H69: Héritage romain | I69: Couleur | J69: Magnificence italienne | K69: Or & noir #1A1A2E | L69: Cabochons colorés | M69: Volume architectural | N69: Serpenti | O69: Tenue milanaise moderne
B70: Givenchy | C70: 1952 | D70: Hubert de Givenchy | E70: Paris | F70: La robe Sabrina porte Audrey Hepburn | G70: Élégance parisienne | H70: Couture | I70: Modernité | J70: L'élégance sans effort | K70: Noir & blanc | L70: Soie fluide | M70: Drapé couture | N70: Sac Antigona | O70: Tenue noire classique
B71: Céline | C71: 1945 | D71: Céline Vipiana | E71: Paris | F71: Minimalisme redevenu désirable sous Phoebe Philo | G71: Minimalisme | H71: Qualité | I71: Fonctionnalité | J71: Sophistication discrète | K71: Beige & brun | L71: Cuir souple | M71: Coupe épurée | N71: Sac Luggage | O71: Tenue minimaliste neutre
B72: Balenciaga | C72: 1919 | D72: Cristóbal Balenciaga | E72: Paris | F72: Le roi de la couture inventait des formes futures | G72: Innovation | H72: Architecture | I72: Subversion | J72: La mode est une architecture | K72: Noir #000000 | L72: Néoprène | M72: Coupe structurée | N72: Triple S | O72: Streetwear structuré
B73: Saint Laurent | C73: 1961 | D73: Yves Saint Laurent | E73: Paris | F73: Le smoking féminin de 1966 révolutionne la garde-robe | G73: Liberté | H73: Androgynie | I73: Rock | J73: L'élégance c'est la liberté | K73: Or & noir | L73: Velours | M73: Coupe smoking | N73: Sac de Jour | O73: Smoking noir
B74: Bottega Veneta | C74: 1966 | D74: Michele Taddei | E74: Vicence | F74: Intrecciato : l'artisanat parle de lui-même, sans logo | G74: Artisanat | H74: Discrétion | I74: Qualité | J74: Quand vos initiales suffisent | K74: Vert BV #4D7C5A | L74: Cuir nappa | M74: Tissage intrecciato | N74: Cabat | O74: Tenue sobre cuir naturel

Sheet 04_CHECKLIST
B2: ✅ CHECKLIST FORMATIONS OBLIGATOIRES
B3: =IFERROR("Complétion : "&TEXT(COUNTIF(E6:E13,"☑")/8,"0%")&" ("&COUNTIF(E6:E13,"☑")&"/8 formations validées)","En attente de saisie") -> Complétion : 0% (0/8 formations validées)
B5: Formation | C5: Référence légale | D5: Délai max | E5: Fait | F5: Date réelle | G5: Alerte
B6: Sécurité au poste de travail | C6: Code Travail Art. L.4121 | D6: ='01_PARAMETRES'!$C$17+1 -> 46114 | E6: ☐ | G6: =IF(E6="☑","✅ Fait",IF(TODAY()>'01_PARAMETRES'!$C$17+1,"🔴 EN RETARD de "&TEXT(TODAY()-('01_PARAMETRES'!$C$17+1),"0")&" j",IF(TODAY()>'01_PARAMETRES'!$C$17+1-7,"🟡 Échéance dans "&TEXT('01_PARAMETRES'!$C$17+1-TODAY(),"0")&" j",""))) -> 🟡 Échéance dans 1 j
B7: Gestes premiers secours (SST) | C7: Art. L.4121-1 | D7: ='01_PARAMETRES'!$C$17+30 -> 46143 | E7: ☐ | G7: =IF(E7="☑","✅ Fait",IF(TODAY()>'01_PARAMETRES'!$C$17+30,"🔴 EN RETARD de "&TEXT(TODAY()-('01_PARAMETRES'!$C$17+30),"0")&" j",IF(TODAY()>'01_PARAMETRES'!$C$17+30-7,"🟡 Échéance dans "&TEXT('01_PARAMETRES'!$C$17+30-TODAY(),"0")&" j","")))
B8: Incendie / Évacuation | C8: Art. R.4227-28 | D8: ='01_PARAMETRES'!$C$17+30 -> 46143 | E8: ☐ | G8: =IF(E8="☑","✅ Fait",IF(TODAY()>'01_PARAMETRES'!$C$17+30,"🔴 EN RETARD de "&TEXT(TODAY()-('01_PARAMETRES'!$C$17+30),"0")&" j",IF(TODAY()>'01_PARAMETRES'!$C$17+30-7,"🟡 Échéance dans "&TEXT('01_PARAMETRES'!$C$17+30-TODAY(),"0")&" j","")))
B9: RGPD — Sensibilisation données | C9: Règlement (UE) 2016/679 | D9: ='01_PARAMETRES'!$C$17+60 -> 46173 | E9: ☐ | G9: =IF(E9="☑","✅ Fait",IF(TODAY()>'01_PARAMETRES'!$C$17+60,"🔴 EN RETARD de "&TEXT(TODAY()-('01_PARAMETRES'!$C$17+60),"0")&" j",IF(TODAY()>'01_PARAMETRES'!$C$17+60-7,"🟡 Échéance dans "&TEXT('01_PARAMETRES'!$C$17+60-TODAY(),"0")&" j","")))
B10: Anti-corruption — Sapin II | C10: Loi 2016-1691 | D10: ='01_PARAMETRES'!$C$17+60 -> 46173 | E10: ☐ | G10: =IF(E10="☑","✅ Fait",IF(TODAY()>'01_PARAMETRES'!$C$17+60,"🔴 EN RETARD de "&TEXT(TODAY()-('01_PARAMETRES'!$C$17+60),"0")&" j",IF(TODAY()>'01_PARAMETRES'!$C$17+60-7,"🟡 Échéance dans "&TEXT('01_PARAMETRES'!$C$17+60-TODAY(),"0")&" j","")))
B11: Harcèlement moral & sexuel | C11: Art. L.1152-1 | D11: ='01_PARAMETRES'!$C$17+90 -> 46203 | E11: ☐ | G11: =IF(E11="☑","✅ Fait",IF(TODAY()>'01_PARAMETRES'!$C$17+90,"🔴 EN RETARD de "&TEXT(TODAY()-('01_PARAMETRES'!$C$17+90),"0")&" j",IF(TODAY()>'01_PARAMETRES'!$C$17+90-7,"🟡 Échéance dans "&TEXT('01_PARAMETRES'!$C$17+90-TODAY(),"0")&" j","")))
B12: Export control | C12: Règlement UE 428/2009 | D12: ='01_PARAMETRES'!$C$17+90 -> 46203 | E12: ☐ | G12: =IF(E12="☑","✅ Fait",IF(TODAY()>'01_PARAMETRES'!$C$17+90,"🔴 EN RETARD de "&TEXT(TODAY()-('01_PARAMETRES'!$C$17+90),"0")&" j",IF(TODAY()>'01_PARAMETRES'!$C$17+90-7,"🟡 Échéance dans "&TEXT('01_PARAMETRES'!$C$17+90-TODAY(),"0")&" j","")))
B13: Développement durable — CSRD | C13: Directive (UE) 2022/2464 | D13: ='01_PARAMETRES'!$C$17+120 -> 46233 | E13: ☐ | G13: =IF(E13="☑","✅ Fait",IF(TODAY()>'01_PARAMETRES'!$C$17+120,"🔴 EN RETARD de "&TEXT(TODAY()-('01_PARAMETRES'!$C$17+120),"0")&" j",IF(TODAY()>'01_PARAMETRES'!$C$17+120-7,"🟡 Échéance dans "&TEXT('01_PARAMETRES'!$C$17+120-TODAY(),"0")&" j","")))
B15: NEURAL — Intelligence Augmentée pour l'Entreprise | Données confidentielles — Usage interne

Sheet 05_BUDDY
B2: 🤝 BUDDY / MENTORAT — Suivi des Points
B4: 👤 BUDDY ASSIGNÉ
B5: Buddy / Mentor | C5: ='01_PARAMETRES'!C13 -> 0
B6: Maison | C6: ='01_PARAMETRES'!C6 -> Louis Vuitton
B7: Collaborateur | C7: ='01_PARAMETRES'!C7 -> Labeaut Ludovic
B9: 📅 POINTS BUDDY — Calendrier & Notations (1–5)
B10: Point # | C10: Date | D10: Fait | E10: Écoute /5 | F10: Disponib. /5 | G10: Pédagogie /5 | H10: Technique /5 | I10: Observations
B11: 1 — J+15 | C11: ='01_PARAMETRES'!$C$17+15 -> 46128 | D11: ☐
B12: 2 — J+30 | C12: ='01_PARAMETRES'!$C$17+30 -> 46143 | D12: ☐
B13: 3 — J+60 | C13: ='01_PARAMETRES'!$C$17+60 -> 46173 | D13: ☐
B14: 4 — J+90 | C14: ='01_PARAMETRES'!$C$17+90 -> 46203 | D14: ☐
B15: 5 — J+120 | C15: ='01_PARAMETRES'!$C$17+120 -> 46233 | D15: ☐
B16: 6 — J+180 | C16: ='01_PARAMETRES'!$C$17+180 -> 46293 | D16: ☐
B18: MOYENNE BUDDY | E18: =IFERROR(AVERAGE(E11:E16),"") | F18: =IFERROR(AVERAGE(F11:F16),"") | G18: =IFERROR(AVERAGE(G11:G16),"") | H18: =IFERROR(AVERAGE(H11:H16),"")
B21: Critère | C21: Moy. /5
B22: Écoute | C22: =IFERROR(IF(COUNTA(E11:E16)=0,"—",AVERAGEIF(E11:E16,">0")),"—") -> —
B23: Disponibilité | C23: =IFERROR(IF(COUNTA(F11:F16)=0,"—",AVERAGEIF(F11:F16,">0")),"—") -> —
B24: Pédagogie | C24: =IFERROR(IF(COUNTA(G11:G16)=0,"—",AVERAGEIF(G11:G16,">0")),"—") -> —
B25: Technique | C25: =IFERROR(IF(COUNTA(H11:H16)=0,"—",AVERAGEIF(H11:H16,">0")),"—") -> —
B32: NEURAL — Intelligence Augmentée pour l'Entreprise | Données confidentielles — Usage interne

Sheet 06_EVALUATIONS
B2: 🎯 ÉVALUATIONS — Grille de Compétences
B3: ='01_PARAMETRES'!C7&" — "&'01_PARAMETRES'!C8&" | "&'01_PARAMETRES'!C6 -> Labeaut Ludovic — Étireur Peaux Ganterie | Louis Vuitton
B5: Critère d'évaluation | C5: J+30 | D5: J+60 | E5: J+90 | F5: J+180 | G5: J+365 | H5: Tendance
B6: Dates d'évaluation | C6: ='01_PARAMETRES'!$C$17+30 -> 46143 | D6: ='01_PARAMETRES'!$C$17+60 -> 46173 | E6: ='01_PARAMETRES'!$C$17+90 -> 46203 | F6: ='01_PARAMETRES'!$C$17+180 -> 46293 | G6: ='01_PARAMETRES'!$C$17+365 -> 46478
B7: Maîtrise technique
B8: Autonomie
B9: Qualité du travail
B10: Culture maison
B11: Relations / Intégration
B12: Initiative & Proactivité
B14: 📊 SCORE MOYEN /10 | C14: =IFERROR(AVERAGE(C7:C12),"") | D14: =IFERROR(AVERAGE(D7:D12),"") | E14: =IFERROR(AVERAGE(E7:E12),"") | F14: =IFERROR(AVERAGE(F7:F12),"") | G14: =IFERROR(AVERAGE(G7:G12),"") | H14: =IF(COUNT(C14:G14)<2,"—",IF(G14<>"",IF(G14>IFERROR(INDEX(C14:F14,MATCH(9E+99,C14:F14)),G14),"↗️",IF(G14=IFERROR(INDEX(C14:F14,MATCH(9E+99,C14:F14)),G14),"→","↘️")),IF(F14>IFERROR(INDEX(C14:E14,MATCH(9E+99,C14:E14)),F14),"↗️",IF(F14=IFERROR(INDEX(C14:E14,MATCH(9E+99,C14:E14)),F14),"→","↘️")))) -> —
B17: Période | C17: Score moyen | D17: Seuil (5)
B18: J+30 | C18: =IFERROR(C14,"") | D18: 5
B19: J+60 | C19: =IFERROR(D14,"") | D19: 5
B20: J+90 | C20: =IFERROR(E14,"") | D20: 5
B21: J+180 | C21: =IFERROR(F14,"") | D21: 5
B22: J+365 | C22: =IFERROR(G14,"") | D22: 5
B44: NEURAL — Intelligence Augmentée pour l'Entreprise | Données confidentielles — Usage interne

Sheet 07_PROBATION
B2: ⚖️ PÉRIODE D'ESSAI — Tableau Décisionnel
B4: 📅 DATES CLÉS
B5: Date d'entrée | C5: ='01_PARAMETRES'!C17 -> 46113
B6: Fin de période d'essai | C6: ='01_PARAMETRES'!C19 -> 46203
B7: Jours écoulés | C7: =IFERROR(IF('01_PARAMETRES'!C17="","—",TODAY()-'01_PARAMETRES'!C17),"—") -> 0
B8: Jours restants | C8: =IFERROR(IF('01_PARAMETRES'!C19="","—",'01_PARAMETRES'!C19-TODAY()),"—") -> 90
B9: Avancement | C9: =IFERROR(IF(OR('01_PARAMETRES'!C17="",'01_PARAMETRES'!C19=""),"",(TODAY()-'01_PARAMETRES'!C17)/('01_PARAMETRES'!C19-'01_PARAMETRES'!C17)),"") -> 0
B11: ⏰ PROGRESSION PÉRIODE D'ESSAI
B12: =IFERROR("["&REPT(CHAR(9608),ROUND(C9*20,0))&REPT(CHAR(9617),20-ROUND(C9*20,0))&"] "&TEXT(C9,"0%")&" - "&TEXT(C8,"0")&" jours restants","En attente de date d'entrée") -> En attente de date d'entrée
B14: ✅ CRITÈRES DE DÉCISION GO / NO-GO
B15: Critère | C15: Résultat | D15: Commentaire / Source | E15: Poids
B16: Score technique J+90 >= 6/10 | C16: =IFERROR(IF('06_EVALUATIONS'!E14>=6,"✅","❌"),"⏳ En attente") -> ✅ | D16: =IFERROR("Score actuel : "&TEXT('06_EVALUATIONS'!E14,"0.0")&"/10","Eval J+90 non saisie") -> Score actuel : /10 | E16: 0.3
B17: Checklist formations 100% | C17: =IFERROR(IF(COUNTIF('04_CHECKLIST'!E6:E13,"☑")=8,"✅","❌"),"⏳") -> ❌ | D17: =IFERROR(TEXT(COUNTIF('04_CHECKLIST'!E6:E13,"☑")/8,"0%")&" ("&COUNTIF('04_CHECKLIST'!E6:E13,"☑")&"/8)","Checklist vide") -> 0% (0/8) | E17: 0.15
B18: Score culture maison >= 7/10 | C18: =IFERROR(IF('06_EVALUATIONS'!E11>=7,"✅","❌"),"⏳ En attente") -> ❌ | D18: =IFERROR("Culture J+90 : "&TEXT('06_EVALUATIONS'!E11,"0.0")&"/10","Eval non saisie") -> Culture J+90 : 0.0/10 | E18: 0.25
B19: Moyenne buddy >= 3/5 | C19: =IFERROR(IF(AVERAGE('05_BUDDY'!E11:H16)>=3,"✅","❌"),"⏳ En attente") -> ⏳ En attente | D19: =IFERROR("Moy. buddy : "&TEXT(AVERAGE('05_BUDDY'!E11:H16),"0.0")&"/5","Points buddy vides") -> Points buddy vides | E19: 0.15
B20: Aucune alerte RH / disciplinaire | C20: ✅ | D20: Saisie manuelle — Vérifier avec RH avant décision | E20: 0.15
B22: {=IFERROR(_xlfn.LET(_xlpm.sc,SUMPRODUCT((C16:C20="✅")*E16:E20),_xlpm.crit,AND(C16="✅",C18="✅"),_xlpm.faibles,IF(C16<>"✅",B16&" ","")&IF(C17<>"✅",B17&" ","")&IF(C18<>"✅",B18&" ","")&IF(C19<>"✅",B19&" ","")&IF(C20<>"✅",B20&" ",""),IF(AND(_xlpm.sc>=0.85,_xlpm.crit),"🟢 VALIDER (≥ 85%) — Score : "&TEXT(_xlpm.sc,"0%"),IF(NOT(_xlpm.crit),"🔴 NE PAS VALIDER — Critères critiques : "&IF(C16<>"✅","Technique ","")&IF(C18<>"✅","Culture",""),IF(_xlpm.sc>=0.6,"🟡 PROLONGER (60–85%) — Score : "&TEXT(_xlpm.sc,"0%")&" — Travailler : "&TRIM(_xlpm.faibles),"🔴 NE PAS VALIDER — Score insuffisant : "&TEXT(_xlpm.sc,"0%"))))),"Critères non encore évalués")} -> 🔴 NE PAS VALIDER — Critères critiques : Culture | D22: {=IFERROR("Score pondéré : "&TEXT(SUMPRODUCT((C16:C20="✅")*E16:E20),"0%")&" (seuil VALIDER ≥85%, PROLONGER ≥60%)","")} -> Score pondéré : 45% (seuil VALIDER ≥85%, PROLONGER ≥60%)
B24: NEURAL — Intelligence Augmentée pour l'Entreprise | Données confidentielles — Usage interne

Sheet 08_DASHBOARD
B2: =IFERROR("Onboarding — "&'01_PARAMETRES'!C7&" | "&'01_PARAMETRES'!C8&" | "&'01_PARAMETRES'!C6&" — Entré le "&TEXT('01_PARAMETRES'!C17,"jj/mm/aaaa"),"NEURAL — LuxeOnboarding Dashboard") -> Onboarding — Labeaut Ludovic | Étireur Peaux Ganterie | Louis Vuitton — Entré le 01/04/2026
B3: NEURAL — Intelligence Augmentée pour l'Entreprise | Onboarding Luxe Personnalisé
B5: 📋 Avancement Checklist | C5: 🎯 Score Actuel | D5: 📅 Jours Restants | E5: ⚡ Statut Probation
B6: =IFERROR(TEXT(COUNTIF('04_CHECKLIST'!E6:E13,"☑")/8,"0%"),"—") -> 0% | C6: =IFERROR(TEXT(MAX('06_EVALUATIONS'!C14:G14),"0.0")&"/10","—") -> 0.0/10 | D6: =IFERROR(TEXT('01_PARAMETRES'!C19-TODAY(),"0")&" j","—") -> 90 j | E6: {=IFERROR(_xlfn.LET(_xlpm.sc,SUMPRODUCT(('07_PROBATION'!C16:C20="✅")*'07_PROBATION'!E16:E20),_xlpm.crit,AND('07_PROBATION'!C16="✅",'07_PROBATION'!C18="✅"),IF(AND(_xlpm.sc>=0.85,_xlpm.crit),"🟢 VALIDER — "&TEXT(_xlpm.sc,"0%"),IF(NOT(_xlpm.crit),"🔴 À RISQUE — "&TEXT(_xlpm.sc,"0%"),IF(_xlpm.sc>=0.6,"🟡 PROLONGER — "&TEXT(_xlpm.sc,"0%"),"🔴 À RISQUE — "&TEXT(_xlpm.sc,"0%"))))),"⏳ En cours")} -> 🔴 À RISQUE — 45%
B7: =IFERROR(COUNTIF('04_CHECKLIST'!E6:E13,"☑")&"/8 formations","") -> 0/8 formations | C7: =IFERROR("Dernière évaluation saisie","") -> Dernière évaluation saisie | D7: =IFERROR("Fin : "&TEXT('01_PARAMETRES'!C19,"jj/mm/aa"),"") -> Fin : 30/06/26 | E7: =IFERROR(COUNTIF('07_PROBATION'!C16:C20,"✅")&"/5 critères OK","") -> 2/5 critères OK
B9: 📋 SYNTHÈSE PARCOURS
B10: Collaborateur | C10: ='01_PARAMETRES'!C7 -> Labeaut Ludovic
B11: Maison | C11: ='01_PARAMETRES'!C6 -> Louis Vuitton
B12: Poste | C12: ='01_PARAMETRES'!C8 -> Étireur Peaux Ganterie
B13: Métier d'art | C13: ='01_PARAMETRES'!C9 -> Ganterie
B14: Niveau | C14: ='01_PARAMETRES'!C10 -> N1
B15: Manager | C15: ='01_PARAMETRES'!C12 -> 0
B16: Buddy | C16: ='01_PARAMETRES'!C13 -> 0
B17: Date entrée | C17: =IFERROR(IF('01_PARAMETRES'!C17="","Non renseignée",TEXT('01_PARAMETRES'!C17,"jj/mm/aa")),"Non renseignée") -> 01/04/26
B18: Fin essai | C18: =IFERROR(IF('01_PARAMETRES'!C19="","—",TEXT('01_PARAMETRES'!C19,"jj/mm/aa")),"—") -> 30/06/26
B19: Type contrat | C19: ='01_PARAMETRES'!C21 -> CDD
B21: ✅ CHECKLIST FORMATIONS — ÉTAT RAPIDE
B22: Sécurité poste | C22: ='04_CHECKLIST'!E6 -> ☐ | D22: ='04_CHECKLIST'!G6 -> 🟡 Échéance dans 1 j
B23: SST | C23: ='04_CHECKLIST'!E7 -> ☐ | D23: ='04_CHECKLIST'!G7
B24: Incendie | C24: ='04_CHECKLIST'!E8 -> ☐ | D24: ='04_CHECKLIST'!G8
B25: RGPD | C25: ='04_CHECKLIST'!E9 -> ☐ | D25: ='04_CHECKLIST'!G9
B26: Anti-corruption | C26: ='04_CHECKLIST'!E10 -> ☐ | D26: ='04_CHECKLIST'!G10
B27: Harcèlement | C27: ='04_CHECKLIST'!E11 -> ☐ | D27: ='04_CHECKLIST'!G11
B28: Export control | C28: ='04_CHECKLIST'!E12 -> ☐ | D28: ='04_CHECKLIST'!G12
B29: CSRD | C29: ='04_CHECKLIST'!E13 -> ☐ | D29: ='04_CHECKLIST'!G13
B31: 🔗 NAVIGATION
B32: ⚙️ Paramètres | C32: 📋 Parcours | D32: 🏛️ Culture | E32: ✅ Checklist
B33: 🤝 Buddy | C33: 🎯 Évaluations | D33: ⚖️ Probation | E33: 📊 Dashboard
B35: NEURAL — Intelligence Augmentée pour l'Entreprise | Données confidentielles — Usage interne uniquement

Sheet _REF_POSTES
A1: Maroquinerie | B1: Sellerie | C1: Orfèvrerie | D1: Joaillerie | E1: Couture | F1: Chapellerie | G1: Botterie | H1: Ganterie | I1: Soierie | J1: Parfumerie | K1: Horlogerie | M1: Postes_Actifs
A2: Artisan Maroquinier | B2: Artisan Sellier | C2: Orfèvre | D2: Joaillier | E2: Couturier / Couturière | F2: Chapelier / Chapelière | G2: Bottier | H2: Gantier | I2: Tisseur Soie | J2: Nez / Parfumeur | K2: Horloger | M2: {=IFERROR(INDEX($A$2:$K$11,ROW()-1,MATCH('01_PARAMETRES'!$C$9,$A$1:$K$1,0)),"")} -> Gantier
A3: Coupeur Cuir | B3: Sellier-Garnisseur | C3: Ciseleur | D3: Sertisseur | E3: Modéliste | F3: Formier Chapellerie | G3: Monteur Chaussures | H3: Coupeur Ganterie | I3: Dessinateur Textile | J3: Évaluateur Parfums | K3: Horloger Régleur | M3: {=IFERROR(INDEX($A$2:$K$11,ROW()-1,MATCH('01_PARAMETRES'!$C$9,$A$1:$K$1,0)),"")} -> Coupeur Ganterie
A4: Piqueur / Couseur | B4: Coupeur Sellerie | C4: Polisseur Métaux Précieux | D4: Lapidaire | E4: Coupeur Tissu | F4: Garnisseur Chapeaux | G4: Patronnier Botterie | H4: Couseur Gants | I4: Coloriste Textile | J4: Chef de Projet Parfums | K4: Emboîteur | M4: {=IFERROR(INDEX($A$2:$K$11,ROW()-1,MATCH('01_PARAMETRES'!$C$9,$A$1:$K$1,0)),"")} -> Couseur Gants
A5: Monteur Maroquinerie | B5: Monteur Sellerie | C5: Fondeur Orfèvrerie | D5: Polisseur Joaillerie | E5: Tailleur | F5: Feutrier | G5: Coupeur Botterie | H5: Étireur Peaux Ganterie | I5: Imprimeur sur Soie | J5: Technicien Formulation | K5: Cadranier | M5: {=IFERROR(INDEX($A$2:$K$11,ROW()-1,MATCH('01_PARAMETRES'!$C$9,$A$1:$K$1,0)),"")} -> Étireur Peaux Ganterie
A6: Coloriste Cuir | B6: Sellier Harnacheur | C6: Graveur sur Métal | D6: Gemmologue | E6: Brodeuse / Brodeur | F6: Coupeur Chapellerie | G6: Piqueur Botterie | H6: Finisseur Gants | I6: Canneteur / Ourdisseur | J6: Responsable Développement Olfactif | K6: Graveur Horlogerie | M6: {=IFERROR(INDEX($A$2:$K$11,ROW()-1,MATCH('01_PARAMETRES'!$C$9,$A$1:$K$1,0)),"")} -> Finisseur Gants
A7: Préparateur Peaux | B7: Restaurateur Sellerie | C7: Monteur Orfèvrerie | D7: Dessinateur Joaillerie | E7: Retoucheur Couture | F7: Prototypiste Chapellerie | G7: Finisseur Chaussures | H7: Prototypiste Ganterie | I7: Contrôleur Qualité Soierie | J7: Artisan Conditionneur | K7: Polisseur Horlogerie | M7: {=IFERROR(INDEX($A$2:$K$11,ROW()-1,MATCH('01_PARAMETRES'!$C$9,$A$1:$K$1,0)),"")} -> Prototypiste Ganterie
A8: Chef d'Atelier Maroquinerie | B8: Chef d'Atelier Sellerie | C8: Chef d'Atelier Orfèvrerie | D8: Chef d'Atelier Joaillerie | E8: Première d'Atelier | F8: Chef d'Atelier Chapellerie | G8: Chef d'Atelier Botterie | H8: Chef d'Atelier Ganterie | I8: Chef d'Atelier Soierie | J8: Contrôleur Qualité Parfums | K8: Chef d'Atelier Horlogerie | M8: {=IFERROR(INDEX($A$2:$K$11,ROW()-1,MATCH('01_PARAMETRES'!$C$9,$A$1:$K$1,0)),"")} -> Chef d'Atelier Ganterie
A9: Contrôleur Qualité Cuir | B9: Contrôleur Qualité Sellerie | C9: Contrôleur Qualité Orfèvrerie | D9: Contrôleur Qualité Joaillerie | E9: Chef d'Atelier Couture | F9: Contrôleur Qualité Chapellerie | G9: Contrôleur Qualité Botterie | H9: Contrôleur Qualité Ganterie | I9: Prototypiste Soierie | J9: Responsable Réglementaire Cosmétique | K9: Contrôleur Qualité Horlogerie | M9: {=IFERROR(INDEX($A$2:$K$11,ROW()-1,MATCH('01_PARAMETRES'!$C$9,$A$1:$K$1,0)),"")} -> Contrôleur Qualité Ganterie
A10: Prototypiste Maroquinerie | B10: Prototypiste Sellerie | C10: Prototypiste Orfèvrerie | D10: Prototypiste Joaillerie | E10: Prototypiste Couture | F10: Restaurateur Chapeaux | G10: Prototypiste Botterie | H10: Coloriste Ganterie | I10: Restaurateur Soieries Anciennes | J10: Chef de Produit Parfums | K10: Prototypiste Horlogerie | M10: {=IFERROR(INDEX($A$2:$K$11,ROW()-1,MATCH('01_PARAMETRES'!$C$9,$A$1:$K$1,0)),"")} -> Coloriste Ganterie
A11: Responsable Production Maroquinerie | B11: Formateur Gestes Sellier | C11: Restaurateur Pièces d'Orfèvrerie | D11: Responsable Achats Pierres | E11: Responsable Qualité Couture | F11: Designer Accessoires Tête | G11: Formier Chaussures | H11: Responsable Production Ganterie | I11: Responsable Production Soierie | J11: Opérateur Production Parfumerie | K11: Restaurateur Montres Anciennes | M11: {=IFERROR(INDEX($A$2:$K$11,ROW()-1,MATCH('01_PARAMETRES'!$C$9,$A$1:$K$1,0)),"")} -> Responsable Production Ganterie
